Workbook

Sheet 美森360
A1: 应付 | B1: 上海——LB | F1: 费用类型 | G1: 币种 | H1: 单价 | I1: 数量 | J1: 备注 | K1: 统计 | N1: 拆送分段成本（KG） | P1: 组合分段成本（KG） | R1: 整柜直送分段成本 | T1: 拆送分段成本（CBM） | V1: 组合分段成本（CBM） | X1: 整柜直送分段成本（CBM）
B2: 起运港 | C2: 拖车+报关 | F2: 装柜费 | G2: RMB | H2: 500 | I2: 1 | N2: =H2/H12 -> 0.03992016 | P2: =H2/H12 -> 0.03992016 | R2: =H2/H12 -> 0.03992016 | T2: =H2/$B$12 -> 6.6666667 | V2: =H2/B12 -> 6.6666667 | X2: =H2/B12 -> 6.6666667
F3: 拖车费 | G3: RMB | H3: 9000 | I3: 1 | N3: =H3/H12 -> 0.71856287 | P3: =H3/H12 -> 0.71856287 | R3: =H3/H12 -> 0.71856287 | T3: =H3/$B$12 -> 120 | V3: =H3/B12 -> 120 | X3: =H3/B12 -> 120
F4: 报关费 | G4: RMB | H4: 1800 | I4: 1 | N4: =H4/H12 -> 0.14371257 | P4: =H4/H12 -> 0.14371257 | R4: =H4/H12 -> 0.14371257 | T4: =H4/$B$12 -> 24 | V4: =H4/B12 -> 24 | X4: =H4/B12 -> 24
F5: 港杂费RMB部分 | G5: RMB | H5: 3000 | I5: 1 | N5: =H5/H12 -> 0.23952096 | P5: =H5/H12 -> 0.23952096 | R5: =H5/H12 -> 0.23952096 | T5: =H5/$B$12 -> 40 | V5: =H5/B12 -> 40 | X5: =H5/B12 -> 40
F6: 海运费（变动） | G6: USD | H6: 10429 | I6: 1 | N6: =H6*7/H12 -> 5.8285828 | P6: =H6*7/H12 -> 5.8285828 | R6: =H6*J10/H12 -> 5.8285828 | T6: =H6/$B$12*7 -> 973.37333 | V6: =H6*7/B12 -> 973.37333 | X6: =H6*7/B12 -> 973.37333
B7: 目的港 | C7: 提柜+拆柜 | F7: 提拆一口价 | G7: USD | H7: 1480 | I7: 1 | N7: =H7*J10/H12 -> 0.82714571 | T7: =H7/$B$12*7 -> 138.13333
C8: 清关+缴税 | F8: 清关费 | G8: USD | I8: 1 | T8: =H8/$B$12*7 -> 0
F9: 税金 | G9: USD | H9: 1500 | L9: 每板KG | N9: =H9*J10/H12 -> 0.83832335 | P9: =H9*7/H12 -> 0.83832335 | R9: =H9*J10/H12 -> 0.83832335 | T9: =H9/$B$12*7 -> 140 | V9: =H9*J10/B12 -> 140 | X9: =H9*J10/B12 -> 140
A10: 上海-LB | B10: 人民币应付 | G10: RMB | H10: =SUM(H2:H5) -> 14300 | I10: 汇率 | J10: 7 | K10: =H10/J10 -> 2042.8571 | L10: 350 | N10: =(C15*J10)/L10 -> 0.6
A11: 报价：2025/03/16 | B11: 含税KG/CBM | G11: USD | H11: =SUM(H6:H9) -> 13409 | I11: 合计 | J11: =H11+K10 -> 15451.857 | K11: =J11*J10 -> 108163 | L11: CBM
A12: CBM标准 | B12: 75 | E12: CBM计费标准 | F12: =K11/B12 -> 1442.1733 | G12: KG标准 | H12: 12525 | I12: KG计费标准 | J12: =F12/167 -> 8.6357685 | L12: 1.8
B13: 派送费 | C13: 美金/板 | D13: 组合一口价 | E13: 整柜一口价 | F13: 拆送KG含税 | G13: 组合KG | H13: 直送KG | I13: 拆送CBM含税 | J13: 组合CBM | K13: 直送CBM | L13: 直客报价101KG+ | M13: 拆送末端（KG） | N13: 拆送头程（KG） | O13: 组合末端（KG） | P13: 组合头程（KG） | Q13: 整柜直送末端（KG） | R13: 整柜直送头程（KG） | S13: 拆送末端（m³） | T13: 拆送头程（m³） | U13: 组合末端（m³） | V13: 组合头程（m³） | W13: 整柜直送末端（m³） | X13: 整柜直送头程（m³）
A14: 美西 一区 | B14: ONT8 | C14: 30 | D14: 1980 | E14: 1430 | F14: =$J$12+(C14*$J$10/$L$10) -> 9.2357685 | G14: =IF(D14="","",($J$11-$H$7+D14)*$J$10/$H$12) -> 8.9152096 | H14: =IF(E14="","",($J$11-$H$7+E14)*$J$10/$H$12) -> 8.6078244 | I14: =$F$12+(C14*$J$10/$L$12) -> 1558.84 | J14: =IF(D14="","",($J$11-$H$7+D14)*$J$10/$B$12) -> 1488.84 | K14: =IF(E14="","",($J$11-$H$7+E14)*$J$10/$B$12) -> 1437.5067 | L14: 10.1 | M14: =C14*J10/L10 -> 0.6 | N14: =SUM(N2:N9) -> 8.6357685 | O14: =D14*J10/H12 -> 1.1065868 | P14: =(J11-H7)*J10/H12 -> 7.8086228 | Q14: =E14*J10/H12 -> 0.7992016 | R14: =SUM(R2:R9) -> 7.8086228 | S14: =C14*J10/L12 -> 116.66667 | T14: =K11/B12 -> 1442.1733 | U14: =D14*J10/B12 -> 184.8 | V14: =(J11-H7)*J10/B12 -> 1304.04 | W14: =E14*J10/B12 -> 133.46667 | X14: =SUM(X2:X9) -> 1304.04
B15: LGB8 | C15: 30 | D15: 1980 | E15: 1430 | F15: =$J$12+(C15*$J$10/$L$10) -> 9.2357685 | G15: =IF(D15="","",($J$11-$H$7+D15)*$J$10/$H$12) -> 8.9152096 | H15: =IF(E15="","",($J$11-$H$7+E15)*$J$10/$H$12) -> 8.6078244 | I15: =$F$12+(C15*$J$10/$L$12) -> 1558.84 | J15: =IF(D15="","",($J$11-$H$7+D15)*$J$10/$B$12) -> 1488.84 | K15: =IF(E15="","",($J$11-$H$7+E15)*$J$10/$B$12) -> 1437.5067 | L15: 10.1
B16: SBD1 | C16: 35 | D16: 1980 | E16: 1430 | F16: =$J$12+(C16*$J$10/$L$10) -> 9.3357685 | G16: =IF(D16="","",($J$11-$H$7+D16)*$J$10/$H$12) -> 8.9152096 | H16: =IF(E16="","",($J$11-$H$7+E16)*$J$10/$H$12) -> 8.6078244 | I16: =$F$12+(C16*$J$10/$L$12) -> 1578.2844 | J16: =IF(D16="","",($J$11-$H$7+D16)*$J$10/$B$12) -> 1488.84 | K16: =IF(E16="","",($J$11-$H$7+E16)*$J$10/$B$12) -> 1437.5067 | L16: 10.1
B17: LAX9 | C17: 30 | D17: 1980 | E17: 1430 | F17: =$J$12+(C17*$J$10/$L$10) -> 9.2357685 | G17: =IF(D17="","",($J$11-$H$7+D17)*$J$10/$H$12) -> 8.9152096 | H17: =IF(E17="","",($J$11-$H$7+E17)*$J$10/$H$12) -> 8.6078244 | I17: =$F$12+(C17*$J$10/$L$12) -> 1558.84 | J17: =IF(D17="","",($J$11-$H$7+D17)*$J$10/$B$12) -> 1488.84 | K17: =IF(E17="","",($J$11-$H$7+E17)*$J$10/$B$12) -> 1437.5067 | L17: 10.1
A18: 美西 二区 | B18: SMF3 | C18: 70 | D18: 2980 | E18: 2730 | F18: =$J$12+(C18*$J$10/$L$10) -> 10.035768 | G18: =IF(D18="","",($J$11-$H$7+D18)*$J$10/$H$12) -> 9.4740918 | H18: =IF(E18="","",($J$11-$H$7+E18)*$J$10/$H$12) -> 9.3343713 | I18: =$F$12+(C18*$J$10/$L$12) -> 1714.3956 | J18: =IF(D18="","",($J$11-$H$7+D18)*$J$10/$B$12) -> 1582.1733 | K18: =IF(E18="","",($J$11-$H$7+E18)*$J$10/$B$12) -> 1558.84 | L18: 10.9
B19: SCK4 | C19: 70 | D19: 2980 | E19: 2730 | F19: =$J$12+(C19*$J$10/$L$10) -> 10.035768 | G19: =IF(D19="","",($J$11-$H$7+D19)*$J$10/$H$12) -> 9.4740918 | H19: =IF(E19="","",($J$11-$H$7+E19)*$J$10/$H$12) -> 9.3343713 | I19: =$F$12+(C19*$J$10/$L$12) -> 1714.3956 | J19: =IF(D19="","",($J$11-$H$7+D19)*$J$10/$B$12) -> 1582.1733 | K19: =IF(E19="","",($J$11-$H$7+E19)*$J$10/$B$12) -> 1558.84 | L19: 10.9
B20: GYR2 | C20: 70 | D20: 2980 | E20: 2530 | F20: =$J$12+(C20*$J$10/$L$10) -> 10.035768 | G20: =IF(D20="","",($J$11-$H$7+D20)*$J$10/$H$12) -> 9.4740918 | H20: =IF(E20="","",($J$11-$H$7+E20)*$J$10/$H$12) -> 9.2225948 | I20: =$F$12+(C20*$J$10/$L$12) -> 1714.3956 | J20: =IF(D20="","",($J$11-$H$7+D20)*$J$10/$B$12) -> 1582.1733 | K20: =IF(E20="","",($J$11-$H$7+E20)*$J$10/$B$12) -> 1540.1733 | L20: 10.9
B21: GYR3 | C21: 70 | D21: 2980 | E21: 2530 | F21: =$J$12+(C21*$J$10/$L$10) -> 10.035768 | G21: =IF(D21="","",($J$11-$H$7+D21)*$J$10/$H$12) -> 9.4740918 | H21: =IF(E21="","",($J$11-$H$7+E21)*$J$10/$H$12) -> 9.2225948 | I21: =$F$12+(C21*$J$10/$L$12) -> 1714.3956 | J21: =IF(D21="","",($J$11-$H$7+D21)*$J$10/$B$12) -> 1582.1733 | K21: =IF(E21="","",($J$11-$H$7+E21)*$J$10/$B$12) -> 1540.1733 | L21: 10.9
B22: LAS1 | C22: 70 | D22: 2980 | E22: 2430 | F22: =$J$12+(C22*$J$10/$L$10) -> 10.035768 | G22: =IF(D22="","",($J$11-$H$7+D22)*$J$10/$H$12) -> 9.4740918 | H22: =IF(E22="","",($J$11-$H$7+E22)*$J$10/$H$12) -> 9.1667066 | I22: =$F$12+(C22*$J$10/$L$12) -> 1714.3956 | J22: =IF(D22="","",($J$11-$H$7+D22)*$J$10/$B$12) -> 1582.1733 | K22: =IF(E22="","",($J$11-$H$7+E22)*$J$10/$B$12) -> 1530.84 | L22: 10.9
B23: VGT2 | C23: 70 | D23: 2980 | E23: 2430 | F23: =$J$12+(C23*$J$10/$L$10) -> 10.035768 | G23: =IF(D23="","",($J$11-$H$7+D23)*$J$10/$H$12) -> 9.4740918 | H23: =IF(E23="","",($J$11-$H$7+E23)*$J$10/$H$12) -> 9.1667066 | I23: =$F$12+(C23*$J$10/$L$12) -> 1714.3956 | J23: =IF(D23="","",($J$11-$H$7+D23)*$J$10/$B$12) -> 1582.1733 | K23: =IF(E23="","",($J$11-$H$7+E23)*$J$10/$B$12) -> 1530.84 | L23: 10.9
A24: 美西 三区 | B24: POC1 | C24: 55 | D24: 2180 | E24: 1430 | F24: =$J$12+(C24*$J$10/$L$10) -> 9.7357685 | G24: =IF(D24="","",($J$11-$H$7+D24)*$J$10/$H$12) -> 9.026986 | H24: =IF(E24="","",($J$11-$H$7+E24)*$J$10/$H$12) -> 8.6078244 | I24: =$F$12+(C24*$J$10/$L$12) -> 1656.0622 | J24: =IF(D24="","",($J$11-$H$7+D24)*$J$10/$B$12) -> 1507.5067 | K24: =IF(E24="","",($J$11-$H$7+E24)*$J$10/$B$12) -> 1437.5067 | L24: 10.1
B25: POC2 | C25: 55 | D25: 2180 | F25: =$J$12+(C25*$J$10/$L$10) -> 9.7357685 | G25: =IF(D25="","",($J$11-$H$7+D25)*$J$10/$H$12) -> 9.026986 | H25: =IF(E25="","",($J$11-$H$7+E25)*$J$10/$H$12) | I25: =$F$12+(C25*$J$10/$L$12) -> 1656.0622 | J25: =IF(D25="","",($J$11-$H$7+D25)*$J$10/$B$12) -> 1507.5067 | K25: =IF(E25="","",($J$11-$H$7+E25)*$J$10/$B$12) | L25: 10.1
B26: POC3 | C26: 55 | D26: 2180 | E26: 1430 | F26: =$J$12+(C26*$J$10/$L$10) -> 9.7357685 | G26: =IF(D26="","",($J$11-$H$7+D26)*$J$10/$H$12) -> 9.026986 | H26: =IF(E26="","",($J$11-$H$7+E26)*$J$10/$H$12) -> 8.6078244 | I26: =$F$12+(C26*$J$10/$L$12) -> 1656.0622 | J26: =IF(D26="","",($J$11-$H$7+D26)*$J$10/$B$12) -> 1507.5067 | K26: =IF(E26="","",($J$11-$H$7+E26)*$J$10/$B$12) -> 1437.5067 | L26: 10.1
B27: SNA4 | C27: 50 | D27: 2180 | E27: 1480 | F27: =$J$12+(C27*$J$10/$L$10) -> 9.6357685 | G27: =IF(D27="","",($J$11-$H$7+D27)*$J$10/$H$12) -> 9.026986 | H27: =IF(E27="","",($J$11-$H$7+E27)*$J$10/$H$12) -> 8.6357685 | I27: =$F$12+(C27*$J$10/$L$12) -> 1636.6178 | J27: =IF(D27="","",($J$11-$H$7+D27)*$J$10/$B$12) -> 1507.5067 | K27: =IF(E27="","",($J$11-$H$7+E27)*$J$10/$B$12) -> 1442.1733
B28: KRB1 | C28: 50 | D28: 2180 | F28: =$J$12+(C28*$J$10/$L$10) -> 9.6357685 | G28: =IF(D28="","",($J$11-$H$7+D28)*$J$10/$H$12) -> 9.026986 | H28: =IF(E28="","",($J$11-$H$7+E28)*$J$10/$H$12) | I28: =$F$12+(C28*$J$10/$L$12) -> 1636.6178 | J28: =IF(D28="","",($J$11-$H$7+D28)*$J$10/$B$12) -> 1507.5067 | K28: =IF(E28="","",($J$11-$H$7+E28)*$J$10/$B$12)
B29: KRB4 | C29: 50 | D29: 2180 | F29: =$J$12+(C29*$J$10/$L$10) -> 9.6357685 | G29: =IF(D29="","",($J$11-$H$7+D29)*$J$10/$H$12) -> 9.026986 | H29: =IF(E29="","",($J$11-$H$7+E29)*$J$10/$H$12) | I29: =$F$12+(C29*$J$10/$L$12) -> 1636.6178 | J29: =IF(D29="","",($J$11-$H$7+D29)*$J$10/$B$12) -> 1507.5067 | K29: =IF(E29="","",($J$11-$H$7+E29)*$J$10/$B$12)
B30: IUSJ | C30: 65 | D30: 2180 | E30: 1580 | F30: =$J$12+(C30*$J$10/$L$10) -> 9.9357685 | G30: =IF(D30="","",($J$11-$H$7+D30)*$J$10/$H$12) -> 9.026986 | H30: =IF(E30="","",($J$11-$H$7+E30)*$J$10/$H$12) -> 8.6916567 | I30: =$F$12+(C30*$J$10/$L$12) -> 1694.9511 | J30: =IF(D30="","",($J$11-$H$7+D30)*$J$10/$B$12) -> 1507.5067 | K30: =IF(E30="","",($J$11-$H$7+E30)*$J$10/$B$12) -> 1451.5067 | L30: 10.6
B31: IUSP | C31: 65 | D31: 2180 | E31: 1580 | F31: =$J$12+(C31*$J$10/$L$10) -> 9.9357685 | G31: =IF(D31="","",($J$11-$H$7+D31)*$J$10/$H$12) -> 9.026986 | H31: =IF(E31="","",($J$11-$H$7+E31)*$J$10/$H$12) -> 8.6916567 | I31: =$F$12+(C31*$J$10/$L$12) -> 1694.9511 | J31: =IF(D31="","",($J$11-$H$7+D31)*$J$10/$B$12) -> 1507.5067 | K31: =IF(E31="","",($J$11-$H$7+E31)*$J$10/$B$12) -> 1451.5067 | L31: 10.6
B32: IUSQ | C32: 65 | D32: 2180 | E32: 1580 | F32: =$J$12+(C32*$J$10/$L$10) -> 9.9357685 | G32: =IF(D32="","",($J$11-$H$7+D32)*$J$10/$H$12) -> 9.026986 | H32: =IF(E32="","",($J$11-$H$7+E32)*$J$10/$H$12) -> 8.6916567 | I32: =$F$12+(C32*$J$10/$L$12) -> 1694.9511 | J32: =IF(D32="","",($J$11-$H$7+D32)*$J$10/$B$12) -> 1507.5067 | K32: =IF(E32="","",($J$11-$H$7+E32)*$J$10/$B$12) -> 1451.5067 | L32: 10.6
A33: 美西 四区 | B33: GEU3 | C33: 85 | D33: 3180 | E33: 2750 | F33: =$J$12+(C33*$J$10/$L$10) -> 10.335768 | G33: =IF(D33="","",($J$11-$H$7+D33)*$J$10/$H$12) -> 9.5858683 | H33: =IF(E33="","",($J$11-$H$7+E33)*$J$10/$H$12) -> 9.3455489 | I33: =$F$12+(C33*$J$10/$L$12) -> 1772.7289 | J33: =IF(D33="","",($J$11-$H$7+D33)*$J$10/$B$12) -> 1600.84 | K33: =IF(E33="","",($J$11-$H$7+E33)*$J$10/$B$12) -> 1560.7067 | L33: 10.9
B34: GEU2 | C34: 85 | D34: 3180 | E34: 2750 | F34: =$J$12+(C34*$J$10/$L$10) -> 10.335768 | G34: =IF(D34="","",($J$11-$H$7+D34)*$J$10/$H$12) -> 9.5858683 | H34: =IF(E34="","",($J$11-$H$7+E34)*$J$10/$H$12) -> 9.3455489 | I34: =$F$12+(C34*$J$10/$L$12) -> 1772.7289 | J34: =IF(D34="","",($J$11-$H$7+D34)*$J$10/$B$12) -> 1600.84 | K34: =IF(E34="","",($J$11-$H$7+E34)*$J$10/$B$12) -> 1560.7067 | L34: 10.9
B35: MIT2 | C35: 85 | D35: 3180 | E35: 2500 | F35: =$J$12+(C35*$J$10/$L$10) -> 10.335768 | G35: =IF(D35="","",($J$11-$H$7+D35)*$J$10/$H$12) -> 9.5858683 | H35: =IF(E35="","",($J$11-$H$7+E35)*$J$10/$H$12) -> 9.2058283 | I35: =$F$12+(C35*$J$10/$L$12) -> 1772.7289 | J35: =IF(D35="","",($J$11-$H$7+D35)*$J$10/$B$12) -> 1600.84 | K35: =IF(E35="","",($J$11-$H$7+E35)*$J$10/$B$12) -> 1537.3733 | L35: 10.9
B36: OAK3 | C36: 85 | D36: 3180 | F36: =$J$12+(C36*$J$10/$L$10) -> 10.335768 | G36: =IF(D36="","",($J$11-$H$7+D36)*$J$10/$H$12) -> 9.5858683 | H36: =IF(E36="","",($J$11-$H$7+E36)*$J$10/$H$12) | I36: =$F$12+(C36*$J$10/$L$12) -> 1772.7289 | J36: =IF(D36="","",($J$11-$H$7+D36)*$J$10/$B$12) -> 1600.84 | K36: =IF(E36="","",($J$11-$H$7+E36)*$J$10/$B$12)
B37: LAS6 | C37: 85 | D37: 3180 | E37: 2480 | F37: =$J$12+(C37*$J$10/$L$10) -> 10.335768 | G37: =IF(D37="","",($J$11-$H$7+D37)*$J$10/$H$12) -> 9.5858683 | H37: =IF(E37="","",($J$11-$H$7+E37)*$J$10/$H$12) -> 9.1946507 | I37: =$F$12+(C37*$J$10/$L$12) -> 1772.7289 | J37: =IF(D37="","",($J$11-$H$7+D37)*$J$10/$B$12) -> 1600.84 | K37: =IF(E37="","",($J$11-$H$7+E37)*$J$10/$B$12) -> 1535.5067
B38: SMF6 | C38: 85 | D38: 3180 | F38: =$J$12+(C38*$J$10/$L$10) -> 10.335768 | G38: =IF(D38="","",($J$11-$H$7+D38)*$J$10/$H$12) -> 9.5858683 | H38: =IF(E38="","",($J$11-$H$7+E38)*$J$10/$H$12) | I38: =$F$12+(C38*$J$10/$L$12) -> 1772.7289 | J38: =IF(D38="","",($J$11-$H$7+D38)*$J$10/$B$12) -> 1600.84 | K38: =IF(E38="","",($J$11-$H$7+E38)*$J$10/$B$12)
B39: SCK8 | C39: 85 | D39: 3180 | F39: =$J$12+(C39*$J$10/$L$10) -> 10.335768 | G39: =IF(D39="","",($J$11-$H$7+D39)*$J$10/$H$12) -> 9.5858683 | H39: =IF(E39="","",($J$11-$H$7+E39)*$J$10/$H$12) | I39: =$F$12+(C39*$J$10/$L$12) -> 1772.7289 | J39: =IF(D39="","",($J$11-$H$7+D39)*$J$10/$B$12) -> 1600.84 | K39: =IF(E39="","",($J$11-$H$7+E39)*$J$10/$B$12) | L39: 10.9
B40: GEU5 | C40: 85 | D40: 3180 | E40: 2750 | F40: =$J$12+(C40*$J$10/$L$10) -> 10.335768 | G40: =IF(D40="","",($J$11-$H$7+D40)*$J$10/$H$12) -> 9.5858683 | H40: =IF(E40="","",($J$11-$H$7+E40)*$J$10/$H$12) -> 9.3455489 | I40: =$F$12+(C40*$J$10/$L$12) -> 1772.7289 | J40: =IF(D40="","",($J$11-$H$7+D40)*$J$10/$B$12) -> 1600.84 | K40: =IF(E40="","",($J$11-$H$7+E40)*$J$10/$B$12) -> 1560.7067
B41: HLI2 | C41: 85 | D41: 3180 | E41: 2730 | F41: =$J$12+(C41*$J$10/$L$10) -> 10.335768 | G41: =IF(D41="","",($J$11-$H$7+D41)*$J$10/$H$12) -> 9.5858683 | H41: =IF(E41="","",($J$11-$H$7+E41)*$J$10/$H$12) -> 9.3343713 | I41: =$F$12+(C41*$J$10/$L$12) -> 1772.7289 | J41: =IF(D41="","",($J$11-$H$7+D41)*$J$10/$B$12) -> 1600.84 | K41: =IF(E41="","",($J$11-$H$7+E41)*$J$10/$B$12) -> 1558.84 | L41: 10.9
B42: TCY2/TCY1 | C42: 85 | D42: 3180 | E42: 2730 | F42: =$J$12+(C42*$J$10/$L$10) -> 10.335768 | G42: =IF(D42="","",($J$11-$H$7+D42)*$J$10/$H$12) -> 9.5858683 | H42: =IF(E42="","",($J$11-$H$7+E42)*$J$10/$H$12) -> 9.3343713 | I42: =$F$12+(C42*$J$10/$L$12) -> 1772.7289 | J42: =IF(D42="","",($J$11-$H$7+D42)*$J$10/$B$12) -> 1600.84 | K42: =IF(E42="","",($J$11-$H$7+E42)*$J$10/$B$12) -> 1558.84
A43: 美中 一区 | B43: DFW6 | C43: 160 | D43: 5380 | F43: =$J$12+(C43*$J$10/$L$10) -> 11.835768 | G43: =IF(D43="","",($J$11-$H$7+D43)*$J$10/$H$12) -> 10.815409 | H43: =IF(E43="","",($J$11-$H$7+E43)*$J$10/$H$12) | I43: =$F$12+(C43*$J$10/$L$12) -> 2064.3956 | J43: =IF(D43="","",($J$11-$H$7+D43)*$J$10/$B$12) -> 1806.1733 | K43: =IF(E43="","",($J$11-$H$7+E43)*$J$10/$B$12)
B44: AMA1 | C44: 170 | D44: 5380 | F44: =$J$12+(C44*$J$10/$L$10) -> 12.035768 | G44: =IF(D44="","",($J$11-$H$7+D44)*$J$10/$H$12) -> 10.815409 | H44: =IF(E44="","",($J$11-$H$7+E44)*$J$10/$H$12) | I44: =$F$12+(C44*$J$10/$L$12) -> 2103.2844 | J44: =IF(D44="","",($J$11-$H$7+D44)*$J$10/$B$12) -> 1806.1733 | K44: =IF(E44="","",($J$11-$H$7+E44)*$J$10/$B$12)
B45: IAH3 | C45: 190 | D45: 5380 | F45: =$J$12+(C45*$J$10/$L$10) -> 12.435768 | G45: =IF(D45="","",($J$11-$H$7+D45)*$J$10/$H$12) -> 10.815409 | H45: =IF(E45="","",($J$11-$H$7+E45)*$J$10/$H$12) | I45: =$F$12+(C45*$J$10/$L$12) -> 2181.0622 | J45: =IF(D45="","",($J$11-$H$7+D45)*$J$10/$B$12) -> 1806.1733 | K45: =IF(E45="","",($J$11-$H$7+E45)*$J$10/$B$12) | L45: 13.2
B46: ABQ2 | C46: 160 | D46: 5380 | E46: 4280 | F46: =$J$12+(C46*$J$10/$L$10) -> 11.835768 | G46: =IF(D46="","",($J$11-$H$7+D46)*$J$10/$H$12) -> 10.815409 | H46: =IF(E46="","",($J$11-$H$7+E46)*$J$10/$H$12) -> 10.200639 | I46: =$F$12+(C46*$J$10/$L$12) -> 2064.3956 | J46: =IF(D46="","",($J$11-$H$7+D46)*$J$10/$B$12) -> 1806.1733 | K46: =IF(E46="","",($J$11-$H$7+E46)*$J$10/$B$12) -> 1703.5067 | L46: 12.7
A47: 美中二区 | B47: PSC2 | C47: 215 | D47: 6380 | F47: =$J$12+(C47*$J$10/$L$10) -> 12.935768 | G47: =IF(D47="","",($J$11-$H$7+D47)*$J$10/$H$12) -> 11.374291 | H47: =IF(E47="","",($J$11-$H$7+E47)*$J$10/$H$12) | I47: =$F$12+(C47*$J$10/$L$12) -> 2278.2844 | J47: =IF(D47="","",($J$11-$H$7+D47)*$J$10/$B$12) -> 1899.5067 | K47: =IF(E47="","",($J$11-$H$7+E47)*$J$10/$B$12) | L47: 13.2
B48: FTW1 | C48: 150 | D48: 5380 | F48: =$J$12+(C48*$J$10/$L$10) -> 11.635768 | G48: =IF(D48="","",($J$11-$H$7+D48)*$J$10/$H$12) -> 10.815409 | H48: =IF(E48="","",($J$11-$H$7+E48)*$J$10/$H$12) | I48: =$F$12+(C48*$J$10/$L$12) -> 2025.5067 | J48: =IF(D48="","",($J$11-$H$7+D48)*$J$10/$B$12) -> 1806.1733 | K48: =IF(E48="","",($J$11-$H$7+E48)*$J$10/$B$12) | L48: 12.7
B49: IND9 | C49: 190 | D49: 6380 | F49: =$J$12+(C49*$J$10/$L$10) -> 12.435768 | G49: =IF(D49="","",($J$11-$H$7+D49)*$J$10/$H$12) -> 11.374291 | H49: =IF(E49="","",($J$11-$H$7+E49)*$J$10/$H$12) | I49: =$F$12+(C49*$J$10/$L$12) -> 2181.0622 | J49: =IF(D49="","",($J$11-$H$7+D49)*$J$10/$B$12) -> 1899.5067 | K49: =IF(E49="","",($J$11-$H$7+E49)*$J$10/$B$12) | L49: 13.2
B50: MDW2 | C50: 190 | D50: 6380 | F50: =$J$12+(C50*$J$10/$L$10) -> 12.435768 | G50: =IF(D50="","",($J$11-$H$7+D50)*$J$10/$H$12) -> 11.374291 | H50: =IF(E50="","",($J$11-$H$7+E50)*$J$10/$H$12) | I50: =$F$12+(C50*$J$10/$L$12) -> 2181.0622 | J50: =IF(D50="","",($J$11-$H$7+D50)*$J$10/$B$12) -> 1899.5067 | K50: =IF(E50="","",($J$11-$H$7+E50)*$J$10/$B$12) | L50: 13.2
B51: MEM1 | C51: 190 | D51: 6380 | F51: =$J$12+(C51*$J$10/$L$10) -> 12.435768 | G51: =IF(D51="","",($J$11-$H$7+D51)*$J$10/$H$12) -> 11.374291 | H51: =IF(E51="","",($J$11-$H$7+E51)*$J$10/$H$12) | I51: =$F$12+(C51*$J$10/$L$12) -> 2181.0622 | J51: =IF(D51="","",($J$11-$H$7+D51)*$J$10/$B$12) -> 1899.5067 | K51: =IF(E51="","",($J$11-$H$7+E51)*$J$10/$B$12) | L51: 13.2
B52: MQJ1 | C52: 190 | D52: 6380 | F52: =$J$12+(C52*$J$10/$L$10) -> 12.435768 | G52: =IF(D52="","",($J$11-$H$7+D52)*$J$10/$H$12) -> 11.374291 | H52: =IF(E52="","",($J$11-$H$7+E52)*$J$10/$H$12) | I52: =$F$12+(C52*$J$10/$L$12) -> 2181.0622 | J52: =IF(D52="","",($J$11-$H$7+D52)*$J$10/$B$12) -> 1899.5067 | K52: =IF(E52="","",($J$11-$H$7+E52)*$J$10/$B$12) | L52: 13.2
A53: 美中 长途 | B53: FTW3 | C53: 180 | D53: 5880 | F53: =$J$12+(C53*$J$10/$L$10) -> 12.235768 | G53: =IF(D53="","",($J$11-$H$7+D53)*$J$10/$H$12) -> 11.09485 | H53: =IF(E53="","",($J$11-$H$7+E53)*$J$10/$H$12) | I53: =$F$12+(C53*$J$10/$L$12) -> 2142.1733 | J53: =IF(D53="","",($J$11-$H$7+D53)*$J$10/$B$12) -> 1852.84 | K53: =IF(E53="","",($J$11-$H$7+E53)*$J$10/$B$12)
B54: SAT4 | C54: 180 | D54: 5880 | F54: =$J$12+(C54*$J$10/$L$10) -> 12.235768 | G54: =IF(D54="","",($J$11-$H$7+D54)*$J$10/$H$12) -> 11.09485 | H54: =IF(E54="","",($J$11-$H$7+E54)*$J$10/$H$12) | I54: =$F$12+(C54*$J$10/$L$12) -> 2142.1733 | J54: =IF(D54="","",($J$11-$H$7+D54)*$J$10/$B$12) -> 1852.84 | K54: =IF(E54="","",($J$11-$H$7+E54)*$J$10/$B$12) | L54: 13.2
B55: SAT6 | C55: 180 | D55: 5880 | F55: =$J$12+(C55*$J$10/$L$10) -> 12.235768 | G55: =IF(D55="","",($J$11-$H$7+D55)*$J$10/$H$12) -> 11.09485 | H55: =IF(E55="","",($J$11-$H$7+E55)*$J$10/$H$12) | I55: =$F$12+(C55*$J$10/$L$12) -> 2142.1733 | J55: =IF(D55="","",($J$11-$H$7+D55)*$J$10/$B$12) -> 1852.84 | K55: =IF(E55="","",($J$11-$H$7+E55)*$J$10/$B$12)
B56: HOU8 | C56: 195 | D56: 5880 | F56: =$J$12+(C56*$J$10/$L$10) -> 12.535768 | G56: =IF(D56="","",($J$11-$H$7+D56)*$J$10/$H$12) -> 11.09485 | H56: =IF(E56="","",($J$11-$H$7+E56)*$J$10/$H$12) | I56: =$F$12+(C56*$J$10/$L$12) -> 2200.5067 | J56: =IF(D56="","",($J$11-$H$7+D56)*$J$10/$B$12) -> 1852.84 | K56: =IF(E56="","",($J$11-$H$7+E56)*$J$10/$B$12)
B57: SLC2 | C57: 130 | D57: 5880 | F57: =$J$12+(C57*$J$10/$L$10) -> 11.235768 | G57: =IF(D57="","",($J$11-$H$7+D57)*$J$10/$H$12) -> 11.09485 | H57: =IF(E57="","",($J$11-$H$7+E57)*$J$10/$H$12) | I57: =$F$12+(C57*$J$10/$L$12) -> 1947.7289 | J57: =IF(D57="","",($J$11-$H$7+D57)*$J$10/$B$12) -> 1852.84 | K57: =IF(E57="","",($J$11-$H$7+E57)*$J$10/$B$12)
B58: DEN2 | C58: 195 | D58: 5880 | F58: =$J$12+(C58*$J$10/$L$10) -> 12.535768 | G58: =IF(D58="","",($J$11-$H$7+D58)*$J$10/$H$12) -> 11.09485 | H58: =IF(E58="","",($J$11-$H$7+E58)*$J$10/$H$12) | I58: =$F$12+(C58*$J$10/$L$12) -> 2200.5067 | J58: =IF(D58="","",($J$11-$H$7+D58)*$J$10/$B$12) -> 1852.84 | K58: =IF(E58="","",($J$11-$H$7+E58)*$J$10/$B$12)
B59: DEN8 | C59: 195 | D59: 5880 | F59: =$J$12+(C59*$J$10/$L$10) -> 12.535768 | G59: =IF(D59="","",($J$11-$H$7+D59)*$J$10/$H$12) -> 11.09485 | H59: =IF(E59="","",($J$11-$H$7+E59)*$J$10/$H$12) | I59: =$F$12+(C59*$J$10/$L$12) -> 2200.5067 | J59: =IF(D59="","",($J$11-$H$7+D59)*$J$10/$B$12) -> 1852.84 | K59: =IF(E59="","",($J$11-$H$7+E59)*$J$10/$B$12)
B60: RNO4 | C60: 130 | D60: 5880 | F60: =$J$12+(C60*$J$10/$L$10) -> 11.235768 | G60: =IF(D60="","",($J$11-$H$7+D60)*$J$10/$H$12) -> 11.09485 | H60: =IF(E60="","",($J$11-$H$7+E60)*$J$10/$H$12) | I60: =$F$12+(C60*$J$10/$L$12) -> 1947.7289 | J60: =IF(D60="","",($J$11-$H$7+D60)*$J$10/$B$12) -> 1852.84 | K60: =IF(E60="","",($J$11-$H$7+E60)*$J$10/$B$12)
B61: ORD2 | C61: 195 | D61: 7280 | F61: =$J$12+(C61*$J$10/$L$10) -> 12.535768 | G61: =IF(D61="","",($J$11-$H$7+D61)*$J$10/$H$12) -> 11.877285 | H61: =IF(E61="","",($J$11-$H$7+E61)*$J$10/$H$12) | I61: =$F$12+(C61*$J$10/$L$12) -> 2200.5067 | J61: =IF(D61="","",($J$11-$H$7+D61)*$J$10/$B$12) -> 1983.5067 | K61: =IF(E61="","",($J$11-$H$7+E61)*$J$10/$B$12)
B62: FWA4 | C62: 190 | D62: 7280 | F62: =$J$12+(C62*$J$10/$L$10) -> 12.435768 | G62: =IF(D62="","",($J$11-$H$7+D62)*$J$10/$H$12) -> 11.877285 | H62: =IF(E62="","",($J$11-$H$7+E62)*$J$10/$H$12) | I62: =$F$12+(C62*$J$10/$L$12) -> 2181.0622 | J62: =IF(D62="","",($J$11-$H$7+D62)*$J$10/$B$12) -> 1983.5067 | K62: =IF(E62="","",($J$11-$H$7+E62)*$J$10/$B$12) | L62: 13.2
B63: RFD2 | C63: 220 | D63: 7280 | F63: =$J$12+(C63*$J$10/$L$10) -> 13.035768 | G63: =IF(D63="","",($J$11-$H$7+D63)*$J$10/$H$12) -> 11.877285 | H63: =IF(E63="","",($J$11-$H$7+E63)*$J$10/$H$12) | I63: =$F$12+(C63*$J$10/$L$12) -> 2297.7289 | J63: =IF(D63="","",($J$11-$H$7+D63)*$J$10/$B$12) -> 1983.5067 | K63: =IF(E63="","",($J$11-$H$7+E63)*$J$10/$B$12) | L63: 13.2
B64: STL3 | C64: 190 | D64: 7280 | F64: =$J$12+(C64*$J$10/$L$10) -> 12.435768 | G64: =IF(D64="","",($J$11-$H$7+D64)*$J$10/$H$12) -> 11.877285 | H64: =IF(E64="","",($J$11-$H$7+E64)*$J$10/$H$12) | I64: =$F$12+(C64*$J$10/$L$12) -> 2181.0622 | J64: =IF(D64="","",($J$11-$H$7+D64)*$J$10/$B$12) -> 1983.5067 | K64: =IF(E64="","",($J$11-$H$7+E64)*$J$10/$B$12)
B65: STL4 | C65: 190 | D65: 7280 | F65: =$J$12+(C65*$J$10/$L$10) -> 12.435768 | G65: =IF(D65="","",($J$11-$H$7+D65)*$J$10/$H$12) -> 11.877285 | H65: =IF(E65="","",($J$11-$H$7+E65)*$J$10/$H$12) | I65: =$F$12+(C65*$J$10/$L$12) -> 2181.0622 | J65: =IF(D65="","",($J$11-$H$7+D65)*$J$10/$B$12) -> 1983.5067 | K65: =IF(E65="","",($J$11-$H$7+E65)*$J$10/$B$12)
B66: IND2 | C66: 225 | D66: 7280 | F66: =$J$12+(C66*$J$10/$L$10) -> 13.135768 | G66: =IF(D66="","",($J$11-$H$7+D66)*$J$10/$H$12) -> 11.877285 | H66: =IF(E66="","",($J$11-$H$7+E66)*$J$10/$H$12) | I66: =$F$12+(C66*$J$10/$L$12) -> 2317.1733 | J66: =IF(D66="","",($J$11-$H$7+D66)*$J$10/$B$12) -> 1983.5067 | K66: =IF(E66="","",($J$11-$H$7+E66)*$J$10/$B$12)
B67: IND4 | C67: 225 | D67: 7280 | F67: =$J$12+(C67*$J$10/$L$10) -> 13.135768 | G67: =IF(D67="","",($J$11-$H$7+D67)*$J$10/$H$12) -> 11.877285 | H67: =IF(E67="","",($J$11-$H$7+E67)*$J$10/$H$12) | I67: =$F$12+(C67*$J$10/$L$12) -> 2317.1733 | J67: =IF(D67="","",($J$11-$H$7+D67)*$J$10/$B$12) -> 1983.5067 | K67: =IF(E67="","",($J$11-$H$7+E67)*$J$10/$B$12)
B68: MEM6 | C68: 190 | D68: 7280 | F68: =$J$12+(C68*$J$10/$L$10) -> 12.435768 | G68: =IF(D68="","",($J$11-$H$7+D68)*$J$10/$H$12) -> 11.877285 | H68: =IF(E68="","",($J$11-$H$7+E68)*$J$10/$H$12) | I68: =$F$12+(C68*$J$10/$L$12) -> 2181.0622 | J68: =IF(D68="","",($J$11-$H$7+D68)*$J$10/$B$12) -> 1983.5067 | K68: =IF(E68="","",($J$11-$H$7+E68)*$J$10/$B$12)
B69: BNA6 | C69: 235 | D69: 7280 | F69: =$J$12+(C69*$J$10/$L$10) -> 13.335768 | G69: =IF(D69="","",($J$11-$H$7+D69)*$J$10/$H$12) -> 11.877285 | H69: =IF(E69="","",($J$11-$H$7+E69)*$J$10/$H$12) | I69: =$F$12+(C69*$J$10/$L$12) -> 2356.0622 | J69: =IF(D69="","",($J$11-$H$7+D69)*$J$10/$B$12) -> 1983.5067 | K69: =IF(E69="","",($J$11-$H$7+E69)*$J$10/$B$12) | L69: 14.4
B70: OKC2 | C70: 215 | D70: 7280 | F70: =$J$12+(C70*$J$10/$L$10) -> 12.935768 | G70: =IF(D70="","",($J$11-$H$7+D70)*$J$10/$H$12) -> 11.877285 | H70: =IF(E70="","",($J$11-$H$7+E70)*$J$10/$H$12) | I70: =$F$12+(C70*$J$10/$L$12) -> 2278.2844 | J70: =IF(D70="","",($J$11-$H$7+D70)*$J$10/$B$12) -> 1983.5067 | K70: =IF(E70="","",($J$11-$H$7+E70)*$J$10/$B$12)
B71: LIT2 | C71: 235 | D71: 7280 | F71: =$J$12+(C71*$J$10/$L$10) -> 13.335768 | G71: =IF(D71="","",($J$11-$H$7+D71)*$J$10/$H$12) -> 11.877285 | H71: =IF(E71="","",($J$11-$H$7+E71)*$J$10/$H$12) | I71: =$F$12+(C71*$J$10/$L$12) -> 2356.0622 | J71: =IF(D71="","",($J$11-$H$7+D71)*$J$10/$B$12) -> 1983.5067 | K71: =IF(E71="","",($J$11-$H$7+E71)*$J$10/$B$12)
B72: JVL1 | C72: 235 | D72: 7280 | F72: =$J$12+(C72*$J$10/$L$10) -> 13.335768 | G72: =IF(D72="","",($J$11-$H$7+D72)*$J$10/$H$12) -> 11.877285 | H72: =IF(E72="","",($J$11-$H$7+E72)*$J$10/$H$12) | I72: =$F$12+(C72*$J$10/$L$12) -> 2356.0622 | J72: =IF(D72="","",($J$11-$H$7+D72)*$J$10/$B$12) -> 1983.5067 | K72: =IF(E72="","",($J$11-$H$7+E72)*$J$10/$B$12)
A73: 美东9区 | B73: CLT2 | C73: 255 | D73: 7980 | F73: =$J$12+(C73*$J$10/$L$10) -> 13.735768 | G73: =IF(D73="","",($J$11-$H$7+D73)*$J$10/$H$12) -> 12.268503 | H73: =IF(E73="","",($J$11-$H$7+E73)*$J$10/$H$12) | I73: =$F$12+(C73*$J$10/$L$12) -> 2433.84 | J73: =IF(D73="","",($J$11-$H$7+D73)*$J$10/$B$12) -> 2048.84 | K73: =IF(E73="","",($J$11-$H$7+E73)*$J$10/$B$12) | L73: 13.9
B74: MCO2 | C74: 265 | D74: 7980 | F74: =$J$12+(C74*$J$10/$L$10) -> 13.935768 | G74: =IF(D74="","",($J$11-$H$7+D74)*$J$10/$H$12) -> 12.268503 | H74: =IF(E74="","",($J$11-$H$7+E74)*$J$10/$H$12) | I74: =$F$12+(C74*$J$10/$L$12) -> 2472.7289 | J74: =IF(D74="","",($J$11-$H$7+D74)*$J$10/$B$12) -> 2048.84 | K74: =IF(E74="","",($J$11-$H$7+E74)*$J$10/$B$12)
B75: TPA2 | C75: 265 | D75: 7980 | F75: =$J$12+(C75*$J$10/$L$10) -> 13.935768 | G75: =IF(D75="","",($J$11-$H$7+D75)*$J$10/$H$12) -> 12.268503 | H75: =IF(E75="","",($J$11-$H$7+E75)*$J$10/$H$12) | I75: =$F$12+(C75*$J$10/$L$12) -> 2472.7289 | J75: =IF(D75="","",($J$11-$H$7+D75)*$J$10/$B$12) -> 2048.84 | K75: =IF(E75="","",($J$11-$H$7+E75)*$J$10/$B$12) | L75: 13.9
B76: TPA3 | C76: 265 | D76: 7980 | F76: =$J$12+(C76*$J$10/$L$10) -> 13.935768 | G76: =IF(D76="","",($J$11-$H$7+D76)*$J$10/$H$12) -> 12.268503 | H76: =IF(E76="","",($J$11-$H$7+E76)*$J$10/$H$12) | I76: =$F$12+(C76*$J$10/$L$12) -> 2472.7289 | J76: =IF(D76="","",($J$11-$H$7+D76)*$J$10/$B$12) -> 2048.84 | K76: =IF(E76="","",($J$11-$H$7+E76)*$J$10/$B$12) | L76: 13.9
B77: CMH2 | C77: 230 | D77: 7980 | F77: =$J$12+(C77*$J$10/$L$10) -> 13.235768 | G77: =IF(D77="","",($J$11-$H$7+D77)*$J$10/$H$12) -> 12.268503 | H77: =IF(E77="","",($J$11-$H$7+E77)*$J$10/$H$12) | I77: =$F$12+(C77*$J$10/$L$12) -> 2336.6178 | J77: =IF(D77="","",($J$11-$H$7+D77)*$J$10/$B$12) -> 2048.84 | K77: =IF(E77="","",($J$11-$H$7+E77)*$J$10/$B$12)
B78: CMH3 | C78: 230 | D78: 7980 | F78: =$J$12+(C78*$J$10/$L$10) -> 13.235768 | G78: =IF(D78="","",($J$11-$H$7+D78)*$J$10/$H$12) -> 12.268503 | H78: =IF(E78="","",($J$11-$H$7+E78)*$J$10/$H$12) | I78: =$F$12+(C78*$J$10/$L$12) -> 2336.6178 | J78: =IF(D78="","",($J$11-$H$7+D78)*$J$10/$B$12) -> 2048.84 | K78: =IF(E78="","",($J$11-$H$7+E78)*$J$10/$B$12)
B79: DET1 | C79: 250 | D79: 7980 | F79: =$J$12+(C79*$J$10/$L$10) -> 13.635768 | G79: =IF(D79="","",($J$11-$H$7+D79)*$J$10/$H$12) -> 12.268503 | H79: =IF(E79="","",($J$11-$H$7+E79)*$J$10/$H$12) | I79: =$F$12+(C79*$J$10/$L$12) -> 2414.3956 | J79: =IF(D79="","",($J$11-$H$7+D79)*$J$10/$B$12) -> 2048.84 | K79: =IF(E79="","",($J$11-$H$7+E79)*$J$10/$B$12)
B80: DET2 | C80: 250 | D80: 7980 | F80: =$J$12+(C80*$J$10/$L$10) -> 13.635768 | G80: =IF(D80="","",($J$11-$H$7+D80)*$J$10/$H$12) -> 12.268503 | H80: =IF(E80="","",($J$11-$H$7+E80)*$J$10/$H$12) | I80: =$F$12+(C80*$J$10/$L$12) -> 2414.3956 | J80: =IF(D80="","",($J$11-$H$7+D80)*$J$10/$B$12) -> 2048.84 | K80: =IF(E80="","",($J$11-$H$7+E80)*$J$10/$B$12)
B81: AKR1 | C81: 270 | D81: 7980 | F81: =$J$12+(C81*$J$10/$L$10) -> 14.035768 | G81: =IF(D81="","",($J$11-$H$7+D81)*$J$10/$H$12) -> 12.268503 | H81: =IF(E81="","",($J$11-$H$7+E81)*$J$10/$H$12) | I81: =$F$12+(C81*$J$10/$L$12) -> 2492.1733 | J81: =IF(D81="","",($J$11-$H$7+D81)*$J$10/$B$12) -> 2048.84 | K81: =IF(E81="","",($J$11-$H$7+E81)*$J$10/$B$12)
B82: LAN2 | C82: 250 | D82: 7980 | F82: =$J$12+(C82*$J$10/$L$10) -> 13.635768 | G82: =IF(D82="","",($J$11-$H$7+D82)*$J$10/$H$12) -> 12.268503 | H82: =IF(E82="","",($J$11-$H$7+E82)*$J$10/$H$12) | I82: =$F$12+(C82*$J$10/$L$12) -> 2414.3956 | J82: =IF(D82="","",($J$11-$H$7+D82)*$J$10/$B$12) -> 2048.84 | K82: =IF(E82="","",($J$11-$H$7+E82)*$J$10/$B$12)
B83: RYY2 | C83: 250 | D83: 7980 | F83: =$J$12+(C83*$J$10/$L$10) -> 13.635768 | G83: =IF(D83="","",($J$11-$H$7+D83)*$J$10/$H$12) -> 12.268503 | H83: =IF(E83="","",($J$11-$H$7+E83)*$J$10/$H$12) | I83: =$F$12+(C83*$J$10/$L$12) -> 2414.3956 | J83: =IF(D83="","",($J$11-$H$7+D83)*$J$10/$B$12) -> 2048.84 | K83: =IF(E83="","",($J$11-$H$7+E83)*$J$10/$B$12)
B84: JAX3 | C84: 295 | D84: 7980 | F84: =$J$12+(C84*$J$10/$L$10) -> 14.535768 | G84: =IF(D84="","",($J$11-$H$7+D84)*$J$10/$H$12) -> 12.268503 | H84: =IF(E84="","",($J$11-$H$7+E84)*$J$10/$H$12) | I84: =$F$12+(C84*$J$10/$L$12) -> 2589.3956 | J84: =IF(D84="","",($J$11-$H$7+D84)*$J$10/$B$12) -> 2048.84 | K84: =IF(E84="","",($J$11-$H$7+E84)*$J$10/$B$12)
B85: PBI3 | C85: 295 | D85: 7980 | F85: =$J$12+(C85*$J$10/$L$10) -> 14.535768 | G85: =IF(D85="","",($J$11-$H$7+D85)*$J$10/$H$12) -> 12.268503 | H85: =IF(E85="","",($J$11-$H$7+E85)*$J$10/$H$12) | I85: =$F$12+(C85*$J$10/$L$12) -> 2589.3956 | J85: =IF(D85="","",($J$11-$H$7+D85)*$J$10/$B$12) -> 2048.84 | K85: =IF(E85="","",($J$11-$H$7+E85)*$J$10/$B$12)
B86: RDU2 | C86: 280 | D86: 7980 | F86: =$J$12+(C86*$J$10/$L$10) -> 14.235768 | G86: =IF(D86="","",($J$11-$H$7+D86)*$J$10/$H$12) -> 12.268503 | H86: =IF(E86="","",($J$11-$H$7+E86)*$J$10/$H$12) | I86: =$F$12+(C86*$J$10/$L$12) -> 2531.0622 | J86: =IF(D86="","",($J$11-$H$7+D86)*$J$10/$B$12) -> 2048.84 | K86: =IF(E86="","",($J$11-$H$7+E86)*$J$10/$B$12) | L86: 13.9
A87: 美东10区 | B87: ORF2 | C87: 290 | D87: 8680 | F87: =$J$12+(C87*$J$10/$L$10) -> 14.435768 | G87: =IF(D87="","",($J$11-$H$7+D87)*$J$10/$H$12) -> 12.659721 | H87: =IF(E87="","",($J$11-$H$7+E87)*$J$10/$H$12) | I87: =$F$12+(C87*$J$10/$L$12) -> 2569.9511 | J87: =IF(D87="","",($J$11-$H$7+D87)*$J$10/$B$12) -> 2114.1733 | K87: =IF(E87="","",($J$11-$H$7+E87)*$J$10/$B$12) | L87: 14.4
B88: CHO1 | C88: 290 | D88: 8680 | F88: =$J$12+(C88*$J$10/$L$10) -> 14.435768 | G88: =IF(D88="","",($J$11-$H$7+D88)*$J$10/$H$12) -> 12.659721 | H88: =IF(E88="","",($J$11-$H$7+E88)*$J$10/$H$12) | I88: =$F$12+(C88*$J$10/$L$12) -> 2569.9511 | J88: =IF(D88="","",($J$11-$H$7+D88)*$J$10/$B$12) -> 2114.1733 | K88: =IF(E88="","",($J$11-$H$7+E88)*$J$10/$B$12)
B89: RMN3 | C89: 285 | D89: 8680 | F89: =$J$12+(C89*$J$10/$L$10) -> 14.335768 | G89: =IF(D89="","",($J$11-$H$7+D89)*$J$10/$H$12) -> 12.659721 | H89: =IF(E89="","",($J$11-$H$7+E89)*$J$10/$H$12) | I89: =$F$12+(C89*$J$10/$L$12) -> 2550.5067 | J89: =IF(D89="","",($J$11-$H$7+D89)*$J$10/$B$12) -> 2114.1733 | K89: =IF(E89="","",($J$11-$H$7+E89)*$J$10/$B$12) | L89: 14.4
B90: DCA6 | C90: 285 | D90: 8680 | F90: =$J$12+(C90*$J$10/$L$10) -> 14.335768 | G90: =IF(D90="","",($J$11-$H$7+D90)*$J$10/$H$12) -> 12.659721 | H90: =IF(E90="","",($J$11-$H$7+E90)*$J$10/$H$12) | I90: =$F$12+(C90*$J$10/$L$12) -> 2550.5067 | J90: =IF(D90="","",($J$11-$H$7+D90)*$J$10/$B$12) -> 2114.1733 | K90: =IF(E90="","",($J$11-$H$7+E90)*$J$10/$B$12)
B91: TEB3 | C91: 290 | D91: 8680 | F91: =$J$12+(C91*$J$10/$L$10) -> 14.435768 | G91: =IF(D91="","",($J$11-$H$7+D91)*$J$10/$H$12) -> 12.659721 | H91: =IF(E91="","",($J$11-$H$7+E91)*$J$10/$H$12) | I91: =$F$12+(C91*$J$10/$L$12) -> 2569.9511 | J91: =IF(D91="","",($J$11-$H$7+D91)*$J$10/$B$12) -> 2114.1733 | K91: =IF(E91="","",($J$11-$H$7+E91)*$J$10/$B$12) | L91: 14.4
B92: TEB4 | C92: 290 | D92: 8680 | F92: =$J$12+(C92*$J$10/$L$10) -> 14.435768 | G92: =IF(D92="","",($J$11-$H$7+D92)*$J$10/$H$12) -> 12.659721 | H92: =IF(E92="","",($J$11-$H$7+E92)*$J$10/$H$12) | I92: =$F$12+(C92*$J$10/$L$12) -> 2569.9511 | J92: =IF(D92="","",($J$11-$H$7+D92)*$J$10/$B$12) -> 2114.1733 | K92: =IF(E92="","",($J$11-$H$7+E92)*$J$10/$B$12)
B93: TEB6 | C93: 295 | D93: 8680 | F93: =$J$12+(C93*$J$10/$L$10) -> 14.535768 | G93: =IF(D93="","",($J$11-$H$7+D93)*$J$10/$H$12) -> 12.659721 | H93: =IF(E93="","",($J$11-$H$7+E93)*$J$10/$H$12) | I93: =$F$12+(C93*$J$10/$L$12) -> 2589.3956 | J93: =IF(D93="","",($J$11-$H$7+D93)*$J$10/$B$12) -> 2114.1733 | K93: =IF(E93="","",($J$11-$H$7+E93)*$J$10/$B$12)
B94: TEB9 | C94: 295 | D94: 8680 | F94: =$J$12+(C94*$J$10/$L$10) -> 14.535768 | G94: =IF(D94="","",($J$11-$H$7+D94)*$J$10/$H$12) -> 12.659721 | H94: =IF(E94="","",($J$11-$H$7+E94)*$J$10/$H$12) | I94: =$F$12+(C94*$J$10/$L$12) -> 2589.3956 | J94: =IF(D94="","",($J$11-$H$7+D94)*$J$10/$B$12) -> 2114.1733 | K94: =IF(E94="","",($J$11-$H$7+E94)*$J$10/$B$12) | L94: 14.4
B95: ACY2 | C95: 300 | D95: 8680 | F95: =$J$12+(C95*$J$10/$L$10) -> 14.635768 | G95: =IF(D95="","",($J$11-$H$7+D95)*$J$10/$H$12) -> 12.659721 | H95: =IF(E95="","",($J$11-$H$7+E95)*$J$10/$H$12) | I95: =$F$12+(C95*$J$10/$L$12) -> 2608.84 | J95: =IF(D95="","",($J$11-$H$7+D95)*$J$10/$B$12) -> 2114.1733 | K95: =IF(E95="","",($J$11-$H$7+E95)*$J$10/$B$12)
B96: ABE4 | C96: 290 | D96: 8680 | F96: =$J$12+(C96*$J$10/$L$10) -> 14.435768 | G96: =IF(D96="","",($J$11-$H$7+D96)*$J$10/$H$12) -> 12.659721 | H96: =IF(E96="","",($J$11-$H$7+E96)*$J$10/$H$12) | I96: =$F$12+(C96*$J$10/$L$12) -> 2569.9511 | J96: =IF(D96="","",($J$11-$H$7+D96)*$J$10/$B$12) -> 2114.1733 | K96: =IF(E96="","",($J$11-$H$7+E96)*$J$10/$B$12)
B97: ABE8 | C97: 275 | D97: 8680 | F97: =$J$12+(C97*$J$10/$L$10) -> 14.135768 | G97: =IF(D97="","",($J$11-$H$7+D97)*$J$10/$H$12) -> 12.659721 | H97: =IF(E97="","",($J$11-$H$7+E97)*$J$10/$H$12) | I97: =$F$12+(C97*$J$10/$L$12) -> 2511.6178 | J97: =IF(D97="","",($J$11-$H$7+D97)*$J$10/$B$12) -> 2114.1733 | K97: =IF(E97="","",($J$11-$H$7+E97)*$J$10/$B$12) | L97: 14.4
B98: AVP1 | C98: 295 | D98: 8680 | F98: =$J$12+(C98*$J$10/$L$10) -> 14.535768 | G98: =IF(D98="","",($J$11-$H$7+D98)*$J$10/$H$12) -> 12.659721 | H98: =IF(E98="","",($J$11-$H$7+E98)*$J$10/$H$12) | I98: =$F$12+(C98*$J$10/$L$12) -> 2589.3956 | J98: =IF(D98="","",($J$11-$H$7+D98)*$J$10/$B$12) -> 2114.1733 | K98: =IF(E98="","",($J$11-$H$7+E98)*$J$10/$B$12) | L98: 14.4
B99: AVP3 | C99: 290 | D99: 8680 | F99: =$J$12+(C99*$J$10/$L$10) -> 14.435768 | G99: =IF(D99="","",($J$11-$H$7+D99)*$J$10/$H$12) -> 12.659721 | H99: =IF(E99="","",($J$11-$H$7+E99)*$J$10/$H$12) | I99: =$F$12+(C99*$J$10/$L$12) -> 2569.9511 | J99: =IF(D99="","",($J$11-$H$7+D99)*$J$10/$B$12) -> 2114.1733 | K99: =IF(E99="","",($J$11-$H$7+E99)*$J$10/$B$12) | L99: 14.4
B100: PIT2 | C100: 290 | D100: 8680 | F100: =$J$12+(C100*$J$10/$L$10) -> 14.435768 | G100: =IF(D100="","",($J$11-$H$7+D100)*$J$10/$H$12) -> 12.659721 | H100: =IF(E100="","",($J$11-$H$7+E100)*$J$10/$H$12) | I100: =$F$12+(C100*$J$10/$L$12) -> 2569.9511 | J100: =IF(D100="","",($J$11-$H$7+D100)*$J$10/$B$12) -> 2114.1733 | K100: =IF(E100="","",($J$11-$H$7+E100)*$J$10/$B$12)
...

Sheet 美森432
A1: 应付 | B1: 上海——LB | F1: 费用类型 | G1: 币种 | H1: 单价 | I1: 数量 | J1: 备注 | K1: 统计
B2: 起运港 | C2: 拖车+报关 | F2: 装柜费 | G2: RMB | H2: 500 | I2: 1
F3: 拖车费 | G3: RMB | H3: 9000 | I3: 1
F4: 报关费 | G4: RMB | H4: 1800 | I4: 1
F5: 港杂费RMB部分 | G5: RMB | H5: 3000 | I5: 1
F6: 海运费（变动） | G6: USD | H6: 9104 | I6: 1
B7: 目的港 | C7: 提柜+拆柜 | F7: 提拆一口价 | G7: USD | H7: 1480 | I7: 1
C8: 清关+缴税 | F8: 清关费 | G8: USD | I8: 1
F9: 税金 | G9: USD | H9: 1800 | I9: 1 | L9: 每板KG
A10: 上海-LB | B10: 人民币应付 | G10: RMB | H10: =SUM(H2:H5) -> 14300 | I10: 汇率 | J10: 7 | K10: =H10/J10 -> 2042.8571 | L10: 350
A11: 报价：2025/03/16 | B11: 含税KG/CBM | G11: USD | H11: =SUM(H6:H9) -> 12384 | I11: 合计 | J11: =H11+K10 -> 14426.857 | K11: =J11*J10 -> 100988 | L11: CBM
A12: CBM标准 | B12: 75 | E12: CBM计费标准 | F12: =K11/B12 -> 1346.5067 | G12: KG标准 | H12: 12525 | I12: KG计费标准 | J12: =F12/167 -> 8.0629142 | L12: 1.8
B13: 派送费 | C13: 美金/板 | D13: 组合一口价 | E13: 整柜一口价 | F13: 拆送KG含税 | G13: 组合KG | H13: 直送KG | I13: 拆送CBM含税 | J13: 组合CBM | K13: 直送CBM | L13: 直客报价101KG+
A14: 美西 一区 | B14: ONT8 | C14: 30 | D14: 1980 | E14: 1430 | F14: =$J$12+(C14*$J$10/$L$10) -> 8.6629142 | G14: =IF(D14="","",($J$11-$H$7+D14)*$J$10/$H$12) -> 8.3423553 | H14: =IF(E14="","",($J$11-$H$7+E14)*$J$10/$H$12) -> 8.0349701 | I14: =$F$12+(C14*$J$10/$L$12) -> 1463.1733 | J14: =IF(D14="","",($J$11-$H$7+D14)*$J$10/$B$12) -> 1393.1733 | K14: =IF(E14="","",($J$11-$H$7+E14)*$J$10/$B$12) -> 1341.84 | L14: 9.8
B15: LGB8 | C15: 30 | D15: 1980 | E15: 1430 | F15: =$J$12+(C15*$J$10/$L$10) -> 8.6629142 | G15: =IF(D15="","",($J$11-$H$7+D15)*$J$10/$H$12) -> 8.3423553 | H15: =IF(E15="","",($J$11-$H$7+E15)*$J$10/$H$12) -> 8.0349701 | I15: =$F$12+(C15*$J$10/$L$12) -> 1463.1733 | J15: =IF(D15="","",($J$11-$H$7+D15)*$J$10/$B$12) -> 1393.1733 | K15: =IF(E15="","",($J$11-$H$7+E15)*$J$10/$B$12) -> 1341.84 | L15: 9.8
B16: SBD1 | C16: 35 | D16: 1980 | E16: 1430 | F16: =$J$12+(C16*$J$10/$L$10) -> 8.7629142 | G16: =IF(D16="","",($J$11-$H$7+D16)*$J$10/$H$12) -> 8.3423553 | H16: =IF(E16="","",($J$11-$H$7+E16)*$J$10/$H$12) -> 8.0349701 | I16: =$F$12+(C16*$J$10/$L$12) -> 1482.6178 | J16: =IF(D16="","",($J$11-$H$7+D16)*$J$10/$B$12) -> 1393.1733 | K16: =IF(E16="","",($J$11-$H$7+E16)*$J$10/$B$12) -> 1341.84 | L16: 9.8
B17: LAX9 | C17: 30 | D17: 1980 | E17: 1430 | F17: =$J$12+(C17*$J$10/$L$10) -> 8.6629142 | G17: =IF(D17="","",($J$11-$H$7+D17)*$J$10/$H$12) -> 8.3423553 | H17: =IF(E17="","",($J$11-$H$7+E17)*$J$10/$H$12) -> 8.0349701 | I17: =$F$12+(C17*$J$10/$L$12) -> 1463.1733 | J17: =IF(D17="","",($J$11-$H$7+D17)*$J$10/$B$12) -> 1393.1733 | K17: =IF(E17="","",($J$11-$H$7+E17)*$J$10/$B$12) -> 1341.84 | L17: 9.8
A18: 美西 二区 | B18: SMF3 | C18: 70 | D18: 2980 | E18: 2730 | F18: =$J$12+(C18*$J$10/$L$10) -> 9.4629142 | G18: =IF(D18="","",($J$11-$H$7+D18)*$J$10/$H$12) -> 8.9012375 | H18: =IF(E18="","",($J$11-$H$7+E18)*$J$10/$H$12) -> 8.761517 | I18: =$F$12+(C18*$J$10/$L$12) -> 1618.7289 | J18: =IF(D18="","",($J$11-$H$7+D18)*$J$10/$B$12) -> 1486.5067 | K18: =IF(E18="","",($J$11-$H$7+E18)*$J$10/$B$12) -> 1463.1733 | L18: 10.6
B19: SCK4 | C19: 70 | D19: 2980 | E19: 2730 | F19: =$J$12+(C19*$J$10/$L$10) -> 9.4629142 | G19: =IF(D19="","",($J$11-$H$7+D19)*$J$10/$H$12) -> 8.9012375 | H19: =IF(E19="","",($J$11-$H$7+E19)*$J$10/$H$12) -> 8.761517 | I19: =$F$12+(C19*$J$10/$L$12) -> 1618.7289 | J19: =IF(D19="","",($J$11-$H$7+D19)*$J$10/$B$12) -> 1486.5067 | K19: =IF(E19="","",($J$11-$H$7+E19)*$J$10/$B$12) -> 1463.1733 | L19: 10.6
B20: GYR2 | C20: 70 | D20: 2980 | E20: 2530 | F20: =$J$12+(C20*$J$10/$L$10) -> 9.4629142 | G20: =IF(D20="","",($J$11-$H$7+D20)*$J$10/$H$12) -> 8.9012375 | H20: =IF(E20="","",($J$11-$H$7+E20)*$J$10/$H$12) -> 8.6497405 | I20: =$F$12+(C20*$J$10/$L$12) -> 1618.7289 | J20: =IF(D20="","",($J$11-$H$7+D20)*$J$10/$B$12) -> 1486.5067 | K20: =IF(E20="","",($J$11-$H$7+E20)*$J$10/$B$12) -> 1444.5067 | L20: 10.6
B21: GYR3 | C21: 70 | D21: 2980 | E21: 2530 | F21: =$J$12+(C21*$J$10/$L$10) -> 9.4629142 | G21: =IF(D21="","",($J$11-$H$7+D21)*$J$10/$H$12) -> 8.9012375 | H21: =IF(E21="","",($J$11-$H$7+E21)*$J$10/$H$12) -> 8.6497405 | I21: =$F$12+(C21*$J$10/$L$12) -> 1618.7289 | J21: =IF(D21="","",($J$11-$H$7+D21)*$J$10/$B$12) -> 1486.5067 | K21: =IF(E21="","",($J$11-$H$7+E21)*$J$10/$B$12) -> 1444.5067 | L21: 10.6
B22: LAS1 | C22: 70 | D22: 2980 | E22: 2430 | F22: =$J$12+(C22*$J$10/$L$10) -> 9.4629142 | G22: =IF(D22="","",($J$11-$H$7+D22)*$J$10/$H$12) -> 8.9012375 | H22: =IF(E22="","",($J$11-$H$7+E22)*$J$10/$H$12) -> 8.5938523 | I22: =$F$12+(C22*$J$10/$L$12) -> 1618.7289 | J22: =IF(D22="","",($J$11-$H$7+D22)*$J$10/$B$12) -> 1486.5067 | K22: =IF(E22="","",($J$11-$H$7+E22)*$J$10/$B$12) -> 1435.1733 | L22: 10.6
B23: VGT2 | C23: 70 | D23: 2980 | E23: 2430 | F23: =$J$12+(C23*$J$10/$L$10) -> 9.4629142 | G23: =IF(D23="","",($J$11-$H$7+D23)*$J$10/$H$12) -> 8.9012375 | H23: =IF(E23="","",($J$11-$H$7+E23)*$J$10/$H$12) -> 8.5938523 | I23: =$F$12+(C23*$J$10/$L$12) -> 1618.7289 | J23: =IF(D23="","",($J$11-$H$7+D23)*$J$10/$B$12) -> 1486.5067 | K23: =IF(E23="","",($J$11-$H$7+E23)*$J$10/$B$12) -> 1435.1733 | L23: 10.6
A24: 美西 三区 | B24: POC1 | C24: 55 | D24: 2180 | E24: 1430 | F24: =$J$12+(C24*$J$10/$L$10) -> 9.1629142 | G24: =IF(D24="","",($J$11-$H$7+D24)*$J$10/$H$12) -> 8.4541317 | H24: =IF(E24="","",($J$11-$H$7+E24)*$J$10/$H$12) -> 8.0349701 | I24: =$F$12+(C24*$J$10/$L$12) -> 1560.3956 | J24: =IF(D24="","",($J$11-$H$7+D24)*$J$10/$B$12) -> 1411.84 | K24: =IF(E24="","",($J$11-$H$7+E24)*$J$10/$B$12) -> 1341.84 | L24: 9.8
B25: POC2 | C25: 55 | D25: 2180 | F25: =$J$12+(C25*$J$10/$L$10) -> 9.1629142 | G25: =IF(D25="","",($J$11-$H$7+D25)*$J$10/$H$12) -> 8.4541317 | H25: =IF(E25="","",($J$11-$H$7+E25)*$J$10/$H$12) | I25: =$F$12+(C25*$J$10/$L$12) -> 1560.3956 | J25: =IF(D25="","",($J$11-$H$7+D25)*$J$10/$B$12) -> 1411.84 | K25: =IF(E25="","",($J$11-$H$7+E25)*$J$10/$B$12) | L25: 9.8
B26: POC3 | C26: 55 | D26: 2180 | E26: 1430 | F26: =$J$12+(C26*$J$10/$L$10) -> 9.1629142 | G26: =IF(D26="","",($J$11-$H$7+D26)*$J$10/$H$12) -> 8.4541317 | H26: =IF(E26="","",($J$11-$H$7+E26)*$J$10/$H$12) -> 8.0349701 | I26: =$F$12+(C26*$J$10/$L$12) -> 1560.3956 | J26: =IF(D26="","",($J$11-$H$7+D26)*$J$10/$B$12) -> 1411.84 | K26: =IF(E26="","",($J$11-$H$7+E26)*$J$10/$B$12) -> 1341.84 | L26: 9.8
B27: SNA4 | C27: 50 | D27: 2180 | E27: 1480 | F27: =$J$12+(C27*$J$10/$L$10) -> 9.0629142 | G27: =IF(D27="","",($J$11-$H$7+D27)*$J$10/$H$12) -> 8.4541317 | H27: =IF(E27="","",($J$11-$H$7+E27)*$J$10/$H$12) -> 8.0629142 | I27: =$F$12+(C27*$J$10/$L$12) -> 1540.9511 | J27: =IF(D27="","",($J$11-$H$7+D27)*$J$10/$B$12) -> 1411.84 | K27: =IF(E27="","",($J$11-$H$7+E27)*$J$10/$B$12) -> 1346.5067
B28: KRB1 | C28: 50 | D28: 2180 | F28: =$J$12+(C28*$J$10/$L$10) -> 9.0629142 | G28: =IF(D28="","",($J$11-$H$7+D28)*$J$10/$H$12) -> 8.4541317 | H28: =IF(E28="","",($J$11-$H$7+E28)*$J$10/$H$12) | I28: =$F$12+(C28*$J$10/$L$12) -> 1540.9511 | J28: =IF(D28="","",($J$11-$H$7+D28)*$J$10/$B$12) -> 1411.84 | K28: =IF(E28="","",($J$11-$H$7+E28)*$J$10/$B$12)
B29: KRB4 | C29: 50 | D29: 2180 | F29: =$J$12+(C29*$J$10/$L$10) -> 9.0629142 | G29: =IF(D29="","",($J$11-$H$7+D29)*$J$10/$H$12) -> 8.4541317 | H29: =IF(E29="","",($J$11-$H$7+E29)*$J$10/$H$12) | I29: =$F$12+(C29*$J$10/$L$12) -> 1540.9511 | J29: =IF(D29="","",($J$11-$H$7+D29)*$J$10/$B$12) -> 1411.84 | K29: =IF(E29="","",($J$11-$H$7+E29)*$J$10/$B$12)
B30: IUSJ | C30: 65 | D30: 2180 | E30: 1580 | F30: =$J$12+(C30*$J$10/$L$10) -> 9.3629142 | G30: =IF(D30="","",($J$11-$H$7+D30)*$J$10/$H$12) -> 8.4541317 | H30: =IF(E30="","",($J$11-$H$7+E30)*$J$10/$H$12) -> 8.1188024 | I30: =$F$12+(C30*$J$10/$L$12) -> 1599.2844 | J30: =IF(D30="","",($J$11-$H$7+D30)*$J$10/$B$12) -> 1411.84 | K30: =IF(E30="","",($J$11-$H$7+E30)*$J$10/$B$12) -> 1355.84 | L30: 10.3
B31: IUSP | C31: 65 | D31: 2180 | E31: 1580 | F31: =$J$12+(C31*$J$10/$L$10) -> 9.3629142 | G31: =IF(D31="","",($J$11-$H$7+D31)*$J$10/$H$12) -> 8.4541317 | H31: =IF(E31="","",($J$11-$H$7+E31)*$J$10/$H$12) -> 8.1188024 | I31: =$F$12+(C31*$J$10/$L$12) -> 1599.2844 | J31: =IF(D31="","",($J$11-$H$7+D31)*$J$10/$B$12) -> 1411.84 | K31: =IF(E31="","",($J$11-$H$7+E31)*$J$10/$B$12) -> 1355.84 | L31: 10.3
B32: IUSQ | C32: 65 | D32: 2180 | E32: 1580 | F32: =$J$12+(C32*$J$10/$L$10) -> 9.3629142 | G32: =IF(D32="","",($J$11-$H$7+D32)*$J$10/$H$12) -> 8.4541317 | H32: =IF(E32="","",($J$11-$H$7+E32)*$J$10/$H$12) -> 8.1188024 | I32: =$F$12+(C32*$J$10/$L$12) -> 1599.2844 | J32: =IF(D32="","",($J$11-$H$7+D32)*$J$10/$B$12) -> 1411.84 | K32: =IF(E32="","",($J$11-$H$7+E32)*$J$10/$B$12) -> 1355.84 | L32: 10.3
A33: 美西 四区 | B33: GEU3 | C33: 85 | D33: 3180 | E33: 2750 | F33: =$J$12+(C33*$J$10/$L$10) -> 9.7629142 | G33: =IF(D33="","",($J$11-$H$7+D33)*$J$10/$H$12) -> 9.013014 | H33: =IF(E33="","",($J$11-$H$7+E33)*$J$10/$H$12) -> 8.7726946 | I33: =$F$12+(C33*$J$10/$L$12) -> 1677.0622 | J33: =IF(D33="","",($J$11-$H$7+D33)*$J$10/$B$12) -> 1505.1733 | K33: =IF(E33="","",($J$11-$H$7+E33)*$J$10/$B$12) -> 1465.04 | L33: 10.6
B34: GEU2 | C34: 85 | D34: 3180 | E34: 2750 | F34: =$J$12+(C34*$J$10/$L$10) -> 9.7629142 | G34: =IF(D34="","",($J$11-$H$7+D34)*$J$10/$H$12) -> 9.013014 | H34: =IF(E34="","",($J$11-$H$7+E34)*$J$10/$H$12) -> 8.7726946 | I34: =$F$12+(C34*$J$10/$L$12) -> 1677.0622 | J34: =IF(D34="","",($J$11-$H$7+D34)*$J$10/$B$12) -> 1505.1733 | K34: =IF(E34="","",($J$11-$H$7+E34)*$J$10/$B$12) -> 1465.04 | L34: 10.6
B35: MIT2 | C35: 85 | D35: 3180 | E35: 2500 | F35: =$J$12+(C35*$J$10/$L$10) -> 9.7629142 | G35: =IF(D35="","",($J$11-$H$7+D35)*$J$10/$H$12) -> 9.013014 | H35: =IF(E35="","",($J$11-$H$7+E35)*$J$10/$H$12) -> 8.6329741 | I35: =$F$12+(C35*$J$10/$L$12) -> 1677.0622 | J35: =IF(D35="","",($J$11-$H$7+D35)*$J$10/$B$12) -> 1505.1733 | K35: =IF(E35="","",($J$11-$H$7+E35)*$J$10/$B$12) -> 1441.7067 | L35: 10.6
B36: OAK3 | C36: 85 | D36: 3180 | F36: =$J$12+(C36*$J$10/$L$10) -> 9.7629142 | G36: =IF(D36="","",($J$11-$H$7+D36)*$J$10/$H$12) -> 9.013014 | H36: =IF(E36="","",($J$11-$H$7+E36)*$J$10/$H$12) | I36: =$F$12+(C36*$J$10/$L$12) -> 1677.0622 | J36: =IF(D36="","",($J$11-$H$7+D36)*$J$10/$B$12) -> 1505.1733 | K36: =IF(E36="","",($J$11-$H$7+E36)*$J$10/$B$12)
B37: LAS6 | C37: 85 | D37: 3180 | E37: 2480 | F37: =$J$12+(C37*$J$10/$L$10) -> 9.7629142 | G37: =IF(D37="","",($J$11-$H$7+D37)*$J$10/$H$12) -> 9.013014 | H37: =IF(E37="","",($J$11-$H$7+E37)*$J$10/$H$12) -> 8.6217964 | I37: =$F$12+(C37*$J$10/$L$12) -> 1677.0622 | J37: =IF(D37="","",($J$11-$H$7+D37)*$J$10/$B$12) -> 1505.1733 | K37: =IF(E37="","",($J$11-$H$7+E37)*$J$10/$B$12) -> 1439.84
B38: SMF6 | C38: 85 | D38: 3180 | F38: =$J$12+(C38*$J$10/$L$10) -> 9.7629142 | G38: =IF(D38="","",($J$11-$H$7+D38)*$J$10/$H$12) -> 9.013014 | H38: =IF(E38="","",($J$11-$H$7+E38)*$J$10/$H$12) | I38: =$F$12+(C38*$J$10/$L$12) -> 1677.0622 | J38: =IF(D38="","",($J$11-$H$7+D38)*$J$10/$B$12) -> 1505.1733 | K38: =IF(E38="","",($J$11-$H$7+E38)*$J$10/$B$12)
B39: SCK8 | C39: 85 | D39: 3180 | F39: =$J$12+(C39*$J$10/$L$10) -> 9.7629142 | G39: =IF(D39="","",($J$11-$H$7+D39)*$J$10/$H$12) -> 9.013014 | H39: =IF(E39="","",($J$11-$H$7+E39)*$J$10/$H$12) | I39: =$F$12+(C39*$J$10/$L$12) -> 1677.0622 | J39: =IF(D39="","",($J$11-$H$7+D39)*$J$10/$B$12) -> 1505.1733 | K39: =IF(E39="","",($J$11-$H$7+E39)*$J$10/$B$12) | L39: 10.6
B40: GEU5 | C40: 85 | D40: 3180 | E40: 2750 | F40: =$J$12+(C40*$J$10/$L$10) -> 9.7629142 | G40: =IF(D40="","",($J$11-$H$7+D40)*$J$10/$H$12) -> 9.013014 | H40: =IF(E40="","",($J$11-$H$7+E40)*$J$10/$H$12) -> 8.7726946 | I40: =$F$12+(C40*$J$10/$L$12) -> 1677.0622 | J40: =IF(D40="","",($J$11-$H$7+D40)*$J$10/$B$12) -> 1505.1733 | K40: =IF(E40="","",($J$11-$H$7+E40)*$J$10/$B$12) -> 1465.04
B41: HLI2 | C41: 85 | D41: 3180 | E41: 2730 | F41: =$J$12+(C41*$J$10/$L$10) -> 9.7629142 | G41: =IF(D41="","",($J$11-$H$7+D41)*$J$10/$H$12) -> 9.013014 | H41: =IF(E41="","",($J$11-$H$7+E41)*$J$10/$H$12) -> 8.761517 | I41: =$F$12+(C41*$J$10/$L$12) -> 1677.0622 | J41: =IF(D41="","",($J$11-$H$7+D41)*$J$10/$B$12) -> 1505.1733 | K41: =IF(E41="","",($J$11-$H$7+E41)*$J$10/$B$12) -> 1463.1733 | L41: 10.6
B42: TCY2 | C42: 85 | D42: 3180 | E42: 2730 | F42: =$J$12+(C42*$J$10/$L$10) -> 9.7629142 | G42: =IF(D42="","",($J$11-$H$7+D42)*$J$10/$H$12) -> 9.013014 | H42: =IF(E42="","",($J$11-$H$7+E42)*$J$10/$H$12) -> 8.761517 | I42: =$F$12+(C42*$J$10/$L$12) -> 1677.0622 | J42: =IF(D42="","",($J$11-$H$7+D42)*$J$10/$B$12) -> 1505.1733 | K42: =IF(E42="","",($J$11-$H$7+E42)*$J$10/$B$12) -> 1463.1733 | L42: 10.6
A43: 美中 一区 | B43: DFW6 | C43: 160 | D43: 5380 | F43: =$J$12+(C43*$J$10/$L$10) -> 11.262914 | G43: =IF(D43="","",($J$11-$H$7+D43)*$J$10/$H$12) -> 10.242555 | H43: =IF(E43="","",($J$11-$H$7+E43)*$J$10/$H$12) | I43: =$F$12+(C43*$J$10/$L$12) -> 1968.7289 | J43: =IF(D43="","",($J$11-$H$7+D43)*$J$10/$B$12) -> 1710.5067 | K43: =IF(E43="","",($J$11-$H$7+E43)*$J$10/$B$12)
B44: AMA1 | C44: 170 | D44: 5380 | F44: =$J$12+(C44*$J$10/$L$10) -> 11.462914 | G44: =IF(D44="","",($J$11-$H$7+D44)*$J$10/$H$12) -> 10.242555 | H44: =IF(E44="","",($J$11-$H$7+E44)*$J$10/$H$12) | I44: =$F$12+(C44*$J$10/$L$12) -> 2007.6178 | J44: =IF(D44="","",($J$11-$H$7+D44)*$J$10/$B$12) -> 1710.5067 | K44: =IF(E44="","",($J$11-$H$7+E44)*$J$10/$B$12)
B45: IAH3 | C45: 190 | D45: 5380 | F45: =$J$12+(C45*$J$10/$L$10) -> 11.862914 | G45: =IF(D45="","",($J$11-$H$7+D45)*$J$10/$H$12) -> 10.242555 | H45: =IF(E45="","",($J$11-$H$7+E45)*$J$10/$H$12) | I45: =$F$12+(C45*$J$10/$L$12) -> 2085.3956 | J45: =IF(D45="","",($J$11-$H$7+D45)*$J$10/$B$12) -> 1710.5067 | K45: =IF(E45="","",($J$11-$H$7+E45)*$J$10/$B$12) | L45: 12.9
B46: ABQ2 | C46: 160 | D46: 5380 | E46: 4280 | F46: =$J$12+(C46*$J$10/$L$10) -> 11.262914 | G46: =IF(D46="","",($J$11-$H$7+D46)*$J$10/$H$12) -> 10.242555 | H46: =IF(E46="","",($J$11-$H$7+E46)*$J$10/$H$12) -> 9.6277844 | I46: =$F$12+(C46*$J$10/$L$12) -> 1968.7289 | J46: =IF(D46="","",($J$11-$H$7+D46)*$J$10/$B$12) -> 1710.5067 | K46: =IF(E46="","",($J$11-$H$7+E46)*$J$10/$B$12) -> 1607.84 | L46: 12.4
A47: 美中二区 | B47: PSC2 | C47: 215 | D47: 6380 | F47: =$J$12+(C47*$J$10/$L$10) -> 12.362914 | G47: =IF(D47="","",($J$11-$H$7+D47)*$J$10/$H$12) -> 10.801437 | H47: =IF(E47="","",($J$11-$H$7+E47)*$J$10/$H$12) | I47: =$F$12+(C47*$J$10/$L$12) -> 2182.6178 | J47: =IF(D47="","",($J$11-$H$7+D47)*$J$10/$B$12) -> 1803.84 | K47: =IF(E47="","",($J$11-$H$7+E47)*$J$10/$B$12) | L47: 12.9
B48: FTW1 | C48: 150 | D48: 5380 | F48: =$J$12+(C48*$J$10/$L$10) -> 11.062914 | G48: =IF(D48="","",($J$11-$H$7+D48)*$J$10/$H$12) -> 10.242555 | H48: =IF(E48="","",($J$11-$H$7+E48)*$J$10/$H$12) | I48: =$F$12+(C48*$J$10/$L$12) -> 1929.84 | J48: =IF(D48="","",($J$11-$H$7+D48)*$J$10/$B$12) -> 1710.5067 | K48: =IF(E48="","",($J$11-$H$7+E48)*$J$10/$B$12) | L48: 12.4
B49: IND9 | C49: 190 | D49: 6380 | F49: =$J$12+(C49*$J$10/$L$10) -> 11.862914 | G49: =IF(D49="","",($J$11-$H$7+D49)*$J$10/$H$12) -> 10.801437 | H49: =IF(E49="","",($J$11-$H$7+E49)*$J$10/$H$12) | I49: =$F$12+(C49*$J$10/$L$12) -> 2085.3956 | J49: =IF(D49="","",($J$11-$H$7+D49)*$J$10/$B$12) -> 1803.84 | K49: =IF(E49="","",($J$11-$H$7+E49)*$J$10/$B$12) | L49: 12.9
B50: MDW2 | C50: 190 | D50: 6380 | F50: =$J$12+(C50*$J$10/$L$10) -> 11.862914 | G50: =IF(D50="","",($J$11-$H$7+D50)*$J$10/$H$12) -> 10.801437 | H50: =IF(E50="","",($J$11-$H$7+E50)*$J$10/$H$12) | I50: =$F$12+(C50*$J$10/$L$12) -> 2085.3956 | J50: =IF(D50="","",($J$11-$H$7+D50)*$J$10/$B$12) -> 1803.84 | K50: =IF(E50="","",($J$11-$H$7+E50)*$J$10/$B$12) | L50: 12.9
B51: MEM1 | C51: 190 | D51: 6380 | F51: =$J$12+(C51*$J$10/$L$10) -> 11.862914 | G51: =IF(D51="","",($J$11-$H$7+D51)*$J$10/$H$12) -> 10.801437 | H51: =IF(E51="","",($J$11-$H$7+E51)*$J$10/$H$12) | I51: =$F$12+(C51*$J$10/$L$12) -> 2085.3956 | J51: =IF(D51="","",($J$11-$H$7+D51)*$J$10/$B$12) -> 1803.84 | K51: =IF(E51="","",($J$11-$H$7+E51)*$J$10/$B$12) | L51: 12.9
B52: MQJ1 | C52: 190 | D52: 6380 | F52: =$J$12+(C52*$J$10/$L$10) -> 11.862914 | G52: =IF(D52="","",($J$11-$H$7+D52)*$J$10/$H$12) -> 10.801437 | H52: =IF(E52="","",($J$11-$H$7+E52)*$J$10/$H$12) | I52: =$F$12+(C52*$J$10/$L$12) -> 2085.3956 | J52: =IF(D52="","",($J$11-$H$7+D52)*$J$10/$B$12) -> 1803.84 | K52: =IF(E52="","",($J$11-$H$7+E52)*$J$10/$B$12) | L52: 12.9
A53: 美中 长途 | B53: FTW3 | C53: 180 | D53: 5880 | F53: =$J$12+(C53*$J$10/$L$10) -> 11.662914 | G53: =IF(D53="","",($J$11-$H$7+D53)*$J$10/$H$12) -> 10.521996 | H53: =IF(E53="","",($J$11-$H$7+E53)*$J$10/$H$12) | I53: =$F$12+(C53*$J$10/$L$12) -> 2046.5067 | J53: =IF(D53="","",($J$11-$H$7+D53)*$J$10/$B$12) -> 1757.1733 | K53: =IF(E53="","",($J$11-$H$7+E53)*$J$10/$B$12)
B54: SAT4 | C54: 180 | D54: 5880 | F54: =$J$12+(C54*$J$10/$L$10) -> 11.662914 | G54: =IF(D54="","",($J$11-$H$7+D54)*$J$10/$H$12) -> 10.521996 | H54: =IF(E54="","",($J$11-$H$7+E54)*$J$10/$H$12) | I54: =$F$12+(C54*$J$10/$L$12) -> 2046.5067 | J54: =IF(D54="","",($J$11-$H$7+D54)*$J$10/$B$12) -> 1757.1733 | K54: =IF(E54="","",($J$11-$H$7+E54)*$J$10/$B$12) | L54: 12.9
B55: SAT6 | C55: 180 | D55: 5880 | F55: =$J$12+(C55*$J$10/$L$10) -> 11.662914 | G55: =IF(D55="","",($J$11-$H$7+D55)*$J$10/$H$12) -> 10.521996 | H55: =IF(E55="","",($J$11-$H$7+E55)*$J$10/$H$12) | I55: =$F$12+(C55*$J$10/$L$12) -> 2046.5067 | J55: =IF(D55="","",($J$11-$H$7+D55)*$J$10/$B$12) -> 1757.1733 | K55: =IF(E55="","",($J$11-$H$7+E55)*$J$10/$B$12)
B56: HOU8 | C56: 195 | D56: 5880 | F56: =$J$12+(C56*$J$10/$L$10) -> 11.962914 | G56: =IF(D56="","",($J$11-$H$7+D56)*$J$10/$H$12) -> 10.521996 | H56: =IF(E56="","",($J$11-$H$7+E56)*$J$10/$H$12) | I56: =$F$12+(C56*$J$10/$L$12) -> 2104.84 | J56: =IF(D56="","",($J$11-$H$7+D56)*$J$10/$B$12) -> 1757.1733 | K56: =IF(E56="","",($J$11-$H$7+E56)*$J$10/$B$12)
B57: SLC2 | C57: 130 | D57: 5880 | F57: =$J$12+(C57*$J$10/$L$10) -> 10.662914 | G57: =IF(D57="","",($J$11-$H$7+D57)*$J$10/$H$12) -> 10.521996 | H57: =IF(E57="","",($J$11-$H$7+E57)*$J$10/$H$12) | I57: =$F$12+(C57*$J$10/$L$12) -> 1852.0622 | J57: =IF(D57="","",($J$11-$H$7+D57)*$J$10/$B$12) -> 1757.1733 | K57: =IF(E57="","",($J$11-$H$7+E57)*$J$10/$B$12)
B58: DEN2 | C58: 195 | D58: 5880 | F58: =$J$12+(C58*$J$10/$L$10) -> 11.962914 | G58: =IF(D58="","",($J$11-$H$7+D58)*$J$10/$H$12) -> 10.521996 | H58: =IF(E58="","",($J$11-$H$7+E58)*$J$10/$H$12) | I58: =$F$12+(C58*$J$10/$L$12) -> 2104.84 | J58: =IF(D58="","",($J$11-$H$7+D58)*$J$10/$B$12) -> 1757.1733 | K58: =IF(E58="","",($J$11-$H$7+E58)*$J$10/$B$12)
B59: DEN8 | C59: 195 | D59: 5880 | F59: =$J$12+(C59*$J$10/$L$10) -> 11.962914 | G59: =IF(D59="","",($J$11-$H$7+D59)*$J$10/$H$12) -> 10.521996 | H59: =IF(E59="","",($J$11-$H$7+E59)*$J$10/$H$12) | I59: =$F$12+(C59*$J$10/$L$12) -> 2104.84 | J59: =IF(D59="","",($J$11-$H$7+D59)*$J$10/$B$12) -> 1757.1733 | K59: =IF(E59="","",($J$11-$H$7+E59)*$J$10/$B$12)
B60: RNO4 | C60: 130 | D60: 5880 | F60: =$J$12+(C60*$J$10/$L$10) -> 10.662914 | G60: =IF(D60="","",($J$11-$H$7+D60)*$J$10/$H$12) -> 10.521996 | H60: =IF(E60="","",($J$11-$H$7+E60)*$J$10/$H$12) | I60: =$F$12+(C60*$J$10/$L$12) -> 1852.0622 | J60: =IF(D60="","",($J$11-$H$7+D60)*$J$10/$B$12) -> 1757.1733 | K60: =IF(E60="","",($J$11-$H$7+E60)*$J$10/$B$12)
B61: ORD2 | C61: 195 | D61: 7280 | F61: =$J$12+(C61*$J$10/$L$10) -> 11.962914 | G61: =IF(D61="","",($J$11-$H$7+D61)*$J$10/$H$12) -> 11.304431 | H61: =IF(E61="","",($J$11-$H$7+E61)*$J$10/$H$12) | I61: =$F$12+(C61*$J$10/$L$12) -> 2104.84 | J61: =IF(D61="","",($J$11-$H$7+D61)*$J$10/$B$12) -> 1887.84 | K61: =IF(E61="","",($J$11-$H$7+E61)*$J$10/$B$12)
B62: FWA4 | C62: 190 | D62: 7280 | F62: =$J$12+(C62*$J$10/$L$10) -> 11.862914 | G62: =IF(D62="","",($J$11-$H$7+D62)*$J$10/$H$12) -> 11.304431 | H62: =IF(E62="","",($J$11-$H$7+E62)*$J$10/$H$12) | I62: =$F$12+(C62*$J$10/$L$12) -> 2085.3956 | J62: =IF(D62="","",($J$11-$H$7+D62)*$J$10/$B$12) -> 1887.84 | K62: =IF(E62="","",($J$11-$H$7+E62)*$J$10/$B$12) | L62: 12.9
B63: RFD2 | C63: 220 | D63: 7280 | F63: =$J$12+(C63*$J$10/$L$10) -> 12.462914 | G63: =IF(D63="","",($J$11-$H$7+D63)*$J$10/$H$12) -> 11.304431 | H63: =IF(E63="","",($J$11-$H$7+E63)*$J$10/$H$12) | I63: =$F$12+(C63*$J$10/$L$12) -> 2202.0622 | J63: =IF(D63="","",($J$11-$H$7+D63)*$J$10/$B$12) -> 1887.84 | K63: =IF(E63="","",($J$11-$H$7+E63)*$J$10/$B$12) | L63: 12.9
B64: STL3 | C64: 190 | D64: 7280 | F64: =$J$12+(C64*$J$10/$L$10) -> 11.862914 | G64: =IF(D64="","",($J$11-$H$7+D64)*$J$10/$H$12) -> 11.304431 | H64: =IF(E64="","",($J$11-$H$7+E64)*$J$10/$H$12) | I64: =$F$12+(C64*$J$10/$L$12) -> 2085.3956 | J64: =IF(D64="","",($J$11-$H$7+D64)*$J$10/$B$12) -> 1887.84 | K64: =IF(E64="","",($J$11-$H$7+E64)*$J$10/$B$12)
B65: STL4 | C65: 190 | D65: 7280 | F65: =$J$12+(C65*$J$10/$L$10) -> 11.862914 | G65: =IF(D65="","",($J$11-$H$7+D65)*$J$10/$H$12) -> 11.304431 | H65: =IF(E65="","",($J$11-$H$7+E65)*$J$10/$H$12) | I65: =$F$12+(C65*$J$10/$L$12) -> 2085.3956 | J65: =IF(D65="","",($J$11-$H$7+D65)*$J$10/$B$12) -> 1887.84 | K65: =IF(E65="","",($J$11-$H$7+E65)*$J$10/$B$12)
B66: IND2 | C66: 225 | D66: 7280 | F66: =$J$12+(C66*$J$10/$L$10) -> 12.562914 | G66: =IF(D66="","",($J$11-$H$7+D66)*$J$10/$H$12) -> 11.304431 | H66: =IF(E66="","",($J$11-$H$7+E66)*$J$10/$H$12) | I66: =$F$12+(C66*$J$10/$L$12) -> 2221.5067 | J66: =IF(D66="","",($J$11-$H$7+D66)*$J$10/$B$12) -> 1887.84 | K66: =IF(E66="","",($J$11-$H$7+E66)*$J$10/$B$12)
B67: IND4 | C67: 225 | D67: 7280 | F67: =$J$12+(C67*$J$10/$L$10) -> 12.562914 | G67: =IF(D67="","",($J$11-$H$7+D67)*$J$10/$H$12) -> 11.304431 | H67: =IF(E67="","",($J$11-$H$7+E67)*$J$10/$H$12) | I67: =$F$12+(C67*$J$10/$L$12) -> 2221.5067 | J67: =IF(D67="","",($J$11-$H$7+D67)*$J$10/$B$12) -> 1887.84 | K67: =IF(E67="","",($J$11-$H$7+E67)*$J$10/$B$12)
B68: MEM6 | C68: 190 | D68: 7280 | F68: =$J$12+(C68*$J$10/$L$10) -> 11.862914 | G68: =IF(D68="","",($J$11-$H$7+D68)*$J$10/$H$12) -> 11.304431 | H68: =IF(E68="","",($J$11-$H$7+E68)*$J$10/$H$12) | I68: =$F$12+(C68*$J$10/$L$12) -> 2085.3956 | J68: =IF(D68="","",($J$11-$H$7+D68)*$J$10/$B$12) -> 1887.84 | K68: =IF(E68="","",($J$11-$H$7+E68)*$J$10/$B$12)
B69: BNA6 | C69: 235 | D69: 7280 | F69: =$J$12+(C69*$J$10/$L$10) -> 12.762914 | G69: =IF(D69="","",($J$11-$H$7+D69)*$J$10/$H$12) -> 11.304431 | H69: =IF(E69="","",($J$11-$H$7+E69)*$J$10/$H$12) | I69: =$F$12+(C69*$J$10/$L$12) -> 2260.3956 | J69: =IF(D69="","",($J$11-$H$7+D69)*$J$10/$B$12) -> 1887.84 | K69: =IF(E69="","",($J$11-$H$7+E69)*$J$10/$B$12) | L69: 14.1
B70: OKC2 | C70: 215 | D70: 7280 | F70: =$J$12+(C70*$J$10/$L$10) -> 12.362914 | G70: =IF(D70="","",($J$11-$H$7+D70)*$J$10/$H$12) -> 11.304431 | H70: =IF(E70="","",($J$11-$H$7+E70)*$J$10/$H$12) | I70: =$F$12+(C70*$J$10/$L$12) -> 2182.6178 | J70: =IF(D70="","",($J$11-$H$7+D70)*$J$10/$B$12) -> 1887.84 | K70: =IF(E70="","",($J$11-$H$7+E70)*$J$10/$B$12)
B71: LIT2 | C71: 235 | D71: 7280 | F71: =$J$12+(C71*$J$10/$L$10) -> 12.762914 | G71: =IF(D71="","",($J$11-$H$7+D71)*$J$10/$H$12) -> 11.304431 | H71: =IF(E71="","",($J$11-$H$7+E71)*$J$10/$H$12) | I71: =$F$12+(C71*$J$10/$L$12) -> 2260.3956 | J71: =IF(D71="","",($J$11-$H$7+D71)*$J$10/$B$12) -> 1887.84 | K71: =IF(E71="","",($J$11-$H$7+E71)*$J$10/$B$12)
B72: JVL1 | C72: 235 | D72: 7280 | F72: =$J$12+(C72*$J$10/$L$10) -> 12.762914 | G72: =IF(D72="","",($J$11-$H$7+D72)*$J$10/$H$12) -> 11.304431 | H72: =IF(E72="","",($J$11-$H$7+E72)*$J$10/$H$12) | I72: =$F$12+(C72*$J$10/$L$12) -> 2260.3956 | J72: =IF(D72="","",($J$11-$H$7+D72)*$J$10/$B$12) -> 1887.84 | K72: =IF(E72="","",($J$11-$H$7+E72)*$J$10/$B$12)
A73: 美东9区 | B73: CLT2 | C73: 255 | D73: 7980 | F73: =$J$12+(C73*$J$10/$L$10) -> 13.162914 | G73: =IF(D73="","",($J$11-$H$7+D73)*$J$10/$H$12) -> 11.695649 | H73: =IF(E73="","",($J$11-$H$7+E73)*$J$10/$H$12) | I73: =$F$12+(C73*$J$10/$L$12) -> 2338.1733 | J73: =IF(D73="","",($J$11-$H$7+D73)*$J$10/$B$12) -> 1953.1733 | K73: =IF(E73="","",($J$11-$H$7+E73)*$J$10/$B$12) | L73: 13.6
B74: MCO2 | C74: 265 | D74: 7980 | F74: =$J$12+(C74*$J$10/$L$10) -> 13.362914 | G74: =IF(D74="","",($J$11-$H$7+D74)*$J$10/$H$12) -> 11.695649 | H74: =IF(E74="","",($J$11-$H$7+E74)*$J$10/$H$12) | I74: =$F$12+(C74*$J$10/$L$12) -> 2377.0622 | J74: =IF(D74="","",($J$11-$H$7+D74)*$J$10/$B$12) -> 1953.1733 | K74: =IF(E74="","",($J$11-$H$7+E74)*$J$10/$B$12)
B75: TPA2 | C75: 265 | D75: 7980 | F75: =$J$12+(C75*$J$10/$L$10) -> 13.362914 | G75: =IF(D75="","",($J$11-$H$7+D75)*$J$10/$H$12) -> 11.695649 | H75: =IF(E75="","",($J$11-$H$7+E75)*$J$10/$H$12) | I75: =$F$12+(C75*$J$10/$L$12) -> 2377.0622 | J75: =IF(D75="","",($J$11-$H$7+D75)*$J$10/$B$12) -> 1953.1733 | K75: =IF(E75="","",($J$11-$H$7+E75)*$J$10/$B$12) | L75: 13.6
B76: TPA3 | C76: 265 | D76: 7980 | F76: =$J$12+(C76*$J$10/$L$10) -> 13.362914 | G76: =IF(D76="","",($J$11-$H$7+D76)*$J$10/$H$12) -> 11.695649 | H76: =IF(E76="","",($J$11-$H$7+E76)*$J$10/$H$12) | I76: =$F$12+(C76*$J$10/$L$12) -> 2377.0622 | J76: =IF(D76="","",($J$11-$H$7+D76)*$J$10/$B$12) -> 1953.1733 | K76: =IF(E76="","",($J$11-$H$7+E76)*$J$10/$B$12) | L76: 13.6
B77: CMH2 | C77: 230 | D77: 7980 | F77: =$J$12+(C77*$J$10/$L$10) -> 12.662914 | G77: =IF(D77="","",($J$11-$H$7+D77)*$J$10/$H$12) -> 11.695649 | H77: =IF(E77="","",($J$11-$H$7+E77)*$J$10/$H$12) | I77: =$F$12+(C77*$J$10/$L$12) -> 2240.9511 | J77: =IF(D77="","",($J$11-$H$7+D77)*$J$10/$B$12) -> 1953.1733 | K77: =IF(E77="","",($J$11-$H$7+E77)*$J$10/$B$12)
B78: CMH3 | C78: 230 | D78: 7980 | F78: =$J$12+(C78*$J$10/$L$10) -> 12.662914 | G78: =IF(D78="","",($J$11-$H$7+D78)*$J$10/$H$12) -> 11.695649 | H78: =IF(E78="","",($J$11-$H$7+E78)*$J$10/$H$12) | I78: =$F$12+(C78*$J$10/$L$12) -> 2240.9511 | J78: =IF(D78="","",($J$11-$H$7+D78)*$J$10/$B$12) -> 1953.1733 | K78: =IF(E78="","",($J$11-$H$7+E78)*$J$10/$B$12)
B79: DET1 | C79: 250 | D79: 7980 | F79: =$J$12+(C79*$J$10/$L$10) -> 13.062914 | G79: =IF(D79="","",($J$11-$H$7+D79)*$J$10/$H$12) -> 11.695649 | H79: =IF(E79="","",($J$11-$H$7+E79)*$J$10/$H$12) | I79: =$F$12+(C79*$J$10/$L$12) -> 2318.7289 | J79: =IF(D79="","",($J$11-$H$7+D79)*$J$10/$B$12) -> 1953.1733 | K79: =IF(E79="","",($J$11-$H$7+E79)*$J$10/$B$12)
B80: DET2 | C80: 250 | D80: 7980 | F80: =$J$12+(C80*$J$10/$L$10) -> 13.062914 | G80: =IF(D80="","",($J$11-$H$7+D80)*$J$10/$H$12) -> 11.695649 | H80: =IF(E80="","",($J$11-$H$7+E80)*$J$10/$H$12) | I80: =$F$12+(C80*$J$10/$L$12) -> 2318.7289 | J80: =IF(D80="","",($J$11-$H$7+D80)*$J$10/$B$12) -> 1953.1733 | K80: =IF(E80="","",($J$11-$H$7+E80)*$J$10/$B$12)
B81: AKR1 | C81: 270 | D81: 7980 | F81: =$J$12+(C81*$J$10/$L$10) -> 13.462914 | G81: =IF(D81="","",($J$11-$H$7+D81)*$J$10/$H$12) -> 11.695649 | H81: =IF(E81="","",($J$11-$H$7+E81)*$J$10/$H$12) | I81: =$F$12+(C81*$J$10/$L$12) -> 2396.5067 | J81: =IF(D81="","",($J$11-$H$7+D81)*$J$10/$B$12) -> 1953.1733 | K81: =IF(E81="","",($J$11-$H$7+E81)*$J$10/$B$12)
B82: LAN2 | C82: 250 | D82: 7980 | F82: =$J$12+(C82*$J$10/$L$10) -> 13.062914 | G82: =IF(D82="","",($J$11-$H$7+D82)*$J$10/$H$12) -> 11.695649 | H82: =IF(E82="","",($J$11-$H$7+E82)*$J$10/$H$12) | I82: =$F$12+(C82*$J$10/$L$12) -> 2318.7289 | J82: =IF(D82="","",($J$11-$H$7+D82)*$J$10/$B$12) -> 1953.1733 | K82: =IF(E82="","",($J$11-$H$7+E82)*$J$10/$B$12)
B83: RYY2 | C83: 250 | D83: 7980 | F83: =$J$12+(C83*$J$10/$L$10) -> 13.062914 | G83: =IF(D83="","",($J$11-$H$7+D83)*$J$10/$H$12) -> 11.695649 | H83: =IF(E83="","",($J$11-$H$7+E83)*$J$10/$H$12) | I83: =$F$12+(C83*$J$10/$L$12) -> 2318.7289 | J83: =IF(D83="","",($J$11-$H$7+D83)*$J$10/$B$12) -> 1953.1733 | K83: =IF(E83="","",($J$11-$H$7+E83)*$J$10/$B$12)
B84: JAX3 | C84: 295 | D84: 7980 | F84: =$J$12+(C84*$J$10/$L$10) -> 13.962914 | G84: =IF(D84="","",($J$11-$H$7+D84)*$J$10/$H$12) -> 11.695649 | H84: =IF(E84="","",($J$11-$H$7+E84)*$J$10/$H$12) | I84: =$F$12+(C84*$J$10/$L$12) -> 2493.7289 | J84: =IF(D84="","",($J$11-$H$7+D84)*$J$10/$B$12) -> 1953.1733 | K84: =IF(E84="","",($J$11-$H$7+E84)*$J$10/$B$12)
B85: PBI3 | C85: 295 | D85: 7980 | F85: =$J$12+(C85*$J$10/$L$10) -> 13.962914 | G85: =IF(D85="","",($J$11-$H$7+D85)*$J$10/$H$12) -> 11.695649 | H85: =IF(E85="","",($J$11-$H$7+E85)*$J$10/$H$12) | I85: =$F$12+(C85*$J$10/$L$12) -> 2493.7289 | J85: =IF(D85="","",($J$11-$H$7+D85)*$J$10/$B$12) -> 1953.1733 | K85: =IF(E85="","",($J$11-$H$7+E85)*$J$10/$B$12)
B86: RDU2 | C86: 280 | D86: 7980 | F86: =$J$12+(C86*$J$10/$L$10) -> 13.662914 | G86: =IF(D86="","",($J$11-$H$7+D86)*$J$10/$H$12) -> 11.695649 | H86: =IF(E86="","",($J$11-$H$7+E86)*$J$10/$H$12) | I86: =$F$12+(C86*$J$10/$L$12) -> 2435.3956 | J86: =IF(D86="","",($J$11-$H$7+D86)*$J$10/$B$12) -> 1953.1733 | K86: =IF(E86="","",($J$11-$H$7+E86)*$J$10/$B$12) | L86: 13.6
A87: 美东10区 | B87: ORF2 | C87: 290 | D87: 8680 | F87: =$J$12+(C87*$J$10/$L$10) -> 13.862914 | G87: =IF(D87="","",($J$11-$H$7+D87)*$J$10/$H$12) -> 12.086866 | H87: =IF(E87="","",($J$11-$H$7+E87)*$J$10/$H$12) | I87: =$F$12+(C87*$J$10/$L$12) -> 2474.2844 | J87: =IF(D87="","",($J$11-$H$7+D87)*$J$10/$B$12) -> 2018.5067 | K87: =IF(E87="","",($J$11-$H$7+E87)*$J$10/$B$12) | L87: 14.1
B88: CHO1 | C88: 290 | D88: 8680 | F88: =$J$12+(C88*$J$10/$L$10) -> 13.862914 | G88: =IF(D88="","",($J$11-$H$7+D88)*$J$10/$H$12) -> 12.086866 | H88: =IF(E88="","",($J$11-$H$7+E88)*$J$10/$H$12) | I88: =$F$12+(C88*$J$10/$L$12) -> 2474.2844 | J88: =IF(D88="","",($J$11-$H$7+D88)*$J$10/$B$12) -> 2018.5067 | K88: =IF(E88="","",($J$11-$H$7+E88)*$J$10/$B$12)
B89: RMN3 | C89: 285 | D89: 8680 | F89: =$J$12+(C89*$J$10/$L$10) -> 13.762914 | G89: =IF(D89="","",($J$11-$H$7+D89)*$J$10/$H$12) -> 12.086866 | H89: =IF(E89="","",($J$11-$H$7+E89)*$J$10/$H$12) | I89: =$F$12+(C89*$J$10/$L$12) -> 2454.84 | J89: =IF(D89="","",($J$11-$H$7+D89)*$J$10/$B$12) -> 2018.5067 | K89: =IF(E89="","",($J$11-$H$7+E89)*$J$10/$B$12) | L89: 14.1
B90: DCA6 | C90: 285 | D90: 8680 | F90: =$J$12+(C90*$J$10/$L$10) -> 13.762914 | G90: =IF(D90="","",($J$11-$H$7+D90)*$J$10/$H$12) -> 12.086866 | H90: =IF(E90="","",($J$11-$H$7+E90)*$J$10/$H$12) | I90: =$F$12+(C90*$J$10/$L$12) -> 2454.84 | J90: =IF(D90="","",($J$11-$H$7+D90)*$J$10/$B$12) -> 2018.5067 | K90: =IF(E90="","",($J$11-$H$7+E90)*$J$10/$B$12)
B91: TEB3 | C91: 290 | D91: 8680 | F91: =$J$12+(C91*$J$10/$L$10) -> 13.862914 | G91: =IF(D91="","",($J$11-$H$7+D91)*$J$10/$H$12) -> 12.086866 | H91: =IF(E91="","",($J$11-$H$7+E91)*$J$10/$H$12) | I91: =$F$12+(C91*$J$10/$L$12) -> 2474.2844 | J91: =IF(D91="","",($J$11-$H$7+D91)*$J$10/$B$12) -> 2018.5067 | K91: =IF(E91="","",($J$11-$H$7+E91)*$J$10/$B$12) | L91: 14.1
B92: TEB4 | C92: 290 | D92: 8680 | F92: =$J$12+(C92*$J$10/$L$10) -> 13.862914 | G92: =IF(D92="","",($J$11-$H$7+D92)*$J$10/$H$12) -> 12.086866 | H92: =IF(E92="","",($J$11-$H$7+E92)*$J$10/$H$12) | I92: =$F$12+(C92*$J$10/$L$12) -> 2474.2844 | J92: =IF(D92="","",($J$11-$H$7+D92)*$J$10/$B$12) -> 2018.5067 | K92: =IF(E92="","",($J$11-$H$7+E92)*$J$10/$B$12)
B93: TEB6 | C93: 295 | D93: 8680 | F93: =$J$12+(C93*$J$10/$L$10) -> 13.962914 | G93: =IF(D93="","",($J$11-$H$7+D93)*$J$10/$H$12) -> 12.086866 | H93: =IF(E93="","",($J$11-$H$7+E93)*$J$10/$H$12) | I93: =$F$12+(C93*$J$10/$L$12) -> 2493.7289 | J93: =IF(D93="","",($J$11-$H$7+D93)*$J$10/$B$12) -> 2018.5067 | K93: =IF(E93="","",($J$11-$H$7+E93)*$J$10/$B$12)
B94: TEB9 | C94: 295 | D94: 8680 | F94: =$J$12+(C94*$J$10/$L$10) -> 13.962914 | G94: =IF(D94="","",($J$11-$H$7+D94)*$J$10/$H$12) -> 12.086866 | H94: =IF(E94="","",($J$11-$H$7+E94)*$J$10/$H$12) | I94: =$F$12+(C94*$J$10/$L$12) -> 2493.7289 | J94: =IF(D94="","",($J$11-$H$7+D94)*$J$10/$B$12) -> 2018.5067 | K94: =IF(E94="","",($J$11-$H$7+E94)*$J$10/$B$12) | L94: 14.1
B95: ACY2 | C95: 300 | D95: 8680 | F95: =$J$12+(C95*$J$10/$L$10) -> 14.062914 | G95: =IF(D95="","",($J$11-$H$7+D95)*$J$10/$H$12) -> 12.086866 | H95: =IF(E95="","",($J$11-$H$7+E95)*$J$10/$H$12) | I95: =$F$12+(C95*$J$10/$L$12) -> 2513.1733 | J95: =IF(D95="","",($J$11-$H$7+D95)*$J$10/$B$12) -> 2018.5067 | K95: =IF(E95="","",($J$11-$H$7+E95)*$J$10/$B$12)
B96: ABE4 | C96: 290 | D96: 8680 | F96: =$J$12+(C96*$J$10/$L$10) -> 13.862914 | G96: =IF(D96="","",($J$11-$H$7+D96)*$J$10/$H$12) -> 12.086866 | H96: =IF(E96="","",($J$11-$H$7+E96)*$J$10/$H$12) | I96: =$F$12+(C96*$J$10/$L$12) -> 2474.2844 | J96: =IF(D96="","",($J$11-$H$7+D96)*$J$10/$B$12) -> 2018.5067 | K96: =IF(E96="","",($J$11-$H$7+E96)*$J$10/$B$12)
B97: ABE8 | C97: 275 | D97: 8680 | F97: =$J$12+(C97*$J$10/$L$10) -> 13.562914 | G97: =IF(D97="","",($J$11-$H$7+D97)*$J$10/$H$12) -> 12.086866 | H97: =IF(E97="","",($J$11-$H$7+E97)*$J$10/$H$12) | I97: =$F$12+(C97*$J$10/$L$12) -> 2415.9511 | J97: =IF(D97="","",($J$11-$H$7+D97)*$J$10/$B$12) -> 2018.5067 | K97: =IF(E97="","",($J$11-$H$7+E97)*$J$10/$B$12) | L97: 14.1
B98: AVP1 | C98: 295 | D98: 8680 | F98: =$J$12+(C98*$J$10/$L$10) -> 13.962914 | G98: =IF(D98="","",($J$11-$H$7+D98)*$J$10/$H$12) -> 12.086866 | H98: =IF(E98="","",($J$11-$H$7+E98)*$J$10/$H$12) | I98: =$F$12+(C98*$J$10/$L$12) -> 2493.7289 | J98: =IF(D98="","",($J$11-$H$7+D98)*$J$10/$B$12) -> 2018.5067 | K98: =IF(E98="","",($J$11-$H$7+E98)*$J$10/$B$12) | L98: 14.1
B99: AVP3 | C99: 290 | D99: 8680 | F99: =$J$12+(C99*$J$10/$L$10) -> 13.862914 | G99: =IF(D99="","",($J$11-$H$7+D99)*$J$10/$H$12) -> 12.086866 | H99: =IF(E99="","",($J$11-$H$7+E99)*$J$10/$H$12) | I99: =$F$12+(C99*$J$10/$L$12) -> 2474.2844 | J99: =IF(D99="","",($J$11-$H$7+D99)*$J$10/$B$12) -> 2018.5067 | K99: =IF(E99="","",($J$11-$H$7+E99)*$J$10/$B$12) | L99: 14.1
B100: PIT2 | C100: 290 | D100: 8680 | F100: =$J$12+(C100*$J$10/$L$10) -> 13.862914 | G100: =IF(D100="","",($J$11-$H$7+D100)*$J$10/$H$12) -> 12.086866 | H100: =IF(E100="","",($J$11-$H$7+E100)*$J$10/$H$12) | I100: =$F$12+(C100*$J$10/$L$12) -> 2474.2844 | J100: =IF(D100="","",($J$11-$H$7+D100)*$J$10/$B$12) -> 2018.5067 | K100: =IF(E100="","",($J$11-$H$7+E100)*$J$10/$B$12)
...

Sheet EX456
A1: 应付 | B1: 盐田——LA | F1: 费用类型 | G1: 币种 | H1: 单价 | I1: 数量 | J1: 备注 | K1: 统计
B2: 起运港 | C2: 拖车+报关 | F2: 装柜费 | G2: RMB | H2: 500 | I2: 1
F3: 拖车费 | G3: RMB | H3: 1950 | I3: 1
F4: 报关费 | G4: RMB | H4: 500 | I4: 0 | J4: 实报实销 | K4: 100/票
F5: 港杂费RMB部分 | G5: RMB | H5: 3000 | I5: 1
F6: 海运费（变动） | G6: USD | H6: 5000 | I6: 1
B7: 目的港 | C7: 提柜+拆柜 | F7: 提拆一口价 | G7: USD | H7: 1400 | I7: 1
C8: 清关+缴税 | F8: 清关费 | G8: USD | I8: 1
F9: 税金 | G9: USD | H9: 1500 | L9: 每板KG
A10: 盐田-LA | B10: 人民币应付 | G10: RMB | H10: =SUM(H2:H5) -> 5950 | I10: 汇率 | J10: 7 | K10: =H10/J10 -> 850 | L10: 350
A11: 报价：2025/03/16 | B11: 含税/CBM | G11: USD | H11: =SUM(H6:H9) -> 7900 | I11: 合计 | J11: =H11+K10 -> 8750 | K11: =J11*J10 -> 61250 | L11: CBM
A12: CBM标准 | B12: 75 | E12: CBM计费标准 | F12: =K11/B12 -> 816.66667 | G12: KG标准 | H12: 12525 | I12: KG计费标准 | J12: =F12/167 -> 4.8902196 | L12: 1.8
B13: 派送费 | C13: 美金/板 | D13: 组合一口价 | E13: 整柜一口价 | F13: 拆送KG含税 | G13: 组合KG | H13: 直送KG | I13: 拆送CBM含税 | J13: 组合CBM | K13: 直送CBM | L13: 直客报价101KG+
A14: 美西 一区 | B14: ONT8 | C14: 30 | D14: 1980 | E14: 1430 | F14: =$J$12+(C14*$J$10/$L$10) -> 5.4902196 | G14: =IF(D14="","",($J$11-$H$7+D14)*$J$10/$H$12) -> 5.2143713 | H14: =IF(E14="","",($J$11-$H$7+E14)*$J$10/$H$12) -> 4.906986 | I14: =$F$12+(C14*$J$10/$L$12) -> 933.33333 | J14: =IF(D14="","",($J$11-$H$7+D14)*$J$10/$B$12) -> 870.8 | K14: =IF(E14="","",($J$11-$H$7+E14)*$J$10/$B$12) -> 819.46667 | L14: 6.4
B15: LGB8 | C15: 30 | D15: 1980 | E15: 1430 | F15: =$J$12+(C15*$J$10/$L$10) -> 5.4902196 | G15: =IF(D15="","",($J$11-$H$7+D15)*$J$10/$H$12) -> 5.2143713 | H15: =IF(E15="","",($J$11-$H$7+E15)*$J$10/$H$12) -> 4.906986 | I15: =$F$12+(C15*$J$10/$L$12) -> 933.33333 | J15: =IF(D15="","",($J$11-$H$7+D15)*$J$10/$B$12) -> 870.8 | K15: =IF(E15="","",($J$11-$H$7+E15)*$J$10/$B$12) -> 819.46667 | L15: 6.4
B16: SBD1 | C16: 35 | D16: 1980 | E16: 1430 | F16: =$J$12+(C16*$J$10/$L$10) -> 5.5902196 | G16: =IF(D16="","",($J$11-$H$7+D16)*$J$10/$H$12) -> 5.2143713 | H16: =IF(E16="","",($J$11-$H$7+E16)*$J$10/$H$12) -> 4.906986 | I16: =$F$12+(C16*$J$10/$L$12) -> 952.77778 | J16: =IF(D16="","",($J$11-$H$7+D16)*$J$10/$B$12) -> 870.8 | K16: =IF(E16="","",($J$11-$H$7+E16)*$J$10/$B$12) -> 819.46667 | L16: 6.4
B17: LAX9 | C17: 30 | D17: 1980 | E17: 1430 | F17: =$J$12+(C17*$J$10/$L$10) -> 5.4902196 | G17: =IF(D17="","",($J$11-$H$7+D17)*$J$10/$H$12) -> 5.2143713 | H17: =IF(E17="","",($J$11-$H$7+E17)*$J$10/$H$12) -> 4.906986 | I17: =$F$12+(C17*$J$10/$L$12) -> 933.33333 | J17: =IF(D17="","",($J$11-$H$7+D17)*$J$10/$B$12) -> 870.8 | K17: =IF(E17="","",($J$11-$H$7+E17)*$J$10/$B$12) -> 819.46667 | L17: 6.4
A18: 美西 二区 | B18: SMF3 | C18: 70 | D18: 2980 | E18: 2730 | F18: =$J$12+(C18*$J$10/$L$10) -> 6.2902196 | G18: =IF(D18="","",($J$11-$H$7+D18)*$J$10/$H$12) -> 5.7732535 | H18: =IF(E18="","",($J$11-$H$7+E18)*$J$10/$H$12) -> 5.6335329 | I18: =$F$12+(C18*$J$10/$L$12) -> 1088.8889 | J18: =IF(D18="","",($J$11-$H$7+D18)*$J$10/$B$12) -> 964.13333 | K18: =IF(E18="","",($J$11-$H$7+E18)*$J$10/$B$12) -> 940.8 | L18: 7.2
B19: SCK4 | C19: 70 | D19: 2980 | E19: 2730 | F19: =$J$12+(C19*$J$10/$L$10) -> 6.2902196 | G19: =IF(D19="","",($J$11-$H$7+D19)*$J$10/$H$12) -> 5.7732535 | H19: =IF(E19="","",($J$11-$H$7+E19)*$J$10/$H$12) -> 5.6335329 | I19: =$F$12+(C19*$J$10/$L$12) -> 1088.8889 | J19: =IF(D19="","",($J$11-$H$7+D19)*$J$10/$B$12) -> 964.13333 | K19: =IF(E19="","",($J$11-$H$7+E19)*$J$10/$B$12) -> 940.8 | L19: 7.2
B20: GYR2 | C20: 70 | D20: 2980 | E20: 2530 | F20: =$J$12+(C20*$J$10/$L$10) -> 6.2902196 | G20: =IF(D20="","",($J$11-$H$7+D20)*$J$10/$H$12) -> 5.7732535 | H20: =IF(E20="","",($J$11-$H$7+E20)*$J$10/$H$12) -> 5.5217565 | I20: =$F$12+(C20*$J$10/$L$12) -> 1088.8889 | J20: =IF(D20="","",($J$11-$H$7+D20)*$J$10/$B$12) -> 964.13333 | K20: =IF(E20="","",($J$11-$H$7+E20)*$J$10/$B$12) -> 922.13333 | L20: 7.2
B21: GYR3 | C21: 70 | D21: 2980 | E21: 2530 | F21: =$J$12+(C21*$J$10/$L$10) -> 6.2902196 | G21: =IF(D21="","",($J$11-$H$7+D21)*$J$10/$H$12) -> 5.7732535 | H21: =IF(E21="","",($J$11-$H$7+E21)*$J$10/$H$12) -> 5.5217565 | I21: =$F$12+(C21*$J$10/$L$12) -> 1088.8889 | J21: =IF(D21="","",($J$11-$H$7+D21)*$J$10/$B$12) -> 964.13333 | K21: =IF(E21="","",($J$11-$H$7+E21)*$J$10/$B$12) -> 922.13333 | L21: 7.2
B22: LAS1 | C22: 70 | D22: 2980 | E22: 2430 | F22: =$J$12+(C22*$J$10/$L$10) -> 6.2902196 | G22: =IF(D22="","",($J$11-$H$7+D22)*$J$10/$H$12) -> 5.7732535 | H22: =IF(E22="","",($J$11-$H$7+E22)*$J$10/$H$12) -> 5.4658683 | I22: =$F$12+(C22*$J$10/$L$12) -> 1088.8889 | J22: =IF(D22="","",($J$11-$H$7+D22)*$J$10/$B$12) -> 964.13333 | K22: =IF(E22="","",($J$11-$H$7+E22)*$J$10/$B$12) -> 912.8 | L22: 7.2
B23: VGT2 | C23: 70 | D23: 2980 | E23: 2430 | F23: =$J$12+(C23*$J$10/$L$10) -> 6.2902196 | G23: =IF(D23="","",($J$11-$H$7+D23)*$J$10/$H$12) -> 5.7732535 | H23: =IF(E23="","",($J$11-$H$7+E23)*$J$10/$H$12) -> 5.4658683 | I23: =$F$12+(C23*$J$10/$L$12) -> 1088.8889 | J23: =IF(D23="","",($J$11-$H$7+D23)*$J$10/$B$12) -> 964.13333 | K23: =IF(E23="","",($J$11-$H$7+E23)*$J$10/$B$12) -> 912.8 | L23: 7.2
A24: 美西 三区 | B24: POC1 | C24: 55 | D24: 2180 | E24: 1430 | F24: =$J$12+(C24*$J$10/$L$10) -> 5.9902196 | G24: =IF(D24="","",($J$11-$H$7+D24)*$J$10/$H$12) -> 5.3261477 | H24: =IF(E24="","",($J$11-$H$7+E24)*$J$10/$H$12) -> 4.906986 | I24: =$F$12+(C24*$J$10/$L$12) -> 1030.5556 | J24: =IF(D24="","",($J$11-$H$7+D24)*$J$10/$B$12) -> 889.46667 | K24: =IF(E24="","",($J$11-$H$7+E24)*$J$10/$B$12) -> 819.46667 | L24: 6.4
B25: POC2 | C25: 55 | D25: 2180 | F25: =$J$12+(C25*$J$10/$L$10) -> 5.9902196 | G25: =IF(D25="","",($J$11-$H$7+D25)*$J$10/$H$12) -> 5.3261477 | H25: =IF(E25="","",($J$11-$H$7+E25)*$J$10/$H$12) | I25: =$F$12+(C25*$J$10/$L$12) -> 1030.5556 | J25: =IF(D25="","",($J$11-$H$7+D25)*$J$10/$B$12) -> 889.46667 | K25: =IF(E25="","",($J$11-$H$7+E25)*$J$10/$B$12) | L25: 6.4
B26: POC3 | C26: 55 | D26: 2180 | E26: 1430 | F26: =$J$12+(C26*$J$10/$L$10) -> 5.9902196 | G26: =IF(D26="","",($J$11-$H$7+D26)*$J$10/$H$12) -> 5.3261477 | H26: =IF(E26="","",($J$11-$H$7+E26)*$J$10/$H$12) -> 4.906986 | I26: =$F$12+(C26*$J$10/$L$12) -> 1030.5556 | J26: =IF(D26="","",($J$11-$H$7+D26)*$J$10/$B$12) -> 889.46667 | K26: =IF(E26="","",($J$11-$H$7+E26)*$J$10/$B$12) -> 819.46667 | L26: 6.4
B27: SNA4 | C27: 50 | D27: 2180 | E27: 1480 | F27: =$J$12+(C27*$J$10/$L$10) -> 5.8902196 | G27: =IF(D27="","",($J$11-$H$7+D27)*$J$10/$H$12) -> 5.3261477 | H27: =IF(E27="","",($J$11-$H$7+E27)*$J$10/$H$12) -> 4.9349301 | I27: =$F$12+(C27*$J$10/$L$12) -> 1011.1111 | J27: =IF(D27="","",($J$11-$H$7+D27)*$J$10/$B$12) -> 889.46667 | K27: =IF(E27="","",($J$11-$H$7+E27)*$J$10/$B$12) -> 824.13333
B28: KRB1 | C28: 50 | D28: 2180 | F28: =$J$12+(C28*$J$10/$L$10) -> 5.8902196 | G28: =IF(D28="","",($J$11-$H$7+D28)*$J$10/$H$12) -> 5.3261477 | H28: =IF(E28="","",($J$11-$H$7+E28)*$J$10/$H$12) | I28: =$F$12+(C28*$J$10/$L$12) -> 1011.1111 | J28: =IF(D28="","",($J$11-$H$7+D28)*$J$10/$B$12) -> 889.46667 | K28: =IF(E28="","",($J$11-$H$7+E28)*$J$10/$B$12)
B29: KRB4 | C29: 50 | D29: 2180 | F29: =$J$12+(C29*$J$10/$L$10) -> 5.8902196 | G29: =IF(D29="","",($J$11-$H$7+D29)*$J$10/$H$12) -> 5.3261477 | H29: =IF(E29="","",($J$11-$H$7+E29)*$J$10/$H$12) | I29: =$F$12+(C29*$J$10/$L$12) -> 1011.1111 | J29: =IF(D29="","",($J$11-$H$7+D29)*$J$10/$B$12) -> 889.46667 | K29: =IF(E29="","",($J$11-$H$7+E29)*$J$10/$B$12)
B30: IUSJ | C30: 65 | D30: 2180 | E30: 1580 | F30: =$J$12+(C30*$J$10/$L$10) -> 6.1902196 | G30: =IF(D30="","",($J$11-$H$7+D30)*$J$10/$H$12) -> 5.3261477 | H30: =IF(E30="","",($J$11-$H$7+E30)*$J$10/$H$12) -> 4.9908184 | I30: =$F$12+(C30*$J$10/$L$12) -> 1069.4444 | J30: =IF(D30="","",($J$11-$H$7+D30)*$J$10/$B$12) -> 889.46667 | K30: =IF(E30="","",($J$11-$H$7+E30)*$J$10/$B$12) -> 833.46667 | L30: 6.9
B31: IUSP | C31: 65 | D31: 2180 | E31: 1580 | F31: =$J$12+(C31*$J$10/$L$10) -> 6.1902196 | G31: =IF(D31="","",($J$11-$H$7+D31)*$J$10/$H$12) -> 5.3261477 | H31: =IF(E31="","",($J$11-$H$7+E31)*$J$10/$H$12) -> 4.9908184 | I31: =$F$12+(C31*$J$10/$L$12) -> 1069.4444 | J31: =IF(D31="","",($J$11-$H$7+D31)*$J$10/$B$12) -> 889.46667 | K31: =IF(E31="","",($J$11-$H$7+E31)*$J$10/$B$12) -> 833.46667 | L31: 6.9
B32: IUSQ | C32: 65 | D32: 2180 | E32: 1580 | F32: =$J$12+(C32*$J$10/$L$10) -> 6.1902196 | G32: =IF(D32="","",($J$11-$H$7+D32)*$J$10/$H$12) -> 5.3261477 | H32: =IF(E32="","",($J$11-$H$7+E32)*$J$10/$H$12) -> 4.9908184 | I32: =$F$12+(C32*$J$10/$L$12) -> 1069.4444 | J32: =IF(D32="","",($J$11-$H$7+D32)*$J$10/$B$12) -> 889.46667 | K32: =IF(E32="","",($J$11-$H$7+E32)*$J$10/$B$12) -> 833.46667 | L32: 6.9
A33: 美西 四区 | B33: GEU3 | C33: 85 | D33: 3180 | E33: 2750 | F33: =$J$12+(C33*$J$10/$L$10) -> 6.5902196 | G33: =IF(D33="","",($J$11-$H$7+D33)*$J$10/$H$12) -> 5.8850299 | H33: =IF(E33="","",($J$11-$H$7+E33)*$J$10/$H$12) -> 5.6447106 | I33: =$F$12+(C33*$J$10/$L$12) -> 1147.2222 | J33: =IF(D33="","",($J$11-$H$7+D33)*$J$10/$B$12) -> 982.8 | K33: =IF(E33="","",($J$11-$H$7+E33)*$J$10/$B$12) -> 942.66667 | L33: 7.2
B34: QXY8 | C34: 86 | D34: 3181 | E34: 2751 | F34: =$J$12+(C34*$J$10/$L$10) -> 6.6102196 | G34: =IF(D34="","",($J$11-$H$7+D34)*$J$10/$H$12) -> 5.8855888 | H34: =IF(E34="","",($J$11-$H$7+E34)*$J$10/$H$12) -> 5.6452695 | I34: =$F$12+(C34*$J$10/$L$12) -> 1151.1111 | J34: =IF(D34="","",($J$11-$H$7+D34)*$J$10/$B$12) -> 982.89333 | K34: =IF(E34="","",($J$11-$H$7+E34)*$J$10/$B$12) -> 942.76 | L34: 7.2
B35: GEU2 | C35: 85 | D35: 3180 | E35: 2750 | F35: =$J$12+(C35*$J$10/$L$10) -> 6.5902196 | G35: =IF(D35="","",($J$11-$H$7+D35)*$J$10/$H$12) -> 5.8850299 | H35: =IF(E35="","",($J$11-$H$7+E35)*$J$10/$H$12) -> 5.6447106 | I35: =$F$12+(C35*$J$10/$L$12) -> 1147.2222 | J35: =IF(D35="","",($J$11-$H$7+D35)*$J$10/$B$12) -> 982.8 | K35: =IF(E35="","",($J$11-$H$7+E35)*$J$10/$B$12) -> 942.66667 | L35: 7.2
B36: GEU5 | C36: 85 | D36: 3180 | E36: 2750 | F36: =$J$12+(C36*$J$10/$L$10) -> 6.5902196 | G36: =IF(D36="","",($J$11-$H$7+D36)*$J$10/$H$12) -> 5.8850299 | H36: =IF(E36="","",($J$11-$H$7+E36)*$J$10/$H$12) -> 5.6447106 | I36: =$F$12+(C36*$J$10/$L$12) -> 1147.2222 | J36: =IF(D36="","",($J$11-$H$7+D36)*$J$10/$B$12) -> 982.8 | K36: =IF(E36="","",($J$11-$H$7+E36)*$J$10/$B$12) -> 942.66667
B37: MIT2 | C37: 85 | D37: 3180 | E37: 2500 | F37: =$J$12+(C37*$J$10/$L$10) -> 6.5902196 | G37: =IF(D37="","",($J$11-$H$7+D37)*$J$10/$H$12) -> 5.8850299 | H37: =IF(E37="","",($J$11-$H$7+E37)*$J$10/$H$12) -> 5.50499 | I37: =$F$12+(C37*$J$10/$L$12) -> 1147.2222 | J37: =IF(D37="","",($J$11-$H$7+D37)*$J$10/$B$12) -> 982.8 | K37: =IF(E37="","",($J$11-$H$7+E37)*$J$10/$B$12) -> 919.33333 | L37: 7.2
B38: OAK3 | C38: 85 | D38: 3180 | F38: =$J$12+(C38*$J$10/$L$10) -> 6.5902196 | G38: =IF(D38="","",($J$11-$H$7+D38)*$J$10/$H$12) -> 5.8850299 | H38: =IF(E38="","",($J$11-$H$7+E38)*$J$10/$H$12) | I38: =$F$12+(C38*$J$10/$L$12) -> 1147.2222 | J38: =IF(D38="","",($J$11-$H$7+D38)*$J$10/$B$12) -> 982.8 | K38: =IF(E38="","",($J$11-$H$7+E38)*$J$10/$B$12)
B39: LAS6 | C39: 85 | D39: 3180 | E39: 2480 | F39: =$J$12+(C39*$J$10/$L$10) -> 6.5902196 | G39: =IF(D39="","",($J$11-$H$7+D39)*$J$10/$H$12) -> 5.8850299 | H39: =IF(E39="","",($J$11-$H$7+E39)*$J$10/$H$12) -> 5.4938124 | I39: =$F$12+(C39*$J$10/$L$12) -> 1147.2222 | J39: =IF(D39="","",($J$11-$H$7+D39)*$J$10/$B$12) -> 982.8 | K39: =IF(E39="","",($J$11-$H$7+E39)*$J$10/$B$12) -> 917.46667
B40: SMF6 | C40: 85 | D40: 3180 | F40: =$J$12+(C40*$J$10/$L$10) -> 6.5902196 | G40: =IF(D40="","",($J$11-$H$7+D40)*$J$10/$H$12) -> 5.8850299 | H40: =IF(E40="","",($J$11-$H$7+E40)*$J$10/$H$12) | I40: =$F$12+(C40*$J$10/$L$12) -> 1147.2222 | J40: =IF(D40="","",($J$11-$H$7+D40)*$J$10/$B$12) -> 982.8 | K40: =IF(E40="","",($J$11-$H$7+E40)*$J$10/$B$12)
B41: SCK8 | C41: 85 | D41: 3180 | F41: =$J$12+(C41*$J$10/$L$10) -> 6.5902196 | G41: =IF(D41="","",($J$11-$H$7+D41)*$J$10/$H$12) -> 5.8850299 | H41: =IF(E41="","",($J$11-$H$7+E41)*$J$10/$H$12) | I41: =$F$12+(C41*$J$10/$L$12) -> 1147.2222 | J41: =IF(D41="","",($J$11-$H$7+D41)*$J$10/$B$12) -> 982.8 | K41: =IF(E41="","",($J$11-$H$7+E41)*$J$10/$B$12) | L41: 7.2
A42: 美中 一区 | B42: DFW6 | C42: 160 | D42: 5380 | F42: =$J$12+(C42*$J$10/$L$10) -> 8.0902196 | G42: =IF(D42="","",($J$11-$H$7+D42)*$J$10/$H$12) -> 7.1145709 | H42: =IF(E42="","",($J$11-$H$7+E42)*$J$10/$H$12) | I42: =$F$12+(C42*$J$10/$L$12) -> 1438.8889 | J42: =IF(D42="","",($J$11-$H$7+D42)*$J$10/$B$12) -> 1188.1333 | K42: =IF(E42="","",($J$11-$H$7+E42)*$J$10/$B$12)
B43: AMA1 | C43: 170 | D43: 5380 | F43: =$J$12+(C43*$J$10/$L$10) -> 8.2902196 | G43: =IF(D43="","",($J$11-$H$7+D43)*$J$10/$H$12) -> 7.1145709 | H43: =IF(E43="","",($J$11-$H$7+E43)*$J$10/$H$12) | I43: =$F$12+(C43*$J$10/$L$12) -> 1477.7778 | J43: =IF(D43="","",($J$11-$H$7+D43)*$J$10/$B$12) -> 1188.1333 | K43: =IF(E43="","",($J$11-$H$7+E43)*$J$10/$B$12)
B44: IAH3 | C44: 190 | D44: 5380 | F44: =$J$12+(C44*$J$10/$L$10) -> 8.6902196 | G44: =IF(D44="","",($J$11-$H$7+D44)*$J$10/$H$12) -> 7.1145709 | H44: =IF(E44="","",($J$11-$H$7+E44)*$J$10/$H$12) | I44: =$F$12+(C44*$J$10/$L$12) -> 1555.5556 | J44: =IF(D44="","",($J$11-$H$7+D44)*$J$10/$B$12) -> 1188.1333 | K44: =IF(E44="","",($J$11-$H$7+E44)*$J$10/$B$12) | L44: 8.8
B45: ABQ2 | C45: 160 | D45: 5380 | E45: 4280 | F45: =$J$12+(C45*$J$10/$L$10) -> 8.0902196 | G45: =IF(D45="","",($J$11-$H$7+D45)*$J$10/$H$12) -> 7.1145709 | H45: =IF(E45="","",($J$11-$H$7+E45)*$J$10/$H$12) -> 6.4998004 | I45: =$F$12+(C45*$J$10/$L$12) -> 1438.8889 | J45: =IF(D45="","",($J$11-$H$7+D45)*$J$10/$B$12) -> 1188.1333 | K45: =IF(E45="","",($J$11-$H$7+E45)*$J$10/$B$12) -> 1085.4667 | L45: 8.3
A46: 美中二区 | B46: PSC2 | C46: 215 | D46: 5380 | F46: =$J$12+(C46*$J$10/$L$10) -> 9.1902196 | G46: =IF(D46="","",($J$11-$H$7+D46)*$J$10/$H$12) -> 7.1145709 | H46: =IF(E46="","",($J$11-$H$7+E46)*$J$10/$H$12) | I46: =$F$12+(C46*$J$10/$L$12) -> 1652.7778 | J46: =IF(D46="","",($J$11-$H$7+D46)*$J$10/$B$12) -> 1188.1333 | K46: =IF(E46="","",($J$11-$H$7+E46)*$J$10/$B$12) | L46: 8.8
B47: FTW1 | C47: 150 | D47: 6380 | F47: =$J$12+(C47*$J$10/$L$10) -> 7.8902196 | G47: =IF(D47="","",($J$11-$H$7+D47)*$J$10/$H$12) -> 7.6734531 | H47: =IF(E47="","",($J$11-$H$7+E47)*$J$10/$H$12) | I47: =$F$12+(C47*$J$10/$L$12) -> 1400 | J47: =IF(D47="","",($J$11-$H$7+D47)*$J$10/$B$12) -> 1281.4667 | K47: =IF(E47="","",($J$11-$H$7+E47)*$J$10/$B$12) | L47: 8.3
B48: IND9 | C48: 190 | D48: 6380 | F48: =$J$12+(C48*$J$10/$L$10) -> 8.6902196 | G48: =IF(D48="","",($J$11-$H$7+D48)*$J$10/$H$12) -> 7.6734531 | H48: =IF(E48="","",($J$11-$H$7+E48)*$J$10/$H$12) | I48: =$F$12+(C48*$J$10/$L$12) -> 1555.5556 | J48: =IF(D48="","",($J$11-$H$7+D48)*$J$10/$B$12) -> 1281.4667 | K48: =IF(E48="","",($J$11-$H$7+E48)*$J$10/$B$12) | L48: 8.8
B49: MDW2 | C49: 190 | D49: 6380 | F49: =$J$12+(C49*$J$10/$L$10) -> 8.6902196 | G49: =IF(D49="","",($J$11-$H$7+D49)*$J$10/$H$12) -> 7.6734531 | H49: =IF(E49="","",($J$11-$H$7+E49)*$J$10/$H$12) | I49: =$F$12+(C49*$J$10/$L$12) -> 1555.5556 | J49: =IF(D49="","",($J$11-$H$7+D49)*$J$10/$B$12) -> 1281.4667 | K49: =IF(E49="","",($J$11-$H$7+E49)*$J$10/$B$12) | L49: 8.8
B50: MEM1 | C50: 190 | D50: 6380 | F50: =$J$12+(C50*$J$10/$L$10) -> 8.6902196 | G50: =IF(D50="","",($J$11-$H$7+D50)*$J$10/$H$12) -> 7.6734531 | H50: =IF(E50="","",($J$11-$H$7+E50)*$J$10/$H$12) | I50: =$F$12+(C50*$J$10/$L$12) -> 1555.5556 | J50: =IF(D50="","",($J$11-$H$7+D50)*$J$10/$B$12) -> 1281.4667 | K50: =IF(E50="","",($J$11-$H$7+E50)*$J$10/$B$12) | L50: 8.8
B51: MQJ1 | C51: 190 | D51: 6380 | F51: =$J$12+(C51*$J$10/$L$10) -> 8.6902196 | G51: =IF(D51="","",($J$11-$H$7+D51)*$J$10/$H$12) -> 7.6734531 | H51: =IF(E51="","",($J$11-$H$7+E51)*$J$10/$H$12) | I51: =$F$12+(C51*$J$10/$L$12) -> 1555.5556 | J51: =IF(D51="","",($J$11-$H$7+D51)*$J$10/$B$12) -> 1281.4667 | K51: =IF(E51="","",($J$11-$H$7+E51)*$J$10/$B$12) | L51: 8.8
A52: 美中 长途 | B52: FTW3 | C52: 180 | D52: 5880 | F52: =$J$12+(C52*$J$10/$L$10) -> 8.4902196 | G52: =IF(D52="","",($J$11-$H$7+D52)*$J$10/$H$12) -> 7.394012 | H52: =IF(E52="","",($J$11-$H$7+E52)*$J$10/$H$12) | I52: =$F$12+(C52*$J$10/$L$12) -> 1516.6667 | J52: =IF(D52="","",($J$11-$H$7+D52)*$J$10/$B$12) -> 1234.8 | K52: =IF(E52="","",($J$11-$H$7+E52)*$J$10/$B$12)
B53: SAT4 | C53: 180 | D53: 5880 | F53: =$J$12+(C53*$J$10/$L$10) -> 8.4902196 | G53: =IF(D53="","",($J$11-$H$7+D53)*$J$10/$H$12) -> 7.394012 | H53: =IF(E53="","",($J$11-$H$7+E53)*$J$10/$H$12) | I53: =$F$12+(C53*$J$10/$L$12) -> 1516.6667 | J53: =IF(D53="","",($J$11-$H$7+D53)*$J$10/$B$12) -> 1234.8 | K53: =IF(E53="","",($J$11-$H$7+E53)*$J$10/$B$12) | L53: 8.8
B54: SAT6 | C54: 180 | D54: 5880 | F54: =$J$12+(C54*$J$10/$L$10) -> 8.4902196 | G54: =IF(D54="","",($J$11-$H$7+D54)*$J$10/$H$12) -> 7.394012 | H54: =IF(E54="","",($J$11-$H$7+E54)*$J$10/$H$12) | I54: =$F$12+(C54*$J$10/$L$12) -> 1516.6667 | J54: =IF(D54="","",($J$11-$H$7+D54)*$J$10/$B$12) -> 1234.8 | K54: =IF(E54="","",($J$11-$H$7+E54)*$J$10/$B$12)
B55: HOU8 | C55: 195 | D55: 5880 | F55: =$J$12+(C55*$J$10/$L$10) -> 8.7902196 | G55: =IF(D55="","",($J$11-$H$7+D55)*$J$10/$H$12) -> 7.394012 | H55: =IF(E55="","",($J$11-$H$7+E55)*$J$10/$H$12) | I55: =$F$12+(C55*$J$10/$L$12) -> 1575 | J55: =IF(D55="","",($J$11-$H$7+D55)*$J$10/$B$12) -> 1234.8 | K55: =IF(E55="","",($J$11-$H$7+E55)*$J$10/$B$12)
B56: SLC2 | C56: 130 | D56: 5880 | F56: =$J$12+(C56*$J$10/$L$10) -> 7.4902196 | G56: =IF(D56="","",($J$11-$H$7+D56)*$J$10/$H$12) -> 7.394012 | H56: =IF(E56="","",($J$11-$H$7+E56)*$J$10/$H$12) | I56: =$F$12+(C56*$J$10/$L$12) -> 1322.2222 | J56: =IF(D56="","",($J$11-$H$7+D56)*$J$10/$B$12) -> 1234.8 | K56: =IF(E56="","",($J$11-$H$7+E56)*$J$10/$B$12)
B57: DEN2 | C57: 195 | D57: 5880 | F57: =$J$12+(C57*$J$10/$L$10) -> 8.7902196 | G57: =IF(D57="","",($J$11-$H$7+D57)*$J$10/$H$12) -> 7.394012 | H57: =IF(E57="","",($J$11-$H$7+E57)*$J$10/$H$12) | I57: =$F$12+(C57*$J$10/$L$12) -> 1575 | J57: =IF(D57="","",($J$11-$H$7+D57)*$J$10/$B$12) -> 1234.8 | K57: =IF(E57="","",($J$11-$H$7+E57)*$J$10/$B$12)
B58: DEN8 | C58: 195 | D58: 5880 | F58: =$J$12+(C58*$J$10/$L$10) -> 8.7902196 | G58: =IF(D58="","",($J$11-$H$7+D58)*$J$10/$H$12) -> 7.394012 | H58: =IF(E58="","",($J$11-$H$7+E58)*$J$10/$H$12) | I58: =$F$12+(C58*$J$10/$L$12) -> 1575 | J58: =IF(D58="","",($J$11-$H$7+D58)*$J$10/$B$12) -> 1234.8 | K58: =IF(E58="","",($J$11-$H$7+E58)*$J$10/$B$12)
B59: RNO4 | C59: 130 | D59: 5880 | F59: =$J$12+(C59*$J$10/$L$10) -> 7.4902196 | G59: =IF(D59="","",($J$11-$H$7+D59)*$J$10/$H$12) -> 7.394012 | H59: =IF(E59="","",($J$11-$H$7+E59)*$J$10/$H$12) | I59: =$F$12+(C59*$J$10/$L$12) -> 1322.2222 | J59: =IF(D59="","",($J$11-$H$7+D59)*$J$10/$B$12) -> 1234.8 | K59: =IF(E59="","",($J$11-$H$7+E59)*$J$10/$B$12)
B60: ORD2 | C60: 195 | D60: 7280 | F60: =$J$12+(C60*$J$10/$L$10) -> 8.7902196 | G60: =IF(D60="","",($J$11-$H$7+D60)*$J$10/$H$12) -> 8.1764471 | H60: =IF(E60="","",($J$11-$H$7+E60)*$J$10/$H$12) | I60: =$F$12+(C60*$J$10/$L$12) -> 1575 | J60: =IF(D60="","",($J$11-$H$7+D60)*$J$10/$B$12) -> 1365.4667 | K60: =IF(E60="","",($J$11-$H$7+E60)*$J$10/$B$12)
B61: FWA4 | C61: 190 | D61: 7280 | F61: =$J$12+(C61*$J$10/$L$10) -> 8.6902196 | G61: =IF(D61="","",($J$11-$H$7+D61)*$J$10/$H$12) -> 8.1764471 | H61: =IF(E61="","",($J$11-$H$7+E61)*$J$10/$H$12) | I61: =$F$12+(C61*$J$10/$L$12) -> 1555.5556 | J61: =IF(D61="","",($J$11-$H$7+D61)*$J$10/$B$12) -> 1365.4667 | K61: =IF(E61="","",($J$11-$H$7+E61)*$J$10/$B$12) | L61: 8.8
B62: RFD2 | C62: 220 | D62: 7280 | F62: =$J$12+(C62*$J$10/$L$10) -> 9.2902196 | G62: =IF(D62="","",($J$11-$H$7+D62)*$J$10/$H$12) -> 8.1764471 | H62: =IF(E62="","",($J$11-$H$7+E62)*$J$10/$H$12) | I62: =$F$12+(C62*$J$10/$L$12) -> 1672.2222 | J62: =IF(D62="","",($J$11-$H$7+D62)*$J$10/$B$12) -> 1365.4667 | K62: =IF(E62="","",($J$11-$H$7+E62)*$J$10/$B$12) | L62: 8.8
B63: STL3 | C63: 190 | D63: 7280 | F63: =$J$12+(C63*$J$10/$L$10) -> 8.6902196 | G63: =IF(D63="","",($J$11-$H$7+D63)*$J$10/$H$12) -> 8.1764471 | H63: =IF(E63="","",($J$11-$H$7+E63)*$J$10/$H$12) | I63: =$F$12+(C63*$J$10/$L$12) -> 1555.5556 | J63: =IF(D63="","",($J$11-$H$7+D63)*$J$10/$B$12) -> 1365.4667 | K63: =IF(E63="","",($J$11-$H$7+E63)*$J$10/$B$12)
B64: STL4 | C64: 190 | D64: 7280 | F64: =$J$12+(C64*$J$10/$L$10) -> 8.6902196 | G64: =IF(D64="","",($J$11-$H$7+D64)*$J$10/$H$12) -> 8.1764471 | H64: =IF(E64="","",($J$11-$H$7+E64)*$J$10/$H$12) | I64: =$F$12+(C64*$J$10/$L$12) -> 1555.5556 | J64: =IF(D64="","",($J$11-$H$7+D64)*$J$10/$B$12) -> 1365.4667 | K64: =IF(E64="","",($J$11-$H$7+E64)*$J$10/$B$12)
B65: IND2 | C65: 225 | D65: 7280 | F65: =$J$12+(C65*$J$10/$L$10) -> 9.3902196 | G65: =IF(D65="","",($J$11-$H$7+D65)*$J$10/$H$12) -> 8.1764471 | H65: =IF(E65="","",($J$11-$H$7+E65)*$J$10/$H$12) | I65: =$F$12+(C65*$J$10/$L$12) -> 1691.6667 | J65: =IF(D65="","",($J$11-$H$7+D65)*$J$10/$B$12) -> 1365.4667 | K65: =IF(E65="","",($J$11-$H$7+E65)*$J$10/$B$12)
B66: IND4 | C66: 225 | D66: 7280 | F66: =$J$12+(C66*$J$10/$L$10) -> 9.3902196 | G66: =IF(D66="","",($J$11-$H$7+D66)*$J$10/$H$12) -> 8.1764471 | H66: =IF(E66="","",($J$11-$H$7+E66)*$J$10/$H$12) | I66: =$F$12+(C66*$J$10/$L$12) -> 1691.6667 | J66: =IF(D66="","",($J$11-$H$7+D66)*$J$10/$B$12) -> 1365.4667 | K66: =IF(E66="","",($J$11-$H$7+E66)*$J$10/$B$12)
B67: MEM6 | C67: 190 | D67: 7280 | F67: =$J$12+(C67*$J$10/$L$10) -> 8.6902196 | G67: =IF(D67="","",($J$11-$H$7+D67)*$J$10/$H$12) -> 8.1764471 | H67: =IF(E67="","",($J$11-$H$7+E67)*$J$10/$H$12) | I67: =$F$12+(C67*$J$10/$L$12) -> 1555.5556 | J67: =IF(D67="","",($J$11-$H$7+D67)*$J$10/$B$12) -> 1365.4667 | K67: =IF(E67="","",($J$11-$H$7+E67)*$J$10/$B$12)
B68: BNA6 | C68: 235 | D68: 7280 | F68: =$J$12+(C68*$J$10/$L$10) -> 9.5902196 | G68: =IF(D68="","",($J$11-$H$7+D68)*$J$10/$H$12) -> 8.1764471 | H68: =IF(E68="","",($J$11-$H$7+E68)*$J$10/$H$12) | I68: =$F$12+(C68*$J$10/$L$12) -> 1730.5556 | J68: =IF(D68="","",($J$11-$H$7+D68)*$J$10/$B$12) -> 1365.4667 | K68: =IF(E68="","",($J$11-$H$7+E68)*$J$10/$B$12) | L68: 10.1
B69: OKC2 | C69: 215 | D69: 7280 | F69: =$J$12+(C69*$J$10/$L$10) -> 9.1902196 | G69: =IF(D69="","",($J$11-$H$7+D69)*$J$10/$H$12) -> 8.1764471 | H69: =IF(E69="","",($J$11-$H$7+E69)*$J$10/$H$12) | I69: =$F$12+(C69*$J$10/$L$12) -> 1652.7778 | J69: =IF(D69="","",($J$11-$H$7+D69)*$J$10/$B$12) -> 1365.4667 | K69: =IF(E69="","",($J$11-$H$7+E69)*$J$10/$B$12)
B70: LIT2 | C70: 235 | D70: 7280 | F70: =$J$12+(C70*$J$10/$L$10) -> 9.5902196 | G70: =IF(D70="","",($J$11-$H$7+D70)*$J$10/$H$12) -> 8.1764471 | H70: =IF(E70="","",($J$11-$H$7+E70)*$J$10/$H$12) | I70: =$F$12+(C70*$J$10/$L$12) -> 1730.5556 | J70: =IF(D70="","",($J$11-$H$7+D70)*$J$10/$B$12) -> 1365.4667 | K70: =IF(E70="","",($J$11-$H$7+E70)*$J$10/$B$12)
B71: JVL1 | C71: 235 | D71: 7280 | F71: =$J$12+(C71*$J$10/$L$10) -> 9.5902196 | G71: =IF(D71="","",($J$11-$H$7+D71)*$J$10/$H$12) -> 8.1764471 | H71: =IF(E71="","",($J$11-$H$7+E71)*$J$10/$H$12) | I71: =$F$12+(C71*$J$10/$L$12) -> 1730.5556 | J71: =IF(D71="","",($J$11-$H$7+D71)*$J$10/$B$12) -> 1365.4667 | K71: =IF(E71="","",($J$11-$H$7+E71)*$J$10/$B$12)
A72: 美东9区 | B72: CLT2 | C72: 255 | D72: 7980 | F72: =$J$12+(C72*$J$10/$L$10) -> 9.9902196 | G72: =IF(D72="","",($J$11-$H$7+D72)*$J$10/$H$12) -> 8.5676647 | H72: =IF(E72="","",($J$11-$H$7+E72)*$J$10/$H$12) | I72: =$F$12+(C72*$J$10/$L$12) -> 1808.3333 | J72: =IF(D72="","",($J$11-$H$7+D72)*$J$10/$B$12) -> 1430.8 | K72: =IF(E72="","",($J$11-$H$7+E72)*$J$10/$B$12) | L72: 9.6
B73: MCO2 | C73: 265 | D73: 7980 | F73: =$J$12+(C73*$J$10/$L$10) -> 10.19022 | G73: =IF(D73="","",($J$11-$H$7+D73)*$J$10/$H$12) -> 8.5676647 | H73: =IF(E73="","",($J$11-$H$7+E73)*$J$10/$H$12) | I73: =$F$12+(C73*$J$10/$L$12) -> 1847.2222 | J73: =IF(D73="","",($J$11-$H$7+D73)*$J$10/$B$12) -> 1430.8 | K73: =IF(E73="","",($J$11-$H$7+E73)*$J$10/$B$12)
B74: TPA2 | C74: 265 | D74: 7980 | F74: =$J$12+(C74*$J$10/$L$10) -> 10.19022 | G74: =IF(D74="","",($J$11-$H$7+D74)*$J$10/$H$12) -> 8.5676647 | H74: =IF(E74="","",($J$11-$H$7+E74)*$J$10/$H$12) | I74: =$F$12+(C74*$J$10/$L$12) -> 1847.2222 | J74: =IF(D74="","",($J$11-$H$7+D74)*$J$10/$B$12) -> 1430.8 | K74: =IF(E74="","",($J$11-$H$7+E74)*$J$10/$B$12) | L74: 9.6
B75: TPA3 | C75: 265 | D75: 7980 | F75: =$J$12+(C75*$J$10/$L$10) -> 10.19022 | G75: =IF(D75="","",($J$11-$H$7+D75)*$J$10/$H$12) -> 8.5676647 | H75: =IF(E75="","",($J$11-$H$7+E75)*$J$10/$H$12) | I75: =$F$12+(C75*$J$10/$L$12) -> 1847.2222 | J75: =IF(D75="","",($J$11-$H$7+D75)*$J$10/$B$12) -> 1430.8 | K75: =IF(E75="","",($J$11-$H$7+E75)*$J$10/$B$12) | L75: 9.6
B76: CMH2 | C76: 230 | D76: 7980 | F76: =$J$12+(C76*$J$10/$L$10) -> 9.4902196 | G76: =IF(D76="","",($J$11-$H$7+D76)*$J$10/$H$12) -> 8.5676647 | H76: =IF(E76="","",($J$11-$H$7+E76)*$J$10/$H$12) | I76: =$F$12+(C76*$J$10/$L$12) -> 1711.1111 | J76: =IF(D76="","",($J$11-$H$7+D76)*$J$10/$B$12) -> 1430.8 | K76: =IF(E76="","",($J$11-$H$7+E76)*$J$10/$B$12)
B77: CMH3 | C77: 230 | D77: 7980 | F77: =$J$12+(C77*$J$10/$L$10) -> 9.4902196 | G77: =IF(D77="","",($J$11-$H$7+D77)*$J$10/$H$12) -> 8.5676647 | H77: =IF(E77="","",($J$11-$H$7+E77)*$J$10/$H$12) | I77: =$F$12+(C77*$J$10/$L$12) -> 1711.1111 | J77: =IF(D77="","",($J$11-$H$7+D77)*$J$10/$B$12) -> 1430.8 | K77: =IF(E77="","",($J$11-$H$7+E77)*$J$10/$B$12)
B78: DET1 | C78: 250 | D78: 7980 | F78: =$J$12+(C78*$J$10/$L$10) -> 9.8902196 | G78: =IF(D78="","",($J$11-$H$7+D78)*$J$10/$H$12) -> 8.5676647 | H78: =IF(E78="","",($J$11-$H$7+E78)*$J$10/$H$12) | I78: =$F$12+(C78*$J$10/$L$12) -> 1788.8889 | J78: =IF(D78="","",($J$11-$H$7+D78)*$J$10/$B$12) -> 1430.8 | K78: =IF(E78="","",($J$11-$H$7+E78)*$J$10/$B$12)
B79: DET2 | C79: 250 | D79: 7980 | F79: =$J$12+(C79*$J$10/$L$10) -> 9.8902196 | G79: =IF(D79="","",($J$11-$H$7+D79)*$J$10/$H$12) -> 8.5676647 | H79: =IF(E79="","",($J$11-$H$7+E79)*$J$10/$H$12) | I79: =$F$12+(C79*$J$10/$L$12) -> 1788.8889 | J79: =IF(D79="","",($J$11-$H$7+D79)*$J$10/$B$12) -> 1430.8 | K79: =IF(E79="","",($J$11-$H$7+E79)*$J$10/$B$12)
B80: AKR1 | C80: 270 | D80: 7980 | F80: =$J$12+(C80*$J$10/$L$10) -> 10.29022 | G80: =IF(D80="","",($J$11-$H$7+D80)*$J$10/$H$12) -> 8.5676647 | H80: =IF(E80="","",($J$11-$H$7+E80)*$J$10/$H$12) | I80: =$F$12+(C80*$J$10/$L$12) -> 1866.6667 | J80: =IF(D80="","",($J$11-$H$7+D80)*$J$10/$B$12) -> 1430.8 | K80: =IF(E80="","",($J$11-$H$7+E80)*$J$10/$B$12)
B81: LAN2 | C81: 250 | D81: 7980 | F81: =$J$12+(C81*$J$10/$L$10) -> 9.8902196 | G81: =IF(D81="","",($J$11-$H$7+D81)*$J$10/$H$12) -> 8.5676647 | H81: =IF(E81="","",($J$11-$H$7+E81)*$J$10/$H$12) | I81: =$F$12+(C81*$J$10/$L$12) -> 1788.8889 | J81: =IF(D81="","",($J$11-$H$7+D81)*$J$10/$B$12) -> 1430.8 | K81: =IF(E81="","",($J$11-$H$7+E81)*$J$10/$B$12)
B82: RYY2 | C82: 250 | D82: 7980 | F82: =$J$12+(C82*$J$10/$L$10) -> 9.8902196 | G82: =IF(D82="","",($J$11-$H$7+D82)*$J$10/$H$12) -> 8.5676647 | H82: =IF(E82="","",($J$11-$H$7+E82)*$J$10/$H$12) | I82: =$F$12+(C82*$J$10/$L$12) -> 1788.8889 | J82: =IF(D82="","",($J$11-$H$7+D82)*$J$10/$B$12) -> 1430.8 | K82: =IF(E82="","",($J$11-$H$7+E82)*$J$10/$B$12)
B83: JAX3 | C83: 295 | D83: 7980 | F83: =$J$12+(C83*$J$10/$L$10) -> 10.79022 | G83: =IF(D83="","",($J$11-$H$7+D83)*$J$10/$H$12) -> 8.5676647 | H83: =IF(E83="","",($J$11-$H$7+E83)*$J$10/$H$12) | I83: =$F$12+(C83*$J$10/$L$12) -> 1963.8889 | J83: =IF(D83="","",($J$11-$H$7+D83)*$J$10/$B$12) -> 1430.8 | K83: =IF(E83="","",($J$11-$H$7+E83)*$J$10/$B$12)
B84: PBI3 | C84: 295 | D84: 7980 | F84: =$J$12+(C84*$J$10/$L$10) -> 10.79022 | G84: =IF(D84="","",($J$11-$H$7+D84)*$J$10/$H$12) -> 8.5676647 | H84: =IF(E84="","",($J$11-$H$7+E84)*$J$10/$H$12) | I84: =$F$12+(C84*$J$10/$L$12) -> 1963.8889 | J84: =IF(D84="","",($J$11-$H$7+D84)*$J$10/$B$12) -> 1430.8 | K84: =IF(E84="","",($J$11-$H$7+E84)*$J$10/$B$12)
B85: RDU2 | C85: 280 | D85: 7980 | F85: =$J$12+(C85*$J$10/$L$10) -> 10.49022 | G85: =IF(D85="","",($J$11-$H$7+D85)*$J$10/$H$12) -> 8.5676647 | H85: =IF(E85="","",($J$11-$H$7+E85)*$J$10/$H$12) | I85: =$F$12+(C85*$J$10/$L$12) -> 1905.5556 | J85: =IF(D85="","",($J$11-$H$7+D85)*$J$10/$B$12) -> 1430.8 | K85: =IF(E85="","",($J$11-$H$7+E85)*$J$10/$B$12) | L85: 9.6
A86: 美东10区 | B86: ORF2 | C86: 290 | D86: 8680 | F86: =$J$12+(C86*$J$10/$L$10) -> 10.69022 | G86: =IF(D86="","",($J$11-$H$7+D86)*$J$10/$H$12) -> 8.9588822 | H86: =IF(E86="","",($J$11-$H$7+E86)*$J$10/$H$12) | I86: =$F$12+(C86*$J$10/$L$12) -> 1944.4444 | J86: =IF(D86="","",($J$11-$H$7+D86)*$J$10/$B$12) -> 1496.1333 | K86: =IF(E86="","",($J$11-$H$7+E86)*$J$10/$B$12) | L86: 10.1
B87: CHO1 | C87: 290 | D87: 8680 | F87: =$J$12+(C87*$J$10/$L$10) -> 10.69022 | G87: =IF(D87="","",($J$11-$H$7+D87)*$J$10/$H$12) -> 8.9588822 | H87: =IF(E87="","",($J$11-$H$7+E87)*$J$10/$H$12) | I87: =$F$12+(C87*$J$10/$L$12) -> 1944.4444 | J87: =IF(D87="","",($J$11-$H$7+D87)*$J$10/$B$12) -> 1496.1333 | K87: =IF(E87="","",($J$11-$H$7+E87)*$J$10/$B$12)
B88: RMN3 | C88: 285 | D88: 8680 | F88: =$J$12+(C88*$J$10/$L$10) -> 10.59022 | G88: =IF(D88="","",($J$11-$H$7+D88)*$J$10/$H$12) -> 8.9588822 | H88: =IF(E88="","",($J$11-$H$7+E88)*$J$10/$H$12) | I88: =$F$12+(C88*$J$10/$L$12) -> 1925 | J88: =IF(D88="","",($J$11-$H$7+D88)*$J$10/$B$12) -> 1496.1333 | K88: =IF(E88="","",($J$11-$H$7+E88)*$J$10/$B$12) | L88: 10.1
B89: DCA6 | C89: 285 | D89: 8680 | F89: =$J$12+(C89*$J$10/$L$10) -> 10.59022 | G89: =IF(D89="","",($J$11-$H$7+D89)*$J$10/$H$12) -> 8.9588822 | H89: =IF(E89="","",($J$11-$H$7+E89)*$J$10/$H$12) | I89: =$F$12+(C89*$J$10/$L$12) -> 1925 | J89: =IF(D89="","",($J$11-$H$7+D89)*$J$10/$B$12) -> 1496.1333 | K89: =IF(E89="","",($J$11-$H$7+E89)*$J$10/$B$12)
B90: TEB3 | C90: 290 | D90: 8680 | F90: =$J$12+(C90*$J$10/$L$10) -> 10.69022 | G90: =IF(D90="","",($J$11-$H$7+D90)*$J$10/$H$12) -> 8.9588822 | H90: =IF(E90="","",($J$11-$H$7+E90)*$J$10/$H$12) | I90: =$F$12+(C90*$J$10/$L$12) -> 1944.4444 | J90: =IF(D90="","",($J$11-$H$7+D90)*$J$10/$B$12) -> 1496.1333 | K90: =IF(E90="","",($J$11-$H$7+E90)*$J$10/$B$12) | L90: 10.1
B91: TEB4 | C91: 290 | D91: 8680 | F91: =$J$12+(C91*$J$10/$L$10) -> 10.69022 | G91: =IF(D91="","",($J$11-$H$7+D91)*$J$10/$H$12) -> 8.9588822 | H91: =IF(E91="","",($J$11-$H$7+E91)*$J$10/$H$12) | I91: =$F$12+(C91*$J$10/$L$12) -> 1944.4444 | J91: =IF(D91="","",($J$11-$H$7+D91)*$J$10/$B$12) -> 1496.1333 | K91: =IF(E91="","",($J$11-$H$7+E91)*$J$10/$B$12)
B92: TEB6 | C92: 295 | D92: 8680 | F92: =$J$12+(C92*$J$10/$L$10) -> 10.79022 | G92: =IF(D92="","",($J$11-$H$7+D92)*$J$10/$H$12) -> 8.9588822 | H92: =IF(E92="","",($J$11-$H$7+E92)*$J$10/$H$12) | I92: =$F$12+(C92*$J$10/$L$12) -> 1963.8889 | J92: =IF(D92="","",($J$11-$H$7+D92)*$J$10/$B$12) -> 1496.1333 | K92: =IF(E92="","",($J$11-$H$7+E92)*$J$10/$B$12)
B93: TEB9 | C93: 295 | D93: 8680 | F93: =$J$12+(C93*$J$10/$L$10) -> 10.79022 | G93: =IF(D93="","",($J$11-$H$7+D93)*$J$10/$H$12) -> 8.9588822 | H93: =IF(E93="","",($J$11-$H$7+E93)*$J$10/$H$12) | I93: =$F$12+(C93*$J$10/$L$12) -> 1963.8889 | J93: =IF(D93="","",($J$11-$H$7+D93)*$J$10/$B$12) -> 1496.1333 | K93: =IF(E93="","",($J$11-$H$7+E93)*$J$10/$B$12) | L93: 10.1
B94: ACY2 | C94: 300 | D94: 8680 | F94: =$J$12+(C94*$J$10/$L$10) -> 10.89022 | G94: =IF(D94="","",($J$11-$H$7+D94)*$J$10/$H$12) -> 8.9588822 | H94: =IF(E94="","",($J$11-$H$7+E94)*$J$10/$H$12) | I94: =$F$12+(C94*$J$10/$L$12) -> 1983.3333 | J94: =IF(D94="","",($J$11-$H$7+D94)*$J$10/$B$12) -> 1496.1333 | K94: =IF(E94="","",($J$11-$H$7+E94)*$J$10/$B$12)
B95: ABE4 | C95: 290 | D95: 8680 | F95: =$J$12+(C95*$J$10/$L$10) -> 10.69022 | G95: =IF(D95="","",($J$11-$H$7+D95)*$J$10/$H$12) -> 8.9588822 | H95: =IF(E95="","",($J$11-$H$7+E95)*$J$10/$H$12) | I95: =$F$12+(C95*$J$10/$L$12) -> 1944.4444 | J95: =IF(D95="","",($J$11-$H$7+D95)*$J$10/$B$12) -> 1496.1333 | K95: =IF(E95="","",($J$11-$H$7+E95)*$J$10/$B$12)
B96: ABE8 | C96: 275 | D96: 8680 | F96: =$J$12+(C96*$J$10/$L$10) -> 10.39022 | G96: =IF(D96="","",($J$11-$H$7+D96)*$J$10/$H$12) -> 8.9588822 | H96: =IF(E96="","",($J$11-$H$7+E96)*$J$10/$H$12) | I96: =$F$12+(C96*$J$10/$L$12) -> 1886.1111 | J96: =IF(D96="","",($J$11-$H$7+D96)*$J$10/$B$12) -> 1496.1333 | K96: =IF(E96="","",($J$11-$H$7+E96)*$J$10/$B$12) | L96: 10.1
B97: AVP1 | C97: 295 | D97: 8680 | F97: =$J$12+(C97*$J$10/$L$10) -> 10.79022 | G97: =IF(D97="","",($J$11-$H$7+D97)*$J$10/$H$12) -> 8.9588822 | H97: =IF(E97="","",($J$11-$H$7+E97)*$J$10/$H$12) | I97: =$F$12+(C97*$J$10/$L$12) -> 1963.8889 | J97: =IF(D97="","",($J$11-$H$7+D97)*$J$10/$B$12) -> 1496.1333 | K97: =IF(E97="","",($J$11-$H$7+E97)*$J$10/$B$12) | L97: 10.1
B98: AVP3 | C98: 290 | D98: 8680 | F98: =$J$12+(C98*$J$10/$L$10) -> 10.69022 | G98: =IF(D98="","",($J$11-$H$7+D98)*$J$10/$H$12) -> 8.9588822 | H98: =IF(E98="","",($J$11-$H$7+E98)*$J$10/$H$12) | I98: =$F$12+(C98*$J$10/$L$12) -> 1944.4444 | J98: =IF(D98="","",($J$11-$H$7+D98)*$J$10/$B$12) -> 1496.1333 | K98: =IF(E98="","",($J$11-$H$7+E98)*$J$10/$B$12) | L98: 10.1
B99: PIT2 | C99: 290 | D99: 8680 | F99: =$J$12+(C99*$J$10/$L$10) -> 10.69022 | G99: =IF(D99="","",($J$11-$H$7+D99)*$J$10/$H$12) -> 8.9588822 | H99: =IF(E99="","",($J$11-$H$7+E99)*$J$10/$H$12) | I99: =$F$12+(C99*$J$10/$L$12) -> 1944.4444 | J99: =IF(D99="","",($J$11-$H$7+D99)*$J$10/$B$12) -> 1496.1333 | K99: =IF(E99="","",($J$11-$H$7+E99)*$J$10/$B$12)
B100: PHL5 | C100: 290 | D100: 8680 | F100: =$J$12+(C100*$J$10/$L$10) -> 10.69022 | G100: =IF(D100="","",($J$11-$H$7+D100)*$J$10/$H$12) -> 8.9588822 | H100: =IF(E100="","",($J$11-$H$7+E100)*$J$10/$H$12) | I100: =$F$12+(C100*$J$10/$L$12) -> 1944.4444 | J100: =IF(D100="","",($J$11-$H$7+D100)*$J$10/$B$12) -> 1496.1333 | K100: =IF(E100="","",($J$11-$H$7+E100)*$J$10/$B$12)
...

Sheet 洛杉矶600
A1: 应付 | B1: 盐田——LB | F1: 费用类型 | G1: 币种 | H1: 单价 | I1: 数量 | J1: 备注 | K1: 统计
B2: 起运港 | C2: 拖车+报关 | F2: 装柜费 | G2: RMB | H2: 500 | I2: 1
F3: 拖车费 | G3: RMB | H3: 1950 | I3: 1
F4: 报关费 | G4: RMB | H4: 500 | I4: 0 | J4: 实报实销 | K4: 100/票
F5: 港杂费RMB部分 | G5: RMB | H5: 3000 | I5: 1
F6: 海运费（变动） | G6: USD | H6: 2850 | I6: 1
B7: 目的港 | C7: 提柜+拆柜 | F7: 提拆一口价 | G7: USD | H7: 1400 | I7: 1
C8: 清关+缴税 | F8: 清关费 | G8: USD | I8: 1
F9: 税金 | G9: USD | H9: 1300 | I9: 1 | L9: 每板KG
A10: 盐田-LB/LA | B10: 人民币应付 | G10: RMB | H10: =SUM(H2:H5) -> 5950 | I10: 汇率 | J10: 7 | K10: =H10/J10 -> 850 | L10: 350
A11: 报价：2025/03/16 | B11: 含税/CBM | G11: USD | H11: =SUM(H6:H9) -> 5550 | I11: 合计 | J11: =H11+K10 -> 6400 | K11: =J11*J10 -> 44800 | L11: CBM
A12: CBM标准 | B12: 75 | E12: CBM计费标准 | F12: =K11/B12 -> 597.33333 | G12: KG标准 | H12: =B12*167 -> 12525 | I12: KG计费标准 | J12: =F12/167 -> 3.5768463 | L12: 1.8
B13: 派送费 | C13: 美金/板 | D13: 组合一口价 | E13: 整柜一口价 | F13: 拆送KG含税 | G13: 组合KG | H13: 直送KG | I13: 拆送CBM含税 | J13: 组合CBM | K13: 直送CBM | L13: 直客报价101KG+
A14: 美西 组合一 | B14: ONT8 | C14: 30 | D14: 1900 | E14: 1350 | F14: =$J$12+(C14*$J$10/$L$10) -> 4.1768463 | G14: =IF(D14="","",($J$11-$H$7+D14)*$J$10/$H$12) -> 3.8562874 | H14: =IF(E14="","",($J$11-$H$7+E14)*$J$10/$H$12) -> 3.5489022 | I14: =$F$12+(C14*$J$10/$L$12) -> 714 | J14: =IF(D14="","",($J$11-$H$7+D14)*$J$10/$B$12) -> 644 | K14: =IF(E14="","",($J$11-$H$7+E14)*$J$10/$B$12) -> 592.66667 | L14: 4.8
B15: LGB8 | C15: 30 | D15: 1900 | E15: 1350 | F15: =$J$12+(C15*$J$10/$L$10) -> 4.1768463 | G15: =IF(D15="","",($J$11-$H$7+D15)*$J$10/$H$12) -> 3.8562874 | H15: =IF(E15="","",($J$11-$H$7+E15)*$J$10/$H$12) -> 3.5489022 | I15: =$F$12+(C15*$J$10/$L$12) -> 714 | J15: =IF(D15="","",($J$11-$H$7+D15)*$J$10/$B$12) -> 644 | K15: =IF(E15="","",($J$11-$H$7+E15)*$J$10/$B$12) -> 592.66667 | L15: 4.8
B16: LAX9 | C16: 30 | D16: 1900 | E16: 1350 | F16: =$J$12+(C16*$J$10/$L$10) -> 4.1768463 | G16: =IF(D16="","",($J$11-$H$7+D16)*$J$10/$H$12) -> 3.8562874 | H16: =IF(E16="","",($J$11-$H$7+E16)*$J$10/$H$12) -> 3.5489022 | I16: =$F$12+(C16*$J$10/$L$12) -> 714 | J16: =IF(D16="","",($J$11-$H$7+D16)*$J$10/$B$12) -> 644 | K16: =IF(E16="","",($J$11-$H$7+E16)*$J$10/$B$12) -> 592.66667 | L16: 4.8
B17: SBD1 | C17: 30 | D17: 1900 | E17: 1350 | F17: =$J$12+(C17*$J$10/$L$10) -> 4.1768463 | G17: =IF(D17="","",($J$11-$H$7+D17)*$J$10/$H$12) -> 3.8562874 | H17: =IF(E17="","",($J$11-$H$7+E17)*$J$10/$H$12) -> 3.5489022 | I17: =$F$12+(C17*$J$10/$L$12) -> 714 | J17: =IF(D17="","",($J$11-$H$7+D17)*$J$10/$B$12) -> 644 | K17: =IF(E17="","",($J$11-$H$7+E17)*$J$10/$B$12) -> 592.66667 | L17: 4.8
B18: POC1 | C18: 35 | D18: 1900 | E18: 1350 | F18: =$J$12+(C18*$J$10/$L$10) -> 4.2768463 | G18: =IF(D18="","",($J$11-$H$7+D18)*$J$10/$H$12) -> 3.8562874 | H18: =IF(E18="","",($J$11-$H$7+E18)*$J$10/$H$12) -> 3.5489022 | I18: =$F$12+(C18*$J$10/$L$12) -> 733.44444 | J18: =IF(D18="","",($J$11-$H$7+D18)*$J$10/$B$12) -> 644 | K18: =IF(E18="","",($J$11-$H$7+E18)*$J$10/$B$12) -> 592.66667 | L18: 4.8
B19: POC3 | C19: 35 | D19: 1900 | E19: 1350 | F19: =$J$12+(C19*$J$10/$L$10) -> 4.2768463 | G19: =IF(D19="","",($J$11-$H$7+D19)*$J$10/$H$12) -> 3.8562874 | H19: =IF(E19="","",($J$11-$H$7+E19)*$J$10/$H$12) -> 3.5489022 | I19: =$F$12+(C19*$J$10/$L$12) -> 733.44444 | J19: =IF(D19="","",($J$11-$H$7+D19)*$J$10/$B$12) -> 644 | K19: =IF(E19="","",($J$11-$H$7+E19)*$J$10/$B$12) -> 592.66667 | L19: 4.8
A20: 美西 组合二 | B20: SMF3 | C20: 70 | D20: 2800 | E20: 2550 | F20: =$J$12+(C20*$J$10/$L$10) -> 4.9768463 | G20: =IF(D20="","",($J$11-$H$7+D20)*$J$10/$H$12) -> 4.3592814 | H20: =IF(E20="","",($J$11-$H$7+E20)*$J$10/$H$12) -> 4.2195609 | I20: =$F$12+(C20*$J$10/$L$12) -> 869.55556 | J20: =IF(D20="","",($J$11-$H$7+D20)*$J$10/$B$12) -> 728 | K20: =IF(E20="","",($J$11-$H$7+E20)*$J$10/$B$12) -> 704.66667 | L20: 5.6
B21: SCK4 | C21: 70 | D21: 2800 | E21: 2550 | F21: =$J$12+(C21*$J$10/$L$10) -> 4.9768463 | G21: =IF(D21="","",($J$11-$H$7+D21)*$J$10/$H$12) -> 4.3592814 | H21: =IF(E21="","",($J$11-$H$7+E21)*$J$10/$H$12) -> 4.2195609 | I21: =$F$12+(C21*$J$10/$L$12) -> 869.55556 | J21: =IF(D21="","",($J$11-$H$7+D21)*$J$10/$B$12) -> 728 | K21: =IF(E21="","",($J$11-$H$7+E21)*$J$10/$B$12) -> 704.66667 | L21: 5.6
B22: GYR2 | C22: 70 | D22: 2800 | E22: 2450 | F22: =$J$12+(C22*$J$10/$L$10) -> 4.9768463 | G22: =IF(D22="","",($J$11-$H$7+D22)*$J$10/$H$12) -> 4.3592814 | H22: =IF(E22="","",($J$11-$H$7+E22)*$J$10/$H$12) -> 4.1636727 | I22: =$F$12+(C22*$J$10/$L$12) -> 869.55556 | J22: =IF(D22="","",($J$11-$H$7+D22)*$J$10/$B$12) -> 728 | K22: =IF(E22="","",($J$11-$H$7+E22)*$J$10/$B$12) -> 695.33333 | L22: 5.6
B23: GYR3 | C23: 70 | D23: 2800 | E23: 2450 | F23: =$J$12+(C23*$J$10/$L$10) -> 4.9768463 | G23: =IF(D23="","",($J$11-$H$7+D23)*$J$10/$H$12) -> 4.3592814 | H23: =IF(E23="","",($J$11-$H$7+E23)*$J$10/$H$12) -> 4.1636727 | I23: =$F$12+(C23*$J$10/$L$12) -> 869.55556 | J23: =IF(D23="","",($J$11-$H$7+D23)*$J$10/$B$12) -> 728 | K23: =IF(E23="","",($J$11-$H$7+E23)*$J$10/$B$12) -> 695.33333 | L23: 5.6
B24: GEU2 | C24: 70 | D24: 2800 | E24: 2450 | F24: =$J$12+(C24*$J$10/$L$10) -> 4.9768463 | G24: =IF(D24="","",($J$11-$H$7+D24)*$J$10/$H$12) -> 4.3592814 | H24: =IF(E24="","",($J$11-$H$7+E24)*$J$10/$H$12) -> 4.1636727 | I24: =$F$12+(C24*$J$10/$L$12) -> 869.55556 | J24: =IF(D24="","",($J$11-$H$7+D24)*$J$10/$B$12) -> 728 | K24: =IF(E24="","",($J$11-$H$7+E24)*$J$10/$B$12) -> 695.33333 | L24: 5.6
B25: GEU3 | C25: 70 | D25: 2800 | E25: 2450 | F25: =$J$12+(C25*$J$10/$L$10) -> 4.9768463 | G25: =IF(D25="","",($J$11-$H$7+D25)*$J$10/$H$12) -> 4.3592814 | H25: =IF(E25="","",($J$11-$H$7+E25)*$J$10/$H$12) -> 4.1636727 | I25: =$F$12+(C25*$J$10/$L$12) -> 869.55556 | J25: =IF(D25="","",($J$11-$H$7+D25)*$J$10/$B$12) -> 728 | K25: =IF(E25="","",($J$11-$H$7+E25)*$J$10/$B$12) -> 695.33333 | L25: 5.6
B26: GEU5 | C26: 70 | D26: 2800 | E26: 2450 | F26: =$J$12+(C26*$J$10/$L$10) -> 4.9768463 | G26: =IF(D26="","",($J$11-$H$7+D26)*$J$10/$H$12) -> 4.3592814 | H26: =IF(E26="","",($J$11-$H$7+E26)*$J$10/$H$12) -> 4.1636727 | I26: =$F$12+(C26*$J$10/$L$12) -> 869.55556 | J26: =IF(D26="","",($J$11-$H$7+D26)*$J$10/$B$12) -> 728 | K26: =IF(E26="","",($J$11-$H$7+E26)*$J$10/$B$12) -> 695.33333
B27: LAS1 | C27: 70 | D27: 2800 | E27: 2250 | F27: =$J$12+(C27*$J$10/$L$10) -> 4.9768463 | G27: =IF(D27="","",($J$11-$H$7+D27)*$J$10/$H$12) -> 4.3592814 | H27: =IF(E27="","",($J$11-$H$7+E27)*$J$10/$H$12) -> 4.0518962 | I27: =$F$12+(C27*$J$10/$L$12) -> 869.55556 | J27: =IF(D27="","",($J$11-$H$7+D27)*$J$10/$B$12) -> 728 | K27: =IF(E27="","",($J$11-$H$7+E27)*$J$10/$B$12) -> 676.66667 | L27: 5.6
B28: VGT2 | C28: 70 | D28: 2800 | E28: 2250 | F28: =$J$12+(C28*$J$10/$L$10) -> 4.9768463 | G28: =IF(D28="","",($J$11-$H$7+D28)*$J$10/$H$12) -> 4.3592814 | H28: =IF(E28="","",($J$11-$H$7+E28)*$J$10/$H$12) -> 4.0518962 | I28: =$F$12+(C28*$J$10/$L$12) -> 869.55556 | J28: =IF(D28="","",($J$11-$H$7+D28)*$J$10/$B$12) -> 728 | K28: =IF(E28="","",($J$11-$H$7+E28)*$J$10/$B$12) -> 676.66667 | L28: 5.6
B29: MIT2 | C29: 70 | D29: 2800 | E29: 2050 | F29: =$J$12+(C29*$J$10/$L$10) -> 4.9768463 | G29: =IF(D29="","",($J$11-$H$7+D29)*$J$10/$H$12) -> 4.3592814 | H29: =IF(E29="","",($J$11-$H$7+E29)*$J$10/$H$12) -> 3.9401198 | I29: =$F$12+(C29*$J$10/$L$12) -> 869.55556 | J29: =IF(D29="","",($J$11-$H$7+D29)*$J$10/$B$12) -> 728 | K29: =IF(E29="","",($J$11-$H$7+E29)*$J$10/$B$12) -> 658 | L29: 5.6
B30: TCY1 | C30: 70 | D30: 2800 | E30: 2550 | F30: =$J$12+(C30*$J$10/$L$10) -> 4.9768463 | G30: =IF(D30="","",($J$11-$H$7+D30)*$J$10/$H$12) -> 4.3592814 | H30: =IF(E30="","",($J$11-$H$7+E30)*$J$10/$H$12) -> 4.2195609 | I30: =$F$12+(C30*$J$10/$L$12) -> 869.55556 | J30: =IF(D30="","",($J$11-$H$7+D30)*$J$10/$B$12) -> 728 | K30: =IF(E30="","",($J$11-$H$7+E30)*$J$10/$B$12) -> 704.66667 | L30: 5.6
B31: TCY2 | C31: 70 | D31: 2800 | E31: 2550 | F31: =$J$12+(C31*$J$10/$L$10) -> 4.9768463 | G31: =IF(D31="","",($J$11-$H$7+D31)*$J$10/$H$12) -> 4.3592814 | H31: =IF(E31="","",($J$11-$H$7+E31)*$J$10/$H$12) -> 4.2195609 | I31: =$F$12+(C31*$J$10/$L$12) -> 869.55556 | J31: =IF(D31="","",($J$11-$H$7+D31)*$J$10/$B$12) -> 728 | K31: =IF(E31="","",($J$11-$H$7+E31)*$J$10/$B$12) -> 704.66667 | L31: 5.6
B32: QXY8 | C32: 71 | D32: 2800 | E32: 2550 | F32: =$J$12+(C32*$J$10/$L$10) -> 4.9968463 | G32: =IF(D32="","",($J$11-$H$7+D32)*$J$10/$H$12) -> 4.3592814 | H32: =IF(E32="","",($J$11-$H$7+E32)*$J$10/$H$12) -> 4.2195609 | I32: =$F$12+(C32*$J$10/$L$12) -> 873.44444 | J32: =IF(D32="","",($J$11-$H$7+D32)*$J$10/$B$12) -> 728 | K32: =IF(E32="","",($J$11-$H$7+E32)*$J$10/$B$12) -> 704.66667 | L32: 5.7
B33: SCK8 | C33: 80 | D33: 2800 | E33: 2550 | F33: =$J$12+(C33*$J$10/$L$10) -> 5.1768463 | G33: =IF(D33="","",($J$11-$H$7+D33)*$J$10/$H$12) -> 4.3592814 | H33: =IF(E33="","",($J$11-$H$7+E33)*$J$10/$H$12) -> 4.2195609 | I33: =$F$12+(C33*$J$10/$L$12) -> 908.44444 | J33: =IF(D33="","",($J$11-$H$7+D33)*$J$10/$B$12) -> 728 | K33: =IF(E33="","",($J$11-$H$7+E33)*$J$10/$B$12) -> 704.66667 | L33: 5.6
B34: HLI2 | C34: 80 | D34: 2800 | F34: =$J$12+(C34*$J$10/$L$10) -> 5.1768463 | G34: =IF(D34="","",($J$11-$H$7+D34)*$J$10/$H$12) -> 4.3592814 | H34: =IF(E34="","",($J$11-$H$7+E34)*$J$10/$H$12) | I34: =$F$12+(C34*$J$10/$L$12) -> 908.44444 | J34: =IF(D34="","",($J$11-$H$7+D34)*$J$10/$B$12) -> 728 | K34: =IF(E34="","",($J$11-$H$7+E34)*$J$10/$B$12) | L34: 5.6
A35: 美西 组合三 | B35: FTW1 | C35: 170 | D35: 5400 | F35: =$J$12+(C35*$J$10/$L$10) -> 6.9768463 | G35: =IF(D35="","",($J$11-$H$7+D35)*$J$10/$H$12) -> 5.8123752 | H35: =IF(E35="","",($J$11-$H$7+E35)*$J$10/$H$12) | I35: =$F$12+(C35*$J$10/$L$12) -> 1258.4444 | J35: =IF(D35="","",($J$11-$H$7+D35)*$J$10/$B$12) -> 970.66667 | K35: =IF(E35="","",($J$11-$H$7+E35)*$J$10/$B$12) | L35: 7.1
B36: FTW5 | C36: 170 | D36: 5400 | F36: =$J$12+(C36*$J$10/$L$10) -> 6.9768463 | G36: =IF(D36="","",($J$11-$H$7+D36)*$J$10/$H$12) -> 5.8123752 | H36: =IF(E36="","",($J$11-$H$7+E36)*$J$10/$H$12) | I36: =$F$12+(C36*$J$10/$L$12) -> 1258.4444 | J36: =IF(D36="","",($J$11-$H$7+D36)*$J$10/$B$12) -> 970.66667 | K36: =IF(E36="","",($J$11-$H$7+E36)*$J$10/$B$12) | L36: 7.4
B37: SAT1 | C37: 180 | D37: 5400 | F37: =$J$12+(C37*$J$10/$L$10) -> 7.1768463 | G37: =IF(D37="","",($J$11-$H$7+D37)*$J$10/$H$12) -> 5.8123752 | H37: =IF(E37="","",($J$11-$H$7+E37)*$J$10/$H$12) | I37: =$F$12+(C37*$J$10/$L$12) -> 1297.3333 | J37: =IF(D37="","",($J$11-$H$7+D37)*$J$10/$B$12) -> 970.66667 | K37: =IF(E37="","",($J$11-$H$7+E37)*$J$10/$B$12) | L37: 7.4
B38: SAT4 | C38: 180 | D38: 5400 | F38: =$J$12+(C38*$J$10/$L$10) -> 7.1768463 | G38: =IF(D38="","",($J$11-$H$7+D38)*$J$10/$H$12) -> 5.8123752 | H38: =IF(E38="","",($J$11-$H$7+E38)*$J$10/$H$12) | I38: =$F$12+(C38*$J$10/$L$12) -> 1297.3333 | J38: =IF(D38="","",($J$11-$H$7+D38)*$J$10/$B$12) -> 970.66667 | K38: =IF(E38="","",($J$11-$H$7+E38)*$J$10/$B$12) | L38: 7.4
B39: AMA1 | C39: 170 | D39: 5400 | F39: =$J$12+(C39*$J$10/$L$10) -> 6.9768463 | G39: =IF(D39="","",($J$11-$H$7+D39)*$J$10/$H$12) -> 5.8123752 | H39: =IF(E39="","",($J$11-$H$7+E39)*$J$10/$H$12) | I39: =$F$12+(C39*$J$10/$L$12) -> 1258.4444 | J39: =IF(D39="","",($J$11-$H$7+D39)*$J$10/$B$12) -> 970.66667 | K39: =IF(E39="","",($J$11-$H$7+E39)*$J$10/$B$12)
B40: DFW6 | C40: 170 | D40: 5400 | F40: =$J$12+(C40*$J$10/$L$10) -> 6.9768463 | G40: =IF(D40="","",($J$11-$H$7+D40)*$J$10/$H$12) -> 5.8123752 | H40: =IF(E40="","",($J$11-$H$7+E40)*$J$10/$H$12) | I40: =$F$12+(C40*$J$10/$L$12) -> 1258.4444 | J40: =IF(D40="","",($J$11-$H$7+D40)*$J$10/$B$12) -> 970.66667 | K40: =IF(E40="","",($J$11-$H$7+E40)*$J$10/$B$12) | L40: 7.4
B41: IAH3 | C41: 180 | D41: 5400 | F41: =$J$12+(C41*$J$10/$L$10) -> 7.1768463 | G41: =IF(D41="","",($J$11-$H$7+D41)*$J$10/$H$12) -> 5.8123752 | H41: =IF(E41="","",($J$11-$H$7+E41)*$J$10/$H$12) | I41: =$F$12+(C41*$J$10/$L$12) -> 1297.3333 | J41: =IF(D41="","",($J$11-$H$7+D41)*$J$10/$B$12) -> 970.66667 | K41: =IF(E41="","",($J$11-$H$7+E41)*$J$10/$B$12) | L41: 7.4
B42: ABQ2 | C42: 140 | D42: 5400 | E42: 4050 | F42: =$J$12+(C42*$J$10/$L$10) -> 6.3768463 | G42: =IF(D42="","",($J$11-$H$7+D42)*$J$10/$H$12) -> 5.8123752 | H42: =IF(E42="","",($J$11-$H$7+E42)*$J$10/$H$12) -> 5.0578842 | I42: =$F$12+(C42*$J$10/$L$12) -> 1141.7778 | J42: =IF(D42="","",($J$11-$H$7+D42)*$J$10/$B$12) -> 970.66667 | K42: =IF(E42="","",($J$11-$H$7+E42)*$J$10/$B$12) -> 844.66667 | L42: 7.1
B43: IUSF | C43: 170 | D43: 5400 | F43: =$J$12+(C43*$J$10/$L$10) -> 6.9768463 | G43: =IF(D43="","",($J$11-$H$7+D43)*$J$10/$H$12) -> 5.8123752 | H43: =IF(E43="","",($J$11-$H$7+E43)*$J$10/$H$12) | I43: =$F$12+(C43*$J$10/$L$12) -> 1258.4444 | J43: =IF(D43="","",($J$11-$H$7+D43)*$J$10/$B$12) -> 970.66667 | K43: =IF(E43="","",($J$11-$H$7+E43)*$J$10/$B$12)
B44: HOU8 | C44: 180 | D44: 5400 | F44: =$J$12+(C44*$J$10/$L$10) -> 7.1768463 | G44: =IF(D44="","",($J$11-$H$7+D44)*$J$10/$H$12) -> 5.8123752 | H44: =IF(E44="","",($J$11-$H$7+E44)*$J$10/$H$12) | I44: =$F$12+(C44*$J$10/$L$12) -> 1297.3333 | J44: =IF(D44="","",($J$11-$H$7+D44)*$J$10/$B$12) -> 970.66667 | K44: =IF(E44="","",($J$11-$H$7+E44)*$J$10/$B$12)
A45: 美西 四区 | B45: MEM1 | C45: 170 | D45: 6200 | F45: =$J$12+(C45*$J$10/$L$10) -> 6.9768463 | G45: =IF(D45="","",($J$11-$H$7+D45)*$J$10/$H$12) -> 6.259481 | H45: =IF(E45="","",($J$11-$H$7+E45)*$J$10/$H$12) | I45: =$F$12+(C45*$J$10/$L$12) -> 1258.4444 | J45: =IF(D45="","",($J$11-$H$7+D45)*$J$10/$B$12) -> 1045.3333 | K45: =IF(E45="","",($J$11-$H$7+E45)*$J$10/$B$12) | L45: 7.4
B46: STL3 | C46: 200 | D46: 6200 | F46: =$J$12+(C46*$J$10/$L$10) -> 7.5768463 | G46: =IF(D46="","",($J$11-$H$7+D46)*$J$10/$H$12) -> 6.259481 | H46: =IF(E46="","",($J$11-$H$7+E46)*$J$10/$H$12) | I46: =$F$12+(C46*$J$10/$L$12) -> 1375.1111 | J46: =IF(D46="","",($J$11-$H$7+D46)*$J$10/$B$12) -> 1045.3333 | K46: =IF(E46="","",($J$11-$H$7+E46)*$J$10/$B$12)
B47: STL4 | C47: 200 | D47: 6200 | F47: =$J$12+(C47*$J$10/$L$10) -> 7.5768463 | G47: =IF(D47="","",($J$11-$H$7+D47)*$J$10/$H$12) -> 6.259481 | H47: =IF(E47="","",($J$11-$H$7+E47)*$J$10/$H$12) | I47: =$F$12+(C47*$J$10/$L$12) -> 1375.1111 | J47: =IF(D47="","",($J$11-$H$7+D47)*$J$10/$B$12) -> 1045.3333 | K47: =IF(E47="","",($J$11-$H$7+E47)*$J$10/$B$12)
B48: PSC2 | C48: 180 | D48: 6200 | F48: =$J$12+(C48*$J$10/$L$10) -> 7.1768463 | G48: =IF(D48="","",($J$11-$H$7+D48)*$J$10/$H$12) -> 6.259481 | H48: =IF(E48="","",($J$11-$H$7+E48)*$J$10/$H$12) | I48: =$F$12+(C48*$J$10/$L$12) -> 1297.3333 | J48: =IF(D48="","",($J$11-$H$7+D48)*$J$10/$B$12) -> 1045.3333 | K48: =IF(E48="","",($J$11-$H$7+E48)*$J$10/$B$12) | L48: 7.4
B49: BNA6 | C49: 210 | D49: 6200 | F49: =$J$12+(C49*$J$10/$L$10) -> 7.7768463 | G49: =IF(D49="","",($J$11-$H$7+D49)*$J$10/$H$12) -> 6.259481 | H49: =IF(E49="","",($J$11-$H$7+E49)*$J$10/$H$12) | I49: =$F$12+(C49*$J$10/$L$12) -> 1414 | J49: =IF(D49="","",($J$11-$H$7+D49)*$J$10/$B$12) -> 1045.3333 | K49: =IF(E49="","",($J$11-$H$7+E49)*$J$10/$B$12) | L49: 9
B50: IND9 | C50: 170 | D50: 6200 | F50: =$J$12+(C50*$J$10/$L$10) -> 6.9768463 | G50: =IF(D50="","",($J$11-$H$7+D50)*$J$10/$H$12) -> 6.259481 | H50: =IF(E50="","",($J$11-$H$7+E50)*$J$10/$H$12) | I50: =$F$12+(C50*$J$10/$L$12) -> 1258.4444 | J50: =IF(D50="","",($J$11-$H$7+D50)*$J$10/$B$12) -> 1045.3333 | K50: =IF(E50="","",($J$11-$H$7+E50)*$J$10/$B$12) | L50: 7.4
B51: MDW2 | C51: 170 | D51: 6200 | F51: =$J$12+(C51*$J$10/$L$10) -> 6.9768463 | G51: =IF(D51="","",($J$11-$H$7+D51)*$J$10/$H$12) -> 6.259481 | H51: =IF(E51="","",($J$11-$H$7+E51)*$J$10/$H$12) | I51: =$F$12+(C51*$J$10/$L$12) -> 1258.4444 | J51: =IF(D51="","",($J$11-$H$7+D51)*$J$10/$B$12) -> 1045.3333 | K51: =IF(E51="","",($J$11-$H$7+E51)*$J$10/$B$12) | L51: 7.4
B52: FWA4 | C52: 170 | D52: 6200 | F52: =$J$12+(C52*$J$10/$L$10) -> 6.9768463 | G52: =IF(D52="","",($J$11-$H$7+D52)*$J$10/$H$12) -> 6.259481 | H52: =IF(E52="","",($J$11-$H$7+E52)*$J$10/$H$12) | I52: =$F$12+(C52*$J$10/$L$12) -> 1258.4444 | J52: =IF(D52="","",($J$11-$H$7+D52)*$J$10/$B$12) -> 1045.3333 | K52: =IF(E52="","",($J$11-$H$7+E52)*$J$10/$B$12) | L52: 7.4
B53: MQJ1 | C53: 170 | D53: 6200 | F53: =$J$12+(C53*$J$10/$L$10) -> 6.9768463 | G53: =IF(D53="","",($J$11-$H$7+D53)*$J$10/$H$12) -> 6.259481 | H53: =IF(E53="","",($J$11-$H$7+E53)*$J$10/$H$12) | I53: =$F$12+(C53*$J$10/$L$12) -> 1258.4444 | J53: =IF(D53="","",($J$11-$H$7+D53)*$J$10/$B$12) -> 1045.3333 | K53: =IF(E53="","",($J$11-$H$7+E53)*$J$10/$B$12) | L53: 7.4
B54: RFD2 | C54: 200 | D54: 6200 | F54: =$J$12+(C54*$J$10/$L$10) -> 7.5768463 | G54: =IF(D54="","",($J$11-$H$7+D54)*$J$10/$H$12) -> 6.259481 | H54: =IF(E54="","",($J$11-$H$7+E54)*$J$10/$H$12) | I54: =$F$12+(C54*$J$10/$L$12) -> 1375.1111 | J54: =IF(D54="","",($J$11-$H$7+D54)*$J$10/$B$12) -> 1045.3333 | K54: =IF(E54="","",($J$11-$H$7+E54)*$J$10/$B$12) | L54: 7.4
B55: ORD2 | C55: 200 | D55: 6200 | F55: =$J$12+(C55*$J$10/$L$10) -> 7.5768463 | G55: =IF(D55="","",($J$11-$H$7+D55)*$J$10/$H$12) -> 6.259481 | H55: =IF(E55="","",($J$11-$H$7+E55)*$J$10/$H$12) | I55: =$F$12+(C55*$J$10/$L$12) -> 1375.1111 | J55: =IF(D55="","",($J$11-$H$7+D55)*$J$10/$B$12) -> 1045.3333 | K55: =IF(E55="","",($J$11-$H$7+E55)*$J$10/$B$12)
B56: LIT2 | C56: 200 | D56: 6200 | F56: =$J$12+(C56*$J$10/$L$10) -> 7.5768463 | G56: =IF(D56="","",($J$11-$H$7+D56)*$J$10/$H$12) -> 6.259481 | H56: =IF(E56="","",($J$11-$H$7+E56)*$J$10/$H$12) | I56: =$F$12+(C56*$J$10/$L$12) -> 1375.1111 | J56: =IF(D56="","",($J$11-$H$7+D56)*$J$10/$B$12) -> 1045.3333 | K56: =IF(E56="","",($J$11-$H$7+E56)*$J$10/$B$12)
A57: 五区 美东 | B57: CLT2 | C57: 240 | D57: 8200 | F57: =$J$12+(C57*$J$10/$L$10) -> 8.3768463 | G57: =IF(D57="","",($J$11-$H$7+D57)*$J$10/$H$12) -> 7.3772455 | H57: =IF(E57="","",($J$11-$H$7+E57)*$J$10/$H$12) | I57: =$F$12+(C57*$J$10/$L$12) -> 1530.6667 | J57: =IF(D57="","",($J$11-$H$7+D57)*$J$10/$B$12) -> 1232 | K57: =IF(E57="","",($J$11-$H$7+E57)*$J$10/$B$12) | L57: 8.7
B58: RDU2 | C58: 240 | D58: 8200 | F58: =$J$12+(C58*$J$10/$L$10) -> 8.3768463 | G58: =IF(D58="","",($J$11-$H$7+D58)*$J$10/$H$12) -> 7.3772455 | H58: =IF(E58="","",($J$11-$H$7+E58)*$J$10/$H$12) | I58: =$F$12+(C58*$J$10/$L$12) -> 1530.6667 | J58: =IF(D58="","",($J$11-$H$7+D58)*$J$10/$B$12) -> 1232 | K58: =IF(E58="","",($J$11-$H$7+E58)*$J$10/$B$12) | L58: 8.7
B59: ABE8 | C59: 270 | D59: 8200 | F59: =$J$12+(C59*$J$10/$L$10) -> 8.9768463 | G59: =IF(D59="","",($J$11-$H$7+D59)*$J$10/$H$12) -> 7.3772455 | H59: =IF(E59="","",($J$11-$H$7+E59)*$J$10/$H$12) | I59: =$F$12+(C59*$J$10/$L$12) -> 1647.3333 | J59: =IF(D59="","",($J$11-$H$7+D59)*$J$10/$B$12) -> 1232 | K59: =IF(E59="","",($J$11-$H$7+E59)*$J$10/$B$12) | L59: 9
B60: AVP1 | C60: 270 | D60: 8200 | F60: =$J$12+(C60*$J$10/$L$10) -> 8.9768463 | G60: =IF(D60="","",($J$11-$H$7+D60)*$J$10/$H$12) -> 7.3772455 | H60: =IF(E60="","",($J$11-$H$7+E60)*$J$10/$H$12) | I60: =$F$12+(C60*$J$10/$L$12) -> 1647.3333 | J60: =IF(D60="","",($J$11-$H$7+D60)*$J$10/$B$12) -> 1232 | K60: =IF(E60="","",($J$11-$H$7+E60)*$J$10/$B$12) | L60: 9
B61: TEB9 | C61: 270 | D61: 8200 | F61: =$J$12+(C61*$J$10/$L$10) -> 8.9768463 | G61: =IF(D61="","",($J$11-$H$7+D61)*$J$10/$H$12) -> 7.3772455 | H61: =IF(E61="","",($J$11-$H$7+E61)*$J$10/$H$12) | I61: =$F$12+(C61*$J$10/$L$12) -> 1647.3333 | J61: =IF(D61="","",($J$11-$H$7+D61)*$J$10/$B$12) -> 1232 | K61: =IF(E61="","",($J$11-$H$7+E61)*$J$10/$B$12) | L61: 9
B62: SWF2 | C62: 300 | D62: 8200 | F62: =$J$12+(C62*$J$10/$L$10) -> 9.5768463 | G62: =IF(D62="","",($J$11-$H$7+D62)*$J$10/$H$12) -> 7.3772455 | H62: =IF(E62="","",($J$11-$H$7+E62)*$J$10/$H$12) | I62: =$F$12+(C62*$J$10/$L$12) -> 1764 | J62: =IF(D62="","",($J$11-$H$7+D62)*$J$10/$B$12) -> 1232 | K62: =IF(E62="","",($J$11-$H$7+E62)*$J$10/$B$12) | L62: 9
B63: RMN3 | C63: 290 | D63: 8200 | F63: =$J$12+(C63*$J$10/$L$10) -> 9.3768463 | G63: =IF(D63="","",($J$11-$H$7+D63)*$J$10/$H$12) -> 7.3772455 | H63: =IF(E63="","",($J$11-$H$7+E63)*$J$10/$H$12) | I63: =$F$12+(C63*$J$10/$L$12) -> 1725.1111 | J63: =IF(D63="","",($J$11-$H$7+D63)*$J$10/$B$12) -> 1232 | K63: =IF(E63="","",($J$11-$H$7+E63)*$J$10/$B$12) | L63: 9
B64: ORF2 | C64: 290 | D64: 8200 | F64: =$J$12+(C64*$J$10/$L$10) -> 9.3768463 | G64: =IF(D64="","",($J$11-$H$7+D64)*$J$10/$H$12) -> 7.3772455 | H64: =IF(E64="","",($J$11-$H$7+E64)*$J$10/$H$12) | I64: =$F$12+(C64*$J$10/$L$12) -> 1725.1111 | J64: =IF(D64="","",($J$11-$H$7+D64)*$J$10/$B$12) -> 1232 | K64: =IF(E64="","",($J$11-$H$7+E64)*$J$10/$B$12) | L64: 9
B65: ACY2 | C65: 270 | D65: 8200 | F65: =$J$12+(C65*$J$10/$L$10) -> 8.9768463 | G65: =IF(D65="","",($J$11-$H$7+D65)*$J$10/$H$12) -> 7.3772455 | H65: =IF(E65="","",($J$11-$H$7+E65)*$J$10/$H$12) | I65: =$F$12+(C65*$J$10/$L$12) -> 1647.3333 | J65: =IF(D65="","",($J$11-$H$7+D65)*$J$10/$B$12) -> 1232 | K65: =IF(E65="","",($J$11-$H$7+E65)*$J$10/$B$12)
B66: TEB3 | C66: 270 | D66: 8200 | F66: =$J$12+(C66*$J$10/$L$10) -> 8.9768463 | G66: =IF(D66="","",($J$11-$H$7+D66)*$J$10/$H$12) -> 7.3772455 | H66: =IF(E66="","",($J$11-$H$7+E66)*$J$10/$H$12) | I66: =$F$12+(C66*$J$10/$L$12) -> 1647.3333 | J66: =IF(D66="","",($J$11-$H$7+D66)*$J$10/$B$12) -> 1232 | K66: =IF(E66="","",($J$11-$H$7+E66)*$J$10/$B$12) | L66: 9
B67: TEB4 | C67: 270 | D67: 8200 | F67: =$J$12+(C67*$J$10/$L$10) -> 8.9768463 | G67: =IF(D67="","",($J$11-$H$7+D67)*$J$10/$H$12) -> 7.3772455 | H67: =IF(E67="","",($J$11-$H$7+E67)*$J$10/$H$12) | I67: =$F$12+(C67*$J$10/$L$12) -> 1647.3333 | J67: =IF(D67="","",($J$11-$H$7+D67)*$J$10/$B$12) -> 1232 | K67: =IF(E67="","",($J$11-$H$7+E67)*$J$10/$B$12)
B68: TEB6 | C68: 270 | D68: 8200 | F68: =$J$12+(C68*$J$10/$L$10) -> 8.9768463 | G68: =IF(D68="","",($J$11-$H$7+D68)*$J$10/$H$12) -> 7.3772455 | H68: =IF(E68="","",($J$11-$H$7+E68)*$J$10/$H$12) | I68: =$F$12+(C68*$J$10/$L$12) -> 1647.3333 | J68: =IF(D68="","",($J$11-$H$7+D68)*$J$10/$B$12) -> 1232 | K68: =IF(E68="","",($J$11-$H$7+E68)*$J$10/$B$12)
B69: ABE2 | D69: 8200 | F69: =$J$12+(C69*$J$10/$L$10) -> 3.5768463 | G69: =IF(D69="","",($J$11-$H$7+D69)*$J$10/$H$12) -> 7.3772455 | H69: =IF(E69="","",($J$11-$H$7+E69)*$J$10/$H$12) | I69: =$F$12+(C69*$J$10/$L$12) -> 597.33333 | J69: =IF(D69="","",($J$11-$H$7+D69)*$J$10/$B$12) -> 1232 | K69: =IF(E69="","",($J$11-$H$7+E69)*$J$10/$B$12)
B70: ABE3 | D70: 8200 | F70: =$J$12+(C70*$J$10/$L$10) -> 3.5768463 | G70: =IF(D70="","",($J$11-$H$7+D70)*$J$10/$H$12) -> 7.3772455 | H70: =IF(E70="","",($J$11-$H$7+E70)*$J$10/$H$12) | I70: =$F$12+(C70*$J$10/$L$12) -> 597.33333 | J70: =IF(D70="","",($J$11-$H$7+D70)*$J$10/$B$12) -> 1232 | K70: =IF(E70="","",($J$11-$H$7+E70)*$J$10/$B$12)
B71: ABE4 | C71: 270 | D71: 8200 | F71: =$J$12+(C71*$J$10/$L$10) -> 8.9768463 | G71: =IF(D71="","",($J$11-$H$7+D71)*$J$10/$H$12) -> 7.3772455 | H71: =IF(E71="","",($J$11-$H$7+E71)*$J$10/$H$12) | I71: =$F$12+(C71*$J$10/$L$12) -> 1647.3333 | J71: =IF(D71="","",($J$11-$H$7+D71)*$J$10/$B$12) -> 1232 | K71: =IF(E71="","",($J$11-$H$7+E71)*$J$10/$B$12) | L71: 9
B72: AVP3 | D72: 8200 | F72: =$J$12+(C72*$J$10/$L$10) -> 3.5768463 | G72: =IF(D72="","",($J$11-$H$7+D72)*$J$10/$H$12) -> 7.3772455 | H72: =IF(E72="","",($J$11-$H$7+E72)*$J$10/$H$12) | I72: =$F$12+(C72*$J$10/$L$12) -> 597.33333 | J72: =IF(D72="","",($J$11-$H$7+D72)*$J$10/$B$12) -> 1232 | K72: =IF(E72="","",($J$11-$H$7+E72)*$J$10/$B$12) | L72: 9
B73: AVP9 | D73: 8200 | F73: =$J$12+(C73*$J$10/$L$10) -> 3.5768463 | G73: =IF(D73="","",($J$11-$H$7+D73)*$J$10/$H$12) -> 7.3772455 | H73: =IF(E73="","",($J$11-$H$7+E73)*$J$10/$H$12) | I73: =$F$12+(C73*$J$10/$L$12) -> 597.33333 | J73: =IF(D73="","",($J$11-$H$7+D73)*$J$10/$B$12) -> 1232 | K73: =IF(E73="","",($J$11-$H$7+E73)*$J$10/$B$12)
A74: 散货 | B74: KRB4 | C74: 40 | F74: =$J$12+(C74*$J$10/$L$10) -> 4.3768463 | G74: =IF(D74="","",($J$11-$H$7+D74)*$J$10/$H$12) | H74: =IF(E74="","",($J$11-$H$7+E74)*$J$10/$H$12) | I74: =$F$12+(C74*$J$10/$L$12) -> 752.88889 | J74: =IF(D74="","",($J$11-$H$7+D74)*$J$10/$B$12) | K74: =IF(E74="","",($J$11-$H$7+E74)*$J$10/$B$12)
B75: PSP3 | C75: 60 | F75: =$J$12+(C75*$J$10/$L$10) -> 4.7768463 | G75: =IF(D75="","",($J$11-$H$7+D75)*$J$10/$H$12) | H75: =IF(E75="","",($J$11-$H$7+E75)*$J$10/$H$12) | I75: =$F$12+(C75*$J$10/$L$12) -> 830.66667 | L75: 5.7
B76: ONT6 | C76: 40 | F76: =$J$12+(C76*$J$10/$L$10) -> 4.3768463 | G76: =IF(D76="","",($J$11-$H$7+D76)*$J$10/$H$12) | H76: =IF(E76="","",($J$11-$H$7+E76)*$J$10/$H$12) | I76: =$F$12+(C76*$J$10/$L$12) -> 752.88889 | J76: =IF(D76="","",($J$11-$H$7+D76)*$J$10/$B$12) | K76: =IF(E76="","",($J$11-$H$7+E76)*$J$10/$B$12)
B77: LGB6 | C77: 40 | F77: =$J$12+(C77*$J$10/$L$10) -> 4.3768463 | G77: =IF(D77="","",($J$11-$H$7+D77)*$J$10/$H$12) | H77: =IF(E77="","",($J$11-$H$7+E77)*$J$10/$H$12) | I77: =$F$12+(C77*$J$10/$L$12) -> 752.88889 | J77: =IF(D77="","",($J$11-$H$7+D77)*$J$10/$B$12) | K77: =IF(E77="","",($J$11-$H$7+E77)*$J$10/$B$12)
B78: JOT1 | C78: 30 | F78: =$J$12+(C78*$J$10/$L$10) -> 4.1768463 | G78: =IF(D78="","",($J$11-$H$7+D78)*$J$10/$H$12) | H78: =IF(E78="","",($J$11-$H$7+E78)*$J$10/$H$12) | I78: =$F$12+(C78*$J$10/$L$12) -> 714 | J78: =IF(D78="","",($J$11-$H$7+D78)*$J$10/$B$12) | K78: =IF(E78="","",($J$11-$H$7+E78)*$J$10/$B$12) | L78: 5.6
B79: IUSR | C79: 245 | F79: =$J$12+(C79*$J$10/$L$10) -> 8.4768463 | G79: =IF(D79="","",($J$11-$H$7+D79)*$J$10/$H$12) | H79: =IF(E79="","",($J$11-$H$7+E79)*$J$10/$H$12) | I79: =$F$12+(C79*$J$10/$L$12) -> 1550.1111
B80: LAX2T/LAX1 | C80: 45 | F80: =$J$12+(C80*$J$10/$L$10) -> 4.4768463 | G80: =IF(D80="","",($J$11-$H$7+D80)*$J$10/$H$12) | H80: =IF(E80="","",($J$11-$H$7+E80)*$J$10/$H$12) | I80: =$F$12+(C80*$J$10/$L$12) -> 772.33333
B81: ONT9 | C81: 40 | F81: =$J$12+(C81*$J$10/$L$10) -> 4.3768463 | G81: =IF(D81="","",($J$11-$H$7+D81)*$J$10/$H$12) | H81: =IF(E81="","",($J$11-$H$7+E81)*$J$10/$H$12) | I81: =$F$12+(C81*$J$10/$L$12) -> 752.88889 | J81: =IF(D81="","",($J$11-$H$7+D81)*$J$10/$B$12) | K81: =IF(E81="","",($J$11-$H$7+E81)*$J$10/$B$12)
B82: LGB9 | C82: 40 | F82: =$J$12+(C82*$J$10/$L$10) -> 4.3768463 | G82: =IF(D82="","",($J$11-$H$7+D82)*$J$10/$H$12) | H82: =IF(E82="","",($J$11-$H$7+E82)*$J$10/$H$12) | I82: =$F$12+(C82*$J$10/$L$12) -> 752.88889 | J82: =IF(D82="","",($J$11-$H$7+D82)*$J$10/$B$12) | K82: =IF(E82="","",($J$11-$H$7+E82)*$J$10/$B$12)
B83: KRB1 | C83: 40 | F83: =$J$12+(C83*$J$10/$L$10) -> 4.3768463 | G83: =IF(D83="","",($J$11-$H$7+D83)*$J$10/$H$12) | H83: =IF(E83="","",($J$11-$H$7+E83)*$J$10/$H$12) | I83: =$F$12+(C83*$J$10/$L$12) -> 752.88889 | J83: =IF(D83="","",($J$11-$H$7+D83)*$J$10/$B$12) | K83: =IF(E83="","",($J$11-$H$7+E83)*$J$10/$B$12)
B84: ONT2 | C84: 40 | F84: =$J$12+(C84*$J$10/$L$10) -> 4.3768463 | G84: =IF(D84="","",($J$11-$H$7+D84)*$J$10/$H$12) | H84: =IF(E84="","",($J$11-$H$7+E84)*$J$10/$H$12) | I84: =$F$12+(C84*$J$10/$L$12) -> 752.88889 | J84: =IF(D84="","",($J$11-$H$7+D84)*$J$10/$B$12) | K84: =IF(E84="","",($J$11-$H$7+E84)*$J$10/$B$12)
B85: LGB4 | C85: 40 | F85: =$J$12+(C85*$J$10/$L$10) -> 4.3768463 | G85: =IF(D85="","",($J$11-$H$7+D85)*$J$10/$H$12) | H85: =IF(E85="","",($J$11-$H$7+E85)*$J$10/$H$12) | I85: =$F$12+(C85*$J$10/$L$12) -> 752.88889 | J85: =IF(D85="","",($J$11-$H$7+D85)*$J$10/$B$12) | K85: =IF(E85="","",($J$11-$H$7+E85)*$J$10/$B$12)
B86: SBD2 | C86: 40 | F86: =$J$12+(C86*$J$10/$L$10) -> 4.3768463 | G86: =IF(D86="","",($J$11-$H$7+D86)*$J$10/$H$12) | H86: =IF(E86="","",($J$11-$H$7+E86)*$J$10/$H$12) | I86: =$F$12+(C86*$J$10/$L$12) -> 752.88889 | J86: =IF(D86="","",($J$11-$H$7+D86)*$J$10/$B$12) | K86: =IF(E86="","",($J$11-$H$7+E86)*$J$10/$B$12)
B87: SNA4 | C87: 40 | F87: =$J$12+(C87*$J$10/$L$10) -> 4.3768463 | G87: =IF(D87="","",($J$11-$H$7+D87)*$J$10/$H$12) | H87: =IF(E87="","",($J$11-$H$7+E87)*$J$10/$H$12) | I87: =$F$12+(C87*$J$10/$L$12) -> 752.88889 | J87: =IF(D87="","",($J$11-$H$7+D87)*$J$10/$B$12) | K87: =IF(E87="","",($J$11-$H$7+E87)*$J$10/$B$12)
B88: XLG1 | C88: 40 | F88: =$J$12+(C88*$J$10/$L$10) -> 4.3768463 | G88: =IF(D88="","",($J$11-$H$7+D88)*$J$10/$H$12) | H88: =IF(E88="","",($J$11-$H$7+E88)*$J$10/$H$12) | I88: =$F$12+(C88*$J$10/$L$12) -> 752.88889 | J88: =IF(D88="","",($J$11-$H$7+D88)*$J$10/$B$12) | K88: =IF(E88="","",($J$11-$H$7+E88)*$J$10/$B$12)
B89: IUSJ | C89: 40 | F89: =$J$12+(C89*$J$10/$L$10) -> 4.3768463 | G89: =IF(D89="","",($J$11-$H$7+D89)*$J$10/$H$12) | H89: =IF(E89="","",($J$11-$H$7+E89)*$J$10/$H$12) | I89: =$F$12+(C89*$J$10/$L$12) -> 752.88889 | J89: =IF(D89="","",($J$11-$H$7+D89)*$J$10/$B$12) | K89: =IF(E89="","",($J$11-$H$7+E89)*$J$10/$B$12) | L89: 5.4
B90: XLX7 | C90: 45 | F90: =$J$12+(C90*$J$10/$L$10) -> 4.4768463 | G90: =IF(D90="","",($J$11-$H$7+D90)*$J$10/$H$12) | H90: =IF(E90="","",($J$11-$H$7+E90)*$J$10/$H$12) | I90: =$F$12+(C90*$J$10/$L$12) -> 772.33333 | J90: =IF(D90="","",($J$11-$H$7+D90)*$J$10/$B$12) | K90: =IF(E90="","",($J$11-$H$7+E90)*$J$10/$B$12)
B91: IUSP | C91: 45 | F91: =$J$12+(C91*$J$10/$L$10) -> 4.4768463 | G91: =IF(D91="","",($J$11-$H$7+D91)*$J$10/$H$12) | H91: =IF(E91="","",($J$11-$H$7+E91)*$J$10/$H$12) | I91: =$F$12+(C91*$J$10/$L$12) -> 772.33333 | J91: =IF(D91="","",($J$11-$H$7+D91)*$J$10/$B$12) | K91: =IF(E91="","",($J$11-$H$7+E91)*$J$10/$B$12) | L91: 5.4
B92: PIT2 | C92: 270 | F92: =$J$12+(C92*$J$10/$L$10) -> 8.9768463 | G92: =IF(D92="","",($J$11-$H$7+D92)*$J$10/$H$12) | H92: =IF(E92="","",($J$11-$H$7+E92)*$J$10/$H$12) | I92: =$F$12+(C92*$J$10/$L$12) -> 1647.3333 | J92: =IF(D92="","",($J$11-$H$7+D92)*$J$10/$B$12) | K92: =IF(E92="","",($J$11-$H$7+E92)*$J$10/$B$12)
B93: SWF1 | C93: 300 | F93: =$J$12+(C93*$J$10/$L$10) -> 9.5768463 | G93: =IF(D93="","",($J$11-$H$7+D93)*$J$10/$H$12) | H93: =IF(E93="","",($J$11-$H$7+E93)*$J$10/$H$12) | I93: =$F$12+(C93*$J$10/$L$12) -> 1764 | J93: =IF(D93="","",($J$11-$H$7+D93)*$J$10/$B$12) | K93: =IF(E93="","",($J$11-$H$7+E93)*$J$10/$B$12)
B94: QXY9 | C94: 40 | F94: =$J$12+(C94*$J$10/$L$10) -> 4.3768463 | G94: =IF(D94="","",($J$11-$H$7+D94)*$J$10/$H$12) | H94: =IF(E94="","",($J$11-$H$7+E94)*$J$10/$H$12) | I94: =$F$12+(C94*$J$10/$L$12) -> 752.88889 | J94: =IF(D94="","",($J$11-$H$7+D94)*$J$10/$B$12) | K94: =IF(E94="","",($J$11-$H$7+E94)*$J$10/$B$12)
B95: IUSQ | C95: 40 | F95: =$J$12+(C95*$J$10/$L$10) -> 4.3768463 | G95: =IF(D95="","",($J$11-$H$7+D95)*$J$10/$H$12) | H95: =IF(E95="","",($J$11-$H$7+E95)*$J$10/$H$12) | I95: =$F$12+(C95*$J$10/$L$12) -> 752.88889 | J95: =IF(D95="","",($J$11-$H$7+D95)*$J$10/$B$12) | K95: =IF(E95="","",($J$11-$H$7+E95)*$J$10/$B$12) | L95: 5.4
B96: SCK1 | C96: 75 | F96: =$J$12+(C96*$J$10/$L$10) -> 5.0768463 | G96: =IF(D96="","",($J$11-$H$7+D96)*$J$10/$H$12) | H96: =IF(E96="","",($J$11-$H$7+E96)*$J$10/$H$12) | I96: =$F$12+(C96*$J$10/$L$12) -> 889 | J96: =IF(D96="","",($J$11-$H$7+D96)*$J$10/$B$12) | K96: =IF(E96="","",($J$11-$H$7+E96)*$J$10/$B$12)
B97: SCK3 | C97: 75 | F97: =$J$12+(C97*$J$10/$L$10) -> 5.0768463 | G97: =IF(D97="","",($J$11-$H$7+D97)*$J$10/$H$12) | H97: =IF(E97="","",($J$11-$H$7+E97)*$J$10/$H$12) | I97: =$F$12+(C97*$J$10/$L$12) -> 889 | J97: =IF(D97="","",($J$11-$H$7+D97)*$J$10/$B$12) | K97: =IF(E97="","",($J$11-$H$7+E97)*$J$10/$B$12)
B98: QXY5 | C98: 75 | F98: =$J$12+(C98*$J$10/$L$10) -> 5.0768463 | G98: =IF(D98="","",($J$11-$H$7+D98)*$J$10/$H$12) | H98: =IF(E98="","",($J$11-$H$7+E98)*$J$10/$H$12) | I98: =$F$12+(C98*$J$10/$L$12) -> 889 | J98: =IF(D98="","",($J$11-$H$7+D98)*$J$10/$B$12) | K98: =IF(E98="","",($J$11-$H$7+E98)*$J$10/$B$12) | L98: 5.7
B99: SMF1 | C99: 80 | F99: =$J$12+(C99*$J$10/$L$10) -> 5.1768463 | G99: =IF(D99="","",($J$11-$H$7+D99)*$J$10/$H$12) | H99: =IF(E99="","",($J$11-$H$7+E99)*$J$10/$H$12) | I99: =$F$12+(C99*$J$10/$L$12) -> 908.44444 | J99: =IF(D99="","",($J$11-$H$7+D99)*$J$10/$B$12) | K99: =IF(E99="","",($J$11-$H$7+E99)*$J$10/$B$12)
B100: SMF6 | C100: 80 | F100: =$J$12+(C100*$J$10/$L$10) -> 5.1768463 | G100: =IF(D100="","",($J$11-$H$7+D100)*$J$10/$H$12) | H100: =IF(E100="","",($J$11-$H$7+E100)*$J$10/$H$12) | I100: =$F$12+(C100*$J$10/$L$12) -> 908.44444 | J100: =IF(D100="","",($J$11-$H$7+D100)*$J$10/$B$12) | K100: =IF(E100="","",($J$11-$H$7+E100)*$J$10/$B$12)
...

Sheet 奥克兰744
A1: 应付 | B1: 盐田——OAK | F1: 费用类型 | G1: 币种 | H1: 单价 | I1: 数量 | J1: 备注 | K1: 统计
B2: 起运港 | C2: 拖车+报关 | F2: 装柜费 | G2: RMB | H2: 500 | I2: 1
F3: 拖车费 | G3: RMB | H3: 1950 | I3: 1
F4: 报关费 | G4: RMB | H4: 500 | I4: 0 | J4: 实报实销 | K4: 100/票
F5: 港杂费RMB部分 | G5: RMB | H5: 2800 | I5: 1
F6: 海运费（变动） | G6: USD | H6: 2850 | I6: 1
B7: 目的港 | C7: 提柜+拆柜 | F7: 提拆一口价 | G7: USD | H7: 1500 | I7: 1
C8: 清关+缴税 | F8: 清关费 | G8: USD | I8: 1
F9: 税金 | G9: USD | H9: 1500 | I9: 1 | L9: 每板KG
A10: 盐田—OAK | B10: 人民币应付 | G10: RMB | H10: =SUM(H2:H5) -> 5750 | I10: 汇率 | J10: 7 | K10: =H10/J10 -> 821.42857 | L10: 350
A11: 报价：2025/03/16 | B11: 含税/CBM | G11: USD | H11: =SUM(H6:H9) -> 5850 | I11: 合计 | J11: =H11+K10 -> 6671.4286 | K11: =J11*J10 -> 46700 | L11: CBM
A12: CBM标准 | B12: 75 | E12: CBM计费标准 | F12: =K11/B12 -> 622.66667 | G12: KG标准 | H12: 12500 | I12: KG计费标准 | J12: =F12/167 -> 3.7285429 | L12: 1.8
B13: 派送费 | C13: 美金/板 | D13: 组合一口价 | E13: 整柜一口价 | F13: 拆送KG含税 | G13: 组合KG | H13: 直送KG | I13: 拆送CBM含税 | J13: 组合CBM | K13: 直送CBM | L13: 直客报价101KG+
A14: 奥克兰 | B14: SCK4 | C14: 30 | D14: 2100 | E14: 1100 | F14: =$J$12+(C14*$J$10/$L$10) -> 4.3285429 | G14: =IF(D14="","",($J$11-$H$7+D14)*$J$10/$H$12) -> 4.072 | H14: =IF(E14="","",($J$11-$H$7+E14)*$J$10/$H$12) -> 3.512 | I14: =$F$12+(C14*$J$10/$L$12) -> 739.33333 | J14: =IF(D14="","",($J$11-$H$7+D14)*$J$10/$B$12) -> 678.66667 | K14: =IF(E14="","",($J$11-$H$7+E14)*$J$10/$B$12) -> 585.33333 | L14: 5.5
B15: SMF3 | C15: 30 | D15: 2100 | E15: 1100 | F15: =$J$12+(C15*$J$10/$L$10) -> 4.3285429 | G15: =IF(D15="","",($J$11-$H$7+D15)*$J$10/$H$12) -> 4.072 | H15: =IF(E15="","",($J$11-$H$7+E15)*$J$10/$H$12) -> 3.512 | I15: =$F$12+(C15*$J$10/$L$12) -> 739.33333 | J15: =IF(D15="","",($J$11-$H$7+D15)*$J$10/$B$12) -> 678.66667 | K15: =IF(E15="","",($J$11-$H$7+E15)*$J$10/$B$12) -> 585.33333 | L15: 5.5
B16: TCY2 | C16: 45 | D16: 2100 | E16: 1100 | F16: =$J$12+(C16*$J$10/$L$10) -> 4.6285429 | G16: =IF(D16="","",($J$11-$H$7+D16)*$J$10/$H$12)+36/167 -> 4.2875689 | H16: =IF(E16="","",($J$11-$H$7+E16)*$J$10/$H$12) -> 3.512 | I16: =$F$12+(C16*$J$10/$L$12) -> 797.66667 | J16: =IF(D16="","",($J$11-$H$7+D16)*$J$10/$B$12) -> 678.66667 | K16: =IF(E16="","",($J$11-$H$7+E16)*$J$10/$B$12) -> 585.33333 | L16: 5.9
B17: TCY1 | C17: 45 | D17: 2100 | E17: 1100 | F17: =$J$12+(C17*$J$10/$L$10) -> 4.6285429 | G17: =IF(D17="","",($J$11-$H$7+D17)*$J$10/$H$12)+36/167 -> 4.2875689 | H17: =IF(E17="","",($J$11-$H$7+E17)*$J$10/$H$12) -> 3.512 | I17: =$F$12+(C17*$J$10/$L$12) -> 797.66667 | J17: =IF(D17="","",($J$11-$H$7+D17)*$J$10/$B$12) -> 678.66667 | K17: =IF(E17="","",($J$11-$H$7+E17)*$J$10/$B$12) -> 585.33333 | L17: 5.9
B18: HLI2 | C18: 45 | D18: 2100 | E18: 1300 | F18: =$J$12+(C18*$J$10/$L$10) -> 4.6285429 | G18: =IF(D18="","",($J$11-$H$7+D18)*$J$10/$H$12)+72/167 -> 4.5031377 | H18: =IF(E18="","",($J$11-$H$7+E18)*$J$10/$H$12) -> 3.624 | I18: =$F$12+(C18*$J$10/$L$12) -> 797.66667 | J18: =IF(D18="","",($J$11-$H$7+D18)*$J$10/$B$12) -> 678.66667 | K18: =IF(E18="","",($J$11-$H$7+E18)*$J$10/$B$12) -> 604 | L18: 6
B19: SCK1 | C19: 30 | D19: 2100 | E19: 1100 | F19: =$J$12+(C19*$J$10/$L$10) -> 4.3285429 | G19: =IF(D19="","",($J$11-$H$7+D19)*$J$10/$H$12) -> 4.072 | H19: =IF(E19="","",($J$11-$H$7+E19)*$J$10/$H$12) -> 3.512 | I19: =$F$12+(C19*$J$10/$L$12) -> 739.33333 | J19: =IF(D19="","",($J$11-$H$7+D19)*$J$10/$B$12) -> 678.66667 | K19: =IF(E19="","",($J$11-$H$7+E19)*$J$10/$B$12) -> 585.33333 | L19: 5.5
B20: SCK3 | C20: 30 | D20: 2100 | E20: 1100 | F20: =$J$12+(C20*$J$10/$L$10) -> 4.3285429 | G20: =IF(D20="","",($J$11-$H$7+D20)*$J$10/$H$12) -> 4.072 | H20: =IF(E20="","",($J$11-$H$7+E20)*$J$10/$H$12) -> 3.512 | I20: =$F$12+(C20*$J$10/$L$12) -> 739.33333 | J20: =IF(D20="","",($J$11-$H$7+D20)*$J$10/$B$12) -> 678.66667 | K20: =IF(E20="","",($J$11-$H$7+E20)*$J$10/$B$12) -> 585.33333 | L20: 5.5
B21: OAK3 | C21: 30 | D21: 2100 | E21: 1100 | F21: =$J$12+(C21*$J$10/$L$10) -> 4.3285429 | G21: =IF(D21="","",($J$11-$H$7+D21)*$J$10/$H$12) -> 4.072 | H21: =IF(E21="","",($J$11-$H$7+E21)*$J$10/$H$12) -> 3.512 | I21: =$F$12+(C21*$J$10/$L$12) -> 739.33333 | J21: =IF(D21="","",($J$11-$H$7+D21)*$J$10/$B$12) -> 678.66667 | K21: =IF(E21="","",($J$11-$H$7+E21)*$J$10/$B$12) -> 585.33333 | L21: 5.5
B22: QXY5 | C22: 40 | D22: 2100 | F22: =$J$12+(C22*$J$10/$L$10) -> 4.5285429 | G22: =IF(D22="","",($J$11-$H$7+D22)*$J$10/$H$12)+36/167 -> 4.2875689 | H22: =IF(E22="","",($J$11-$H$7+E22)*$J$10/$H$12) | I22: =$F$12+(C22*$J$10/$L$12) -> 778.22222 | J22: =IF(D22="","",($J$11-$H$7+D22)*$J$10/$B$12) -> 678.66667 | K22: =IF(E22="","",($J$11-$H$7+E22)*$J$10/$B$12) | L22: 5.9
B23: SJC7 | C23: 30 | D23: 2100 | E23: 1100 | F23: =$J$12+(C23*$J$10/$L$10) -> 4.3285429 | G23: =IF(D23="","",($J$11-$H$7+D23)*$J$10/$H$12) -> 4.072 | H23: =IF(E23="","",($J$11-$H$7+E23)*$J$10/$H$12) -> 3.512 | I23: =$F$12+(C23*$J$10/$L$12) -> 739.33333 | J23: =IF(D23="","",($J$11-$H$7+D23)*$J$10/$B$12) -> 678.66667 | K23: =IF(E23="","",($J$11-$H$7+E23)*$J$10/$B$12) -> 585.33333
B24: SCK8 | C24: 40 | D24: 2100 | E24: 1100 | F24: =$J$12+(C24*$J$10/$L$10) -> 4.5285429 | G24: =IF(D24="","",($J$11-$H$7+D24)*$J$10/$H$12)+36/167 -> 4.2875689 | H24: =IF(E24="","",($J$11-$H$7+E24)*$J$10/$H$12) -> 3.512 | I24: =$F$12+(C24*$J$10/$L$12) -> 778.22222 | J24: =IF(D24="","",($J$11-$H$7+D24)*$J$10/$B$12)+60 -> 738.66667 | K24: =IF(E24="","",($J$11-$H$7+E24)*$J$10/$B$12) -> 585.33333 | L24: 5.9
B25: SMF7 | C25: 45 | D25: 2100 | E25: 1250 | F25: =$J$12+(C25*$J$10/$L$10) -> 4.6285429 | G25: =IF(D25="","",($J$11-$H$7+D25)*$J$10/$H$12)+54/167 -> 4.3953533 | H25: =IF(E25="","",($J$11-$H$7+E25)*$J$10/$H$12) -> 3.596 | I25: =$F$12+(C25*$J$10/$L$12) -> 797.66667 | J25: =IF(D25="","",($J$11-$H$7+D25)*$J$10/$B$12) -> 678.66667 | K25: =IF(E25="","",($J$11-$H$7+E25)*$J$10/$B$12) -> 599.33333 | L25: 5.9
B26: MCE1 | C26: 40 | D26: 2100 | E26: 1300 | F26: =$J$12+(C26*$J$10/$L$10) -> 4.5285429 | G26: =IF(D26="","",($J$11-$H$7+D26)*$J$10/$H$12)+54/167 -> 4.3953533 | H26: =IF(E26="","",($J$11-$H$7+E26)*$J$10/$H$12) -> 3.624 | I26: =$F$12+(C26*$J$10/$L$12) -> 778.22222 | J26: =IF(D26="","",($J$11-$H$7+D26)*$J$10/$B$12) -> 678.66667 | K26: =IF(E26="","",($J$11-$H$7+E26)*$J$10/$B$12) -> 604 | L26: 5.9
B27: SMF6 | C27: 45 | D27: 2100 | E27: 1300 | F27: =$J$12+(C27*$J$10/$L$10) -> 4.6285429 | G27: =IF(D27="","",($J$11-$H$7+D27)*$J$10/$H$12)+54/167 -> 4.3953533 | H27: =IF(E27="","",($J$11-$H$7+E27)*$J$10/$H$12) -> 3.624 | I27: =$F$12+(C27*$J$10/$L$12) -> 797.66667 | J27: =IF(D27="","",($J$11-$H$7+D27)*$J$10/$B$12) -> 678.66667 | K27: =IF(E27="","",($J$11-$H$7+E27)*$J$10/$B$12) -> 604 | L27: 5.9
B28: MCC1 | D28: 2100 | F28: =$J$12+(C28*$J$10/$L$10) -> 3.7285429 | G28: =IF(D28="","",($J$11-$H$7+D28)*$J$10/$H$12)+72/167 -> 4.5031377 | H28: =IF(E28="","",($J$11-$H$7+E28)*$J$10/$H$12) | I28: =$F$12+(C28*$J$10/$L$12) -> 622.66667 | J28: =IF(D28="","",($J$11-$H$7+D28)*$J$10/$B$12) -> 678.66667 | K28: =IF(E28="","",($J$11-$H$7+E28)*$J$10/$B$12) | L28: 6
B29: FAT2 | C29: 60 | D29: 2100 | E29: 1850 | F29: =$J$12+(C29*$J$10/$L$10) -> 4.9285429 | G29: =IF(D29="","",($J$11-$H$7+D29)*$J$10/$H$12)+72/167 -> 4.5031377 | H29: =IF(E29="","",($J$11-$H$7+E29)*$J$10/$H$12) -> 3.932 | I29: =$F$12+(C29*$J$10/$L$12) -> 856 | J29: =IF(D29="","",($J$11-$H$7+D29)*$J$10/$B$12) -> 678.66667 | K29: =IF(E29="","",($J$11-$H$7+E29)*$J$10/$B$12) -> 655.33333 | L29: 6

Sheet 西雅图788
A1: 应付 | B1: 盐田——西雅图 | F1: 费用类型 | G1: 币种 | H1: 单价 | I1: 数量 | J1: 备注 | K1: 统计
B2: 起运港 | C2: 拖车+报关 | F2: 装柜费 | G2: RMB | H2: 500 | I2: 1
F3: 拖车费 | G3: RMB | H3: 1950 | I3: 1
F4: 报关费 | G4: RMB | H4: 500 | I4: 0 | J4: 实报实销 | K4: 100/票
F5: 港杂费RMB部分 | G5: RMB | H5: 2800 | I5: 1
F6: 海运费（变动） | G6: USD | H6: 2850 | I6: 1
B7: 目的港 | C7: 提柜+拆柜 | F7: 提拆一口价 | G7: USD | H7: 2000 | I7: 1
C8: 清关+缴税 | F8: 清关费 | G8: USD | I8: 1
F9: 税金 | G9: USD | H9: 1500 | I9: 1 | L9: 每板KG
A10: 盐田—西雅图 | B10: 人民币应付 | G10: RMB | H10: =SUM(H2:H5) -> 5750 | I10: 汇率 | J10: 7 | K10: =H10/J10 -> 821.42857 | L10: 350
A11: 报价：2025/03/16 | B11: 含税/CBM | G11: USD | H11: =SUM(H6:H9) -> 6350 | I11: 合计 | J11: =H11+K10 -> 7171.4286 | K11: =J11*J10 -> 50200 | L11: CBM
A12: CBM标准 | B12: 75 | E12: CBM计费标准 | F12: =K11/B12 -> 669.33333 | G12: KG标准 | H12: 12500 | I12: KG计费标准 | J12: =K11/H12 -> 4.016 | L12: 1.8
B13: 派送费 | C13: 美金/板 | D13: 组合一口价 | E13: 整柜一口价 | F13: 拆送KG含税 | G13: 组合KG | H13: 直送KG | I13: 拆送CBM含税 | J13: 组合CBM | K13: 直送CBM | L13: 直客报价101KG+
A14: 西雅图拆送 | B14: BFI3 | C14: 45 | F14: =$J$12+(C14*$J$10/$L$10) -> 4.916 | G14: =IF(D14="","",($J$11-$H$7+D14)*$J$10/$H$12) | H14: =IF(E14="","",($J$11-$H$7+E14)*$J$10/$H$12) | I14: =$F$12+(C14*$J$10/$L$12) -> 844.33333 | J14: =IF(D14="","",($J$11-$H$7+D14)*$J$10/$B$12) | K14: =IF(E14="","",($J$11-$H$7+E14)*$J$10/$B$12) | L14: 6.1
B15: BFI7 | C15: 45 | F15: =$J$12+(C15*$J$10/$L$10) -> 4.916 | G15: =IF(D15="","",($J$11-$H$7+D15)*$J$10/$H$12) | H15: =IF(E15="","",($J$11-$H$7+E15)*$J$10/$H$12) | I15: =$F$12+(C15*$J$10/$L$12) -> 844.33333 | J15: =IF(D15="","",($J$11-$H$7+D15)*$J$10/$B$12) | K15: =IF(E15="","",($J$11-$H$7+E15)*$J$10/$B$12) | L15: 6.1
B16: PDX6 | C16: 65 | F16: =$J$12+(C16*$J$10/$L$10) -> 5.316 | G16: =IF(D16="","",($J$11-$H$7+D16)*$J$10/$H$12) | H16: =IF(E16="","",($J$11-$H$7+E16)*$J$10/$H$12) | I16: =$F$12+(C16*$J$10/$L$12) -> 922.11111 | J16: =IF(D16="","",($J$11-$H$7+D16)*$J$10/$B$12) | K16: =IF(E16="","",($J$11-$H$7+E16)*$J$10/$B$12) | L16: 6.6
B17: PDX7 | C17: 65 | F17: =$J$12+(C17*$J$10/$L$10) -> 5.316 | G17: =IF(D17="","",($J$11-$H$7+D17)*$J$10/$H$12) | H17: =IF(E17="","",($J$11-$H$7+E17)*$J$10/$H$12) | I17: =$F$12+(C17*$J$10/$L$12) -> 922.11111 | J17: =IF(D17="","",($J$11-$H$7+D17)*$J$10/$B$12) | K17: =IF(E17="","",($J$11-$H$7+E17)*$J$10/$B$12) | L17: 6.6
B18: PSC2 | C18: 65 | D18: 3250 | F18: =$J$12+(C18*$J$10/$L$10) -> 5.316 | G18: =IF(D18="","",($J$11-$H$7+D18)*$J$10/$H$12) -> 4.716 | H18: =IF(E18="","",($J$11-$H$7+E18)*$J$10/$H$12) | I18: =$F$12+(C18*$J$10/$L$12) -> 922.11111 | J18: =IF(D18="","",($J$11-$H$7+D18)*$J$10/$B$12) -> 786 | K18: =IF(E18="","",($J$11-$H$7+E18)*$J$10/$B$12) | L18: 6.4
B19: GEG2 | C19: 85 | F19: =$J$12+(C19*$J$10/$L$10) -> 5.716 | G19: =IF(D19="","",($J$11-$H$7+D19)*$J$10/$H$12) | H19: =IF(E19="","",($J$11-$H$7+E19)*$J$10/$H$12) | I19: =$F$12+(C19*$J$10/$L$12) -> 999.88889 | J19: =IF(D19="","",($J$11-$H$7+D19)*$J$10/$B$12) | K19: =IF(E19="","",($J$11-$H$7+E19)*$J$10/$B$12) | L19: 7

Sheet 芝加哥840
A1: 应付 | B1: 盐田——CHI | F1: 费用类型 | G1: 币种 | H1: 单价 | I1: 数量 | J1: 备注 | K1: 统计
B2: 起运港 | C2: 拖车+报关 | F2: 装柜费 | G2: RMB | H2: 500 | I2: 1
F3: 拖车费 | G3: RMB | H3: 1950 | I3: 1 | J3: 广州+东莞 | K3: 2450
F4: 报关费 | G4: RMB | H4: 500 | I4: 0 | J4: 实报实销 | K4: 100/票
F5: 港杂费RMB部分 | G5: RMB | H5: 2800 | I5: 1
F6: 海运费（变动） | G6: USD | H6: 5150 | I6: 1 | J6: OA舱位
B7: 目的港 | C7: 提柜+拆柜 | F7: 提拆一口价 | G7: USD | H7: 1500 | I7: 1
C8: 清关+缴税 | F8: 清关费 | G8: USD | I8: 1
F9: 税金 | G9: USD | H9: 1500 | I9: 1 | L9: 每板KG
A10: 盐田——CHI | B10: 人民币应付 | G10: RMB | H10: =SUM(H2:H5) -> 5750 | I10: 汇率 | J10: 7 | K10: =H10/J10 -> 821.42857 | L10: 350
A11: 报价：2025/03/16 | B11: 含税/CBM | G11: USD | H11: =SUM(H6:H9) -> 8150 | I11: 合计 | J11: =H11+K10 -> 8971.4286 | K11: =J11*J10 -> 62800 | L11: CBM
A12: CBM标准 | B12: 75 | E12: CBM计费标准 | F12: =K11/B12 -> 837.33333 | G12: KG标准 | H12: 12500 | I12: KG计费标准 | J12: =K11/H12 -> 5.024 | L12: 1.8
B13: 派送费 | C13: 美金/板 | D13: 组合一口价 | E13: 整柜一口价 | F13: 拆送KG含税 | G13: 组合KG | H13: 直送KG | I13: 拆送CBM含税 | J13: 组合CBM | K13: 直送CBM | L13: 直客报价101KG+
A14: 芝 加 哥 一区 | B14: MDW2 | C14: 45 | D14: 2600 | E14: 1850 | F14: =$J$12+(C14*$J$10/$L$10) -> 5.924 | G14: =IF(D14="","",($J$11-$H$7+D14)*$J$10/$H$12) -> 5.64 | H14: =IF(E14="","",($J$11-$H$7+E14)*$J$10/$H$12) -> 5.22 | I14: =$F$12+(C14*$J$10/$L$12) -> 1012.3333 | J14: =IF(D14="","",($J$11-$H$7+D14)*$J$10/$B$12) -> 940 | K14: =IF(E14="","",($J$11-$H$7+E14)*$J$10/$B$12) -> 870 | L14: 7
B15: ORD2 | C15: 40 | D15: 2600 | F15: =$J$12+(C15*$J$10/$L$10) -> 5.824 | G15: =IF(D15="","",($J$11-$H$7+D15)*$J$10/$H$12) -> 5.64 | H15: =IF(E15="","",($J$11-$H$7+E15)*$J$10/$H$12) | I15: =$F$12+(C15*$J$10/$L$12) -> 992.88889 | J15: =IF(D15="","",($J$11-$H$7+D15)*$J$10/$B$12) -> 940 | K15: =IF(E15="","",($J$11-$H$7+E15)*$J$10/$B$12) | L15: 7
B16: IGQ2 | C16: 40 | D16: 2600 | F16: =$J$12+(C16*$J$10/$L$10) -> 5.824 | G16: =IF(D16="","",($J$11-$H$7+D16)*$J$10/$H$12) -> 5.64 | H16: =IF(E16="","",($J$11-$H$7+E16)*$J$10/$H$12) | I16: =$F$12+(C16*$J$10/$L$12) -> 992.88889 | J16: =IF(D16="","",($J$11-$H$7+D16)*$J$10/$B$12) -> 940 | K16: =IF(E16="","",($J$11-$H$7+E16)*$J$10/$B$12) | L16: 7
B17: MDW9 | C17: 40 | D17: 2600 | F17: =$J$12+(C17*$J$10/$L$10) -> 5.824 | G17: =IF(D17="","",($J$11-$H$7+D17)*$J$10/$H$12) -> 5.64 | H17: =IF(E17="","",($J$11-$H$7+E17)*$J$10/$H$12) | I17: =$F$12+(C17*$J$10/$L$12) -> 992.88889 | J17: =IF(D17="","",($J$11-$H$7+D17)*$J$10/$B$12) -> 940 | K17: =IF(E17="","",($J$11-$H$7+E17)*$J$10/$B$12) | L17: 7
B18: RFD2 | C18: 50 | D18: 2600 | F18: =$J$12+(C18*$J$10/$L$10) -> 6.024 | G18: =IF(D18="","",($J$11-$H$7+D18)*$J$10/$H$12) -> 5.64 | H18: =IF(E18="","",($J$11-$H$7+E18)*$J$10/$H$12) | I18: =$F$12+(C18*$J$10/$L$12) -> 1031.7778 | J18: =IF(D18="","",($J$11-$H$7+D18)*$J$10/$B$12) -> 940 | K18: =IF(E18="","",($J$11-$H$7+E18)*$J$10/$B$12) | L18: 7
B19: RFD4 | C19: 50 | D19: 2600 | F19: =$J$12+(C19*$J$10/$L$10) -> 6.024 | G19: =IF(D19="","",($J$11-$H$7+D19)*$J$10/$H$12) -> 5.64 | H19: =IF(E19="","",($J$11-$H$7+E19)*$J$10/$H$12) | I19: =$F$12+(C19*$J$10/$L$12) -> 1031.7778 | J19: =IF(D19="","",($J$11-$H$7+D19)*$J$10/$B$12) -> 940 | K19: =IF(E19="","",($J$11-$H$7+E19)*$J$10/$B$12) | L19: 7
B20: JVL1 | C20: 60 | D20: 2600 | F20: =$J$12+(C20*$J$10/$L$10) -> 6.224 | G20: =IF(D20="","",($J$11-$H$7+D20)*$J$10/$H$12) -> 5.64 | H20: =IF(E20="","",($J$11-$H$7+E20)*$J$10/$H$12) | I20: =$F$12+(C20*$J$10/$L$12) -> 1070.6667 | J20: =IF(D20="","",($J$11-$H$7+D20)*$J$10/$B$12) -> 940 | K20: =IF(E20="","",($J$11-$H$7+E20)*$J$10/$B$12) | L20: 7
B21: MDW6 | C21: 35 | D21: 2600 | F21: =$J$12+(C21*$J$10/$L$10) -> 5.724 | G21: =IF(D21="","",($J$11-$H$7+D21)*$J$10/$H$12) -> 5.64 | H21: =IF(E21="","",($J$11-$H$7+E21)*$J$10/$H$12) | I21: =$F$12+(C21*$J$10/$L$12) -> 973.44444 | J21: =IF(D21="","",($J$11-$H$7+D21)*$J$10/$B$12) -> 940 | K21: =IF(E21="","",($J$11-$H$7+E21)*$J$10/$B$12) | L21: 7
B22: 沃尔玛--ORD1S | D22: 2600 | F22: =$J$12+(C22*$J$10/$L$10) -> 5.024 | G22: =IF(D22="","",($J$11-$H$7+D22)*$J$10/$H$12) -> 5.64 | H22: =IF(E22="","",($J$11-$H$7+E22)*$J$10/$H$12) | I22: =$F$12+(C22*$J$10/$L$12) -> 837.33333 | J22: =IF(D22="","",($J$11-$H$7+D22)*$J$10/$B$12) -> 940 | K22: =IF(E22="","",($J$11-$H$7+E22)*$J$10/$B$12)
A23: 芝 加 哥 二区 | B23: IND9 | C23: 60 | D23: 3200 | F23: =$J$12+(C23*$J$10/$L$10) -> 6.224 | G23: =IF(D23="","",($J$11-$H$7+D23)*$J$10/$H$12) -> 5.976 | H23: =IF(E23="","",($J$11-$H$7+E23)*$J$10/$H$12) | I23: =$F$12+(C23*$J$10/$L$12) -> 1070.6667 | J23: =IF(D23="","",($J$11-$H$7+D23)*$J$10/$B$12) -> 996 | K23: =IF(E23="","",($J$11-$H$7+E23)*$J$10/$B$12) | L23: 7.4
B24: FWA4 | C24: 75 | D24: 3200 | F24: =$J$12+(C24*$J$10/$L$10) -> 6.524 | G24: =IF(D24="","",($J$11-$H$7+D24)*$J$10/$H$12) -> 5.976 | H24: =IF(E24="","",($J$11-$H$7+E24)*$J$10/$H$12) | I24: =$F$12+(C24*$J$10/$L$12) -> 1129 | J24: =IF(D24="","",($J$11-$H$7+D24)*$J$10/$B$12) -> 996 | K24: =IF(E24="","",($J$11-$H$7+E24)*$J$10/$B$12) | L24: 7.4
B25: MQJ1 | C25: 65 | D25: 3200 | F25: =$J$12+(C25*$J$10/$L$10) -> 6.324 | G25: =IF(D25="","",($J$11-$H$7+D25)*$J$10/$H$12) -> 5.976 | H25: =IF(E25="","",($J$11-$H$7+E25)*$J$10/$H$12) | I25: =$F$12+(C25*$J$10/$L$12) -> 1090.1111 | J25: =IF(D25="","",($J$11-$H$7+D25)*$J$10/$B$12) -> 996 | K25: =IF(E25="","",($J$11-$H$7+E25)*$J$10/$B$12) | L25: 7.4
B26: MQJ2 | C26: 65 | D26: 3200 | F26: =$J$12+(C26*$J$10/$L$10) -> 6.324 | G26: =IF(D26="","",($J$11-$H$7+D26)*$J$10/$H$12) -> 5.976 | H26: =IF(E26="","",($J$11-$H$7+E26)*$J$10/$H$12) | I26: =$F$12+(C26*$J$10/$L$12) -> 1090.1111 | J26: =IF(D26="","",($J$11-$H$7+D26)*$J$10/$B$12) -> 996 | K26: =IF(E26="","",($J$11-$H$7+E26)*$J$10/$B$12) | L26: 7.4
B27: STL4 | C27: 80 | D27: 3200 | F27: =$J$12+(C27*$J$10/$L$10) -> 6.624 | G27: =IF(D27="","",($J$11-$H$7+D27)*$J$10/$H$12) -> 5.976 | H27: =IF(E27="","",($J$11-$H$7+E27)*$J$10/$H$12) | I27: =$F$12+(C27*$J$10/$L$12) -> 1148.4444 | J27: =IF(D27="","",($J$11-$H$7+D27)*$J$10/$B$12) -> 996 | K27: =IF(E27="","",($J$11-$H$7+E27)*$J$10/$B$12) | L27: 7.4
B28: IND2 | C28: 65 | D28: 3200 | F28: =$J$12+(C28*$J$10/$L$10) -> 6.324 | G28: =IF(D28="","",($J$11-$H$7+D28)*$J$10/$H$12) -> 5.976 | H28: =IF(E28="","",($J$11-$H$7+E28)*$J$10/$H$12) | I28: =$F$12+(C28*$J$10/$L$12) -> 1090.1111 | J28: =IF(D28="","",($J$11-$H$7+D28)*$J$10/$B$12) -> 996 | K28: =IF(E28="","",($J$11-$H$7+E28)*$J$10/$B$12) | L28: 7.4
B29: IND4 | C29: 65 | D29: 3200 | F29: =$J$12+(C29*$J$10/$L$10) -> 6.324 | G29: =IF(D29="","",($J$11-$H$7+D29)*$J$10/$H$12) -> 5.976 | H29: =IF(E29="","",($J$11-$H$7+E29)*$J$10/$H$12) | I29: =$F$12+(C29*$J$10/$L$12) -> 1090.1111 | J29: =IF(D29="","",($J$11-$H$7+D29)*$J$10/$B$12) -> 996 | K29: =IF(E29="","",($J$11-$H$7+E29)*$J$10/$B$12) | L29: 7.4
B30: IND5 | C30: 65 | D30: 3200 | F30: =$J$12+(C30*$J$10/$L$10) -> 6.324 | G30: =IF(D30="","",($J$11-$H$7+D30)*$J$10/$H$12) -> 5.976 | H30: =IF(E30="","",($J$11-$H$7+E30)*$J$10/$H$12) | I30: =$F$12+(C30*$J$10/$L$12) -> 1090.1111 | J30: =IF(D30="","",($J$11-$H$7+D30)*$J$10/$B$12) -> 996 | K30: =IF(E30="","",($J$11-$H$7+E30)*$J$10/$B$12) | L30: 7.4
B31: PPO4 | C31: 70 | D31: 3200 | F31: =$J$12+(C31*$J$10/$L$10) -> 6.424 | G31: =IF(D31="","",($J$11-$H$7+D31)*$J$10/$H$12) -> 5.976 | H31: =IF(E31="","",($J$11-$H$7+E31)*$J$10/$H$12) | I31: =$F$12+(C31*$J$10/$L$12) -> 1109.5556 | J31: =IF(D31="","",($J$11-$H$7+D31)*$J$10/$B$12) -> 996 | K31: =IF(E31="","",($J$11-$H$7+E31)*$J$10/$B$12)
B32: 沃尔玛--IND2 | D32: 3200 | F32: =$J$12+(C32*$J$10/$L$10) -> 5.024 | G32: =IF(D32="","",($J$11-$H$7+D32)*$J$10/$H$12) -> 5.976 | H32: =IF(E32="","",($J$11-$H$7+E32)*$J$10/$H$12) | I32: =$F$12+(C32*$J$10/$L$12) -> 837.33333 | J32: =IF(D32="","",($J$11-$H$7+D32)*$J$10/$B$12) -> 996 | K32: =IF(E32="","",($J$11-$H$7+E32)*$J$10/$B$12)
B33: 沃尔玛--IND3 | D33: 3200 | F33: =$J$12+(C33*$J$10/$L$10) -> 5.024 | G33: =IF(D33="","",($J$11-$H$7+D33)*$J$10/$H$12) -> 5.976 | H33: =IF(E33="","",($J$11-$H$7+E33)*$J$10/$H$12) | I33: =$F$12+(C33*$J$10/$L$12) -> 837.33333 | J33: =IF(D33="","",($J$11-$H$7+D33)*$J$10/$B$12) -> 996
B34: 沃尔玛--IND2N | D34: 3200 | F34: =$J$12+(C34*$J$10/$L$10) -> 5.024 | G34: =IF(D34="","",($J$11-$H$7+D34)*$J$10/$H$12) -> 5.976 | H34: =IF(E34="","",($J$11-$H$7+E34)*$J$10/$H$12) | I34: =$F$12+(C34*$J$10/$L$12) -> 837.33333 | J34: =IF(D34="","",($J$11-$H$7+D34)*$J$10/$B$12) -> 996 | K34: =IF(E34="","",($J$11-$H$7+E34)*$J$10/$B$12)
A35: 芝 加 哥 三区 | B35: DET1 | C35: 80 | D35: 3800 | F35: =$J$12+(C35*$J$10/$L$10) -> 6.624 | G35: =IF(D35="","",($J$11-$H$7+D35)*$J$10/$H$12) -> 6.312 | H35: =IF(E35="","",($J$11-$H$7+E35)*$J$10/$H$12) | I35: =$F$12+(C35*$J$10/$L$12) -> 1148.4444 | J35: =IF(D35="","",($J$11-$H$7+D35)*$J$10/$B$12) -> 1052 | K35: =IF(E35="","",($J$11-$H$7+E35)*$J$10/$B$12) | L35: 7.7
B36: DET2 | C36: 80 | D36: 3800 | F36: =$J$12+(C36*$J$10/$L$10) -> 6.624 | G36: =IF(D36="","",($J$11-$H$7+D36)*$J$10/$H$12) -> 6.312 | H36: =IF(E36="","",($J$11-$H$7+E36)*$J$10/$H$12) | I36: =$F$12+(C36*$J$10/$L$12) -> 1148.4444 | J36: =IF(D36="","",($J$11-$H$7+D36)*$J$10/$B$12) -> 1052 | K36: =IF(E36="","",($J$11-$H$7+E36)*$J$10/$B$12) | L36: 7.7
B37: LAN2 | C37: 120 | D37: 3800 | F37: =$J$12+(C37*$J$10/$L$10) -> 7.424 | G37: =IF(D37="","",($J$11-$H$7+D37)*$J$10/$H$12) -> 6.312 | H37: =IF(E37="","",($J$11-$H$7+E37)*$J$10/$H$12) | I37: =$F$12+(C37*$J$10/$L$12) -> 1304 | J37: =IF(D37="","",($J$11-$H$7+D37)*$J$10/$B$12) -> 1052 | K37: =IF(E37="","",($J$11-$H$7+E37)*$J$10/$B$12)
B38: CMH2 | C38: 80 | D38: 3800 | F38: =$J$12+(C38*$J$10/$L$10) -> 6.624 | G38: =IF(D38="","",($J$11-$H$7+D38)*$J$10/$H$12) -> 6.312 | H38: =IF(E38="","",($J$11-$H$7+E38)*$J$10/$H$12) | I38: =$F$12+(C38*$J$10/$L$12) -> 1148.4444 | J38: =IF(D38="","",($J$11-$H$7+D38)*$J$10/$B$12) -> 1052 | K38: =IF(E38="","",($J$11-$H$7+E38)*$J$10/$B$12) | L38: 7.7
B39: CMH3 | C39: 80 | D39: 3800 | F39: =$J$12+(C39*$J$10/$L$10) -> 6.624 | G39: =IF(D39="","",($J$11-$H$7+D39)*$J$10/$H$12) -> 6.312 | H39: =IF(E39="","",($J$11-$H$7+E39)*$J$10/$H$12) | I39: =$F$12+(C39*$J$10/$L$12) -> 1148.4444 | J39: =IF(D39="","",($J$11-$H$7+D39)*$J$10/$B$12) -> 1052 | K39: =IF(E39="","",($J$11-$H$7+E39)*$J$10/$B$12) | L39: 7.7
B40: CMH7 | C40: 80 | D40: 3800 | F40: =$J$12+(C40*$J$10/$L$10) -> 6.624 | G40: =IF(D40="","",($J$11-$H$7+D40)*$J$10/$H$12) -> 6.312 | H40: =IF(E40="","",($J$11-$H$7+E40)*$J$10/$H$12) | I40: =$F$12+(C40*$J$10/$L$12) -> 1148.4444 | J40: =IF(D40="","",($J$11-$H$7+D40)*$J$10/$B$12) -> 1052 | K40: =IF(E40="","",($J$11-$H$7+E40)*$J$10/$B$12) | L40: 7.7
A41: 芝 加 哥 四区 | B41: FOE1 | C41: 120 | D41: 4600 | F41: =$J$12+(C41*$J$10/$L$10) -> 7.424 | G41: =IF(D41="","",($J$11-$H$7+D41)*$J$10/$H$12) -> 6.76 | H41: =IF(E41="","",($J$11-$H$7+E41)*$J$10/$H$12) | I41: =$F$12+(C41*$J$10/$L$12) -> 1304 | J41: =IF(D41="","",($J$11-$H$7+D41)*$J$10/$B$12) -> 1126.6667 | K41: =IF(E41="","",($J$11-$H$7+E41)*$J$10/$B$12)
B42: MKC4 | C42: 120 | D42: 4600 | F42: =$J$12+(C42*$J$10/$L$10) -> 7.424 | G42: =IF(D42="","",($J$11-$H$7+D42)*$J$10/$H$12) -> 6.76 | H42: =IF(E42="","",($J$11-$H$7+E42)*$J$10/$H$12) | I42: =$F$12+(C42*$J$10/$L$12) -> 1304 | J42: =IF(D42="","",($J$11-$H$7+D42)*$J$10/$B$12) -> 1126.6667 | K42: =IF(E42="","",($J$11-$H$7+E42)*$J$10/$B$12) | L42: 8.2
B43: MEM1 | C43: 155 | D43: 4600 | F43: =$J$12+(C43*$J$10/$L$10) -> 8.124 | G43: =IF(D43="","",($J$11-$H$7+D43)*$J$10/$H$12) -> 6.76 | H43: =IF(E43="","",($J$11-$H$7+E43)*$J$10/$H$12) | I43: =$F$12+(C43*$J$10/$L$12) -> 1440.1111 | J43: =IF(D43="","",($J$11-$H$7+D43)*$J$10/$B$12) -> 1126.6667 | K43: =IF(E43="","",($J$11-$H$7+E43)*$J$10/$B$12)
B44: MEM6 | C44: 155 | D44: 4600 | F44: =$J$12+(C44*$J$10/$L$10) -> 8.124 | G44: =IF(D44="","",($J$11-$H$7+D44)*$J$10/$H$12) -> 6.76 | H44: =IF(E44="","",($J$11-$H$7+E44)*$J$10/$H$12) | I44: =$F$12+(C44*$J$10/$L$12) -> 1440.1111 | J44: =IF(D44="","",($J$11-$H$7+D44)*$J$10/$B$12) -> 1126.6667 | K44: =IF(E44="","",($J$11-$H$7+E44)*$J$10/$B$12)
B45: MCI3 | C45: 120 | D45: 4600 | F45: =$J$12+(C45*$J$10/$L$10) -> 7.424 | G45: =IF(D45="","",($J$11-$H$7+D45)*$J$10/$H$12) -> 6.76 | H45: =IF(E45="","",($J$11-$H$7+E45)*$J$10/$H$12) | I45: =$F$12+(C45*$J$10/$L$12) -> 1304 | J45: =IF(D45="","",($J$11-$H$7+D45)*$J$10/$B$12) -> 1126.6667 | K45: =IF(E45="","",($J$11-$H$7+E45)*$J$10/$B$12) | L45: 8.2
B46: STL3 | C46: 120 | D46: 4600 | F46: =$J$12+(C46*$J$10/$L$10) -> 7.424 | G46: =IF(D46="","",($J$11-$H$7+D46)*$J$10/$H$12) -> 6.76 | H46: =IF(E46="","",($J$11-$H$7+E46)*$J$10/$H$12) | I46: =$F$12+(C46*$J$10/$L$12) -> 1304 | J46: =IF(D46="","",($J$11-$H$7+D46)*$J$10/$B$12) -> 1126.6667 | K46: =IF(E46="","",($J$11-$H$7+E46)*$J$10/$B$12) | L46: 8.2
B47: 沃尔玛--KS1 | D47: 4600 | F47: =$J$12+(C47*$J$10/$L$10) -> 5.024 | G47: =IF(D47="","",($J$11-$H$7+D47)*$J$10/$H$12) -> 6.76 | H47: =IF(E47="","",($J$11-$H$7+E47)*$J$10/$H$12) | I47: =$F$12+(C47*$J$10/$L$12) -> 837.33333 | J47: =IF(D47="","",($J$11-$H$7+D47)*$J$10/$B$12) -> 1126.6667 | K47: =IF(E47="","",($J$11-$H$7+E47)*$J$10/$B$12)
B48: 沃尔玛--MCI1N | D48: 4600 | F48: =$J$12+(C48*$J$10/$L$10) -> 5.024 | G48: =IF(D48="","",($J$11-$H$7+D48)*$J$10/$H$12) -> 6.76 | H48: =IF(E48="","",($J$11-$H$7+E48)*$J$10/$H$12) | I48: =$F$12+(C48*$J$10/$L$12) -> 837.33333 | J48: =IF(D48="","",($J$11-$H$7+D48)*$J$10/$B$12) -> 1126.6667 | K48: =IF(E48="","",($J$11-$H$7+E48)*$J$10/$B$12)
B49: MDW4 | C49: 40 | F49: =$J$12+(C49*$J$10/$L$10) -> 5.824 | G49: =IF(D49="","",($J$11-$H$7+D49)*$J$10/$H$12) | H49: =IF(E49="","",($J$11-$H$7+E49)*$J$10/$H$12) | I49: =$F$12+(C49*$J$10/$L$12) -> 992.88889 | J49: =IF(D49="","",($J$11-$H$7+D49)*$J$10/$B$12) | K49: =IF(E49="","",($J$11-$H$7+E49)*$J$10/$B$12)
B50: MDW7 | C50: 40 | F50: =$J$12+(C50*$J$10/$L$10) -> 5.824 | G50: =IF(D50="","",($J$11-$H$7+D50)*$J$10/$H$12) | H50: =IF(E50="","",($J$11-$H$7+E50)*$J$10/$H$12) | I50: =$F$12+(C50*$J$10/$L$12) -> 992.88889 | J50: =IF(D50="","",($J$11-$H$7+D50)*$J$10/$B$12) | K50: =IF(E50="","",($J$11-$H$7+E50)*$J$10/$B$12)
B51: MDW8 | C51: 40 | F51: =$J$12+(C51*$J$10/$L$10) -> 5.824 | G51: =IF(D51="","",($J$11-$H$7+D51)*$J$10/$H$12) | H51: =IF(E51="","",($J$11-$H$7+E51)*$J$10/$H$12) | I51: =$F$12+(C51*$J$10/$L$12) -> 992.88889 | J51: =IF(D51="","",($J$11-$H$7+D51)*$J$10/$B$12) | K51: =IF(E51="","",($J$11-$H$7+E51)*$J$10/$B$12)
B52: KRB6 | C52: 50 | F52: =$J$12+(C52*$J$10/$L$10) -> 6.024 | G52: =IF(D52="","",($J$11-$H$7+D52)*$J$10/$H$12) | H52: =IF(E52="","",($J$11-$H$7+E52)*$J$10/$H$12) | I52: =$F$12+(C52*$J$10/$L$12) -> 1031.7778 | J52: =IF(D52="","",($J$11-$H$7+D52)*$J$10/$B$12) | K52: =IF(E52="","",($J$11-$H$7+E52)*$J$10/$B$12)
B53: SDF8 | C53: 90 | F53: =$J$12+(C53*$J$10/$L$10) -> 6.824 | G53: =IF(D53="","",($J$11-$H$7+D53)*$J$10/$H$12) | H53: =IF(E53="","",($J$11-$H$7+E53)*$J$10/$H$12) | I53: =$F$12+(C53*$J$10/$L$12) -> 1187.3333 | J53: =IF(D53="","",($J$11-$H$7+D53)*$J$10/$B$12) | K53: =IF(E53="","",($J$11-$H$7+E53)*$J$10/$B$12)
B54: MKE1 | C54: 60 | F54: =$J$12+(C54*$J$10/$L$10) -> 6.224 | G54: =IF(D54="","",($J$11-$H$7+D54)*$J$10/$H$12) | H54: =IF(E54="","",($J$11-$H$7+E54)*$J$10/$H$12) | I54: =$F$12+(C54*$J$10/$L$12) -> 1070.6667 | J54: =IF(D54="","",($J$11-$H$7+D54)*$J$10/$B$12) | K54: =IF(E54="","",($J$11-$H$7+E54)*$J$10/$B$12)
B55: MKE2 | C55: 60 | F55: =$J$12+(C55*$J$10/$L$10) -> 6.224 | G55: =IF(D55="","",($J$11-$H$7+D55)*$J$10/$H$12) | H55: =IF(E55="","",($J$11-$H$7+E55)*$J$10/$H$12) | I55: =$F$12+(C55*$J$10/$L$12) -> 1070.6667 | J55: =IF(D55="","",($J$11-$H$7+D55)*$J$10/$B$12) | K55: =IF(E55="","",($J$11-$H$7+E55)*$J$10/$B$12)
B56: STL6 | C56: 80 | F56: =$J$12+(C56*$J$10/$L$10) -> 6.624 | G56: =IF(D56="","",($J$11-$H$7+D56)*$J$10/$H$12) | H56: =IF(E56="","",($J$11-$H$7+E56)*$J$10/$H$12) | I56: =$F$12+(C56*$J$10/$L$12) -> 1148.4444 | J56: =IF(D56="","",($J$11-$H$7+D56)*$J$10/$B$12) | K56: =IF(E56="","",($J$11-$H$7+E56)*$J$10/$B$12)
B57: CMH1 | C57: 80 | F57: =$J$12+(C57*$J$10/$L$10) -> 6.624 | G57: =IF(D57="","",($J$11-$H$7+D57)*$J$10/$H$12) | H57: =IF(E57="","",($J$11-$H$7+E57)*$J$10/$H$12) | I57: =$F$12+(C57*$J$10/$L$12) -> 1148.4444 | J57: =IF(D57="","",($J$11-$H$7+D57)*$J$10/$B$12) | K57: =IF(E57="","",($J$11-$H$7+E57)*$J$10/$B$12)
B58: CMH4 | C58: 80 | F58: =$J$12+(C58*$J$10/$L$10) -> 6.624 | G58: =IF(D58="","",($J$11-$H$7+D58)*$J$10/$H$12) | H58: =IF(E58="","",($J$11-$H$7+E58)*$J$10/$H$12) | I58: =$F$12+(C58*$J$10/$L$12) -> 1148.4444 | J58: =IF(D58="","",($J$11-$H$7+D58)*$J$10/$B$12) | K58: =IF(E58="","",($J$11-$H$7+E58)*$J$10/$B$12)
B59: CMH6 | C59: 80 | F59: =$J$12+(C59*$J$10/$L$10) -> 6.624 | G59: =IF(D59="","",($J$11-$H$7+D59)*$J$10/$H$12) | H59: =IF(E59="","",($J$11-$H$7+E59)*$J$10/$H$12) | I59: =$F$12+(C59*$J$10/$L$12) -> 1148.4444 | J59: =IF(D59="","",($J$11-$H$7+D59)*$J$10/$B$12) | K59: =IF(E59="","",($J$11-$H$7+E59)*$J$10/$B$12)
B60: CVG1 | C60: 80 | F60: =$J$12+(C60*$J$10/$L$10) -> 6.624 | G60: =IF(D60="","",($J$11-$H$7+D60)*$J$10/$H$12) | H60: =IF(E60="","",($J$11-$H$7+E60)*$J$10/$H$12) | I60: =$F$12+(C60*$J$10/$L$12) -> 1148.4444 | J60: =IF(D60="","",($J$11-$H$7+D60)*$J$10/$B$12) | K60: =IF(E60="","",($J$11-$H$7+E60)*$J$10/$B$12)
... B82: LFT1 | C82: 180 | F82: =$J$12+(C82*$J$10/$L$10) -> 8.624 | G82: =IF(D82="","",($J$11-$H$7+D82)*$J$10/$H$12) | H82: =IF(E82="","",($J$11-$H$7+E82)*$J$10/$H$12) | I82: =$F$12+(C82*$J$10/$L$12) -> 1537.3333 | J82: =IF(D82="","",($J$11-$H$7+D82)*$J$10/$B$12) | K82: =IF(E82="","",($J$11-$H$7+E82)*$J$10/$B$12)

Sheet 休斯顿866
A1: 应付 | B1: 盐田——HOU | F1: 费用类型 | G1: 币种 | H1: 单价 | I1: 数量 | J1: 备注 | K1: 统计
B2: 起运港 | C2: 拖车+报关 | F2: 装柜费 | G2: RMB | H2: 500 | I2: 1
F3: 拖车费 | G3: RMB | H3: 1950 | I3: 1
F4: 报关费 | G4: RMB | H4: 500 | I4: 0 | J4: 实报实销 | K4: 100/票
F5: 港杂费RMB部分 | G5: RMB | H5: 3500 | I5: 1
F6: 海运费（变动） | G6: USD | H6: 3850 | I6: 1
B7: 目的港 | C7: 提柜+拆柜 | F7: 提拆一口价 | G7: USD | H7: 1500 | I7: 1
C8: 清关+缴税 | F8: 清关费 | G8: USD | I8: 1
F9: 税金 | G9: USD | H9: 1500 | I9: 1 | L9: 每板KG
A10: 盐田——HOU | B10: 人民币应付 | G10: RMB | H10: =SUM(H2:H5) -> 6450 | I10: 汇率 | J10: 7 | K10: =H10/J10 -> 921.42857 | L10: 350
A11: 报价：2025/03/16 | B11: 含税/CBM | G11: USD | H11: =SUM(H6:H9) -> 6850 | I11: 合计 | J11: =H11+K10 -> 7771.4286 | K11: =J11*J10 -> 54400 | L11: CBM
A12: CBM标准 | B12: 75 | E12: CBM计费标准 | F12: =K11/B12 -> 725.33333 | G12: KG标准 | H12: 12500 | I12: KG计费标准 | J12: =K11/B12/167 -> 4.3433134 | L12: 1.8
B13: 派送费 | C13: 美金/板 | D13: 组合一口价 | E13: 整柜一口价 | F13: 拆送KG含税 | G13: 组合KG | H13: 直送KG | I13: 拆送CBM含税 | J13: 组合CBM | K13: 直送CBM | L13: 直客报价101KG+
A14: 休斯顿 一区 | B14: HOU8 | C14: 45 | D14: 2000 | F14: =$J$12+(C14*$J$10/$L$10) -> 5.2433134 | G14: =IF(D14="","",($J$11-$H$7+D14)*$J$10/$H$12) -> 4.632 | H14: =IF(E14="","",($J$11-$H$7+E14)*$J$10/$H$12) | I14: =$F$12+(C14*$J$10/$L$12) -> 900.33333 | J14: =IF(D14="","",($J$11-$H$7+D14)*$J$10/$B$12) -> 772 | K14: =IF(E14="","",($J$11-$H$7+E14)*$J$10/$B$12) | L14: 6.2
B15: HOU7 | C15: 45 | D15: 2000 | F15: =$J$12+(C15*$J$10/$L$10) -> 5.2433134 | G15: =IF(D15="","",($J$11-$H$7+D15)*$J$10/$H$12) -> 4.632 | H15: =IF(E15="","",($J$11-$H$7+E15)*$J$10/$H$12) | I15: =$F$12+(C15*$J$10/$L$12) -> 900.33333 | J15: =IF(D15="","",($J$11-$H$7+D15)*$J$10/$B$12) -> 772 | K15: =IF(E15="","",($J$11-$H$7+E15)*$J$10/$B$12) | L15: 6.2
B16: HOU3 | C16: 45 | D16: 2000 | F16: =$J$12+(C16*$J$10/$L$10) -> 5.2433134 | G16: =IF(D16="","",($J$11-$H$7+D16)*$J$10/$H$12) -> 4.632 | H16: =IF(E16="","",($J$11-$H$7+E16)*$J$10/$H$12) | I16: =$F$12+(C16*$J$10/$L$12) -> 900.33333 | J16: =IF(D16="","",($J$11-$H$7+D16)*$J$10/$B$12) -> 772 | K16: =IF(E16="","",($J$11-$H$7+E16)*$J$10/$B$12) | L16: 6.2
B17: HOU2 | C17: 45 | D17: 2000 | F17: =$J$12+(C17*$J$10/$L$10) -> 5.2433134 | G17: =IF(D17="","",($J$11-$H$7+D17)*$J$10/$H$12) -> 4.632 | I17: =$F$12+(C17*$J$10/$L$12) -> 900.33333 | J17: =IF(D17="","",($J$11-$H$7+D17)*$J$10/$B$12) -> 772 | L17: 6.2
B18: HOU1 | D18: 2000 | F18: =$J$12+(C18*$J$10/$L$10) -> 4.3433134 | G18: =IF(D18="","",($J$11-$H$7+D18)*$J$10/$H$12) -> 4.632 | I18: =$F$12+(C18*$J$10/$L$12) -> 725.33333 | J18: =IF(D18="","",($J$11-$H$7+D18)*$J$10/$B$12) -> 772 | L18: 6.2
B19: IAH3 | C19: 65 | D19: 2000 | F19: =$J$12+(C19*$J$10/$L$10) -> 5.6433134 | G19: =IF(D19="","",($J$11-$H$7+D19)*$J$10/$H$12) -> 4.632 | I19: =$F$12+(C19*$J$10/$L$12) -> 978.11111 | J19: =IF(D19="","",($J$11-$H$7+D19)*$J$10/$B$12) -> 772 | L19: 6.2
A20: 休斯顿 二区 | B20: FTW9 | C20: 65 | D20: 2900 | F20: =$J$12+(C20*$J$10/$L$10) -> 5.6433134 | G20: =IF(D20="","",($J$11-$H$7+D20)*$J$10/$H$12) -> 5.136 | I20: =$F$12+(C20*$J$10/$L$12) -> 978.11111 | J20: =IF(D20="","",($J$11-$H$7+D20)*$J$10/$B$12) -> 856 | L20: 6.7
B21: FTW1 | C21: 40 | D21: 2900 | F21: =$J$12+(C21*$J$10/$L$10) -> 5.1433134 | G21: =IF(D21="","",($J$11-$H$7+D21)*$J$10/$H$12) -> 5.136 | H21: =IF(E21="","",($J$11-$H$7+E21)*$J$10/$H$12) | I21: =$F$12+(C21*$J$10/$L$12) -> 880.88889 | J21: =IF(D21="","",($J$11-$H$7+D21)*$J$10/$B$12) -> 856 | K21: =IF(E21="","",($J$11-$H$7+E21)*$J$10/$B$12) | L21: 6.7
B22: FTW5 | C22: 40 | D22: 2900 | F22: =$J$12+(C22*$J$10/$L$10) -> 5.1433134 | G22: =IF(D22="","",($J$11-$H$7+D22)*$J$10/$H$12) -> 5.136 | H22: =IF(E22="","",($J$11-$H$7+E22)*$J$10/$H$12) | I22: =$F$12+(C22*$J$10/$L$12) -> 880.88889 | J22: =IF(D22="","",($J$11-$H$7+D22)*$J$10/$B$12) -> 856 | K22: =IF(E22="","",($J$11-$H$7+E22)*$J$10/$B$12) | L22: 6.7
B23: FTW3 | C23: 65 | D23: 2900 | F23: =$J$12+(C23*$J$10/$L$10) -> 5.6433134 | G23: =IF(D23="","",($J$11-$H$7+D23)*$J$10/$H$12) -> 5.136 | H23: =IF(E23="","",($J$11-$H$7+E23)*$J$10/$H$12) | I23: =$F$12+(C23*$J$10/$L$12) -> 978.11111 | J23: =IF(D23="","",($J$11-$H$7+D23)*$J$10/$B$12) -> 856 | K23: =IF(E23="","",($J$11-$H$7+E23)*$J$10/$B$12) | L23: 6.7
B24: SAT1 | C24: 55 | D24: 2900 | F24: =$J$12+(C24*$J$10/$L$10) -> 5.4433134 | G24: =IF(D24="","",($J$11-$H$7+D24)*$J$10/$H$12) -> 5.136 | H24: =IF(E24="","",($J$11-$H$7+E24)*$J$10/$H$12) | I24: =$F$12+(C24*$J$10/$L$12) -> 939.22222 | J24: =IF(D24="","",($J$11-$H$7+D24)*$J$10/$B$12) -> 856 | K24: =IF(E24="","",($J$11-$H$7+E24)*$J$10/$B$12) | L24: 6.7
B25: FTW2 | C25: 65 | D25: 2900 | F25: =$J$12+(C25*$J$10/$L$10) -> 5.6433134 | G25: =IF(D25="","",($J$11-$H$7+D25)*$J$10/$H$12) -> 5.136 | H25: =IF(E25="","",($J$11-$H$7+E25)*$J$10/$H$12) | I25: =$F$12+(C25*$J$10/$L$12) -> 978.11111 | J25: =IF(D25="","",($J$11-$H$7+D25)*$J$10/$B$12) -> 856 | K25: =IF(E25="","",($J$11-$H$7+E25)*$J$10/$B$12) | L25: 6.7
B26: IUSF | C26: 45 | D26: 2900 | F26: =$J$12+(C26*$J$10/$L$10) -> 5.2433134 | G26: =IF(D26="","",($J$11-$H$7+D26)*$J$10/$H$12) -> 5.136 | H26: =IF(E26="","",($J$11-$H$7+E26)*$J$10/$H$12) | I26: =$F$12+(C26*$J$10/$L$12) -> 900.33333 | J26: =IF(D26="","",($J$11-$H$7+D26)*$J$10/$B$12) -> 856 | K26: =IF(E26="","",($J$11-$H$7+E26)*$J$10/$B$12) | L26: 6.7
B27: DFW7 | C27: 65 | D27: 2900 | F27: =$J$12+(C27*$J$10/$L$10) -> 5.6433134 | G27: =IF(D27="","",($J$11-$H$7+D27)*$J$10/$H$12) -> 5.136 | H27: =IF(E27="","",($J$11-$H$7+E27)*$J$10/$H$12) | I27: =$F$12+(C27*$J$10/$L$12) -> 978.11111 | J27: =IF(D27="","",($J$11-$H$7+D27)*$J$10/$B$12) -> 856 | K27: =IF(E27="","",($J$11-$H$7+E27)*$J$10/$B$12) | L27: 6.7
B28: DFW6 | C28: 50 | D28: 2900 | F28: =$J$12+(C28*$J$10/$L$10) -> 5.3433134 | G28: =IF(D28="","",($J$11-$H$7+D28)*$J$10/$H$12) -> 5.136 | H28: =IF(E28="","",($J$11-$H$7+E28)*$J$10/$H$12) | I28: =$F$12+(C28*$J$10/$L$12) -> 919.77778 | J28: =IF(D28="","",($J$11-$H$7+D28)*$J$10/$B$12) -> 856 | K28: =IF(E28="","",($J$11-$H$7+E28)*$J$10/$B$12) | L28: 6.7
B29: DAL3 | C29: 90 | D29: 2900 | F29: =$J$12+(C29*$J$10/$L$10) -> 6.1433134 | G29: =IF(D29="","",($J$11-$H$7+D29)*$J$10/$H$12) -> 5.136 | I29: =$F$12+(C29*$J$10/$L$12) -> 1075.3333 | J29: =IF(D29="","",($J$11-$H$7+D29)*$J$10/$B$12) -> 856 | L29: 6.7
B30: SAT6 | C30: 85 | D30: 2900 | F30: =$J$12+(C30*$J$10/$L$10) -> 6.0433134 | G30: =IF(D30="","",($J$11-$H$7+D30)*$J$10/$H$12) -> 5.136 | H30: =IF(E30="","",($J$11-$H$7+E30)*$J$10/$H$12) | I30: =$F$12+(C30*$J$10/$L$12) -> 1055.8889 | J30: =IF(D30="","",($J$11-$H$7+D30)*$J$10/$B$12) -> 856 | K30: =IF(E30="","",($J$11-$H$7+E30)*$J$10/$B$12) | L30: 6.7
B31: SAT4 | C31: 55 | D31: 2900 | F31: =$J$12+(C31*$J$10/$L$10) -> 5.4433134 | G31: =IF(D31="","",($J$11-$H$7+D31)*$J$10/$H$12) -> 5.136 | I31: =$F$12+(C31*$J$10/$L$12) -> 939.22222 | J31: =IF(D31="","",($J$11-$H$7+D31)*$J$10/$B$12) -> 856 | L31: 6.7
B32: IUTH | C32: 85 | D32: 2900 | F32: =$J$12+(C32*$J$10/$L$10) -> 6.0433134 | G32: =IF(D32="","",($J$11-$H$7+D32)*$J$10/$H$12) -> 5.136 | I32: =$F$12+(C32*$J$10/$L$12) -> 1055.8889 | J32: =IF(D32="","",($J$11-$H$7+D32)*$J$10/$B$12) -> 856 | L32: 6.7
A33: 休斯顿 三区 | B33: MEM1 | C33: 145 | D33: 4050 | F33: =$J$12+(C33*$J$10/$L$10) -> 7.2433134 | G33: =IF(D33="","",($J$11-$H$7+D33)*$J$10/$H$12) -> 5.78 | I33: =$F$12+(C33*$J$10/$L$12) -> 1289.2222 | J33: =IF(D33="","",($J$11-$H$7+D33)*$J$10/$B$12) -> 963.33333
B34: MEM6 | C34: 115 | D34: 4050 | F34: =$J$12+(C34*$J$10/$L$10) -> 6.6433134 | G34: =IF(D34="","",($J$11-$H$7+D34)*$J$10/$H$12) -> 5.78 | H34: =IF(E34="","",($J$11-$H$7+E34)*$J$10/$H$12) | I34: =$F$12+(C34*$J$10/$L$12) -> 1172.5556 | J34: =IF(D34="","",($J$11-$H$7+D34)*$J$10/$B$12) -> 963.33333 | K34: =IF(E34="","",($J$11-$H$7+E34)*$J$10/$B$12)
B35: LFT1 | C35: 115 | D35: 4050 | F35: =$J$12+(C35*$J$10/$L$10) -> 6.6433134 | G35: =IF(D35="","",($J$11-$H$7+D35)*$J$10/$H$12) -> 5.78 | H35: =IF(E35="","",($J$11-$H$7+E35)*$J$10/$H$12) | I35: =$F$12+(C35*$J$10/$L$12) -> 1172.5556 | J35: =IF(D35="","",($J$11-$H$7+D35)*$J$10/$B$12) -> 963.33333 | K35: =IF(E35="","",($J$11-$H$7+E35)*$J$10/$B$12) | L35: 7.4
B36: AMA1 | C36: 130 | D36: 4050 | F36: =$J$12+(C36*$J$10/$L$10) -> 6.9433134 | G36: =IF(D36="","",($J$11-$H$7+D36)*$J$10/$H$12) -> 5.78 | H36: =IF(E36="","",($J$11-$H$7+E36)*$J$10/$H$12) | I36: =$F$12+(C36*$J$10/$L$12) -> 1230.8889 | J36: =IF(D36="","",($J$11-$H$7+D36)*$J$10/$B$12) -> 963.33333 | K36: =IF(E36="","",($J$11-$H$7+E36)*$J$10/$B$12)
B37: OKC2 | C37: 135 | D37: 4050 | F37: =$J$12+(C37*$J$10/$L$10) -> 7.0433134 | G37: =IF(D37="","",($J$11-$H$7+D37)*$J$10/$H$12) -> 5.78 | H37: =IF(E37="","",($J$11-$H$7+E37)*$J$10/$H$12) | I37: =$F$12+(C37*$J$10/$L$12) -> 1250.3333 | J37: =IF(D37="","",($J$11-$H$7+D37)*$J$10/$B$12) -> 963.33333 | K37: =IF(E37="","",($J$11-$H$7+E37)*$J$10/$B$12) | L37: 7.4
B38: LIT2 | C38: 115 | D38: 4050 | F38: =$J$12+(C38*$J$10/$L$10) -> 6.6433134 | G38: =IF(D38="","",($J$11-$H$7+D38)*$J$10/$H$12) -> 5.78 | H38: =IF(E38="","",($J$11-$H$7+E38)*$J$10/$H$12) | I38: =$F$12+(C38*$J$10/$L$12) -> 1172.5556 | J38: =IF(D38="","",($J$11-$H$7+D38)*$J$10/$B$12) -> 963.33333 | K38: =IF(E38="","",($J$11-$H$7+E38)*$J$10/$B$12) | L38: 7.7
B39: ICT2 | C39: 135 | D39: 4050 | F39: =$J$12+(C39*$J$10/$L$10) -> 7.0433134 | G39: =IF(D39="","",($J$11-$H$7+D39)*$J$10/$H$12) -> 5.78 | H39: =IF(E39="","",($J$11-$H$7+E39)*$J$10/$H$12) | I39: =$F$12+(C39*$J$10/$L$12) -> 1250.3333 | J39: =IF(D39="","",($J$11-$H$7+D39)*$J$10/$B$12) -> 963.33333 | K39: =IF(E39="","",($J$11-$H$7+E39)*$J$10/$B$12) | L39: 7.7
B40: FOE1 | D40: 4050 | F40: =$J$12+(C40*$J$10/$L$10) -> 4.3433134 | G40: =IF(D40="","",($J$11-$H$7+D40)*$J$10/$H$12) -> 5.78 | H40: =IF(E40="","",($J$11-$H$7+E40)*$J$10/$H$12) | I40: =$F$12+(C40*$J$10/$L$12) -> 725.33333 | J40: =IF(D40="","",($J$11-$H$7+D40)*$J$10/$B$12) -> 963.33333 | K40: =IF(E40="","",($J$11-$H$7+E40)*$J$10/$B$12) | L40: 7.7

Sheet 萨凡纳888
A1: 应付 | B1: 盐田——SAV | F1: 费用类型 | G1: 币种 | H1: 单价 | I1: 数量 | J1: 备注 | K1: 统计
B2: 起运港 | C2: 拖车+报关 | F2: 装柜费 | G2: RMB | H2: 500 | I2: 1
F3: 拖车费 | G3: RMB | H3: 1950 | I3: 1
F4: 报关费 | G4: RMB | H4: 500 | I4: 0 | J4: 实报实销 | K4: 100/票
F5: 港杂费RMB部分 | G5: RMB | H5: 3500 | I5: 1
F6: 海运费（变动） | G6: USD | H6: 3850 | I6: 1
B7: 目的港 | C7: 提柜+拆柜 | F7: 提拆一口价 | G7: USD | H7: 1500 | I7: 1
C8: 清关+缴税 | F8: 清关费 | G8: USD | I8: 1
F9: 税金 | G9: USD | H9: 1500 | I9: 1 | L9: 每板KG
A10: 盐田——SAV | B10: 人民币应付 | G10: RMB | H10: =SUM(H2:H5) -> 6450 | I10: 汇率 | J10: 7 | K10: =H10/J10 -> 921.42857 | L10: 350
A11: 报价：2025/03/16 | B11: 含税/CBM | G11: USD | H11: =SUM(H6:H9) -> 6850 | I11: 合计 | J11: =H11+K10 -> 7771.4286 | K11: =J11*J10 -> 54400 | L11: CBM
A12: CBM标准 | B12: 75 | E12: CBM计费标准 | F12: =K11/B12 -> 725.33333 | G12: KG标准 | H12: 12500 | I12: KG计费标准 | J12: =K11/H12 -> 4.352 | L12: 1.8
B13: 派送费 | C13: 美金/板 | D13: 组合一口价 | E13: 整柜一口价 | F13: 拆送KG含税 | G13: 组合KG | H13: 直送KG | I13: 拆送CBM含税 | J13: 组合CBM | K13: 直送CBM | L13: 直客报价101KG+
A14: 萨凡纳 一区 | B14: SAV3 | C14: 65 | D14: 2700 | F14: =$J$12+(C14*$J$10/$L$10) -> 5.652 | G14: =IF(D14="","",($J$11-$H$7+D14)*$J$10/$H$12) -> 5.024 | H14: =IF(E14="","",($J$11-$H$7+E14)*$J$10/$H$12) | I14: =$F$12+(C14*$J$10/$L$12) -> 978.11111 | J14: =IF(D14="","",($J$11-$H$7+D14)*$J$10/$B$12) -> 837.33333 | K14: =IF(E14="","",($J$11-$H$7+E14)*$J$10/$B$12)
B15: JAX3 | C15: 85 | D15: 2700 | F15: =$J$12+(C15*$J$10/$L$10) -> 6.052 | G15: =IF(D15="","",($J$11-$H$7+D15)*$J$10/$H$12) -> 5.024 | H15: =IF(E15="","",($J$11-$H$7+E15)*$J$10/$H$12) | I15: =$F$12+(C15*$J$10/$L$12) -> 1055.8889 | J15: =IF(D15="","",($J$11-$H$7+D15)*$J$10/$B$12) -> 837.33333 | K15: =IF(E15="","",($J$11-$H$7+E15)*$J$10/$B$12) | L15: 6.4
B16: XLX6 | C16: 65 | D16: 2700 | F16: =$J$12+(C16*$J$10/$L$10) -> 5.652 | G16: =IF(D16="","",($J$11-$H$7+D16)*$J$10/$H$12) -> 5.024 | H16: =IF(E16="","",($J$11-$H$7+E16)*$J$10/$H$12) | I16: =$F$12+(C16*$J$10/$L$12) -> 978.11111 | J16: =IF(D16="","",($J$11-$H$7+D16)*$J$10/$B$12) -> 837.33333 | K16: =IF(E16="","",($J$11-$H$7+E16)*$J$10/$B$12) | L16: 6.4
B17: GSP1 | C17: 85 | D17: 2700 | F17: =$J$12+(C17*$J$10/$L$10) -> 6.052 | G17: =IF(D17="","",($J$11-$H$7+D17)*$J$10/$H$12) -> 5.024 | H17: =IF(E17="","",($J$11-$H$7+E17)*$J$10/$H$12) | I17: =$F$12+(C17*$J$10/$L$12) -> 1055.8889 | J17: =IF(D17="","",($J$11-$H$7+D17)*$J$10/$B$12) -> 837.33333 | K17: =IF(E17="","",($J$11-$H$7+E17)*$J$10/$B$12) | L17: 6.4
B18: GSO1 | C18: 105 | D18: 2700 | F18: =$J$12+(C18*$J$10/$L$10) -> 6.452 | G18: =IF(D18="","",($J$11-$H$7+D18)*$J$10/$H$12) -> 5.024 | H18: =IF(E18="","",($J$11-$H$7+E18)*$J$10/$H$12) | I18: =$F$12+(C18*$J$10/$L$12) -> 1133.6667 | J18: =IF(D18="","",($J$11-$H$7+D18)*$J$10/$B$12) -> 837.33333 | K18: =IF(E18="","",($J$11-$H$7+E18)*$J$10/$B$12) | L18: 6.4
B19: IUSR | C19: 80 | D19: 2700 | F19: =$J$12+(C19*$J$10/$L$10) -> 5.952 | G19: =IF(D19="","",($J$11-$H$7+D19)*$J$10/$H$12) -> 5.024 | H19: =IF(E19="","",($J$11-$H$7+E19)*$J$10/$H$12) | I19: =$F$12+(C19*$J$10/$L$12) -> 1036.4444 | J19: =IF(D19="","",($J$11-$H$7+D19)*$J$10/$B$12) -> 837.33333 | K19: =IF(E19="","",($J$11-$H$7+E19)*$J$10/$B$12) | L19: 6.4
B20: CAE1 | C20: 80 | D20: 2700 | F20: =$J$12+(C20*$J$10/$L$10) -> 5.952 | G20: =IF(D20="","",($J$11-$H$7+D20)*$J$10/$H$12) -> 5.024 | H20: =IF(E20="","",($J$11-$H$7+E20)*$J$10/$H$12) | I20: =$F$12+(C20*$J$10/$L$12) -> 1036.4444 | J20: =IF(D20="","",($J$11-$H$7+D20)*$J$10/$B$12) -> 837.33333 | K20: =IF(E20="","",($J$11-$H$7+E20)*$J$10/$B$12) | L20: 6.4
B21: MGE1 | C21: 85 | D21: 2700 | F21: =$J$12+(C21*$J$10/$L$10) -> 6.052 | G21: =IF(D21="","",($J$11-$H$7+D21)*$J$10/$H$12) -> 5.024 | H21: =IF(E21="","",($J$11-$H$7+E21)*$J$10/$H$12) | I21: =$F$12+(C21*$J$10/$L$12) -> 1055.8889 | J21: =IF(D21="","",($J$11-$H$7+D21)*$J$10/$B$12) -> 837.33333 | K21: =IF(E21="","",($J$11-$H$7+E21)*$J$10/$B$12) | L21: 6.4
B22: MGE3 | C22: 85 | D22: 2700 | F22: =$J$12+(C22*$J$10/$L$10) -> 6.052 | G22: =IF(D22="","",($J$11-$H$7+D22)*$J$10/$H$12) -> 5.024 | H22: =IF(E22="","",($J$11-$H$7+E22)*$J$10/$H$12) | I22: =$F$12+(C22*$J$10/$L$12) -> 1055.8889 | J22: =IF(D22="","",($J$11-$H$7+D22)*$J$10/$B$12) -> 837.33333 | K22: =IF(E22="","",($J$11-$H$7+E22)*$J$10/$B$12) | L22: 6.4
B23: RYY2 | C23: 115 | D23: 2700 | F23: =$J$12+(C23*$J$10/$L$10) -> 6.652 | G23: =IF(D23="","",($J$11-$H$7+D23)*$J$10/$H$12) -> 5.024 | H23: =IF(E23="","",($J$11-$H$7+E23)*$J$10/$H$12) | I23: =$F$12+(C23*$J$10/$L$12) -> 1172.5556 | J23: =IF(D23="","",($J$11-$H$7+D23)*$J$10/$B$12) -> 837.33333 | K23: =IF(E23="","",($J$11-$H$7+E23)*$J$10/$B$12) | L23: 6.4
B24: CLT2 | C24: 85 | D24: 2700 | F24: =$J$12+(C24*$J$10/$L$10) -> 6.052 | G24: =IF(D24="","",($J$11-$H$7+D24)*$J$10/$H$12) -> 5.024 | H24: =IF(E24="","",($J$11-$H$7+E24)*$J$10/$H$12) | I24: =$F$12+(C24*$J$10/$L$12) -> 1055.8889 | J24: =IF(D24="","",($J$11-$H$7+D24)*$J$10/$B$12) -> 837.33333 | K24: =IF(E24="","",($J$11-$H$7+E24)*$J$10/$B$12) | L24: 6.4
B25: CLT3 | C25: 85 | D25: 2700 | F25: =$J$12+(C25*$J$10/$L$10) -> 6.052 | G25: =IF(D25="","",($J$11-$H$7+D25)*$J$10/$H$12) -> 5.024 | H25: =IF(E25="","",($J$11-$H$7+E25)*$J$10/$H$12) | I25: =$F$12+(C25*$J$10/$L$12) -> 1055.8889 | J25: =IF(D25="","",($J$11-$H$7+D25)*$J$10/$B$12) -> 837.33333 | K25: =IF(E25="","",($J$11-$H$7+E25)*$J$10/$B$12) | L25: 6.4
B26: RDU2 | C26: 75 | D26: 2700 | F26: =$J$12+(C26*$J$10/$L$10) -> 5.852 | G26: =IF(D26="","",($J$11-$H$7+D26)*$J$10/$H$12) -> 5.024 | H26: =IF(E26="","",($J$11-$H$7+E26)*$J$10/$H$12) | I26: =$F$12+(C26*$J$10/$L$12) -> 1017 | J26: =IF(D26="","",($J$11-$H$7+D26)*$J$10/$B$12) -> 837.33333 | K26: =IF(E26="","",($J$11-$H$7+E26)*$J$10/$B$12) | L26: 6.4
B27: RDU4 | C27: 85 | D27: 2700 | F27: =$J$12+(C27*$J$10/$L$10) -> 6.052 | G27: =IF(D27="","",($J$11-$H$7+D27)*$J$10/$H$12) -> 5.024 | H27: =IF(E27="","",($J$11-$H$7+E27)*$J$10/$H$12) | I27: =$F$12+(C27*$J$10/$L$12) -> 1055.8889 | J27: =IF(D27="","",($J$11-$H$7+D27)*$J$10/$B$12) -> 837.33333 | K27: =IF(E27="","",($J$11-$H$7+E27)*$J$10/$B$12)
B28: XAV3 | C28: 40 | D28: 2700 | F28: =$J$12+(C28*$J$10/$L$10) -> 5.152 | G28: =IF(D28="","",($J$11-$H$7+D28)*$J$10/$H$12) -> 5.024 | H28: =IF(E28="","",($J$11-$H$7+E28)*$J$10/$H$12) | I28: =$F$12+(C28*$J$10/$L$12) -> 880.88889 | J28: =IF(D28="","",($J$11-$H$7+D28)*$J$10/$B$12) -> 837.33333 | K28: =IF(E28="","",($J$11-$H$7+E28)*$J$10/$B$12)
B29: WAL-ATL1 | D29: 2700 | F29: =$J$12+(C29*$J$10/$L$10) -> 4.352 | G29: =IF(D29="","",($J$11-$H$7+D29)*$J$10/$H$12) -> 5.024 | H29: =IF(E29="","",($J$11-$H$7+E29)*$J$10/$H$12) | I29: =$F$12+(C29*$J$10/$L$12) -> 725.33333 | J29: =IF(D29="","",($J$11-$H$7+D29)*$J$10/$B$12) -> 837.33333 | K29: =IF(E29="","",($J$11-$H$7+E29)*$J$10/$B$12)
B30: WAL-ATL3 | D30: 2700 | F30: =$J$12+(C30*$J$10/$L$10) -> 4.352 | G30: =IF(D30="","",($J$11-$H$7+D30)*$J$10/$H$12) -> 5.024 | H30: =IF(E30="","",($J$11-$H$7+E30)*$J$10/$H$12) | I30: =$F$12+(C30*$J$10/$L$12) -> 725.33333 | J30: =IF(D30="","",($J$11-$H$7+D30)*$J$10/$B$12) -> 837.33333 | K30: =IF(E30="","",($J$11-$H$7+E30)*$J$10/$B$12)
A31: 萨凡纳 二区 | B31: MCO1 | C31: 95 | D31: 3200 | F31: =$J$12+(C31*$J$10/$L$10) -> 6.252 | G31: =IF(D31="","",($J$11-$H$7+D31)*$J$10/$H$12) -> 5.304 | H31: =IF(E31="","",($J$11-$H$7+E31)*$J$10/$H$12) | I31: =$F$12+(C31*$J$10/$L$12) -> 1094.7778 | J31: =IF(D31="","",($J$11-$H$7+D31)*$J$10/$B$12) -> 884 | K31: =IF(E31="","",($J$11-$H$7+E31)*$J$10/$B$12) | L31: 6.7
B32: MCO2 | C32: 110 | D32: 3200 | F32: =$J$12+(C32*$J$10/$L$10) -> 6.552 | G32: =IF(D32="","",($J$11-$H$7+D32)*$J$10/$H$12) -> 5.304 | H32: =IF(E32="","",($J$11-$H$7+E32)*$J$10/$H$12) | I32: =$F$12+(C32*$J$10/$L$12) -> 1153.1111 | J32: =IF(D32="","",($J$11-$H$7+D32)*$J$10/$B$12) -> 884 | K32: =IF(E32="","",($J$11-$H$7+E32)*$J$10/$B$12) | L32: 6.7
B33: TPA2 | C33: 90 | D33: 3200 | F33: =$J$12+(C33*$J$10/$L$10) -> 6.152 | G33: =IF(D33="","",($J$11-$H$7+D33)*$J$10/$H$12) -> 5.304 | H33: =IF(E33="","",($J$11-$H$7+E33)*$J$10/$H$12) | I33: =$F$12+(C33*$J$10/$L$12) -> 1075.3333 | J33: =IF(D33="","",($J$11-$H$7+D33)*$J$10/$B$12) -> 884 | K33: =IF(E33="","",($J$11-$H$7+E33)*$J$10/$B$12) | L33: 6.7
B34: TPA3 | C34: 90 | D34: 3200 | F34: =$J$12+(C34*$J$10/$L$10) -> 6.152 | G34: =IF(D34="","",($J$11-$H$7+D34)*$J$10/$H$12) -> 5.304 | H34: =IF(E34="","",($J$11-$H$7+E34)*$J$10/$H$12) | I34: =$F$12+(C34*$J$10/$L$12) -> 1075.3333 | J34: =IF(D34="","",($J$11-$H$7+D34)*$J$10/$B$12) -> 884 | K34: =IF(E34="","",($J$11-$H$7+E34)*$J$10/$B$12) | L34: 6.7
B35: TPA6 | C35: 105 | D35: 3200 | F35: =$J$12+(C35*$J$10/$L$10) -> 6.452 | G35: =IF(D35="","",($J$11-$H$7+D35)*$J$10/$H$12) -> 5.304 | H35: =IF(E35="","",($J$11-$H$7+E35)*$J$10/$H$12) | I35: =$F$12+(C35*$J$10/$L$12) -> 1133.6667 | J35: =IF(D35="","",($J$11-$H$7+D35)*$J$10/$B$12) -> 884 | K35: =IF(E35="","",($J$11-$H$7+E35)*$J$10/$B$12) | L35: 6.7
B36: TMB8 | C36: 160 | D36: 3200 | F36: =$J$12+(C36*$J$10/$L$10) -> 7.552 | G36: =IF(D36="","",($J$11-$H$7+D36)*$J$10/$H$12) -> 5.304 | H36: =IF(E36="","",($J$11-$H$7+E36)*$J$10/$H$12) | I36: =$F$12+(C36*$J$10/$L$12) -> 1347.5556 | J36: =IF(D36="","",($J$11-$H$7+D36)*$J$10/$B$12) -> 884 | K36: =IF(E36="","",($J$11-$H$7+E36)*$J$10/$B$12) | L36: 6.7
B37: PBI2 | C37: 110 | D37: 3200 | F37: =$J$12+(C37*$J$10/$L$10) -> 6.552 | G37: =IF(D37="","",($J$11-$H$7+D37)*$J$10/$H$12) -> 5.304 | H37: =IF(E37="","",($J$11-$H$7+E37)*$J$10/$H$12) | I37: =$F$12+(C37*$J$10/$L$12) -> 1153.1111 | J37: =IF(D37="","",($J$11-$H$7+D37)*$J$10/$B$12) -> 884 | K37: =IF(E37="","",($J$11-$H$7+E37)*$J$10/$B$12) | L37: 6.7
B38: PBI3 | C38: 110 | D38: 3200 | F38: =$J$12+(C38*$J$10/$L$10) -> 6.552 | G38: =IF(D38="","",($J$11-$H$7+D38)*$J$10/$H$12) -> 5.304 | H38: =IF(E38="","",($J$11-$H$7+E38)*$J$10/$H$12) | I38: =$F$12+(C38*$J$10/$L$12) -> 1153.1111 | J38: =IF(D38="","",($J$11-$H$7+D38)*$J$10/$B$12) -> 884 | K38: =IF(E38="","",($J$11-$H$7+E38)*$J$10/$B$12) | L38: 6.7
B39: XPB2 | C39: 100 | D39: 3200 | F39: =$J$12+(C39*$J$10/$L$10) -> 6.352 | G39: =IF(D39="","",($J$11-$H$7+D39)*$J$10/$H$12) -> 5.304 | H39: =IF(E39="","",($J$11-$H$7+E39)*$J$10/$H$12) | I39: =$F$12+(C39*$J$10/$L$12) -> 1114.2222 | J39: =IF(D39="","",($J$11-$H$7+D39)*$J$10/$B$12) -> 884 | K39: =IF(E39="","",($J$11-$H$7+E39)*$J$10/$B$12) | L39: 6.7
A40: 萨凡纳 三区 | B40: BNA2 | C40: 130 | D40: 3700 | F40: =$J$12+(C40*$J$10/$L$10) -> 6.952 | G40: =IF(D40="","",($J$11-$H$7+D40)*$J$10/$H$12) -> 5.584 | H40: =IF(E40="","",($J$11-$H$7+E40)*$J$10/$H$12) | I40: =$F$12+(C40*$J$10/$L$12) -> 1230.8889 | J40: =IF(D40="","",($J$11-$H$7+D40)*$J$10/$B$12) -> 930.66667 | K40: =IF(E40="","",($J$11-$H$7+E40)*$J$10/$B$12) | L40: 7
B41: BNA6 | C41: 125 | D41: 3700 | F41: =$J$12+(C41*$J$10/$L$10) -> 6.852 | G41: =IF(D41="","",($J$11-$H$7+D41)*$J$10/$H$12) -> 5.584 | H41: =IF(E41="","",($J$11-$H$7+E41)*$J$10/$H$12) | I41: =$F$12+(C41*$J$10/$L$12) -> 1211.4444 | J41: =IF(D41="","",($J$11-$H$7+D41)*$J$10/$B$12) -> 930.66667 | K41: =IF(E41="","",($J$11-$H$7+E41)*$J$10/$B$12) | L41: 7
B42: CHA2 | C42: 110 | D42: 3700 | F42: =$J$12+(C42*$J$10/$L$10) -> 6.552 | G42: =IF(D42="","",($J$11-$H$7+D42)*$J$10/$H$12) -> 5.584 | H42: =IF(E42="","",($J$11-$H$7+E42)*$J$10/$H$12) | I42: =$F$12+(C42*$J$10/$L$12) -> 1153.1111 | J42: =IF(D42="","",($J$11-$H$7+D42)*$J$10/$B$12) -> 930.66667 | K42: =IF(E42="","",($J$11-$H$7+E42)*$J$10/$B$12) | L42: 7
B43: HSV1 | C43: 135 | D43: 3700 | F43: =$J$12+(C43*$J$10/$L$10) -> 7.052 | G43: =IF(D43="","",($J$11-$H$7+D43)*$J$10/$H$12) -> 5.584 | H43: =IF(E43="","",($J$11-$H$7+E43)*$J$10/$H$12) | I43: =$F$12+(C43*$J$10/$L$12) -> 1250.3333 | J43: =IF(D43="","",($J$11-$H$7+D43)*$J$10/$B$12) -> 930.66667 | K43: =IF(E43="","",($J$11-$H$7+E43)*$J$10/$B$12) | L43: 7
B44: HSV2 | C44: 135 | D44: 3700 | F44: =$J$12+(C44*$J$10/$L$10) -> 7.052 | G44: =IF(D44="","",($J$11-$H$7+D44)*$J$10/$H$12) -> 5.584 | H44: =IF(E44="","",($J$11-$H$7+E44)*$J$10/$H$12) | I44: =$F$12+(C44*$J$10/$L$12) -> 1250.3333 | J44: =IF(D44="","",($J$11-$H$7+D44)*$J$10/$B$12) -> 930.66667 | K44: =IF(E44="","",($J$11-$H$7+E44)*$J$10/$B$12) | L44: 7
B45: MEM1 | D45: 3700 | F45: =$J$12+(C45*$J$10/$L$10) -> 4.352 | G45: =IF(D45="","",($J$11-$H$7+D45)*$J$10/$H$12) -> 5.584 | H45: =IF(E45="","",($J$11-$H$7+E45)*$J$10/$H$12) | I45: =$F$12+(C45*$J$10/$L$12) -> 725.33333 | J45: =IF(D45="","",($J$11-$H$7+D45)*$J$10/$B$12) -> 930.66667 | K45: =IF(E45="","",($J$11-$H$7+E45)*$J$10/$B$12) | L45: 7
A46: 散货 | B46: WAL-ATL2 | C46: 125 | F46: =$J$12+(C46*$J$10/$L$10) -> 6.852 | G46: =IF(D46="","",($J$11-$H$7+D46)*$J$10/$H$12) | H46: =IF(E46="","",($J$11-$H$7+E46)*$J$10/$H$12) | I46: =$F$12+(C46*$J$10/$L$12) -> 1211.4444 | J46: =IF(D46="","",($J$11-$H$7+D46)*$J$10/$B$12) | K46: =IF(E46="","",($J$11-$H$7+E46)*$J$10/$B$12)
B47: WAL-ATL8 | F47: =$J$12+(C47*$J$10/$L$10) -> 4.352 | G47: =IF(D47="","",($J$11-$H$7+D47)*$J$10/$H$12) | H47: =IF(E47="","",($J$11-$H$7+E47)*$J$10/$H$12) | I47: =$F$12+(C47*$J$10/$L$12) -> 725.33333 | J47: =IF(D47="","",($J$11-$H$7+D47)*$J$10/$B$12) | K47: =IF(E47="","",($J$11-$H$7+E47)*$J$10/$B$12)
B48: WAL-MCO1 | F48: =$J$12+(C48*$J$10/$L$10) -> 4.352 | G48: =IF(D48="","",($J$11-$H$7+D48)*$J$10/$H$12) | H48: =IF(E48="","",($J$11-$H$7+E48)*$J$10/$H$12) | I48: =$F$12+(C48*$J$10/$L$12) -> 725.33333 | J48: =IF(D48="","",($J$11-$H$7+D48)*$J$10/$B$12) | K48: =IF(E48="","",($J$11-$H$7+E48)*$J$10/$B$12)
B49: WAL-MEM1s | F49: =$J$12+(C49*$J$10/$L$10) -> 4.352 | G49: =IF(D49="","",($J$11-$H$7+D49)*$J$10/$H$12) | H49: =IF(E49="","",($J$11-$H$7+E49)*$J$10/$H$12) | I49: =$F$12+(C49*$J$10/$L$12) -> 725.33333 | J49: =IF(D49="","",($J$11-$H$7+D49)*$J$10/$B$12) | K49: =IF(E49="","",($J$11-$H$7+E49)*$J$10/$B$12)

Sheet 纽约960
A1: 应付 | B1: 盐田——NY | F1: 费用类型 | G1: 币种 | H1: 单价 | I1: 数量 | J1: 备注 | K1: 统计
B2: 起运港 | C2: 拖车+报关 | F2: 装柜费 | G2: RMB | H2: 500 | I2: 1
F3: 拖车费 | G3: RMB | H3: 1950 | I3: 1
F4: 报关费 | G4: RMB | H4: 500 | I4: 0 | J4: 实报实销 | K4: 100/票
F5: 港杂费RMB部分 | G5: RMB | H5: 3500 | I5: 1
F6: 海运费（变动） | G6: USD | H6: 3850 | I6: 1
B7: 目的港 | C7: 提柜+拆柜 | F7: 提拆一口价 | G7: USD | H7: 1500 | I7: 1
C8: 清关+缴税 | F8: 清关费 | G8: USD | I8: 1
F9: 税金 | G9: USD | H9: 1300 | I9: 1 | L9: 每板KG
A10: 盐田——NY | B10: 人民币应付 | G10: RMB | H10: =SUM(H2:H5) -> 6450 | I10: 汇率 | J10: 7 | K10: =H10/J10 -> 921.42857 | L10: 350
A11: 报价：2025/03/16 | B11: 含税/CBM | G11: USD | H11: =SUM(H6:H9) -> 6650 | I11: 合计 | J11: =H11+K10 -> 7571.4286 | K11: =J11*J10 -> 53000 | L11: CBM
A12: CBM标准 | B12: 75 | E12: CBM计费标准 | F12: =K11/B12 -> 706.66667 | G12: KG标准 | H12: 12525 | I12: KG计费标准 | J12: =K11/H12 -> 4.2315369 | L12: 1.8
B13: 派送费 | C13: 美金/板 | D13: 组合一口价 | E13: 整柜一口价 | F13: 拆送KG含税 | G13: 组合KG | H13: 直送KG | I13: 拆送CBM含税 | J13: 组合CBM | K13: 直送CBM | L13: 直客报价101KG+
A14: 组合1 | B14: ABE8 | C14: 30 | D14: 2000 | E14: 1450 | F14: =$J$12+(C14*$J$10/$L$10) -> 4.8315369 | G14: =IF(D14="","",($J$11-$H$7+D14)*$J$10/$H$12) -> 4.510978 | H14: =IF(E14="","",($J$11-$H$7+E14)*$J$10/$H$12) -> 4.2035928 | I14: =$F$12+(C14*$J$10/$L$12) -> 823.33333 | J14: =IF(D14="","",($J$11-$H$7+D14)*$J$10/$B$12) -> 753.33333 | K14: =IF(E14="","",($J$11-$H$7+E14)*$J$10/$B$12) -> 702 | L14: 6
B15: ACY2 | C15: 30 | D15: 2000 | E15: 1550 | F15: =$J$12+(C15*$J$10/$L$10) -> 4.8315369 | G15: =IF(D15="","",($J$11-$H$7+D15)*$J$10/$H$12) -> 4.510978 | H15: =IF(E15="","",($J$11-$H$7+E15)*$J$10/$H$12) -> 4.259481 | I15: =$F$12+(C15*$J$10/$L$12) -> 823.33333 | J15: =IF(D15="","",($J$11-$H$7+D15)*$J$10/$B$12) -> 753.33333 | K15: =IF(E15="","",($J$11-$H$7+E15)*$J$10/$B$12) -> 711.33333 | L15: 6
B16: TEB6 | C16: 25 | D16: 2000 | E16: 1250 | F16: =$J$12+(C16*$J$10/$L$10) -> 4.7315369 | G16: =IF(D16="","",($J$11-$H$7+D16)*$J$10/$H$12) -> 4.510978 | H16: =IF(E16="","",($J$11-$H$7+E16)*$J$10/$H$12) -> 4.0918164 | I16: =$F$12+(C16*$J$10/$L$12) -> 803.88889 | J16: =IF(D16="","",($J$11-$H$7+D16)*$J$10/$B$12) -> 753.33333 | K16: =IF(E16="","",($J$11-$H$7+E16)*$J$10/$B$12) -> 683.33333 | L16: 6
B17: TEB9 | C17: 30 | D17: 2000 | E17: 1250 | F17: =$J$12+(C17*$J$10/$L$10) -> 4.8315369 | G17: =IF(D17="","",($J$11-$H$7+D17)*$J$10/$H$12) -> 4.510978 | H17: =IF(E17="","",($J$11-$H$7+E17)*$J$10/$H$12) -> 4.0918164 | I17: =$F$12+(C17*$J$10/$L$12) -> 823.33333 | J17: =IF(D17="","",($J$11-$H$7+D17)*$J$10/$B$12) -> 753.33333 | K17: =IF(E17="","",($J$11-$H$7+E17)*$J$10/$B$12) -> 683.33333 | L17: 6
B18: TTN2 | C18: 25 | D18: 2000 | F18: =$J$12+(C18*$J$10/$L$10) -> 4.7315369 | G18: =IF(D18="","",($J$11-$H$7+D18)*$J$10/$H$12) -> 4.510978 | H18: =IF(E18="","",($J$11-$H$7+E18)*$J$10/$H$12) | I18: =$F$12+(C18*$J$10/$L$12) -> 803.88889 | J18: =IF(D18="","",($J$11-$H$7+D18)*$J$10/$B$12) -> 753.33333 | K18: =IF(E18="","",($J$11-$H$7+E18)*$J$10/$B$12) | L18: 6
B19: TEB3 | C19: 35 | D19: 2000 | E19: 1550 | F19: =$J$12+(C19*$J$10/$L$10) -> 4.9315369 | G19: =IF(D19="","",($J$11-$H$7+D19)*$J$10/$H$12) -> 4.510978 | H19: =IF(E19="","",($J$11-$H$7+E19)*$J$10/$H$12) -> 4.259481 | I19: =$F$12+(C19*$J$10/$L$12) -> 842.77778 | J19: =IF(D19="","",($J$11-$H$7+D19)*$J$10/$B$12) -> 753.33333 | K19: =IF(E19="","",($J$11-$H$7+E19)*$J$10/$B$12) -> 711.33333 | L19: 6
B20: TEB4 | C20: 35 | D20: 2000 | E20: 1550 | F20: =$J$12+(C20*$J$10/$L$10) -> 4.9315369 | G20: =IF(D20="","",($J$11-$H$7+D20)*$J$10/$H$12) -> 4.510978 | H20: =IF(E20="","",($J$11-$H$7+E20)*$J$10/$H$12) -> 4.259481 | I20: =$F$12+(C20*$J$10/$L$12) -> 842.77778 | J20: =IF(D20="","",($J$11-$H$7+D20)*$J$10/$B$12) -> 753.33333 | K20: =IF(E20="","",($J$11-$H$7+E20)*$J$10/$B$12) -> 711.33333 | L20: 6
B21: XEW5 | D21: 2000 | F21: =$J$12+(C21*$J$10/$L$10) -> 4.2315369 | G21: =IF(D21="","",($J$11-$H$7+D21)*$J$10/$H$12) -> 4.510978 | H21: =IF(E21="","",($J$11-$H$7+E21)*$J$10/$H$12) | I21: =$F$12+(C21*$J$10/$L$12) -> 706.66667 | J21: =IF(D21="","",($J$11-$H$7+D21)*$J$10/$B$12) -> 753.33333 | K21: =IF(E21="","",($J$11-$H$7+E21)*$J$10/$B$12) | L21: 6
A22: 组合2 | B22: ABE3 | C22: 40 | D22: 2300 | E22: 1450 | F22: =$J$12+(C22*$J$10/$L$10) -> 5.0315369 | G22: =IF(D22="","",($J$11-$H$7+D22)*$J$10/$H$12) -> 4.6786427 | H22: =IF(E22="","",($J$11-$H$7+E22)*$J$10/$H$12) -> 4.2035928 | I22: =$F$12+(C22*$J$10/$L$12) -> 862.22222 | J22: =IF(D22="","",($J$11-$H$7+D22)*$J$10/$B$12) -> 781.33333 | K22: =IF(E22="","",($J$11-$H$7+E22)*$J$10/$B$12) -> 702 | L22: 6.2
B23: ABE4 | C23: 40 | D23: 2300 | E23: 1450 | F23: =$J$12+(C23*$J$10/$L$10) -> 5.0315369 | G23: =IF(D23="","",($J$11-$H$7+D23)*$J$10/$H$12) -> 4.6786427 | H23: =IF(E23="","",($J$11-$H$7+E23)*$J$10/$H$12) -> 4.2035928 | I23: =$F$12+(C23*$J$10/$L$12) -> 862.22222 | J23: =IF(D23="","",($J$11-$H$7+D23)*$J$10/$B$12) -> 781.33333 | K23: =IF(E23="","",($J$11-$H$7+E23)*$J$10/$B$12) -> 702 | L23: 6.2
B24: AVP1 | C24: 50 | D24: 2300 | E24: 2150 | F24: =$J$12+(C24*$J$10/$L$10) -> 5.2315369 | G24: =IF(D24="","",($J$11-$H$7+D24)*$J$10/$H$12) -> 4.6786427 | H24: =IF(E24="","",($J$11-$H$7+E24)*$J$10/$H$12) -> 4.5948104 | I24: =$F$12+(C24*$J$10/$L$12) -> 901.11111 | J24: =IF(D24="","",($J$11-$H$7+D24)*$J$10/$B$12) -> 781.33333 | K24: =IF(E24="","",($J$11-$H$7+E24)*$J$10/$B$12) -> 767.33333 | L24: 6.2
B25: AVP3 | C25: 50 | D25: 2300 | F25: =$J$12+(C25*$J$10/$L$10) -> 5.2315369 | G25: =IF(D25="","",($J$11-$H$7+D25)*$J$10/$H$12) -> 4.6786427 | H25: =IF(E25="","",($J$11-$H$7+E25)*$J$10/$H$12) | I25: =$F$12+(C25*$J$10/$L$12) -> 901.11111 | J25: =IF(D25="","",($J$11-$H$7+D25)*$J$10/$B$12) -> 781.33333 | K25: =IF(E25="","",($J$11-$H$7+E25)*$J$10/$B$12) | L25: 6.2
B26: AVP9 | C26: 50 | D26: 2300 | F26: =$J$12+(C26*$J$10/$L$10) -> 5.2315369 | G26: =IF(D26="","",($J$11-$H$7+D26)*$J$10/$H$12) -> 4.6786427 | H26: =IF(E26="","",($J$11-$H$7+E26)*$J$10/$H$12) | I26: =$F$12+(C26*$J$10/$L$12) -> 901.11111 | J26: =IF(D26="","",($J$11-$H$7+D26)*$J$10/$B$12) -> 781.33333 | K26: =IF(E26="","",($J$11-$H$7+E26)*$J$10/$B$12) | L26: 6.2
B27: WBW2 | C27: 50 | D27: 2300 | F27: =$J$12+(C27*$J$10/$L$10) -> 5.2315369 | G27: =IF(D27="","",($J$11-$H$7+D27)*$J$10/$H$12) -> 4.6786427 | H27: =IF(E27="","",($J$11-$H$7+E27)*$J$10/$H$12) | I27: =$F$12+(C27*$J$10/$L$12) -> 901.11111 | J27: =IF(D27="","",($J$11-$H$7+D27)*$J$10/$B$12) -> 781.33333 | K27: =IF(E27="","",($J$11-$H$7+E27)*$J$10/$B$12)
A28: 组合3 | B28: HIA1 | C28: 55 | D28: 2550 | F28: =$J$12+(C28*$J$10/$L$10) -> 5.3315369 | G28: =IF(D28="","",($J$11-$H$7+D28)*$J$10/$H$12) -> 4.8183633 | H28: =IF(E28="","",($J$11-$H$7+E28)*$J$10/$H$12) | I28: =$F$12+(C28*$J$10/$L$12) -> 920.55556 | J28: =IF(D28="","",($J$11-$H$7+D28)*$J$10/$B$12) -> 804.66667 | K28: =IF(E28="","",($J$11-$H$7+E28)*$J$10/$B$12) | L28: 6.3
B29: PHL4 | C29: 55 | D29: 2550 | E29: 2250 | F29: =$J$12+(C29*$J$10/$L$10) -> 5.3315369 | G29: =IF(D29="","",($J$11-$H$7+D29)*$J$10/$H$12) -> 4.8183633 | I29: =$F$12+(C29*$J$10/$L$12) -> 920.55556 | J29: =IF(D29="","",($J$11-$H$7+D29)*$J$10/$B$12) -> 804.66667 | L29: 6.3
B30: PHL5 | C30: 55 | D30: 2550 | E30: 2050 | F30: =$J$12+(C30*$J$10/$L$10) -> 5.3315369 | G30: =IF(D30="","",($J$11-$H$7+D30)*$J$10/$H$12) -> 4.8183633 | H30: =IF(E30="","",($J$11-$H$7+E30)*$J$10/$H$12) -> 4.5389222 | I30: =$F$12+(C30*$J$10/$L$12) -> 920.55556 | J30: =IF(D30="","",($J$11-$H$7+D30)*$J$10/$B$12) -> 804.66667 | K30: =IF(E30="","",($J$11-$H$7+E30)*$J$10/$B$12) -> 758 | L30: 6.3
B31: PHL6 | C31: 55 | D31: 2550 | E31: 2050 | F31: =$J$12+(C31*$J$10/$L$10) -> 5.3315369 | G31: =IF(D31="","",($J$11-$H$7+D31)*$J$10/$H$12) -> 4.8183633 | H31: =IF(E31="","",($J$11-$H$7+E31)*$J$10/$H$12) -> 4.5389222 | I31: =$F$12+(C31*$J$10/$L$12) -> 920.55556 | J31: =IF(D31="","",($J$11-$H$7+D31)*$J$10/$B$12) -> 804.66667 | K31: =IF(E31="","",($J$11-$H$7+E31)*$J$10/$B$12) -> 758 | L31: 6.3
B32: MDT1 | C32: 55 | D32: 2550 | E32: 2000 | F32: =$J$12+(C32*$J$10/$L$10) -> 5.3315369 | G32: =IF(D32="","",($J$11-$H$7+D32)*$J$10/$H$12) -> 4.8183633 | H32: =IF(E32="","",($J$11-$H$7+E32)*$J$10/$H$12) -> 4.510978 | I32: =$F$12+(C32*$J$10/$L$12) -> 920.55556 | J32: =IF(D32="","",($J$11-$H$7+D32)*$J$10/$B$12) -> 804.66667 | K32: =IF(E32="","",($J$11-$H$7+E32)*$J$10/$B$12) -> 753.33333 | L32: 6.3
B33: MDT4 | C33: 55 | D33: 2550 | F33: =$J$12+(C33*$J$10/$L$10) -> 5.3315369 | G33: =IF(D33="","",($J$11-$H$7+D33)*$J$10/$H$12) -> 4.8183633 | I33: =$F$12+(C33*$J$10/$L$12) -> 920.55556 | J33: =IF(D33="","",($J$11-$H$7+D33)*$J$10/$B$12) -> 804.66667 | L33: 6.3
B34: PIT2 | C34: 90 | D34: 2550 | F34: =$J$12+(C34*$J$10/$L$10) -> 6.0315369 | G34: =IF(D34="","",($J$11-$H$7+D34)*$J$10/$H$12) -> 4.8183633 | H34: =IF(E34="","",($J$11-$H$7+E34)*$J$10/$H$12) | I34: =$F$12+(C34*$J$10/$L$12) -> 1056.6667 | J34: =IF(D34="","",($J$11-$H$7+D34)*$J$10/$B$12) -> 804.66667 | K34: =IF(E34="","",($J$11-$H$7+E34)*$J$10/$B$12) | L34: 6.3
B35: LBE1 | C35: 90 | D35: 2550 | F35: =$J$12+(C35*$J$10/$L$10) -> 6.0315369 | G35: =IF(D35="","",($J$11-$H$7+D35)*$J$10/$H$12) -> 4.8183633 | H35: =IF(E35="","",($J$11-$H$7+E35)*$J$10/$H$12) | I35: =$F$12+(C35*$J$10/$L$12) -> 1056.6667 | J35: =IF(D35="","",($J$11-$H$7+D35)*$J$10/$B$12) -> 804.66667 | K35: =IF(E35="","",($J$11-$H$7+E35)*$J$10/$B$12) | L35: 6.3
A36: 组合4 | B36: IUSL | C36: 55 | D36: 2900 | F36: =$J$12+(C36*$J$10/$L$10) -> 5.3315369 | G36: =IF(D36="","",($J$11-$H$7+D36)*$J$10/$H$12) -> 5.0139721 | H36: =IF(E36="","",($J$11-$H$7+E36)*$J$10/$H$12) | I36: =$F$12+(C36*$J$10/$L$12) -> 920.55556 | J36: =IF(D36="","",($J$11-$H$7+D36)*$J$10/$B$12) -> 837.33333 | L36: 6.5
B37: MDT2 | C37: 55 | D37: 2900 | F37: =$J$12+(C37*$J$10/$L$10) -> 5.3315369 | G37: =IF(D37="","",($J$11-$H$7+D37)*$J$10/$H$12) -> 5.0139721 | H37: =IF(E37="","",($J$11-$H$7+E37)*$J$10/$H$12) | I37: =$F$12+(C37*$J$10/$L$12) -> 920.55556 | J37: =IF(D37="","",($J$11-$H$7+D37)*$J$10/$B$12) -> 837.33333 | K37: =IF(E37="","",($J$11-$H$7+E37)*$J$10/$B$12) | L37: 6.5
B38: ILG1 | C38: 55 | D38: 2900 | E38: 2050 | F38: =$J$12+(C38*$J$10/$L$10) -> 5.3315369 | G38: =IF(D38="","",($J$11-$H$7+D38)*$J$10/$H$12) -> 5.0139721 | H38: =IF(E38="","",($J$11-$H$7+E38)*$J$10/$H$12) -> 4.5389222 | I38: =$F$12+(C38*$J$10/$L$12) -> 920.55556 | J38: =IF(D38="","",($J$11-$H$7+D38)*$J$10/$B$12) -> 837.33333 | K38: =IF(E38="","",($J$11-$H$7+E38)*$J$10/$B$12) -> 758 | L38: 6.5
B39: DCA6 | C39: 55 | D39: 2900 | F39: =$J$12+(C39*$J$10/$L$10) -> 5.3315369 | G39: =IF(D39="","",($J$11-$H$7+D39)*$J$10/$H$12) -> 5.0139721 | H39: =IF(E39="","",($J$11-$H$7+E39)*$J$10/$H$12) | I39: =$F$12+(C39*$J$10/$L$12) -> 920.55556 | J39: =IF(D39="","",($J$11-$H$7+D39)*$J$10/$B$12) -> 837.33333 | K39: =IF(E39="","",($J$11-$H$7+E39)*$J$10/$B$12) | L39: 6.5
B40: BWI1 | C40: 75 | D40: 2900 | F40: =$J$12+(C40*$J$10/$L$10) -> 5.7315369 | G40: =IF(D40="","",($J$11-$H$7+D40)*$J$10/$H$12) -> 5.0139721 | H40: =IF(E40="","",($J$11-$H$7+E40)*$J$10/$H$12) | I40: =$F$12+(C40*$J$10/$L$12) -> 998.33333 | J40: =IF(D40="","",($J$11-$H$7+D40)*$J$10/$B$12) -> 837.33333 | K40: =IF(E40="","",($J$11-$H$7+E40)*$J$10/$B$12) | L40: 6.5
B41: HGR2 | C41: 70 | D41: 2900 | F41: =$J$12+(C41*$J$10/$L$10) -> 5.6315369 | G41: =IF(D41="","",($J$11-$H$7+D41)*$J$10/$H$12) -> 5.0139721 | H41: =IF(E41="","",($J$11-$H$7+E41)*$J$10/$H$12) | I41: =$F$12+(C41*$J$10/$L$12) -> 978.88889 | J41: =IF(D41="","",($J$11-$H$7+D41)*$J$10/$B$12) -> 837.33333 | K41: =IF(E41="","",($J$11-$H$7+E41)*$J$10/$B$12) | L41: 6.5
B42: XLX1 | C42: 70 | D42: 2900 | F42: =$J$12+(C42*$J$10/$L$10) -> 5.6315369 | G42: =IF(D42="","",($J$11-$H$7+D42)*$J$10/$H$12) -> 5.0139721 | H42: =IF(E42="","",($J$11-$H$7+E42)*$J$10/$H$12) | I42: =$F$12+(C42*$J$10/$L$12) -> 978.88889 | J42: =IF(D42="","",($J$11-$H$7+D42)*$J$10/$B$12) -> 837.33333 | K42: =IF(E42="","",($J$11-$H$7+E42)*$J$10/$B$12) | L42: 6.5
B43: HGR6 | C43: 70 | D43: 2900 | F43: =$J$12+(C43*$J$10/$L$10) -> 5.6315369 | G43: =IF(D43="","",($J$11-$H$7+D43)*$J$10/$H$12) -> 5.0139721 | H43: =IF(E43="","",($J$11-$H$7+E43)*$J$10/$H$12) | I43: =$F$12+(C43*$J$10/$L$12) -> 978.88889 | J43: =IF(D43="","",($J$11-$H$7+D43)*$J$10/$B$12) -> 837.33333 | K43: =IF(E43="","",($J$11-$H$7+E43)*$J$10/$B$12) | L43: 6.5
A44: 组合5 | B44: ALB1 | C44: 60 | D44: 2650 | E44: 1750 | F44: =$J$12+(C44*$J$10/$L$10) -> 5.4315369 | G44: =IF(D44="","",($J$11-$H$7+D44)*$J$10/$H$12) -> 4.8742515 | H44: =IF(E44="","",($J$11-$H$7+E44)*$J$10/$H$12) -> 4.3712575 | I44: =$F$12+(C44*$J$10/$L$12) -> 940 | J44: =IF(D44="","",($J$11-$H$7+D44)*$J$10/$B$12) -> 814 | K44: =IF(E44="","",($J$11-$H$7+E44)*$J$10/$B$12) -> 730 | L44: 6.3
B45: SWF1 | C45: 60 | D45: 2650 | E45: 1750 | F45: =$J$12+(C45*$J$10/$L$10) -> 5.4315369 | G45: =IF(D45="","",($J$11-$H$7+D45)*$J$10/$H$12) -> 4.8742515 | H45: =IF(E45="","",($J$11-$H$7+E45)*$J$10/$H$12) -> 4.3712575 | I45: =$F$12+(C45*$J$10/$L$12) -> 940 | J45: =IF(D45="","",($J$11-$H$7+D45)*$J$10/$B$12) -> 814 | K45: =IF(E45="","",($J$11-$H$7+E45)*$J$10/$B$12) -> 730 | L45: 6.3
B46: SWF2 | C46: 60 | D46: 2650 | E46: 1750 | F46: =$J$12+(C46*$J$10/$L$10) -> 5.4315369 | G46: =IF(D46="","",($J$11-$H$7+D46)*$J$10/$H$12) -> 4.8742515 | H46: =IF(E46="","",($J$11-$H$7+E46)*$J$10/$H$12) -> 4.3712575 | I46: =$F$12+(C46*$J$10/$L$12) -> 940 | J46: =IF(D46="","",($J$11-$H$7+D46)*$J$10/$B$12) -> 814 | K46: =IF(E46="","",($J$11-$H$7+E46)*$J$10/$B$12) -> 730 | L46: 6.3
A47: 组合6 | B47: BDL6 | C47: 80 | D47: 3300 | F47: =$J$12+(C47*$J$10/$L$10) -> 5.8315369 | G47: =IF(D47="","",($J$11-$H$7+D47)*$J$10/$H$12) -> 5.237525 | H47: =IF(E47="","",($J$11-$H$7+E47)*$J$10/$H$12) | I47: =$F$12+(C47*$J$10/$L$12) -> 1017.7778 | J47: =IF(D47="","",($J$11-$H$7+D47)*$J$10/$B$12) -> 874.66667 | K47: =IF(E47="","",($J$11-$H$7+E47)*$J$10/$B$12) | L47: 6.7
B48: BOS7 | C48: 80 | D48: 3300 | F48: =$J$12+(C48*$J$10/$L$10) -> 5.8315369 | G48: =IF(D48="","",($J$11-$H$7+D48)*$J$10/$H$12) -> 5.237525 | H48: =IF(E48="","",($J$11-$H$7+E48)*$J$10/$H$12) | I48: =$F$12+(C48*$J$10/$L$12) -> 1017.7778 | J48: =IF(D48="","",($J$11-$H$7+D48)*$J$10/$B$12) -> 874.66667 | K48: =IF(E48="","",($J$11-$H$7+E48)*$J$10/$B$12) | L48: 6.7
A49: 组合7 | B49: BWI4 | C49: 75 | D49: 3300 | F49: =$J$12+(C49*$J$10/$L$10) -> 5.7315369 | G49: =IF(D49="","",($J$11-$H$7+D49)*$J$10/$H$12) -> 5.237525 | H49: =IF(E49="","",($J$11-$H$7+E49)*$J$10/$H$12) | I49: =$F$12+(C49*$J$10/$L$12) -> 998.33333 | J49: =IF(D49="","",($J$11-$H$7+D49)*$J$10/$B$12) -> 874.66667 | K49: =IF(E49="","",($J$11-$H$7+E49)*$J$10/$B$12) | L49: 6.7
B50: RMN3 | C50: 75 | D50: 3300 | F50: =$J$12+(C50*$J$10/$L$10) -> 5.7315369 | G50: =IF(D50="","",($J$11-$H$7+D50)*$J$10/$H$12) -> 5.237525 | H50: =IF(E50="","",($J$11-$H$7+E50)*$J$10/$H$12) | I50: =$F$12+(C50*$J$10/$L$12) -> 998.33333 | J50: =IF(D50="","",($J$11-$H$7+D50)*$J$10/$B$12) -> 874.66667 | K50: =IF(E50="","",($J$11-$H$7+E50)*$J$10/$B$12) | L50: 6.7
B51: CHO1 | C51: 90 | D51: 3300 | F51: =$J$12+(C51*$J$10/$L$10) -> 6.0315369 | G51: =IF(D51="","",($J$11-$H$7+D51)*$J$10/$H$12) -> 5.237525 | H51: =IF(E51="","",($J$11-$H$7+E51)*$J$10/$H$12) | I51: =$F$12+(C51*$J$10/$L$12) -> 1056.6667 | J51: =IF(D51="","",($J$11-$H$7+D51)*$J$10/$B$12) -> 874.66667 | K51: =IF(E51="","",($J$11-$H$7+E51)*$J$10/$B$12) | L51: 6.7
B52: ORF2 | C52: 90 | D52: 3300 | F52: =$J$12+(C52*$J$10/$L$10) -> 6.0315369 | G52: =IF(D52="","",($J$11-$H$7+D52)*$J$10/$H$12) -> 5.237525 | H52: =IF(E52="","",($J$11-$H$7+E52)*$J$10/$H$12) | I52: =$F$12+(C52*$J$10/$L$12) -> 1056.6667 | J52: =IF(D52="","",($J$11-$H$7+D52)*$J$10/$B$12) -> 874.66667 | K52: =IF(E52="","",($J$11-$H$7+E52)*$J$10/$B$12) | L52: 6.7
B53: RIC1 | C53: 90 | D53: 3300 | F53: =$J$12+(C53*$J$10/$L$10) -> 6.0315369 | G53: =IF(D53="","",($J$11-$H$7+D53)*$J$10/$H$12) -> 5.237525 | H53: =IF(E53="","",($J$11-$H$7+E53)*$J$10/$H$12) | I53: =$F$12+(C53*$J$10/$L$12) -> 1056.6667 | J53: =IF(D53="","",($J$11-$H$7+D53)*$J$10/$B$12) -> 874.66667 | K53: =IF(E53="","",($J$11-$H$7+E53)*$J$10/$B$12) | L53: 6.7
B54: RIC3 | C54: 90 | D54: 3300 | F54: =$J$12+(C54*$J$10/$L$10) -> 6.0315369 | G54: =IF(D54="","",($J$11-$H$7+D54)*$J$10/$H$12) -> 5.237525 | H54: =IF(E54="","",($J$11-$H$7+E54)*$J$10/$H$12) | I54: =$F$12+(C54*$J$10/$L$12) -> 1056.6667 | J54: =IF(D54="","",($J$11-$H$7+D54)*$J$10/$B$12) -> 874.66667 | K54: =IF(E54="","",($J$11-$H$7+E54)*$J$10/$B$12) | L54: 6.7
B55: XRI3 | C55: 90 | D55: 3300 | F55: =$J$12+(C55*$J$10/$L$10) -> 6.0315369 | G55: =IF(D55="","",($J$11-$H$7+D55)*$J$10/$H$12) -> 5.237525 | H55: =IF(E55="","",($J$11-$H$7+E55)*$J$10/$H$12) | I55: =$F$12+(C55*$J$10/$L$12) -> 1056.6667 | J55: =IF(D55="","",($J$11-$H$7+D55)*$J$10/$B$12) -> 874.66667 | K55: =IF(E55="","",($J$11-$H$7+E55)*$J$10/$B$12) | L55: 6.7
