Workbook

Sheet 报价主页
A2: 渠道名称 | B2: 渠道代码 | C2: 进入价格 | D2: 渠道优势说明 | E2: 最快提取/送仓时间 | F2: 备注
A3: 国际快递 | B3: US-GZ | C3: 点击进入 | D3: 大陆自主账号，自主打单，自主发货，一手操作 | E3: 当天提取 | F3: 自主账号
A4: 美国空运240 | B4: USMAF | C4: 点击进入 | D4: 大陆优质航班，时效稳定，整板拆派 | E4: 5-10个自然日提取 | F4: 每周航班
A5: 美森360 | B5: USMS360 | C5: 点击进入 | D5: 飞点旗舰产品，美森CLX服务，360小时延误赔付 | E5: 12-15个自然日提取 | F5: 美线最快方案
A6: 美森432 | B6: USMS432 | C6: 点击进入 | D6: 飞点尖端产品，美森MAX快航服务，对标市场限时达，432小时延误赔付 | E6: 13-17个自然日提取 | F6: 快船首选方案
A7: EX456 | B7: US456 | C7: 点击进入 | D7: ZIM/合德/CMA快提服务，目的港专属通道优先提柜，时效比肩美森MAX，456小时延误赔付 | E7: 14-18个自然日提取 | F7: 华东华南美线优质服务
A8: 快船600 | B8: USOA600 | C8: 点击进入 | D8: COSCO/OOCL/EMC保舱服务，提供甩柜、600小时时效延误双重理赔服务 | E8: 20-25个自然日送仓 | F8: 美西保舱服务,极致性价比
A9: 玩具普船FBA专线 | B9: USWJZX | C9: 点击进入 | D9: 玩具卖家备货性价比首选 | E9: 22-32个自然日 | F9: 玩具产品性价比首选方案
A10: 奥克兰744 | B10: US744 | C10: 点击进入 | D10: 奥克兰低成本之王，开船744小时提取 | E10: 26-34个自然日 | F10: 奥克兰低成本方案
A11: 洛杉矶768 | B11: USW768 | C11: 点击进入 | D11: 美西低成本之王，开船768小时送仓 | E11: 24-32个自然日送仓 | F11: 美西低成本方案
A12: 西雅图788 | B12: US788 | C12: 点击进入 | D12: 美西低成本之王，西雅图港口直提，开船788小时送仓 | E12: 28-37个自然日 | F12: 美西低成本方案
A13: 芝加哥840 | B13: US840 | C13: 点击进入 | D13: 芝加哥仓点性价比之王，LB港口卸船后优先上火车中转芝加哥，开船840小时送仓 | E13: 30-35个自然日 | F13: 美中低成本方案
... A19: 海运快递派 | B19: USKD | C19: 点击进入 | D19: 快递派专线渠道 | E19: 12-15自然日提取 | F19: 最快12-15自然日提取
A20: 报价表有效期：2026/1/19起
A21: 发货前请查看注意事项！
A22: 收货流程：通过我司系统下单→贴外箱唛→群上通知收货→核对出货数据→出货后不接受异议【为了正常转运，请及时支付已出账单运费】
A23: 我司自助下单系统：http://gzfdgy.nextsls.com/wos
A24: 飞点官网：https://freedomscm.com/
A25: 公司总部地址：广州市白云区云城南四路239号云图汇1栋505室飞点跨境供应链（商务接待，不收货） 深圳办公室：深圳市龙岗区双子塔东塔45层4503C号飞点跨境供应链（商务接待，不收货） 佛山办公室：佛山市南海区桂城街道招商置地中心1座1020号飞点跨境供应链（商务接待，不收货） 中山办公室：中山市东区博爱路28号远洋广场2幢1605号飞点跨境供应链（商务接待，不收货） 汕头办公室：汕头市澄海区下窖华新路西二巷1号二楼飞点跨境供应链（商务接待，不收货）
A26: 广州仓：广州市花都区花东镇启源大道6号5栋一楼整层（飞点跨境供应链） 金华仓：浙江省金华市金东区金义综合保税区S2仓C区飞点跨境供应链（园区入口：广顺南路与集贤路交汇处） 澄海仓：汕头市澄海区金鸿公路宝奥城内1-117~132号门(飞点跨境供应链) 东莞仓：广东省东莞市凤观路42号孔雀源物流园D栋（飞点跨境供应链） 中山仓：中山市火炬开发区兴业路27号金辉工业园区8号仓（飞点跨境供应链）

Sheet 海运船期表
A2: 渠道 | B2: 船司 | C2: 航线 | D2: 出发港 | E2: 目的港 | F2: 截单时间 | I2: 预计 开船时间 | J2: 预计 到港时间 | K2: 航程 (自然日） | L2: 最快提取/送仓时间 （开船后第二天算起）
F3: 珠三角 | G3: 汕头 | H3: 义乌
A4: 美森360 | B4: MATSON | C4: CLX | D4: 上海港 | E4: 长滩港 | F4: 46046 | G4: 46046 | H4: 46047 | I4: 46050 | J4: 46061 | K4: 11 | L4: 46063
A5: 美森432 | B5: MATSON | C5: MAX | D5: 上海港 | E5: 长滩港 | F5: 46047 | G5: 46047 | H5: 46048 | I5: 46051 | J5: 46062 | K5: 11 | L5: 46064
A6: EX456 | B6: ZIM/HEDE | C6: ZEX/2601E | D6: 盐田港/南沙港 | E6: 洛杉矶港 | F6: 46047 | G6: 46046 | H6: 46046 | I6: 46050 | J6: 46064 | K6: 14 | L6: 46067
A7: 快船600 | B7: COSCO | C7: SEA/SEA3 | D7: 盐田港 | E7: 长滩港 | F7: 46045 | G7: 46044 | H7: 46044 | I7: 46051 | J7: 46068 | K7: 17 | L7: 46074
B8: COSCO | C8: SEA | D8: 南沙港 | E8: 长滩港 | F8: 46047 | G8: 46046 | H8: 46046 | I8: 46056 | J8: 46074 | K8: 18 | L8: 46081
B9: COSCO | C9: AAC/AAC2 | D9: 宁波港 | E9: 长滩港 | F9: 46046 | G9: 46046 | H9: 46047 | I9: 46056 | J9: 46070 | K9: 14 | L9: 46077
A10: TY720 | B10: COSCO | C10: SEA/SEA3 | D10: 盐田港 | E10: 洛杉矶港 | F10: 46045 | G10: 46044 | H10: 46044 | I10: 46051 | J10: 46068 | K10: 17 | L10: 46075
B11: COSCO | C11: AAC/AAC2 | D11: 宁波港 | E11: 洛杉矶港 | F11: 46046 | G11: 46046 | H11: 46047 | I11: 46056 | J11: 46070 | K11: 14 | L11: 46077
A12: 奥克兰744 | B12: EMC | C12: AAS3 | D12: 盐田港 | E12: 奥克兰港 | F12: 46047 | G12: 46046 | H12: 46046 | I12: 46062 | J12: 46081 | K12: 19 | L12: 46088
B13: EMC | C13: AAC2 | D13: 宁波港 | E13: 奥克兰港 | F13: 46046 | G13: 46046 | H13: 46047 | I13: 46056 | J13: 46079 | K13: 23 | L13: 46086
A14: 洛杉矶768 | B14: COSCO/YML | C14: SEA/PS7 | D14: 南沙港 | E14: 长滩港 | F14: 46047 | G14: 46046 | H14: 46046 | I14: 46063 | J14: 46080 | K14: 17 | L14: 46087
B15: COSCO/YML | C15: SEA/PS3 | D15: 盐田港 | E15: 长滩港 | F15: 46047 | G15: 46046 | H15: 46046 | I15: 46058 | J15: 46074 | K15: 16 | L15: 46081
B16: COSCO/YML | C16: AAC/AAC4/PS5 | D16: 宁波港 | E16: 长滩港 | F16: 46046 | G16: 46046 | H16: 46047 | I16: 46063 | J16: 46077 | K16: 14 | L16: 46084
A17: 西雅图788 | B17: COSCO | C17: MPNM | D17: 盐田港 | E17: 西雅图港 | F17: 46047 | G17: 46046 | H17: 46046 | I17: 46069 | J17: 46097 | K17: 28 | L17: 46104
B18: COSCO | C18: MPNM | D18: 宁波港 | E18: 西雅图港 | F18: 46046 | G18: 46046 | H18: 46047 | I18: 46074 | J18: 46097 | K18: 23 | L18: 46104
A19: 芝加哥840 | B19: COSCO | C19: SEA/SEA3 | D19: 盐田港 | E19: 芝加哥 | F19: 46046 | G19: 46045 | H19: 46045 | I19: 46056 | J19: 46085 | K19: 29 | L19: 46092
B20: COSCO/EMC | C20: AAC2 | D20: 宁波港 | E20: 芝加哥 | F20: 46045 | G20: 46045 | H20: 46046 | I20: 46056 | J20: 46084 | K20: 28 | L20: 46091
A21: 休斯顿866 | B21: COSCO | C21: GME | D21: 盐田港 | E21: 休斯顿港 | F21: 46047 | G21: 46046 | H21: 46046 | I21: 46055 | J21: 46080 | K21: 25 | L21: 46087
B22: COSCO | C22: GME | D22: 宁波港 | E22: 休斯顿港 | F22: 46046 | G22: 46046 | H22: 46047 | I22: 46057 | J22: 46087 | K22: 30 | L22: 46094
A23: 萨凡纳888 | B23: COSCO/EMC | C23: AWE3/AWE4 | D23: 盐田港 | E23: 萨凡纳港 | F23: 46047 | G23: 46046 | H23: 46046 | I23: 46055 | J23: 46086 | K23: 31 | L23: 46093
B24: COSCO/EMC | C24: AWE2/AWE1 | D24: 宁波港 | E24: 萨凡纳港 | F24: 46046 | G24: 46046 | H24: 46047 | I24: 46058 | J24: 46087 | K24: 29 | L24: 46094
A25: 纽约960 | B25: COSCO/EMC | C25: AWE3/AWE4 | D25: 盐田港 | E25: 纽约港 | F25: 46047 | G25: 46046 | H25: 46046 | I25: 46054 | J25: 46087 | K25: 33 | L25: 46094
B26: COSCO/EMC | C26: AWE2/AWE1 | D26: 宁波港 | E26: 纽约港 | F26: 46046 | G26: 46046 | H26: 46047 | I26: 46065 | J26: 46096 | K26: 31 | L26: 46103
A27: 自主装柜 | 海运市场优质后端 | 信誉清关 | 快捷海运转运派送 船期来自船司官网，最终船司可能会有调整，包括但不限于出现延期或者空班等情况，最终时效以实际开船时间为准 本表最终解释权归飞点供应链所有
A28: 用 心 承 载 每 一 份 托 付

Sheet 注意事项
B2: 发货前须知
B3: 如确认在我司发货，即认可我司条款
B4: 为了准确快捷入库，发货前尽量配合贴好入仓标签/FBA标签/SKU标签等，因未贴标签或未及时告知导致仓库未能及时入库延误船期的我司概不负责！国内贴标费1元/张
B5: 国内段运输发票与报关费发票所示价格均不含税，如需开具发票，请提前跟我司客服咨询税点信息。
B6: 自2025年5月12日起 符合美国清关第232条款的钢铁制品、铝制品关税附加费加收0.5元/KG；
B7: 1、所有货物，内包装，及外包装必须有产地标识“MADE IN CHINA”否则我司拒收，软包装如产品破损，或丢失不予理赔
B8: 2、有申报不符、带电、带磁、带电机产品，违禁品，敏感品，未向我司如实申报，瞒报，少报，导致整批货物延误， 此情况极其恶劣，此类货物未申报/申报不符视为冲货，我司将追究其责任，并罚款5000RMB以上。
B9: 3、出货后若有拦截件情况，免仓期7天，超免仓期后未操作需要预收一个月仓储费，若超一个月继续存仓则需要继续再预收下一个月仓储费，以此类推。仓储费：30天内：1美金/方/天；30天-60天内：2美金/天/方；60天-90天3美金/方/天，90天以上：5美金/方/天，不足1方按1方计算。
B10: 索赔流程
B11: 一、索赔标准（签订合同）
B12: 货物在国外（境外）未提取派送前和货物提取派送后丢失、短少、污染、损坏的赔偿方案，赔偿标准： 1）丢件赔偿：海运，海外仓，未提取上网经核实丢件，按照采购价值进行赔偿，赔偿最高为3倍运费且不退运费。 2）空派未提取上网经核实丢件，按照采购价值进行赔偿，赔偿最高为1.5倍运费且不退运费。 3）空派、海派已上网提取丢件，按采购价值赔偿最高不超过100美金/票。（非整箱丢失，内装物品短少，不予赔偿。） 4）头程国际快递丢件赔偿，可协助向快递官方索赔，按官方赔偿金额赔偿。 5）、高货值产品，如客户另外要求亦可自购保险,请发货前仔细阅读,否则视为同意此规定.
B13: 二、索赔标准（未签订合同） 赔偿方案:（选择此渠道发货表示默认我司的赔偿标准） 1）、在国际运输过程中如货物丢失或者扣关（如因侵权问题，我司不承担任何责任并且保留追究发件人因此带来对我司的损失的赔偿）按海运RMB20/KG赔偿，空运RMB20/KG赔偿，不退运费. 2）、提取后丢失或其他问题，协助跟服务商申请索赔，不承诺索赔成功。索赔受理期限为自入库起 30 个自然日内，逾期不予受理。按申报价值赔偿(最高不超（100USD/票);入亚马逊仓的货物网上显示未签收的需提供后台数据方可开查。 3）、同一航次一票货部份提取,剩下部份超过30个工作日未提取可直接申请赔偿.如遇自然灾害以及不可抗因素，本公司将不做任何赔偿！ 如客户另外要求亦可自购保险,请发货前仔细阅读,否则视为同意此规定. 4）、一票多件的货物只要有其中部分有UPS/FEDEX提取信息,其他子单未更新的都属于UPS/FEDEX更新取件问题，不计入提取延误赔偿。 5）、高货值产品，如客户另外要求亦可自购保险,请发货前仔细阅读,否则视为同意此规定.
... B87: 1、珠三角地区：距离入库仓库地址的距离对应的收货重量--30公里-200kg起、50公里-300kg起、70公里-400kg起、100公里500kg起。 2、华东及汕头仓库单询。 3、未达到标准可自行送货或分摊收货费用。

Sheet 国际快递
A2: 美国快递
A3: UPS包税
C4: 珠三角交货价 | F4: 汕头交货价 | I4: 义乌交货价
A5: 国家地区 | B5: 渠道 | C5: 实重23kg+ | D5: 47-72 kg | E5: 73-99 kg | F5: 实重23kg+ | G5: 47-72 kg | H5: 73-99 kg | I5: 实重23kg+ | J5: 47-72 kg | K5: 73-99 kg | L5: 操作要求 | M5: 提取时效 | N5: 备注 | O5: 计重方式
A6: 美国全境 （偏远地区另计） | B6: 大陆UPS红单特快/5000 | C6: 70 | D6: 69.5 | E6: 69 | F6: 70.5 | G6: 70 | H6: 69.5 | I6: 71 | J6: 70.5 | K6: 70 | L6: 单箱8KG起 单箱计费 操作费150元/票 | M6: 特快服务不排仓 不限量 | N6: 私人地址35元/件 带电产品、偏远地区单询 | O6: 体积重/5000，单箱计重
A7: 美国全境 （偏远地区另计） | B7: 大陆UPS红单/5000 | C7: 61 | D7: 60.5 | E7: 60 | F7: 61.5 | G7: 61 | H7: 60.5 | I7: 62 | J7: 61.5 | K7: 61 | M7: 不排仓 不限量
A8: 美国全境 （偏远地区另计） | B8: 香港UPS红单/5000 | C8: 63 | D8: 62.5 | E8: 62 | F8: 64 | G8: 63.5 | H8: 63 | I8: 64 | J8: 63.5 | K8: 63 | M8: 不排仓 不限量 | N8: 私人地址35元/件 偏远地区单询
A9: DHL
A10: 国家地区 | B10: 渠道 | C10: 实重31kg+ | D10: 47-72 kg | E10: 73-99 kg | F10: 实重31kg+ | G10: 47-72 kg | H10: 73-99 kg | I10: 实重31kg+ | J10: 47-72 kg | K10: 73-99 kg | L10: 操作要求 | M10: 提取时效 | N10: 备注 | O10: 计重方式
A11: 美国全境 （偏远地区另计） | B11: 大陆DHL/5000 | C11: * | D11: * | E11: * | F11: * | G11: * | H11: * | I11: * | J11: * | K11: * | L11: 单箱8KG起 单箱计费 | M11: 不排仓 不限量 | N11: 仅限普货和FBA地址 私人地址35元/件 偏远地区单询 | O11: 体积重/5000，单箱计重
A12: 美国全境 （偏远地区另计） | B12: 香港DHL/5000 | C12: * | D12: * | E12: * | F12: * | G12: * | H12: * | I12: * | J12: * | K12: * | N12: 仅限普货和FBA地址 私人地址35元/件 带电产品、偏远地区单询
A13: 自主渠道，自主打单，当天出单号 （已含旺季附加费、燃油、关税）（带电产品单询）
A14: 附加费及要求
A15: UPS代理发货申明：提取后官方时效延误，产品清关问题，产生关税及其它附加费用由客户承担。
A16: 特别提醒：汕头、义乌交货价格以货物实际到广州仓时间报价表价格为准。
A17: 1、单箱重量不得超过24KG，超过24KG需加收超重费，单询
A18: 2、单箱计重，DHL渠道以0.5为一个进位数，如21.23KG，计算为21.5KG；UPS渠道以1为一个进位数，如21.23KG，计算为22KG。
A19: 3、整票以1为一个计费数.整票如50.3，UPS计算为51KG
A20: 4、单箱最低计费重8KG 超过单边120CM需超长费，单询
A21: 5、单票超5个品名以上+30RMB/个
A22: 6、超大件可单询！
A23: 国内贴标费 | G23: 1元/张 | J23: 为了准确快捷入库，请尽量配合贴好入仓标签/FBA标签/SKU标签等，因未贴标签或未及时告知导致仓库未能及时入库延误船期的我司概不负责
A24: 注： 为了您的货物安全顺利到达目的地，大陆渠道只接普货，坚决不收牌子货、违禁品；带电带磁、请走香港渠道，违者扣货，罚款5000元，由于货物问题，产生一切费用由客户承担！
A25: 注意事项：提取后，丢失，损坏或延误，我司只负责协助申请赔偿，具体赔偿方案与金额以UPS官方为准！

Sheet 美国空运240
A2: 美国空运240
A3: 快递派(大陆航班）
C4: 珠三角交货价 | G4: 汕头交货价 | K4: 义乌交货价
A5: 邮编开头 重量段 | C5: 12KG+ | D5: 21KG+ | E5: 51KG+ | F5: 101KG+ | G5: 12KG+ | H5: 21KG+ | I5: 51KG+ | J5: 101KG+ | K5: 12KG+ | L5: 21KG+ | M5: 51KG+ | N5: 101KG+ | O5: 承诺提取时效 交货后第二天算起
A6: 8,9 | C6: 40 | D6: 39 | E6: 38 | F6: 37 | G6: 41 | H6: 40 | I6: 39 | J6: 38 | K6: 41 | L6: 40 | M6: 39 | N6: 38 | O6: 5-12个自然日
A7: 6,7 | C7: 41 | D7: 40 | E7: 39 | F7: 38 | G7: 42 | H7: 41 | I7: 40 | J7: 39 | K7: 42 | L7: 41 | M7: 40 | N7: 39
A8: 4,5 | C8: 42 | D8: 41 | E8: 40 | F8: 39 | G8: 43 | H8: 42 | I8: 41 | J8: 40 | K8: 43 | L8: 42 | M8: 41 | N8: 40
A9: 0,1,2,3 | C9: 43 | D9: 42 | E9: 41 | F9: 40 | G9: 44 | H9: 43 | I9: 42 | J9: 41 | K9: 44 | L9: 43 | M9: 42 | N9: 41
A10: 卡派(大陆航班）
C11: 珠三角交货价 | G11: 汕头交货价 | K11: 义乌交货价
A12: 仓库 重量段 | C12: 12KG+ | E12: 201KG+ | F12: 501KG+ | G12: 12KG+ | I12: 201KG+ | J12: 501KG+ | K12: 12KG+ | M12: 201KG+ | N12: 501KG+ | O12: 参考签收时效 交货后第二天算起
A13: ONT8/LGB8 SBD1/JOT1/POC1/POC3 | C13: * | E13: 41.5 | F13: 41 | G13: * | I13: 42.5 | J13: 42 | K13: * | M13: 43.5 | N13: 43 | O13: 7-15个自然日
A14: SMF3/GYR3 GYR2/SCK4/MIT2/QXY5/GEU3/GEU2/GEU5 | C14: * | E14: 42.5 | F14: 42 | G14: * | I14: 43.5 | J14: 43 | K14: * | M14: 44.5 | N14: 44 | O14: 8-16个自然日
A15: 空派交货第二天算起5-12个自然日提取，第13个自然日起未提取按1元/kg/自然日赔付，单票最高赔付3元/kg/自然日。因不可抗力因素和查验即取消超时赔付服务 单箱最低12KG起 | J15: 空卡交货后第二天算起7-15天签收
A16: 美国空运240（带电/化妆品）
A17: 快递派(香港航班）
C18: 珠三角交货价 | G18: 汕头交货价 | K18: 义乌交货价
A19: 邮编开头 重量段 | C19: 12KG+ | D19: 21KG+ | E19: 51KG+ | F19: 101KG+ | G19: 12KG+ | H19: 21KG+ | I19: 51KG+ | J19: 101KG+ | K19: 12KG+ | L19: 21KG+ | M19: 51KG+ | N19: 101KG+ | O19: 提取时效 交货后第二天算起
A20: 8,9 | C20: * | D20: * | E20: * | F20: * | G20: * | H20: * | I20: * | J20: * | K20: * | L20: * | M20: * | N20: * | O20: 7-14个自然日
A21: 6,7 | C21: * | D21: * | E21: * | F21: * | G21: * | H21: * | I21: * | J21: * | K21: * | L21: * | M21: * | N21: *
A22: 4,5 | C22: * | D22: * | E22: * | F22: * | G22: * | H22: * | I22: * | J22: * | K22: * | L22: * | M22: * | N22: *
A23: 0,1,2,3 | C23: * | D23: * | E23: * | F23: * | G23: * | H23: * | I23: * | J23: * | K23: * | L23: * | M23: * | N23: *
A24: 交货第二天算起7-14个自然日提取，第15个自然日起未提取按1元/kg/自然日赔付，单票最高赔付3元/kg/自然日。因不可抗力因素和查验即取消超时赔付服务 单箱最低12KG起
A25: 特别提醒：汕头、义乌交货价格以货物实际到广州仓时间报价表价格为准。
A26: 赔付条款如遇海关检查/节假日/PO失效或亚马逊推约等不可控因素等原因即取消赔付服务
A27: 附加费及要求
A28: 单独报关件单询！单票超5个品名以上+50RMB/个，偏远费+2RMB/KG，单箱计费重12KG起，尾端UPS/FEDEX派送，非FBA商业地址+1元KG，住宅地址+2KG
A29: 注明：每周报价表为实时报价，不可控因素或市场变化调节过大时，升或降以到仓价格为准
A30: 包税附加费，未列明产品请跟业务联系
A31: 需加收产品及杂费 | G31: 加收金额 | J31: 备注
A32: 除高价值，高关税产品，其余普通产品无附加费 | G32: 无附加费 | J32: 由于产品本身专利或知识产权问题产生扣关，货物退回等后续问题由客户承担，我司保留追究的权力
A33: 纺织品，笔（铅笔不接）、鞋子、服装（穿戴）、包包、蓝牙产品（有标志不接）、玩具类（必须有CPC类证书） | G33: 单询 | J33: FDA类产品，海关可能会查验。由于客户提供错误的FDA ID. 产生扣关，关税，货物退回等后续问题由客户承担，我司并保留追究的权力
A34: 化工品（指甲胶、精油、口红、眼影，卸妆水、洗发水等） | G34: 单询 | J34: 提供真实有效期内商检、MSDS认证视为普货，无需附加费（证书是否有效以相关部门是否认可为准）
A35: 国内贴标费 | G35: 1元/张 | J35: 为了准确快捷入库，请尽量配合贴好入仓标签/FBA标签/SKU标签等，因未贴标签或未及时告知导致仓库未能及时入库延误船期的我司概不负责
A36: 报价未注明的产品，请将提供产品信息给我司客服或业务进行核实是否有附加费 | G36: 待确定 | J36: 因美对华加增2000亿美金关税影响，请单独询问销售
A37: 汽车灯 | J37: 4元/kg，低消50元/票
A38: 普通带磁产品 | J38: 2元/KG，封顶200元
A39: 超5个品名；第6个品名开始收取 | J39: 50元/品名
A40: 马达，电机类产品 | J40: 500元/品名
A41: 木、竹、藤制品 | J41: 100元/票
A42: 针对原木产品或原木包装 | J42: 800元/票
A43: 针对需做FDA申报的产品 | J43: 100元/品名
A44: 偏远地址单询 | G44: 快递派超限附加费：单件实重不可超过22KG,超过22KG或单边长超过110cm，或次长超过76cm加收160RMB/件，周长超260CM加收180元/件 卡派超限附加费：最长边不可超过120CM,次长边不可超过100CM，单箱实重超过30KG单询
A45: 单证报关货物单票101KG起收，报关费250元/票；单票超5个品名以上+50RMB/个，更改地址费100USD/票（不保证一定成功）
A46: 以上为双清含税价，包含清关费。关税及当地UPS/Fedex到门派送服务费用。 温馨提示：请按我司提供的样板提供电子版发票和装箱单，如因发票申报不符造成的无法清关，我司概不负责（清关延误不算在正常派送日内）

Sheet 价格快查表
B2: 渠道价格快速查找 | BO2: 渠道价格快速查找
B3: 输入右边信息 | C3: 国内交货仓 | D3: 平台 | E3: 目的仓/邮编开头 | F3: 计费方式 | G3: 送仓方式 | BL3: 输入右边信息 | BM3: 国内交货仓 | BO3: 目的仓/邮编开头 | BP3: 计费方式 | BQ3: 送仓方式
C4: 珠三角 | D4: 亚马逊 | E4: 8 | F4: KG | G4: 卡派 | BM4: =C4 | BN4: =D4 | BO4: =E4 | BP4: =F4 | BQ4: =G4
B5: 渠道 | C5: 渠道单价 (KG/CBM) | D5: 参考时效 （开船后） | E5: ETD | F5: ETA | G5: 航行日 | BL5: 渠道 | BM5: 渠道单价 (KG/CBM) | BN5: 参考时效 （开船后） | BO5: ETD | BP5: ETA | BQ5: 航行日
B6: 美森360 | C6: =BM6 | D6: =BN6 | E6: =BO6 | F6: =BP6 | G6: =BQ6 | BL6: 美森360 | BM6: =IFERROR(IF(E4="","-",IF(AND($G$4="卡派",$F$4="KG",$C$4="珠三角",$D$4="亚马逊"),CONCATENATE("8KG+："&VLOOKUP("*"&$E$4&"*",'美西特快专线'!$A$6:$E$18,2,0)," 101KG+："&VLOOKUP("*"&$E$4&"*",'美西特快专线'!$A$6:$E$18,3,0)),IF(AND($G$4="卡派",$F$4="KG",$C$4="汕头仓",$D$4="亚马逊"),CONCATENATE("8KG+："&VLOOKUP("*"&$E$4&"*",'美西特快专线'!$A$6:$E$18,2,0)," 101KG+："&VLOOKUP("*"&$E$4&"*",'美西特快专线'!$A$6:$E$18,3,0)),IF(AND($G$4="卡派",$F$4="KG",$C$4="义乌仓",$D$4="亚马逊"),CONCATENATE("8KG+："&VLOOKUP("*"&$E$4&"*",'美西特快专线'!$A$6:$E$18,4,0)," 101KG+："&VLOOKUP("*"&$E$4&"*",'美西特快专线'!$A$6:$E$18,5,0)),IF(AND($G$4="卡派",$F$4="按方不包税",$C$4="珠三角",$D$4="亚马逊"),CONCATENATE("2CBM+："&VLOOKUP("*"&$E$4&"*",'按方不包税'!$A$6:$C$12,2,0)),IF(AND($G$4="卡派",$F$4="按方不包税",$C$4="汕头仓",$D$4="亚马逊"),CONCATENATE("2CBM+："&VLOOKUP("*"&$E$4&"*",'按方不包税'!$A$6:$C$12,2,0)),IF(AND($G$4="卡派",$F$4="按方不包税",$C$4="义乌仓",$D$4="亚马逊"),CONCATENATE("2CBM+："&VLOOKUP("*"&$E$4&"*",'按方不包税'!$A$6:$C$12,3,0)),IF(AND($G$4="卡派",$F$4="KG",$C$4="珠三角",$D$4="沃尔玛专线"),CONCATENATE("501KG+："&VLOOKUP("*"&$E$4&"*",'沃尔玛专线'!$A$6:$G$7,4,0)," 3001KG+："&VLOOKUP("*"&$E$4&"*",'沃尔玛专线'!$A$6:$G$7,5,0)," 5001KG+："&VLOOKUP("*"&$E$4&"*",'沃尔玛专线'!$A$6:$G$7,6,0)),IF(AND($G$4="卡派",$F$4="KG",$C$4="汕头仓",$D$4="沃尔玛专线"),CONCATENATE("501KG+："&VLOOKUP("*"&$E$4&"*",'沃尔玛专线'!$A$6:$G$7,4,0)," 3001KG+："&VLOOKUP("*"&$E$4&"*",'沃尔玛专线'!$A$6:$G$7,5,0)," 5001KG+："&VLOOKUP("*"&$E$4&"*",'沃尔玛专线'!$A$6:$G$7,6,0)),IF(AND($G$4="卡派",$F$4="KG",$C$4="义乌仓",$D$4="沃尔玛专线"),CONCATENATE("501KG+："&VLOOKUP("*"&$E$4&"*",'沃尔玛专线'!$A$6:$G$7,4,0)," 3001KG+："&VLOOKUP("*"&$E$4&"*",'沃尔玛专线'!$A$6:$G$7,5,0)," 5001KG+："&VLOOKUP("*"&$E$4&"*",'沃尔玛专线'!$A$6:$G$7,6,0)),IF(AND($G$4="快递派",$F$4="KG",$C$4="珠三角",$D$4="亚马逊"),CONCATENATE("12KG+："&VLOOKUP("*"&$E$4&"*",'海运快递派'!$A$5:$E$8,3,0)," 51KG+："&VLOOKUP("*"&$E$4&"*",'海运快递派'!$A$5:$E$8,4,0)," 101KG+："&VLOOKUP("*"&$E$4&"*",'海运快递派'!$A$5:$E$8,5,0)),IF(AND($G$4="快递派",$F$4="KG",$C$4="汕头仓",$D$4="亚马逊"),CONCATENATE("12KG+："&VLOOKUP("*"&$E$4&"*",'海运快递派'!$A$5:$E$8,3,0)," 51KG+："&VLOOKUP("*"&$E$4&"*",'海运快递派'!$A$5:$E$8,4,0)," 101KG+："&VLOOKUP("*"&$E$4&"*",'海运快递派'!$A$5:$E$8,5,0)),IF(AND($G$4="快递派",$F$4="KG",$C$4="义乌仓",$D$4="亚马逊"),CONCATENATE("12KG+："&VLOOKUP("*"&$E$4&"*",'海运快递派'!$A$5:$E$8,3,0)," 51KG+："&VLOOKUP("*"&$E$4&"*",'海运快递派'!$A$5:$E$8,4,0)," 101KG+："&VLOOKUP("*"&$E$4&"*",'海运快递派'!$A$5:$E$8,5,0)),"-"))))))))))))),"-") | BN6: =IFERROR(IF($E$4="","-",IF(AND($G$4="卡派",$F$4="KG",$C$4="珠三角",$D$4="亚马逊"),VLOOKUP("*"&$E$4&"*",'美西特快专线'!$A$6:$F$18,6,0),IF(AND($G$4="卡派",$F$4="KG",$C$4="汕头仓",$D$4="亚马逊"),VLOOKUP("*"&$E$4&"*",'美西特快专线'!$A$6:$F$18,6,0),IF(AND($G$4="卡派",$F$4="KG",$C$4="义乌仓",$D$4="亚马逊"),VLOOKUP("*"&$E$4&"*",'美西特快专线'!$A$6:$F$18,6,0),IF(AND($G$4="卡派",$F$4="按方不包税",$C$4="珠三角",$D$4="亚马逊"),VLOOKUP("*"&$E$4&"*",'按方不包税'!$A$6:$E$12,4,0),IF(AND($G$4="卡派",$F$4="按方不包税",$C$4="汕头仓",$D$4="亚马逊"),VLOOKUP("*"&$E$4&"*",'按方不包税'!$A$6:$E$12,4,0),IF(AND($G$4="卡派",$F$4="按方不包税",$C$4="义乌仓",$D$4="亚马逊"),VLOOKUP("*"&$E$4&"*",'按方不包税'!$A$6:$E$12,4,0),IF(AND($G$4="卡派",$F$4="KG",$C$4="珠三角",$D$4="沃尔玛专线"),VLOOKUP("*"&$E$4&"*",'沃尔玛专线'!$A$6:$G$7,7,0),IF(AND($G$4="卡派",$F$4="KG",$C$4="汕头仓",$D$4="沃尔玛专线"),VLOOKUP("*"&$E$4&"*",'沃尔玛专线'!$A$6:$G$7,7,0),IF(AND($G$4="卡派",$F$4="KG",$C$4="义乌仓",$D$4="沃尔玛专线"),VLOOKUP("*"&$E$4&"*",'沃尔玛专线'!$A$6:$G$7,7,0),IF(AND($G$4="快递派",$F$4="KG",$C$4="珠三角",$D$4="亚马逊"),VLOOKUP("*"&$E$4&"*",'海运快递派'!$A$5:$F$8,6,0),IF(AND($G$4="快递派",$F$4="KG",$C$4="汕头仓",$D$4="亚马逊"),VLOOKUP("*"&$E$4&"*",'海运快递派'!$A$5:$F$8,6,0),IF(AND($G$4="快递派",$F$4="KG",$C$4="义乌仓",$D$4="亚马逊"),VLOOKUP("*"&$E$4&"*",'海运快递派'!$A$5:$F$8,6,0),"-"))))))))))))),"-") | BO6: =CONCATENATE('海运船期表'!$B$4,"-"&'海运船期表'!$C$4," : ",TEXT('海运船期表'!$I$4,"MM-DD")) | BP6: =CONCATENATE('海运船期表'!$B$4,"-"&'海运船期表'!$C$4," : ",TEXT('海运船期表'!$J$4,"MM-DD")) | BQ6: ='海运船期表'!$K$4
B7: 美森432 | C7: =BM7 | D7: =BN7 | E7: =BO7 | F7: =BP7 | G7: =BQ7 | BL7: 美森432 | BM7: =IFERROR(IF(E4="","-",IF(AND($G$4="卡派",$F$4="KG",$C$4="珠三角",$D$4="亚马逊"),CONCATENATE("8KG+："&VLOOKUP("*"&$E$4&"*",'美西特快专线'!$A$6:$M$18,9,0)," 101KG+："&VLOOKUP("*"&$E$4&"*",'美西特快专线'!$A$6:$M$18,10,0)),IF(AND($G$4="卡派",$F$4="KG",$C$4="汕头仓",$D$4="亚马逊"),CONCATENATE("8KG+："&VLOOKUP("*"&$E$4&"*",'美西特快专线'!$A$6:$M$18,9,0)," 101KG+："&VLOOKUP("*"&$E$4&"*",'美西特快专线'!$A$6:$M$18,10,0)),IF(AND($G$4="卡派",$F$4="KG",$C$4="义乌仓",$D$4="亚马逊"),CONCATENATE("8KG+："&VLOOKUP("*"&$E$4&"*",'美西特快专线'!$A$6:$M$18,11,0)," 101KG+："&VLOOKUP("*"&$E$4&"*",'美西特快专线'!$A$6:$M$18,12,0)),IF(AND($G$4="卡派",$F$4="按方不包税",$C$4="珠三角",$D$4="亚马逊"),CONCATENATE("2CBM+："&VLOOKUP("*"&$E$4&"*",'按方不包税'!$A$17:$E$23,2,0)),IF(AND($G$4="卡派",$F$4="按方不包税",$C$4="汕头仓",$D$4="亚马逊"),CONCATENATE("2CBM+："&VLOOKUP("*"&$E$4&"*",'按方不包税'!$A$17:$E$23,2,0)),IF(AND($G$4="卡派",$F$4="按方不包税",$C$4="义乌仓",$D$4="亚马逊"),CONCATENATE("2CBM+："&VLOOKUP("*"&$E$4&"*",'按方不包税'!$A$17:$E$23,3,0)),IF(AND($G$4="卡派",$F$4="KG",$C$4="珠三角",$D$4="沃尔玛专线"),CONCATENATE("501KG+："&VLOOKUP("*"&$E$4&"*",'沃尔玛专线'!$A$8:$G$9,4,0)," 3001KG+："&VLOOKUP("*"&$E$4&"*",'沃尔玛专线'!$A$8:$G$9,5,0)," 5001KG+："&VLOOKUP("*"&$E$4&"*",'沃尔玛专线'!$A$8:$G$9,6,0)),IF(AND($G$4="卡派",$F$4="KG",$C$4="汕头仓",$D$4="沃尔玛专线"),CONCATENATE("501KG+："&VLOOKUP("*"&$E$4&"*",'沃尔玛专线'!$A$8:$G$9,4,0)," 3001KG+："&VLOOKUP("*"&$E$4&"*",'沃尔玛专线'!$A$8:$G$9,5,0)," 5001KG+："&VLOOKUP("*"&$E$4&"*",'沃尔玛专线'!$A$8:$G$9,6,0)),IF(AND($G$4="卡派",$F$4="KG",$C$4="义乌仓",$D$4="沃尔玛专线"),CONCATENATE("501KG+："&VLOOKUP("*"&$E$4&"*",'沃尔玛专线'!$A$8:$G$9,0)," 3001KG+："&VLOOKUP("*"&$E$4&"*",'沃尔玛专线'!$A$8:$G$9,5,0)," 5001KG+："&VLOOKUP("*"&$E$4&"*",'沃尔玛专线'!$A$8:$G$9,6,0)),IF(AND($G$4="快递派",$F$4="KG",$C$4="珠三角",$D$4="亚马逊"),CONCATENATE("12KG+："&VLOOKUP("*"&$E$4&"*",'海运快递派'!$A$13:$F$16,3,0)," 51KG+："&VLOOKUP("*"&$E$4&"*",'海运快递派'!$A$13:$F$16,4,0)," 101KG+："&VLOOKUP("*"&$E$4&"*",'海运快递派'!$A$13:$F$16,5,0)),IF(AND($G$4="快递派",$F$4="KG",$C$4="汕头仓",$D$4="亚马逊"),CONCATENATE("12KG+："&VLOOKUP("*"&$E$4&"*",'海运快递派'!$A$13:$F$16,3,0)," 51KG+："&VLOOKUP("*"&$E$4&"*",'海运快递派'!$A$13:$F$16,4,0)," 101KG+："&VLOOKUP("*"&$E$4&"*",'海运快递派'!$A$13:$F$16,5,0)),IF(AND($G$4="快递派",$F$4="KG",$C$4="义乌仓",$D$4="亚马逊"),CONCATENATE("12KG+："&VLOOKUP("*"&$E$4&"*",'海运快递派'!$A$13:$F$16,3,0)," 51KG+："&VLOOKUP("*"&$E$4&"*",'海运快递派'!$A$13:$F$16,4,0)," 101KG+："&VLOOKUP("*"&$E$4&"*",'海运快递派'!$A$13:$F$16,5,0)),"-"))))))))))))),"-") | BN7: =IFERROR(IF($E$4="","-",IF(AND($G$4="卡派",$F$4="KG",$C$4="珠三角",$D$4="亚马逊"),VLOOKUP("*"&$E$4&"*",'美西特快专线'!$A$6:$M$18,13,0),IF(AND($G$4="卡派",$F$4="KG",$C$4="汕头仓",$D$4="亚马逊"),VLOOKUP("*"&$E$4&"*",'美西特快专线'!$A$6:$M$18,13,0),IF(AND($G$4="卡派",$F$4="KG",$C$4="义乌仓",$D$4="亚马逊"),VLOOKUP("*"&$E$4&"*",'美西特快专线'!$A$6:$M$18,13,0),IF(AND($G$4="卡派",$F$4="按方不包税",$C$4="珠三角",$D$4="亚马逊"),VLOOKUP("*"&$E$4&"*",'按方不包税'!$A$17:$E$23,4,0),IF(AND($G$4="卡派",$F$4="按方不包税",$C$4="汕头仓",$D$4="亚马逊"),VLOOKUP("*"&$E$4&"*",'按方不包税'!$A$17:$E$23,4,0),IF(AND($G$4="卡派",$F$4="按方不包税",$C$4="义乌仓",$D$4="亚马逊"),VLOOKUP("*"&$E$4&"*",'按方不包税'!$A$17:$E$23,4,0),IF(AND($G$4="卡派",$F$4="KG",$C$4="珠三角",$D$4="沃尔玛专线"),VLOOKUP("*"&$E$4&"*",'沃尔玛专线'!$A$8:$G$9,7,0),IF(AND($G$4="卡派",$F$4="KG",$C$4="汕头仓",$D$4="沃尔玛专线"),VLOOKUP("*"&$E$4&"*",'沃尔玛专线'!$A$8:$G$9,7,0),IF(AND($G$4="卡派",$F$4="KG",$C$4="义乌仓",$D$4="沃尔玛专线"),VLOOKUP("*"&$E$4&"*",'沃尔玛专线'!$A$8:$G$9,7,0),IF(AND($G$4="快递派",$F$4="KG",$C$4="珠三角",$D$4="亚马逊"),VLOOKUP("*"&$E$4&"*",'海运快递派'!$A$13:$F$16,6,0),IF(AND($G$4="快递派",$F$4="KG",$C$4="汕头仓",$D$4="亚马逊"),VLOOKUP("*"&$E$4&"*",'海运快递派'!$A$13:$F$16,6,0),IF(AND($G$4="快递派",$F$4="KG",$C$4="义乌仓",$D$4="亚马逊"),VLOOKUP("*"&$E$4&"*",'海运快递派'!$A$13:$F$16,6,0),"-"))))))))))))),"-") | BO7: =CONCATENATE('海运船期表'!$B$5,"-"&'海运船期表'!$C$5," : ",TEXT('海运船期表'!$I$5,"MM-DD")) | BP7: =CONCATENATE('海运船期表'!$B$5,"-"&'海运船期表'!$C$5," : ",TEXT('海运船期表'!$J$5,"MM-DD")) | BQ7: ='海运船期表'!$K$5
B8: EX456 | C8: =BM8 | D8: =BN8 | E8: =BO8 | F8: =BP8 | G8: =BQ8 | BL8: EX456 | BM8: =IFERROR(IF($E$4="","-",IF(AND($G$4="卡派",$F$4="KG",$C$4="珠三角",$D$4="亚马逊"),CONCATENATE("8KG+："&VLOOKUP("*"&$E$4&"*",'美西特快专线'!$A$6:$R$18,16,0)," 101KG+："&VLOOKUP("*"&$E$4&"*",'美西特快专线'!$A$6:$R$18,17,0)),IF(AND($G$4="卡派",$F$4="KG",$C$4="汕头仓",$D$4="亚马逊"),CONCATENATE("8KG+："&VLOOKUP("*"&$E$4&"*",'美西特快专线'!$A$6:$R$18,16,0)," 101KG+："&VLOOKUP("*"&$E$4&"*",'美西特快专线'!$A$6:$R$18,17,0)),IF(AND($G$4="卡派",$F$4="KG",$C$4="义乌仓",$D$4="亚马逊"),CONCATENATE("8KG+："&VLOOKUP("*"&$E$4&"*",'美西特快专线'!$A$6:$R$18,16,0)," 101KG+："&VLOOKUP("*"&$E$4&"*",'美西特快专线'!$A$6:$R$18,17,0)),IF(AND($G$4="卡派",$F$4="按方不包税",$C$4="珠三角",$D$4="亚马逊"),CONCATENATE("2CBM+："&VLOOKUP("*"&$E$4&"*",'按方不包税'!$A$28:$E$34,2,0)),IF(AND($G$4="卡派",$F$4="按方不包税",$C$4="汕头仓",$D$4="亚马逊"),CONCATENATE("2CBM+："&VLOOKUP("*"&$E$4&"*",'按方不包税'!$A$28:$E$34,2,0)),IF(AND($G$4="卡派",$F$4="按方不包税",$C$4="义乌仓",$D$4="亚马逊"),CONCATENATE("2CBM+："&VLOOKUP("*"&$E$4&"*",'按方不包税'!$A$28:$E$34,2,0)),IF(AND($G$4="卡派",$F$4="KG",$C$4="珠三角",$D$4="沃尔玛专线"),CONCATENATE("501KG+："&VLOOKUP("*"&$E$4&"*",'沃尔玛专线'!$A$10:$G$11,4,0)," 3001KG+："&VLOOKUP("*"&$E$4&"*",'沃尔玛专线'!$A$10:$G$11,5,0)," 5001KG+："&VLOOKUP("*"&$E$4&"*",'沃尔玛专线'!$A$10:$G$11,6,0)),IF(AND($G$4="卡派",$F$4="KG",$C$4="汕头仓",$D$4="沃尔玛专线"),CONCATENATE("501KG+："&VLOOKUP("*"&$E$4&"*",'沃尔玛专线'!$A$10:$G$11,7,0)," 3001KG+："&VLOOKUP("*"&$E$4&"*",'沃尔玛专线'!$A$10:$G$11,9,0)," 5001KG+："&VLOOKUP("*"&$E$4&"*",'沃尔玛专线'!$A$10:$G$11,9,0)),IF(AND($G$4="卡派",$F$4="KG",$C$4="义乌仓",$D$4="沃尔玛专线"),CONCATENATE("501KG+："&VLOOKUP("*"&$E$4&"*",'沃尔玛专线'!$A$10:$G$11,10,0)," 3001KG+："&VLOOKUP("*"&$E$4&"*",'沃尔玛专线'!$A$10:$G$11,11,0)," 5001KG+："&VLOOKUP("*"&$E$4&"*",'沃尔玛专线'!$A$10:$G$11,12,0)),IF(AND($G$4="快递派",$F$4="KG",$C$4="珠三角",$D$4="亚马逊"),CONCATENATE("12KG+："&VLOOKUP("*"&$E$4&"*",'海运快递派'!$A$21:$F$24,3,0)," 51KG+："&VLOOKUP("*"&$E$4&"*",'海运快递派'!$A$21:$F$24,4,0)," 101KG+："&VLOOKUP("*"&$E$4&"*",'海运快递派'!$A$21:$F$24,5,0)),IF(AND($G$4="快递派",$F$4="KG",$C$4="汕头仓",$D$4="亚马逊"),CONCATENATE("12KG+："&VLOOKUP("*"&$E$4&"*",'海运快递派'!$A$21:$F$24,3,0)," 51KG+："&VLOOKUP("*"&$E$4&"*",'海运快递派'!$A$21:$F$24,4,0)," 101KG+："&VLOOKUP("*"&$E$4&"*",'海运快递派'!$A$21:$F$24,5,0)),IF(AND($G$4="快递派",$F$4="KG",$C$4="义乌仓",$D$4="亚马逊"),CONCATENATE("12KG+："&VLOOKUP("*"&$E$4&"*",'海运快递派'!$A$21:$F$24,3,0)," 51KG+："&VLOOKUP("*"&$E$4&"*",'海运快递派'!$A$21:$F$24,4,0)," 101KG+："&VLOOKUP("*"&$E$4&"*",'海运快递派'!$A$21:$F$24,5,0)),"-"))))))))))))),"-") | BN8: =IFERROR(IF($E$4="","-",IF(AND($G$4="卡派",$F$4="KG",$C$4="珠三角",$D$4="亚马逊"),VLOOKUP("*"&$E$4&"*",'美西特快专线'!$A$6:$R$18,18,0),IF(AND($G$4="卡派",$F$4="KG",$C$4="汕头仓",$D$4="亚马逊"),VLOOKUP("*"&$E$4&"*",'美西特快专线'!$A$6:$R$18,18,0),IF(AND($G$4="卡派",$F$4="KG",$C$4="义乌仓",$D$4="亚马逊"),VLOOKUP("*"&$E$4&"*",'美西特快专线'!$A$6:$R$18,18,0),IF(AND($G$4="卡派",$F$4="按方不包税",$C$4="珠三角",$D$4="亚马逊"),VLOOKUP("*"&$E$4&"*",'按方不包税'!$A$28:$E$34,4,0),IF(AND($G$4="卡派",$F$4="按方不包税",$C$4="汕头仓",$D$4="亚马逊"),VLOOKUP("*"&$E$4&"*",'按方不包税'!$A$28:$E$34,4,0),IF(AND($G$4="卡派",$F$4="按方不包税",$C$4="义乌仓",$D$4="亚马逊"),VLOOKUP("*"&$E$4&"*",'按方不包税'!$A$28:$E$34,4,0),IF(AND($G$4="卡派",$F$4="KG",$C$4="珠三角",$D$4="沃尔玛专线"),VLOOKUP("*"&$E$4&"*",'沃尔玛专线'!$A$10:$G$11,7,0),IF(AND($G$4="卡派",$F$4="KG",$C$4="汕头仓",$D$4="沃尔玛专线"),VLOOKUP("*"&$E$4&"*",'沃尔玛专线'!$A$10:$G$11,7,0),IF(AND($G$4="卡派",$F$4="KG",$C$4="义乌仓",$D$4="沃尔玛专线"),VLOOKUP("*"&$E$4&"*",'沃尔玛专线'!$A$10:$G$11,7,0),IF(AND($G$4="快递派",$F$4="KG",$C$4="珠三角",$D$4="亚马逊"),VLOOKUP("*"&$E$4&"*",'海运快递派'!$A$21:$F$24,6,0),IF(AND($G$4="快递派",$F$4="KG",$C$4="汕头仓",$D$4="亚马逊"),VLOOKUP("*"&$E$4&"*",'海运快递派'!$A$21:$F$24,6,0),IF(AND($G$4="快递派",$F$4="KG",$C$4="义乌仓",$D$4="亚马逊"),VLOOKUP("*"&$E$4&"*",'海运快递派'!$A$21:$F$24,6,0),"-"))))))))))))),"-") | BO8: =CONCATENATE('海运船期表'!$B$6,"-"&'海运船期表'!$C$6," : ",TEXT('海运船期表'!$I$6,"MM-DD")) | BP8: =CONCATENATE('海运船期表'!$B$6,"-"&'海运船期表'!$C$6," : ",TEXT('海运船期表'!$J$6,"MM-DD")) | BQ8: ='海运船期表'!$K$6
B9: 快船600 | C9: =BM9 | D9: =BN9 | E9: =BO9 | F9: =BP9 | G9: =BQ9 | BL9: 快船600 | BM9: =IFERROR(IF($E$4="","-",IF(AND($G$4="卡派",$F$4="KG",$C$4="珠三角",$D$4="亚马逊"),CONCATENATE("8KG+："&VLOOKUP("*"&$E$4&"*",'美西快船专线'!$A$7:$E$19,2,0)," 101KG+："&VLOOKUP("*"&$E$4&"*",'美西快船专线'!$A$7:$E$19,3,0)),IF(AND($G$4="卡派",$F$4="KG",$C$4="汕头仓",$D$4="亚马逊"),CONCATENATE("8KG+："&VLOOKUP("*"&$E$4&"*",'美西快船专线'!$A$7:$E$19,2,0)," 101KG+："&VLOOKUP("*"&$E$4&"*",'美西快船专线'!$A$7:$E$19,3,0)),IF(AND($G$4="卡派",$F$4="KG",$C$4="义乌仓",$D$4="亚马逊"),CONCATENATE("8KG+："&VLOOKUP("*"&$E$4&"*",'美西快船专线'!$A$7:$E$19,2,0)," 101KG+："&VLOOKUP("*"&$E$4&"*",'美西快船专线'!$A$7:$E$19,3,0)),IF(AND($G$4="卡派",$F$4="按方不包税",$C$4="珠三角",$D$4="亚马逊"),CONCATENATE("2CBM+："&VLOOKUP("*"&$E$4&"*",'按方不包税'!$A$40:$E$48,2,0)),IF(AND($G$4="卡派",$F$4="按方不包税",$C$4="汕头仓",$D$4="亚马逊"),CONCATENATE("2CBM+："&VLOOKUP("*"&$E$4&"*",'按方不包税'!$A$40:$E$48,2,0)),IF(AND($G$4="卡派",$F$4="按方不包税",$C$4="义乌仓",$D$4="亚马逊"),CONCATENATE("2CBM+："&VLOOKUP("*"&$E$4&"*",'按方不包税'!$A$40:$E$48,2,0)),IF(AND($G$4="卡派",$F$4="KG",$C$4="珠三角",$D$4="沃尔玛专线"),CONCATENATE("501KG+："&VLOOKUP("*"&$E$4&"*",'沃尔玛专线'!$A$12:$G$13,4,0)," 3001KG+："&VLOOKUP("*"&$E$4&"*",'沃尔玛专线'!$A$12:$G$13,5,0)," 5001KG+："&VLOOKUP("*"&$E$4&"*",'沃尔玛专线'!$A$12:$G$13,6,0)),IF(AND($G$4="卡派",$F$4="KG",$C$4="汕头仓",$D$4="沃尔玛专线"),CONCATENATE("501KG+："&VLOOKUP("*"&$E$4&"*",'沃尔玛专线'!$A$12:$G$13,7,0)," 3001KG+："&VLOOKUP("*"&$E$4&"*",'沃尔玛专线'!$A$12:$G$13,9,0)," 5001KG+："&VLOOKUP("*"&$E$4&"*",'沃尔玛专线'!$A$12:$G$13,9,0)),IF(AND($G$4="卡派",$F$4="KG",$C$4="义乌仓",$D$4="沃尔玛专线"),CONCATENATE("501KG+："&VLOOKUP("*"&$E$4&"*",'沃尔玛专线'!$A$12:$G$13,10,0)," 3001KG+："&VLOOKUP("*"&$E$4&"*",'沃尔玛专线'!$A$12:$G$13,11,0)," 5001KG+："&VLOOKUP("*"&$E$4&"*",'沃尔玛专线'!$A$12:$G$13,12,0)),IF(AND($G$4="快递派",$F$4="KG",$C$4="珠三角",$D$4="亚马逊"),CONCATENATE("12KG+："&VLOOKUP("*"&$E$4&"*",'海运快递派'!$A$29:$F$32,3,0)," 51KG+："&VLOOKUP("*"&$E$4&"*",'海运快递派'!$A$29:$F$32,4,0)," 101KG+："&VLOOKUP("*"&$E$4&"*",'海运快递派'!$A$29:$F$32,5,0)),IF(AND($G$4="快递派",$F$4="KG",$C$4="汕头仓",$D$4="亚马逊"),CONCATENATE("12KG+："&VLOOKUP("*"&$E$4&"*",'海运快递派'!$A$29:$F$32,3,0)," 51KG+："&VLOOKUP("*"&$E$4&"*",'海运快递派'!$A$29:$F$32,4,0)," 101KG+："&VLOOKUP("*"&$E$4&"*",'海运快递派'!$A$29:$F$32,5,0)),IF(AND($G$4="快递派",$F$4="KG",$C$4="义乌仓",$D$4="亚马逊"),CONCATENATE("12KG+："&VLOOKUP("*"&$E$4&"*",'海运快递派'!$A$29:$F$32,3,0)," 51KG+："&VLOOKUP("*"&$E$4&"*",'海运快递派'!$A$29:$F$32,4,0)," 101KG+："&VLOOKUP("*"&$E$4&"*",'海运快递派'!$A$29:$F$32,5,0)),"-"))))))))))))),"-") | BN9: =IFERROR(IF($E$4="","-",IF(AND($G$4="卡派",$F$4="KG",$C$4="珠三角",$D$4="亚马逊"),VLOOKUP("*"&$E$4&"*",'美西快船专线'!$A$7:$E$19,4,0),IF(AND($G$4="卡派",$F$4="KG",$C$4="汕头仓",$D$4="亚马逊"),VLOOKUP("*"&$E$4&"*",'美西快船专线'!$A$7:$E$19,4,0),IF(AND($G$4="卡派",$F$4="KG",$C$4="义乌仓",$D$4="亚马逊"),VLOOKUP("*"&$E$4&"*",'美西快船专线'!$A$7:$E$19,4,0),IF(AND($G$4="卡派",$F$4="按方不包税",$C$4="珠三角",$D$4="亚马逊"),VLOOKUP("*"&$E$4&"*",'按方不包税'!$A$40:$E$48,4,0),IF(AND($G$4="卡派",$F$4="按方不包税",$C$4="汕头仓",$D$4="亚马逊"),VLOOKUP("*"&$E$4&"*",'按方不包税'!$A$40:$E$48,4,0),IF(AND($G$4="卡派",$F$4="按方不包税",$C$4="义乌仓",$D$4="亚马逊"),VLOOKUP("*"&$E$4&"*",'按方不包税'!$A$40:$E$48,4,0),IF(AND($G$4="卡派",$F$4="KG",$C$4="珠三角",$D$4="沃尔玛专线"),VLOOKUP("*"&$E$4&"*",'沃尔玛专线'!$A$12:$G$13,7,0),IF(AND($G$4="卡派",$F$4="KG",$C$4="汕头仓",$D$4="沃尔玛专线"),VLOOKUP("*"&$E$4&"*",'沃尔玛专线'!$A$12:$G$13,7,0),IF(AND($G$4="卡派",$F$4="KG",$C$4="义乌仓",$D$4="沃尔玛专线"),VLOOKUP("*"&$E$4&"*",'沃尔玛专线'!$A$10:$G$11,7,0),IF(AND($G$4="快递派",$F$4="KG",$C$4="珠三角",$D$4="亚马逊"),VLOOKUP("*"&$E$4&"*",'海运快递派'!$A$29:$F$32,6,0),IF(AND($G$4="快递派",$F$4="KG",$C$4="汕头仓",$D$4="亚马逊"),VLOOKUP("*"&$E$4&"*",'海运快递派'!$A$29:$F$32,6,0),IF(AND($G$4="快递派",$F$4="KG",$C$4="义乌仓",$D$4="亚马逊"),VLOOKUP("*"&$E$4&"*",'海运快递派'!$A$29:$F$32,6,0),"-"))))))))))))),"-") | BO9: =CONCATENATE("①",'海运船期表'!$B$7,"-"&'海运船期表'!$C$7," : ",TEXT('海运船期表'!$I$7,"MM-DD")," ②",'海运船期表'!$B$8,"-"&'海运船期表'!$C$8," : ",TEXT('海运船期表'!$I$8,"MM-DD")," ③",'海运船期表'!$B$9,"-"&'海运船期表'!$C$9," : ",TEXT('海运船期表'!$I$9,"MM-DD")) | BP9: =CONCATENATE("①",'海运船期表'!$B$7,"-"&'海运船期表'!$C$7," : ",TEXT('海运船期表'!$J$7,"MM-DD")," ②",'海运船期表'!$B$8,"-"&'海运船期表'!$C$8," : ",TEXT('海运船期表'!$J$8,"MM-DD")," ③",'海运船期表'!$B$9,"-"&'海运船期表'!$C$9," : ",TEXT('海运船期表'!$J$9,"MM-DD")) | BQ9: =CONCATENATE("①："&'海运船期表'!$K$7," ②："&'海运船期表'!$K$8," ③："&'海运船期表'!$K$9)
B10: 奥克兰744 | C10: =BM10 | D10: =BN10 | E10: =BO10 | F10: =BP10 | G10: =BQ10 | BL10: 奥克兰744 | BM10: =IFERROR(IF($E$4="","-",IF(AND($G$4="卡派",$F$4="KG",$C$4="珠三角",$D$4="亚马逊"),CONCATENATE("8KG+："&VLOOKUP("*"&$E$4&"*",'美西普船专线'!$F$7:$I$10,2,0)," 101KG+："&VLOOKUP("*"&$E$4&"*",'美西普船专线'!$F$7:$I$10,3,0)),IF(AND($G$4="卡派",$F$4="KG",$C$4="汕头仓",$D$4="亚马逊"),CONCATENATE("8KG+："&VLOOKUP("*"&$E$4&"*",'美西普船专线'!$F$7:$I$10,2,0)," 101KG+："&VLOOKUP("*"&$E$4&"*",'美西普船专线'!$F$7:$I$10,3,0)),IF(AND($G$4="卡派",$F$4="KG",$C$4="义乌仓",$D$4="亚马逊"),CONCATENATE("8KG+："&VLOOKUP("*"&$E$4&"*",'美西普船专线'!$F$7:$I$10,2,0)," 101KG+："&VLOOKUP("*"&$E$4&"*",'美西普船专线'!$A$7:$D$10,3,0)),IF(AND($G$4="卡派",$F$4="按方不包税",$C$4="珠三角",$D$4="亚马逊"),CONCATENATE("2CBM+："&VLOOKUP("*"&$E$4&"*",'按方不包税'!$A$63:$E$65,2,0)),IF(AND($G$4="卡派",$F$4="按方不包税",$C$4="汕头仓",$D$4="亚马逊"),CONCATENATE("2CBM+："&VLOOKUP("*"&$E$4&"*",'按方不包税'!$A$63:$E$65,2,0)),IF(AND($G$4="卡派",$F$4="按方不包税",$C$4="义乌仓",$D$4="亚马逊"),CONCATENATE("2CBM+："&VLOOKUP("*"&$E$4&"*",'按方不包税'!$A$63:$E$65,2,0)),"-"))))))),"-") | BN10: =IFERROR(IF($E$4="","-",IF(AND($G$4="卡派",$F$4="KG",$C$4="珠三角",$D$4="亚马逊"),VLOOKUP("*"&$E$4&"*",'美西普船专线'!$F$7:$I$10,4,0),IF(AND($G$4="卡派",$F$4="KG",$C$4="汕头仓",$D$4="亚马逊"),VLOOKUP("*"&$E$4&"*",'美西普船专线'!$F$7:$I$10,4,0),IF(AND($G$4="卡派",$F$4="KG",$C$4="义乌仓",$D$4="亚马逊"),VLOOKUP("*"&$E$4&"*",'美西普船专线'!$F$7:$I$10,4,0),IF(AND($G$4="卡派",$F$4="按方不包税KG",$C$4="珠三角",$D$4="亚马逊"),VLOOKUP("*"&$E$4&"*",'按方不包税'!$A$63:$E$65,4,0),IF(AND($G$4="卡派",$F$4="按方不包税",$C$4="汕头仓",$D$4="亚马逊"),VLOOKUP("*"&$E$4&"*",'按方不包税'!$A$63:$E$65,4,0),IF(AND($G$4="卡派",$F$4="按方不包税2CBM+",$C$4="义乌仓",$D$4="亚马逊"),VLOOKUP("*"&$E$4&"*",'按方不包税'!$A$63:$E$65,4,0),"-"))))))),"-") | BO10: =CONCATENATE("①",'海运船期表'!$B$12,"-"&'海运船期表'!$C$12," : ",TEXT('海运船期表'!$I$12,"MM-DD")," ②",'海运船期表'!$B$13,"-"&'海运船期表'!$C$13," : ",TEXT('海运船期表'!$I$13,"MM-DD")) | BP10: =CONCATENATE("①",'海运船期表'!$B$12,"-"&'海运船期表'!$C$12," : ",TEXT('海运船期表'!$J$12,"MM-DD")," ②",'海运船期表'!$B$13,"-"&'海运船期表'!$C$13," : ",TEXT('海运船期表'!$J$13,"MM-DD")) | BQ10: =CONCATENATE("①："&'海运船期表'!$K$12," ②："&'海运船期表'!$K$13)
B11: 洛杉矶768 | C11: =BM11 | D11: =BN11 | E11: =BO11 | F11: =BP11 | G11: =BQ11 | BL11: 洛杉矶768 | BM11: =IFERROR(IF($E$4="","-",IF(AND($G$4="卡派",$F$4="KG",$C$4="珠三角",$D$4="亚马逊"),CONCATENATE("8KG+："&VLOOKUP("*"&$E$4&"*",'美西普船专线'!$A$7:$D$10,2,0)," 101KG+："&VLOOKUP("*"&$E$4&"*",'美西普船专线'!$A$7:$D$10,3,0)),IF(AND($G$4="卡派",$F$4="KG",$C$4="汕头仓",$D$4="亚马逊"),CONCATENATE("8KG+："&VLOOKUP("*"&$E$4&"*",'美西普船专线'!$A$7:$D$10,2,0)," 101KG+："&VLOOKUP("*"&$E$4&"*",'美西普船专线'!$A$7:$D$10,3,0)),IF(AND($G$4="卡派",$F$4="KG",$C$4="义乌仓",$D$4="亚马逊"),CONCATENATE("8KG+："&VLOOKUP("*"&$E$4&"*",'美西普船专线'!$A$7:$D$10,2,0)," 101KG+："&VLOOKUP("*"&$E$4&"*",'美西普船专线'!$A$7:$D$10,3,0)),IF(AND($G$4="卡派",$F$4="按方不包税",$C$4="珠三角",$D$4="亚马逊"),CONCATENATE("2CBM+："&VLOOKUP("*"&$E$4&"*",'按方不包税'!$A$54:$E$55,2,0)),IF(AND($G$4="卡派",$F$4="按方不包税",$C$4="汕头仓",$D$4="亚马逊"),CONCATENATE("2CBM+："&VLOOKUP("*"&$E$4&"*",'按方不包税'!$A$54:$E$55,2,0)),IF(AND($G$4="卡派",$F$4="按方不包税",$C$4="义乌仓",$D$4="亚马逊"),CONCATENATE("2CBM+："&VLOOKUP("*"&$E$4&"*",'按方不包税'!$A$54:$E$55,2,0)),"-"))))))),"-") | BN11: =IFERROR(IF($E$4="","-",IF(AND($G$4="卡派",$F$4="KG",$C$4="珠三角",$D$4="亚马逊"),VLOOKUP("*"&$E$4&"*",'美西普船专线'!$A$7:$D$10,4,0),IF(AND($G$4="卡派",$F$4="KG",$C$4="汕头仓",$D$4="亚马逊"),VLOOKUP("*"&$E$4&"*",'美西普船专线'!$A$7:$D$10,4,0),IF(AND($G$4="卡派",$F$4="KG",$C$4="义乌仓",$D$4="亚马逊"),VLOOKUP("*"&$E$4&"*",'美西普船专线'!$A$7:$D$10,4,0),IF(AND($G$4="卡派",$F$4="按方不包税",$C$4="珠三角",$D$4="亚马逊"),VLOOKUP("*"&$E$4&"*",'按方不包税'!$A$55:$E$56,4,0),IF(AND($G$4="卡派",$F$4="按方不包税",$C$4="汕头仓",$D$4="亚马逊"),VLOOKUP("*"&$E$4&"*",'按方不包税'!$A$55:$E$56,4,0),IF(AND($G$4="卡派",$F$4="按方不包税",$C$4="义乌仓",$D$4="亚马逊"),VLOOKUP("*"&$E$4&"*",'按方不包税'!$A$55:$E$56,4,0),"-"))))))),"-") | BO11: =CONCATENATE("①",'海运船期表'!$B$14,"-"&'海运船期表'!$C$14," : ",TEXT('海运船期表'!$I$14,"MM-DD")," ②",'海运船期表'!$B$15,"-"&'海运船期表'!$C$15," : ",TEXT('海运船期表'!$I$15,"MM-DD")," ③",'海运船期表'!$B$16,"-"&'海运船期表'!$C$16," : ",TEXT('海运船期表'!$I$16,"MM-DD")) | BP11: =CONCATENATE("①",'海运船期表'!$B$14,"-"&'海运船期表'!$C$14," : ",TEXT('海运船期表'!$J$14,"MM-DD")," ②",'海运船期表'!$B$15,"-"&'海运船期表'!$C$15," : ",TEXT('海运船期表'!$J$15,"MM-DD")," ③",'海运船期表'!$B$16,"-"&'海运船期表'!$C$16," : ",TEXT('海运船期表'!$J$16,"MM-DD")) | BQ11: =CONCATENATE("①："&'海运船期表'!$K$14," ②："&'海运船期表'!$K$15," ③："&'海运船期表'!$K$16)
B12: 西雅图788 | C12: =BM12 | D12: =BN12 | E12: =BO12 | F12: =BP12 | G12: =BQ12 | BL12: 西雅图788 | BM12: =IFERROR(IF($E$4="","-",IF(AND($G$4="卡派",$F$4="KG",$C$4="珠三角",$D$4="亚马逊"),CONCATENATE("8KG+："&VLOOKUP("*"&$E$4&"*",'美西普船专线'!$K$7:$N$10,2,0)," 101KG+："&VLOOKUP("*"&$E$4&"*",'美西普船专线'!$K$7:$N$10,3,0)),IF(AND($G$4="卡派",$F$4="KG",$C$4="汕头仓",$D$4="亚马逊"),CONCATENATE("8KG+："&VLOOKUP("*"&$E$4&"*",'美西普船专线'!$K$7:$N$10,2,0)," 101KG+："&VLOOKUP("*"&$E$4&"*",'美西普船专线'!$K$7:$N$10,3,0)),IF(AND($G$4="卡派",$F$4="KG",$C$4="义乌仓",$D$4="亚马逊"),CONCATENATE("8KG+："&VLOOKUP("*"&$E$4&"*",'美西普船专线'!$K$7:$N$10,2,0)," 101KG+："&VLOOKUP("*"&$E$4&"*",'美西普船专线'!$K$7:$N$10,3,0)),IF(AND($G$4="卡派",$F$4="按方不包税",$C$4="珠三角",$D$4="亚马逊"),CONCATENATE("2CBM+："&VLOOKUP("*"&$E$4&"*",'按方不包税'!$A$71:$E$74,2,0)),IF(AND($G$4="卡派",$F$4="按方不包税",$C$4="汕头仓",$D$4="亚马逊"),CONCATENATE("2CBM+："&VLOOKUP("*"&$E$4&"*",'按方不包税'!$A$71:$E$74,2,0)),IF(AND($G$4="卡派",$F$4="按方不包税",$C$4="义乌仓",$D$4="亚马逊"),CONCATENATE("2CBM+："&VLOOKUP("*"&$E$4&"*",'按方不包税'!$A$71:$E$74,2,0)),"-"))))))),"-") | BN12: =IFERROR(IF($E$4="","-",IF(AND($G$4="卡派",$F$4="KG",$C$4="珠三角",$D$4="亚马逊"),VLOOKUP("*"&$E$4&"*",'美西普船专线'!$K$7:$N$10,4,0),IF(AND($G$4="卡派",$F$4="KG",$C$4="汕头仓",$D$4="亚马逊"),VLOOKUP("*"&$E$4&"*",'美西普船专线'!$K$7:$N$10,4,0),IF(AND($G$4="卡派",$F$4="KG",$C$4="义乌仓",$D$4="亚马逊"),VLOOKUP("*"&$E$4&"*",'美西普船专线'!$K$7:$N$10,4,0),IF(AND($G$4="卡派",$F$4="按方不包税KG",$C$4="珠三角",$D$4="亚马逊"),VLOOKUP("*"&$E$4&"*",'按方不包税'!$B$72:$E$75,4,0),IF(AND($G$4="卡派",$F$4="按方不包税",$C$4="汕头仓",$D$4="亚马逊"),VLOOKUP("*"&$E$4&"*",'按方不包税'!$B$72:$E$75,5,0),IF(AND($G$4="卡派",$F$4="按方不包税2CBM+",$C$4="义乌仓",$D$4="亚马逊"),VLOOKUP("*"&$E$4&"*",'按方不包税'!$B$72:$E$75,4,0),"-"))))))),"-") | BO12: =CONCATENATE("①",'海运船期表'!$B$17,"-"&'海运船期表'!$C$17," : ",TEXT('海运船期表'!$I$17,"MM-DD")," ②",'海运船期表'!$B$18,"-"&'海运船期表'!$C$18," : ",TEXT('海运船期表'!$I$18,"MM-DD")) | BP12: =CONCATENATE("①",'海运船期表'!$B$17,"-"&'海运船期表'!$C$17," : ",TEXT('海运船期表'!$J$17,"MM-DD")," ②",'海运船期表'!$B$18,"-"&'海运船期表'!$C$18," : ",TEXT('海运船期表'!$J$18,"MM-DD")) | BQ12: =CONCATENATE("①："&'海运船期表'!$K$17," ②："&'海运船期表'!$K$18)
B13: 芝加哥840 | C13: =BM13 | D13: =BN13 | E13: =BO13 | F13: =BP13 | G13: =BQ13 | BL13: 芝加哥840 | BM13: =IFERROR(IF($E$4="","-",IF(AND($G$4="卡派",$F$4="KG",$C$4="珠三角",$D$4="亚马逊"),CONCATENATE("8KG+："&VLOOKUP("*"&$E$4&"*",'美中普船专线'!$A$7:$D$11,2,0)," 101KG+："&VLOOKUP("*"&$E$4&"*",'美中普船专线'!$A$7:$D$11,3,0)),IF(AND($G$4="卡派",$F$4="KG",$C$4="汕头仓",$D$4="亚马逊"),CONCATENATE("8KG+："&VLOOKUP("*"&$E$4&"*",'美中普船专线'!$A$7:$D$11,2,0)," 101KG+："&VLOOKUP("*"&$E$4&"*",'美中普船专线'!$A$7:$D$11,3,0)),IF(AND($G$4="卡派",$F$4="KG",$C$4="义乌仓",$D$4="亚马逊"),CONCATENATE("8KG+："&VLOOKUP("*"&$E$4&"*",'美中普船专线'!$A$7:$D$11,3,0)," 101KG+："&VLOOKUP("*"&$E$4&"*",'美中普船专线'!$A$7:$D$11,3,0)),IF(AND($G$4="卡派",$F$4="按方不包税",$C$4="珠三角",$D$4="亚马逊"),CONCATENATE("2CBM+："&VLOOKUP("*"&$E$4&"*",'按方不包税'!$A$80:$E$82,2,0)),IF(AND($G$4="卡派",$F$4="按方不包税",$C$4="汕头仓",$D$4="亚马逊"),CONCATENATE("2CBM+："&VLOOKUP("*"&$E$4&"*",'按方不包税'!$A$80:$E$82,2,0)),IF(AND($G$4="卡派",$F$4="按方不包税",$C$4="义乌仓",$D$4="亚马逊"),CONCATENATE("2CBM+："&VLOOKUP("*"&$E$4&"*",'按方不包税'!$A$80:$E$82,2,0)),IF(AND($G$4="卡派",$F$4="KG",$C$4="珠三角",$D$4="沃尔玛专线"),CONCATENATE("501KG+："&VLOOKUP("*"&$E$4&"*",'沃尔玛专线'!$A$14:$G$16,4,0)," 3001KG+："&VLOOKUP("*"&$E$4&"*",'沃尔玛专线'!$A$14:$G$16,5,0)," 5001KG+："&VLOOKUP("*"&$E$4&"*",'沃尔玛专线'!$A$14:$G$16,6,0)),IF(AND($G$4="卡派",$F$4="KG",$C$4="汕头仓",$D$4="沃尔玛专线"),CONCATENATE("501kg+："&VLOOKUP("*"&$E$4&"*",'沃尔玛专线'!$A$14:$G$16,7,0)," 3001kg+："&VLOOKUP("*"&$E$4&"*",'沃尔玛专线'!$A$14:$G$16,8,0)," 5001kg+："&VLOOKUP("*"&$E$4&"*",'沃尔玛专线'!$A$14:$G$16,9,0)),IF(AND($G$4="卡派",$F$4="KG",$C$4="义乌仓",$D$4="沃尔玛专线"),CONCATENATE("501KG+："&VLOOKUP("*"&$E$4&"*",'沃尔玛专线'!$A$14:$G$16,10,0)," 3001KG+："&VLOOKUP("*"&$E$4&"*",'沃尔玛专线'!$A$14:$G$16,11,0)," 5001KG+："&VLOOKUP("*"&$E$4&"*",'沃尔玛专线'!$A$14:$G$16,12,0)),"-")))))))))),"-") | BN13: =IFERROR(IF($E$4="","-",IF(AND($G$4="卡派",$F$4="KG",$C$4="珠三角",$D$4="亚马逊"),VLOOKUP("*"&$E$4&"*",'美中普船专线'!$A$7:$D$11,4,0),IF(AND($G$4="卡派",$F$4="KG",$C$4="汕头仓",$D$4="亚马逊"),VLOOKUP("*"&$E$4&"*",'美中普船专线'!$A$7:$D$11,4,0),IF(AND($G$4="卡派",$F$4="KG",$C$4="义乌仓",$D$4="亚马逊"),VLOOKUP("*"&$E$4&"*",'美中普船专线'!$A$7:$D$11,4,0),IF(AND($G$4="卡派",$F$4="按方不包税",$C$4="珠三角",$D$4="亚马逊"),VLOOKUP("*"&$E$4&"*",'按方不包税'!$A$81:$E$83,4,0),IF(AND($G$4="卡派",$F$4="按方不包税",$C$4="汕头仓",$D$4="亚马逊"),VLOOKUP("*"&$E$4&"*",'按方不包税'!$A$81:$E$83,4,0),IF(AND($G$4="卡派",$F$4="按方不包税",$C$4="义乌仓",$D$4="亚马逊"),VLOOKUP("*"&$E$4&"*",'按方不包税'!$A$81:$E$83,4,0),IF(AND($G$4="卡派",$F$4="KG",$C$4="珠三角",$D$4="沃尔玛专线"),VLOOKUP("*"&$E$4&"*",'沃尔玛专线'!$A$14:$G$16,7,0),IF(AND($G$4="卡派",$F$4="KG",$C$4="汕头仓",$D$4="沃尔玛专线"),VLOOKUP("*"&$E$4&"*",'沃尔玛专线'!$A$14:$G$16,7,0),IF(AND($G$4="卡派",$F$4="KG",$C$4="义乌仓",$D$4="沃尔玛专线"),VLOOKUP("*"&$E$4&"*",'沃尔玛专线'!$A$14:$G$16,7,0),"-")))))))))),"-") | BO13: =CONCATENATE("①",'海运船期表'!$B$19,"-"&'海运船期表'!$C$19," : ",TEXT('海运船期表'!$I$19,"MM-DD")," ②",'海运船期表'!$B$20,"-"&'海运船期表'!$C$20," : ",TEXT('海运船期表'!$I$20,"MM-DD")) | BP13: =CONCATENATE("①",'海运船期表'!$B$19,"-"&'海运船期表'!$C$19," : ",TEXT('海运船期表'!$J$19,"MM-DD")," ②",'海运船期表'!$B$20,"-"&'海运船期表'!$C$20," : ",TEXT('海运船期表'!$J$20,"MM-DD")) | BQ13: =CONCATENATE("①："&'海运船期表'!$K$19," ②："&'海运船期表'!$K$20)
B14: 休斯顿866 | C14: =BM14 | D14: =BN14 | E14: =BO14 | F14: =BP14 | G14: =BQ14 | BL14: 休斯顿866 | BM14: =IFERROR(IF($E$4="","-",IF(AND($G$4="卡派",$F$4="KG",$C$4="珠三角",$D$4="亚马逊"),CONCATENATE("8KG+："&VLOOKUP("*"&$E$4&"*",'美中普船专线'!$F$7:$I$11,2,0)," 101KG+："&VLOOKUP("*"&$E$4&"*",'美中普船专线'!$F$7:$I$11,3,0)),IF(AND($G$4="卡派",$F$4="KG",$C$4="汕头仓",$D$4="亚马逊"),CONCATENATE("8KG+："&VLOOKUP("*"&$E$4&"*",'美中普船专线'!$F$7:$I$11,2,0)," 101KG+："&VLOOKUP("*"&$E$4&"*",'美中普船专线'!$F$7:$I$11,3,0)),IF(AND($G$4="卡派",$F$4="KG",$C$4="义乌仓",$D$4="亚马逊"),CONCATENATE("8KG+："&VLOOKUP("*"&$E$4&"*",'美中普船专线'!$F$7:$I$11,2,0)," 101KG+："&VLOOKUP("*"&$E$4&"*",'美中普船专线'!$F$7:$I$11,3,0)),IF(AND($G$4="卡派",$F$4="按方不包税",$C$4="珠三角",$D$4="亚马逊"),CONCATENATE("2CBM+："&VLOOKUP("*"&$E$4&"*",'按方不包税'!$A$89:$E$91,2,0)),IF(AND($G$4="卡派",$F$4="按方不包税",$C$4="汕头仓",$D$4="亚马逊"),CONCATENATE("2CBM+："&VLOOKUP("*"&$E$4&"*",'按方不包税'!$A$89:$E$91,2,0)),IF(AND($G$4="卡派",$F$4="按方不包税",$C$4="义乌仓",$D$4="亚马逊"),CONCATENATE("2CBM+："&VLOOKUP("*"&$E$4&"*",'按方不包税'!$A$89:$E$91,3,0)),IF(AND($G$4="卡派",$F$4="KG",$C$4="珠三角",$D$4="沃尔玛专线"),CONCATENATE("501KG+："&VLOOKUP("*"&$E$4&"*",'沃尔玛专线'!$A$17:$G$17,4,0)," 3001KG+："&VLOOKUP("*"&$E$4&"*",'沃尔玛专线'!$A$17:$G$17,5,0)," 5001KG+："&VLOOKUP("*"&$E$4&"*",'沃尔玛专线'!$A$17:$G$17,6,0)),IF(AND($G$4="卡派",$F$4="KG",$C$4="汕头仓",$D$4="沃尔玛专线"),CONCATENATE("501kg+："&VLOOKUP("*"&$E$4&"*",'沃尔玛专线'!$A$17:$G$17,4,0)," 3001kg+："&VLOOKUP("*"&$E$4&"*",'沃尔玛专线'!$A$17:$G$17,5,0)," 5001kg+："&VLOOKUP("*"&$E$4&"*",'沃尔玛专线'!$A$17:$G$17,6,0)),IF(AND($G$4="卡派",$F$4="KG",$C$4="义乌仓",$D$4="沃尔玛专线"),CONCATENATE("501KG+："&VLOOKUP("*"&$E$4&"*",'沃尔玛专线'!$A$17:$G$17,4,0)," 3001KG+："&VLOOKUP("*"&$E$4&"*",'沃尔玛专线'!$A$17:$G$17,5,0)," 5001KG+："&VLOOKUP("*"&$E$4&"*",'沃尔玛专线'!$A$17:$G$17,6,0)),"-")))))))))),"-") | BN14: =IFERROR(IF($E$4="","-",IF(AND($G$4="卡派",$F$4="KG",$C$4="珠三角",$D$4="亚马逊"),VLOOKUP("*"&$E$4&"*",'美中普船专线'!$F$7:$I$11,4,0),IF(AND($G$4="卡派",$F$4="KG",$C$4="汕头仓",$D$4="亚马逊"),VLOOKUP("*"&$E$4&"*",'美中普船专线'!$F$7:$I$11,4,0),IF(AND($G$4="卡派",$F$4="KG",$C$4="义乌仓",$D$4="亚马逊"),VLOOKUP("*"&$E$4&"*",'美中普船专线'!$F$7:$I$11,4,0),IF(AND($G$4="卡派",$F$4="按方不包税",$C$4="珠三角",$D$4="亚马逊"),VLOOKUP("*"&$E$4&"*",'按方不包税'!$A$90:$E$92,4,0),IF(AND($G$4="卡派",$F$4="按方不包税",$C$4="汕头仓",$D$4="亚马逊"),VLOOKUP("*"&$E$4&"*",'按方不包税'!$A$90:$E$92,4,0),IF(AND($G$4="卡派",$F$4="按方不包税",$C$4="义乌仓",$D$4="亚马逊"),VLOOKUP("*"&$E$4&"*",'按方不包税'!$A$90:$E$92,4,0),IF(AND($G$4="卡派",$F$4="KG",$C$4="珠三角",$D$4="沃尔玛专线"),VLOOKUP("*"&$E$4&"*",'沃尔玛专线'!$A$17:$G$17,7,0),IF(AND($G$4="卡派",$F$4="KG",$C$4="汕头仓",$D$4="沃尔玛专线"),VLOOKUP("*"&$E$4&"*",'沃尔玛专线'!$A$17:$G$17,7,0),IF(AND($G$4="卡派",$F$4="KG",$C$4="义乌仓",$D$4="沃尔玛专线"),VLOOKUP("*"&$E$4&"*",'沃尔玛专线'!$A$17:$G$17,7,0),"-")))))))))),"-") | BO14: =CONCATENATE("①",'海运船期表'!$B$21,"-"&'海运船期表'!$C$21," : ",TEXT('海运船期表'!$I$21,"MM-DD")," ②",'海运船期表'!$B$22,"-"&'海运船期表'!$C$22," : ",TEXT('海运船期表'!$I$22,"MM-DD")) | BP14: =CONCATENATE("①",'海运船期表'!$B$21,"-"&'海运船期表'!$C$21," : ",TEXT('海运船期表'!$J$21,"MM-DD")," ②",'海运船期表'!$B$22,"-"&'海运船期表'!$C$22," : ",TEXT('海运船期表'!$J$22,"MM-DD")) | BQ14: =CONCATENATE("①："&'海运船期表'!$K$21," ②："&'海运船期表'!$K$22)
B15: 萨凡纳888 | C15: =BM15 | D15: =BN15 | E15: =BO15 | F15: =BP15 | G15: =BQ15 | BL15: 萨凡纳888 | BM15: =IFERROR(IF($E$4="","-",IF(AND($G$4="卡派",$F$4="KG",$C$4="珠三角",$D$4="亚马逊"),CONCATENATE("8KG+："&VLOOKUP("*"&$E$4&"*",'美东普船专线'!$A$7:$D$12,2,0)," 101KG+："&VLOOKUP("*"&$E$4&"*",'美东普船专线'!$A$7:$D$12,3,0)),IF(AND($G$4="卡派",$F$4="KG",$C$4="汕头仓",$D$4="亚马逊"),CONCATENATE("8KG+："&VLOOKUP("*"&$E$4&"*",'美东普船专线'!$A$7:$D$12,2,0)," 101KG+："&VLOOKUP("*"&$E$4&"*",'美东普船专线'!$A$7:$D$12,3,0)),IF(AND($G$4="卡派",$F$4="KG",$C$4="义乌仓",$D$4="亚马逊"),CONCATENATE("8KG+："&VLOOKUP("*"&$E$4&"*",'美东普船专线'!$A$7:$D$12,2,0)," 101KG+："&VLOOKUP("*"&$E$4&"*",'美东普船专线'!$A$7:$D$12,3,0)),IF(AND($G$4="卡派",$F$4="按方不包税",$C$4="珠三角",$D$4="亚马逊"),CONCATENATE("2CBM+："&VLOOKUP("*"&$E$4&"*",'按方不包税'!$A$98:$E$100,2,0)),IF(AND($G$4="卡派",$F$4="按方不包税",$C$4="汕头仓",$D$4="亚马逊"),CONCATENATE("2CBM+："&VLOOKUP("*"&$E$4&"*",'按方不包税'!$A$98:$E$100,2,0)),IF(AND($G$4="卡派",$F$4="按方不包税",$C$4="义乌仓",$D$4="亚马逊"),CONCATENATE("2CBM+："&VLOOKUP("*"&$E$4&"*",'按方不包税'!$A$98:$E$100,2,0)),"-"))))))),"-") | BN15: =IFERROR(IF($E$4="","-",IF(AND($G$4="卡派",$F$4="KG",$C$4="珠三角",$D$4="亚马逊"),VLOOKUP("*"&$E$4&"*",'美东普船专线'!$A$7:$D$12,4,0),IF(AND($G$4="卡派",$F$4="KG",$C$4="汕头仓",$D$4="亚马逊"),VLOOKUP("*"&$E$4&"*",'美东普船专线'!$A$7:$D$12,4,0),IF(AND($G$4="卡派",$F$4="KG",$C$4="义乌仓",$D$4="亚马逊"),VLOOKUP("*"&$E$4&"*",'美东普船专线'!$A$7:$D$12,4,0),IF(AND($G$4="卡派",$F$4="按方不包税",$C$4="珠三角",$D$4="亚马逊"),VLOOKUP("*"&$E$4&"*",'按方不包税'!$A$98:$E$100,4,0),IF(AND($G$4="卡派",$F$4="按方不包税",$C$4="汕头仓",$D$4="亚马逊"),VLOOKUP("*"&$E$4&"*",'按方不包税'!$A$98:$E$100,4,0),IF(AND($G$4="卡派",$F$4="按方不包税",$C$4="义乌仓",$D$4="亚马逊"),VLOOKUP("*"&$E$4&"*",'按方不包税'!$A$98:$E$100,4,0),"-"))))))),"-") | BO15: =CONCATENATE("①",'海运船期表'!$B$23,"-"&'海运船期表'!$C$23," : ",TEXT('海运船期表'!$I$23,"MM-DD")," ②",'海运船期表'!$B$24,"-"&'海运船期表'!$C$24," : ",TEXT('海运船期表'!$I$24,"MM-DD")) | BP15: =CONCATENATE("①",'海运船期表'!$B$23,"-"&'海运船期表'!$C$23," : ",TEXT('海运船期表'!$J$23,"MM-DD")," ②",'海运船期表'!$B$24,"-"&'海运船期表'!$C$24," : ",TEXT('海运船期表'!$J$24,"MM-DD")) | BQ15: =CONCATENATE("①："&'海运船期表'!$K$23," ②："&'海运船期表'!$K$24)
B16: 纽约960 | C16: =BM16 | D16: =BN16 | E16: =BO16 | F16: =BP16 | G16: =BQ16 | BL16: 纽约960 | BM16: =IFERROR(IF($E$4="","-",IF(AND($G$4="卡派",$F$4="KG",$C$4="珠三角",$D$4="亚马逊"),CONCATENATE("8KG+："&VLOOKUP("*"&$E$4&"*",'美东普船专线'!$F$7:$I$13,2,0)," 101KG+："&VLOOKUP("*"&$E$4&"*",'美东普船专线'!$F$7:$I$13,3,0)),IF(AND($G$4="卡派",$F$4="KG",$C$4="汕头仓",$D$4="亚马逊"),CONCATENATE("8KG+："&VLOOKUP("*"&$E$4&"*",'美东普船专线'!$F$7:$I$13,2,0)," 101KG+："&VLOOKUP("*"&$E$4&"*",'美东普船专线'!$F$7:$I$13,3,0)),IF(AND($G$4="卡派",$F$4="KG",$C$4="义乌仓",$D$4="亚马逊"),CONCATENATE("8KG+："&VLOOKUP("*"&$E$4&"*",'美东普船专线'!$F$7:$I$13,2,0)," 101KG+："&VLOOKUP("*"&$E$4&"*",'美东普船专线'!$F$7:$I$13,3,0)),IF(AND($G$4="卡派",$F$4="按方不包税",$C$4="珠三角",$D$4="亚马逊"),CONCATENATE("2BCM+："&VLOOKUP("*"&$E$4&"*",'按方不包税'!$A$104:$E$109,2,0)),IF(AND($G$4="卡派",$F$4="按方不包税",$C$4="汕头仓",$D$4="亚马逊"),CONCATENATE("2BCM+："&VLOOKUP("*"&$E$4&"*",'按方不包税'!$A$104:$E$109,2,0)),IF(AND($G$4="卡派",$F$4="按方不包税",$C$4="义乌仓",$D$4="亚马逊"),CONCATENATE("2BCM+："&VLOOKUP("*"&$E$4&"*",'按方不包税'!$A$104:$E$109,2,0)),IF(AND($G$4="卡派",$F$4="KG",$C$4="珠三角",$D$4="沃尔玛专线"),CONCATENATE("501KG+："&VLOOKUP("*"&$E$4&"*",'沃尔玛专线'!$A$20:$G$22,4,0)," 3001KG+："&VLOOKUP("*"&$E$4&"*",'沃尔玛专线'!$A$20:$G$22,5,0)," 5001KG+："&VLOOKUP("*"&$E$4&"*",'沃尔玛专线'!$A$20:$G$22,6,0)),IF(AND($G$4="卡派",$F$4="KG",$C$4="汕头仓",$D$4="沃尔玛专线"),CONCATENATE("501KG+："&VLOOKUP("*"&$E$4&"*",'沃尔玛专线'!$A$20:$G$22,4,0)," 3001KG+："&VLOOKUP("*"&$E$4&"*",'沃尔玛专线'!$A$20:$G$22,5,0)," 5001KG+："&VLOOKUP("*"&$E$4&"*",'沃尔玛专线'!$A$20:$G$22,6,0)),IF(AND($G$4="卡派",$F$4="KG",$C$4="义乌仓",$D$4="沃尔玛专线"),CONCATENATE("501KG+："&VLOOKUP("*"&$E$4&"*",'沃尔玛专线'!$A$20:$G$22,4,0)," 3001KG+："&VLOOKUP("*"&$E$4&"*",'沃尔玛专线'!$A$20:$G$22,5,0)," 5001KG+："&VLOOKUP("*"&$E$4&"*",'沃尔玛专线'!$A$20:$G$22,5,0)),IF(AND($G$4="快递派",$F$4="KG",$C$4="珠三角",$D$4="亚马逊"),CONCATENATE("12KG+："&VLOOKUP("*"&$E$4&"*",'海运快递派'!$A$37:$F$38,3,0)," 51KG+："&VLOOKUP("*"&$E$4&"*",'海运快递派'!$A$37:$F$38,4,0)," 101KG+："&VLOOKUP("*"&$E$4&"*",'海运快递派'!$A$37:$F$38,5,0)),IF(AND($G$4="快递派",$F$4="KG",$C$4="汕头仓",$D$4="亚马逊"),CONCATENATE("12KG+："&VLOOKUP("*"&$E$4&"*",'海运快递派'!$A$37:$F$38,3,0)," 51KG+："&VLOOKUP("*"&$E$4&"*",'海运快递派'!$A$37:$F$38,4,0)," 101KG+："&VLOOKUP("*"&$E$4&"*",'海运快递派'!$A$37:$F$38,5,0)),IF(AND($G$4="快递派",$F$4="KG",$C$4="义乌仓",$D$4="亚马逊"),CONCATENATE("12KG+："&VLOOKUP("*"&$E$4&"*",'海运快递派'!$A$37:$F$38,3,0)," 51KG+："&VLOOKUP("*"&$E$4&"*",'海运快递派'!$A$37:$F$38,4,0)," 101KG+："&VLOOKUP("*"&$E$4&"*",'海运快递派'!$A$37:$F$38,5,0)),"-"))))))))))))),"-") | BN16: =IFERROR(IF($E$4="","-",IF(AND($G$4="卡派",$F$4="KG",$C$4="珠三角",$D$4="亚马逊"),VLOOKUP("*"&$E$4&"*",'美东普船专线'!$F$7:$I$14,4,0),IF(AND($G$4="卡派",$F$4="KG",$C$4="汕头仓",$D$4="亚马逊"),VLOOKUP("*"&$E$4&"*",'美东普船专线'!$F$7:$I$14,4,0),IF(AND($G$4="卡派",$F$4="KG",$C$4="义乌仓",$D$4="亚马逊"),VLOOKUP("*"&$E$4&"*",'美东普船专线'!$F$7:$I$14,4,0),IF(AND($G$4="卡派",$F$4="按方不包税",$C$4="珠三角",$D$4="亚马逊"),VLOOKUP("*"&$E$4&"*",'按方不包税'!$A$104:$E$110,4,0),IF(AND($G$4="卡派",$F$4="按方不包税",$C$4="汕头仓",$D$4="亚马逊"),VLOOKUP("*"&$E$4&"*",'按方不包税'!$A$104:$E$110,4,0),IF(AND($G$4="卡派",$F$4="按方不包税",$C$4="义乌仓",$D$4="亚马逊"),VLOOKUP("*"&$E$4&"*",'按方不包税'!$A$104:$E$110,4,0),IF(AND($G$4="卡派",$F$4="KG",$C$4="珠三角",$D$4="沃尔玛专线"),VLOOKUP("*"&$E$4&"*",'沃尔玛专线'!$A$20:$G$22,7,0),IF(AND($G$4="卡派",$F$4="KG",$C$4="汕头仓",$D$4="沃尔玛专线"),VLOOKUP("*"&$E$4&"*",'沃尔玛专线'!$A$20:$G$22,7,0),IF(AND($G$4="卡派",$F$4="KG",$C$4="义乌仓",$D$4="沃尔玛专线"),VLOOKUP("*"&$E$4&"*",'沃尔玛专线'!$A$20:$G$22,7,0),IF(AND($G$4="快递派",$F$4="KG",$C$4="珠三角",$D$4="亚马逊"),VLOOKUP("*"&$E$4&"*",'海运快递派'!$A$37:$F$38,6,0),IF(AND($G$4="快递派",$F$4="KG",$C$4="汕头仓",$D$4="亚马逊"),VLOOKUP("*"&$E$4&"*",'海运快递派'!$A$37:$F$38,6,0),IF(AND($G$4="快递派",$F$4="KG",$C$4="义乌仓",$D$4="亚马逊"),VLOOKUP("*"&$E$4&"*",'海运快递派'!$A$37:$F$38,6,0),"-"))))))))))))),"-") | BO16: =CONCATENATE("①",'海运船期表'!$B$25,"-"&'海运船期表'!$C$25," : ",TEXT('海运船期表'!$I$25,"MM-DD")," ②",'海运船期表'!$B$26,"-"&'海运船期表'!$C$26," : ",TEXT('海运船期表'!$I$26,"MM-DD")) | BP16: =CONCATENATE("①",'海运船期表'!$B$25,"-"&'海运船期表'!$C$25," : ",TEXT('海运船期表'!$J$25,"MM-DD")," ②",'海运船期表'!$B$26,"-"&'海运船期表'!$C$26," : ",TEXT('海运船期表'!$J$26,"MM-DD")) | BQ16: =CONCATENATE("①："&'海运船期表'!$K$25," ②："&'海运船期表'!$K$26)
B17: TY720-玩具专线 | C17: =BM17 | D17: =BN17 | E17: =BO17 | F17: =BP17 | G17: =BQ17 | BL17: TY720 | BM17: =IFERROR(IF($E$4="","-",IF(AND($G$4="卡派",$F$4="KG",$C$4="珠三角",$D$4="亚马逊"),CONCATENATE("8KG+："&VLOOKUP("*"&$E$4&"*",'普船玩具专线'!$A$5:$D$10,2,0)," 101KG+："&VLOOKUP("*"&$E$4&"*",'普船玩具专线'!$A$5:$D$10,3,0)),IF(AND($G$4="卡派",$F$4="KG",$C$4="汕头仓",$D$4="亚马逊"),CONCATENATE("8KG+："&VLOOKUP("*"&$E$4&"*",'普船玩具专线'!$A$5:$D$10,2,0)," 101KG+："&VLOOKUP("*"&$E$4&"*",'普船玩具专线'!$A$5:$D$10,3,0)),IF(AND($G$4="卡派",$F$4="KG",$C$4="义乌仓",$D$4="亚马逊"),CONCATENATE("8KG+："&VLOOKUP("*"&$E$4&"*",'普船玩具专线'!$A$5:$D$10,2,0)," 101KG+："&VLOOKUP("*"&$E$4&"*",'普船玩具专线'!$A$5:$D$10,3,0)),"-")))),"-") | BN17: =IFERROR(IF($E$4="","-",IF(AND($G$4="卡派",$F$4="KG",$C$4="珠三角",$D$4="亚马逊"),VLOOKUP("*"&$E$4&"*",'普船玩具专线'!$A$5:$D$10,4,0),IF(AND($G$4="卡派",$F$4="KG",$C$4="汕头仓",$D$4="亚马逊"),VLOOKUP("*"&$E$4&"*",'普船玩具专线'!$A$5:$D$10,4,0),IF(AND($G$4="卡派",$F$4="KG",$C$4="义乌仓",$D$4="亚马逊"),VLOOKUP("*"&$E$4&"*",'普船玩具专线'!$A$5:$D$10,4,0),"-")))),"-") | BO17: =CONCATENATE("①",'海运船期表'!$B$10,"-"&'海运船期表'!$C$10," : ",TEXT('海运船期表'!$I$10,"MM-DD")," ②",'海运船期表'!$B$11,"-"&'海运船期表'!$C$11," : ",TEXT('海运船期表'!$I$11,"MM-DD")) | BP17: =CONCATENATE("①",'海运船期表'!$B$10,"-"&'海运船期表'!$C$10," : ",TEXT('海运船期表'!$J$7,"MM-DD")," ②",'海运船期表'!$B$11,"-"&'海运船期表'!$C$11," : ",TEXT('海运船期表'!$J$11,"MM-DD")) | BQ17: =CONCATENATE("①："&'海运船期表'!$K$10," ②："&'海运船期表'!$K$11)
B18: 奥克兰744-玩具专线 | C18: =BM18 | D18: =BN18 | E18: =BO18 | F18: =BP18 | G18: =BQ18 | BL18: 奥克兰744 | BM18: =IFERROR(IF($E$4="","-",IF(AND($G$4="卡派",$F$4="KG",$C$4="珠三角",$D$4="亚马逊"),CONCATENATE("8KG+："&VLOOKUP("*"&$E$4&"*",'普船玩具专线'!$A$15:$D$17,2,0)," 101KG+："&VLOOKUP("*"&$E$4&"*",'普船玩具专线'!$A$15:$D$17,3,0)),IF(AND($G$4="卡派",$F$4="KG",$C$4="汕头仓",$D$4="亚马逊"),CONCATENATE("8KG+："&VLOOKUP("*"&$E$4&"*",'普船玩具专线'!$A$15:$D$17,2,0)," 101KG+："&VLOOKUP("*"&$E$4&"*",'普船玩具专线'!$A$15:$D$17,3,0)),IF(AND($G$4="卡派",$F$4="KG",$C$4="义乌仓",$D$4="亚马逊"),CONCATENATE("8KG+："&VLOOKUP("*"&$E$4&"*",'普船玩具专线'!$A$15:$D$17,2,0)," 101KG+："&VLOOKUP("*"&$E$4&"*",'普船玩具专线'!$A$15:$D$17,3,0)),"-")))),"-") | BN18: =IFERROR(IF($E$4="","-",IF(AND($G$4="卡派",$F$4="KG",$C$4="珠三角",$D$4="亚马逊"),VLOOKUP("*"&$E$4&"*",'普船玩具专线'!$A$15:$D$17,4,0),IF(AND($G$4="卡派",$F$4="KG",$C$4="汕头仓",$D$4="亚马逊"),VLOOKUP("*"&$E$4&"*",'普船玩具专线'!$A$15:$D$17,4,0),IF(AND($G$4="卡派",$F$4="KG",$C$4="义乌仓",$D$4="亚马逊"),VLOOKUP("*"&$E$4&"*",'普船玩具专线'!$A$15:$D$17,4,0),"-")))),"-") | BO18: =CONCATENATE("①",'海运船期表'!$B$12,"-"&'海运船期表'!$C$12," : ",TEXT('海运船期表'!$I$12,"MM-DD")," ②",'海运船期表'!$B$13,"-"&'海运船期表'!$C$13," : ",TEXT('海运船期表'!$I$13,"MM-DD")) | BP18: =CONCATENATE("①",'海运船期表'!$B$12,"-"&'海运船期表'!$C$12," : ",TEXT('海运船期表'!$J$12,"MM-DD")," ②",'海运船期表'!$B$13,"-"&'海运船期表'!$C$13," : ",TEXT('海运船期表'!$J$13,"MM-DD")) | BQ18: =CONCATENATE("①："&'海运船期表'!$K$12," ②："&'海运船期表'!$K$13)
B19: 芝加哥840-玩具专线 | C19: =BM19 | D19: =BN19 | E19: =BO19 | F19: =BP19 | G19: =BQ19 | BL19: 芝加哥840 | BM19: =IFERROR(IF($E$4="","-",IF(AND($G$4="卡派",$F$4="KG",$C$4="珠三角",$D$4="亚马逊"),CONCATENATE("8KG+："&VLOOKUP("*"&$E$4&"*",'普船玩具专线'!$A$22:$D$25,2,0)," 101KG+："&VLOOKUP("*"&$E$4&"*",'普船玩具专线'!$A$22:$D$25,3,0)),IF(AND($G$4="卡派",$F$4="KG",$C$4="汕头仓",$D$4="亚马逊"),CONCATENATE("8KG+："&VLOOKUP("*"&$E$4&"*",'普船玩具专线'!$A$22:$D$25,2,0)," 101KG+："&VLOOKUP("*"&$E$4&"*",'普船玩具专线'!$A$22:$D$25,3,0)),IF(AND($G$4="卡派",$F$4="KG",$C$4="义乌仓",$D$4="亚马逊"),CONCATENATE("8KG+："&VLOOKUP("*"&$E$4&"*",'普船玩具专线'!$A$22:$D$25,2,0)," 101KG+："&VLOOKUP("*"&$E$4&"*",'普船玩具专线'!$A$22:$D$25,3,0)),"-")))),"-") | BN19: =IFERROR(IF($E$4="","-",IF(AND($G$4="卡派",$F$4="KG",$C$4="珠三角",$D$4="亚马逊"),VLOOKUP("*"&$E$4&"*",'普船玩具专线'!$A$22:$D$25,4,0),IF(AND($G$4="卡派",$F$4="KG",$C$4="汕头仓",$D$4="亚马逊"),VLOOKUP("*"&$E$4&"*",'普船玩具专线'!$A$22:$D$25,4,0),IF(AND($G$4="卡派",$F$4="KG",$C$4="义乌仓",$D$4="亚马逊"),VLOOKUP("*"&$E$4&"*",'普船玩具专线'!$A$22:$D$25,4,0),"-")))),"-") | BO19: =CONCATENATE("①",'海运船期表'!$B$19,"-"&'海运船期表'!$C$19," : ",TEXT('海运船期表'!$I$19,"MM-DD")," ②",'海运船期表'!$B$20,"-"&'海运船期表'!$C$20," : ",TEXT('海运船期表'!$I$20,"MM-DD")) | BP19: =CONCATENATE("①",'海运船期表'!$B$19,"-"&'海运船期表'!$C$19," : ",TEXT('海运船期表'!$J$19,"MM-DD")," ②",'海运船期表'!$B$20,"-"&'海运船期表'!$C$20," : ",TEXT('海运船期表'!$J$20,"MM-DD")) | BQ19: =CONCATENATE("①："&'海运船期表'!$K$19," ②："&'海运船期表'!$K$20)
B20: 休斯顿866-玩具专线 | C20: =BM20 | D20: =BN20 | E20: =BO20 | F20: =BP20 | G20: =BQ20 | BL20: 休斯顿866 | BM20: =IFERROR(IF($E$4="","-",IF(AND($G$4="卡派",$F$4="KG",$C$4="珠三角",$D$4="亚马逊"),CONCATENATE("8KG+："&VLOOKUP("*"&$E$4&"*",'普船玩具专线'!$A$30:$D$32,2,0)," 101KG+："&VLOOKUP("*"&$E$4&"*",'普船玩具专线'!$A$30:$D$32,3,0)),IF(AND($G$4="卡派",$F$4="KG",$C$4="汕头仓",$D$4="亚马逊"),CONCATENATE("8KG+："&VLOOKUP("*"&$E$4&"*",'普船玩具专线'!$A$30:$D$32,2,0)," 101KG+："&VLOOKUP("*"&$E$4&"*",'普船玩具专线'!$A$30:$D$32,3,0)),IF(AND($G$4="卡派",$F$4="KG",$C$4="义乌仓",$D$4="亚马逊"),CONCATENATE("8KG+："&VLOOKUP("*"&$E$4&"*",'普船玩具专线'!$A$30:$D$32,2,0)," 101KG+："&VLOOKUP("*"&$E$4&"*",'普船玩具专线'!$A$30:$D$32,3,0)),"-")))),"-") | BN20: =IFERROR(IF($E$4="","-",IF(AND($G$4="卡派",$F$4="KG",$C$4="珠三角",$D$4="亚马逊"),VLOOKUP("*"&$E$4&"*",'普船玩具专线'!$A$31:$D$33,4,0),IF(AND($G$4="卡派",$F$4="KG",$C$4="汕头仓",$D$4="亚马逊"),VLOOKUP("*"&$E$4&"*",'普船玩具专线'!$A$31:$D$33,4,0),IF(AND($G$4="卡派",$F$4="KG",$C$4="义乌仓",$D$4="亚马逊"),VLOOKUP("*"&$E$4&"*",'普船玩具专线'!$A$31:$D$33,4,0),"-")))),"-") | BO20: =CONCATENATE("①",'海运船期表'!$B$21,"-"&'海运船期表'!$C$21," : ",TEXT('海运船期表'!$I$21,"MM-DD")," ②",'海运船期表'!$B$22,"-"&'海运船期表'!$C$22," : ",TEXT('海运船期表'!$I$22,"MM-DD")) | BP20: =CONCATENATE("①",'海运船期表'!$B$21,"-"&'海运船期表'!$C$21," : ",TEXT('海运船期表'!$J$21,"MM-DD")," ②",'海运船期表'!$B$22,"-"&'海运船期表'!$C$22," : ",TEXT('海运船期表'!$J$22,"MM-DD")) | BQ20: =CONCATENATE("①："&'海运船期表'!$K$21," ②："&'海运船期表'!$K$22)
B21: 萨凡纳888-玩具专线 | C21: =BM21 | D21: =BN21 | E21: =BO21 | F21: =BP21 | G21: =BQ21 | BL21: 萨凡纳888 | BM21: =IFERROR(IF($E$4="","-",IF(AND($G$4="卡派",$F$4="KG",$C$4="珠三角",$D$4="亚马逊"),CONCATENATE("8KG+："&VLOOKUP("*"&$E$4&"*",'普船玩具专线'!$A$37:$D$39,2,0)," 101KG+："&VLOOKUP("*"&$E$4&"*",'普船玩具专线'!$A$37:$D$39,3,0)),IF(AND($G$4="卡派",$F$4="KG",$C$4="汕头仓",$D$4="亚马逊"),CONCATENATE("8KG+："&VLOOKUP("*"&$E$4&"*",'普船玩具专线'!$A$37:$D$39,2,0)," 101KG+："&VLOOKUP("*"&$E$4&"*",'普船玩具专线'!$A$37:$D$39,3,0)),IF(AND($G$4="卡派",$F$4="KG",$C$4="义乌仓",$D$4="亚马逊"),CONCATENATE("8KG+："&VLOOKUP("*"&$E$4&"*",'普船玩具专线'!$A$37:$D$39,2,0)," 101KG+："&VLOOKUP("*"&$E$4&"*",'普船玩具专线'!$A$37:$D$39,3,0)),"-")))),"-") | BN21: =IFERROR(IF($E$4="","-",IF(AND($G$4="卡派",$F$4="KG",$C$4="珠三角",$D$4="亚马逊"),VLOOKUP("*"&$E$4&"*",'普船玩具专线'!$A$37:$D$39,4,0),IF(AND($G$4="卡派",$F$4="KG",$C$4="汕头仓",$D$4="亚马逊"),VLOOKUP("*"&$E$4&"*",'普船玩具专线'!$A$37:$D$39,4,0),IF(AND($G$4="卡派",$F$4="KG",$C$4="义乌仓",$D$4="亚马逊"),VLOOKUP("*"&$E$4&"*",'普船玩具专线'!$A$37:$D$39,4,0),"-")))),"-") | BO21: =CONCATENATE("①",'海运船期表'!$B$23,"-"&'海运船期表'!$C$23," : ",TEXT('海运船期表'!$I$23,"MM-DD")," ②",'海运船期表'!$B$24,"-"&'海运船期表'!$C$24," : ",TEXT('海运船期表'!$I$24,"MM-DD")) | BP21: =CONCATENATE("①",'海运船期表'!$B$23,"-"&'海运船期表'!$C$23," : ",TEXT('海运船期表'!$J$23,"MM-DD")," ②",'海运船期表'!$B$24,"-"&'海运船期表'!$C$24," : ",TEXT('海运船期表'!$J$24,"MM-DD")) | BQ21: =CONCATENATE("①："&'海运船期表'!$K$23," ②："&'海运船期表'!$K$24)
B22: 纽约960-玩具专线 | C22: =BM22 | D22: =BN22 | E22: =BO22 | F22: =BP22 | G22: =BQ22 | BL22: 纽约960 | BM22: =IFERROR(IF($E$4="","-",IF(AND($G$4="卡派",$F$4="KG",$C$4="珠三角",$D$4="亚马逊"),CONCATENATE("8KG+："&VLOOKUP("*"&$E$4&"*",'普船玩具专线'!$A$44:$D$49,2,0)," 101KG+："&VLOOKUP("*"&$E$4&"*",'普船玩具专线'!$A$44:$D$49,3,0)),IF(AND($G$4="卡派",$F$4="KG",$C$4="汕头仓",$D$4="亚马逊"),CONCATENATE("8KG+："&VLOOKUP("*"&$E$4&"*",'普船玩具专线'!$A$44:$D$49,2,0)," 101KG+："&VLOOKUP("*"&$E$4&"*",'普船玩具专线'!$A$44:$D$49,3,0)),IF(AND($G$4="卡派",$F$4="KG",$C$4="义乌仓",$D$4="亚马逊"),CONCATENATE("8KG+："&VLOOKUP("*"&$E$4&"*",'普船玩具专线'!$A$44:$D$49,3,0)," 101KG+："&VLOOKUP("*"&$E$4&"*",'普船玩具专线'!$A$44:$D$49,3,0)),IF(AND($G$4="快递派",$F$4="KG",$C$4="珠三角",$D$4="亚马逊"),CONCATENATE("12KG+："&VLOOKUP("*"&$E$4&"*",'海运快递派'!$A$37:$F$38,3,0)," 51KG+："&VLOOKUP("*"&$E$4&"*",'海运快递派'!$A$37:$F$38,4,0)," 101KG+："&VLOOKUP("*"&$E$4&"*",'海运快递派'!$A$37:$F$38,5,0)),IF(AND($G$4="快递派",$F$4="KG",$C$4="汕头仓",$D$4="亚马逊"),CONCATENATE("12KG+："&VLOOKUP("*"&$E$4&"*",'海运快递派'!$A$37:$F$38,3,0)," 51KG+："&VLOOKUP("*"&$E$4&"*",'海运快递派'!$A$37:$F$38,4,0)," 101KG+："&VLOOKUP("*"&$E$4&"*",'海运快递派'!$A$37:$F$38,5,0)),IF(AND($G$4="快递派",$F$4="KG",$C$4="义乌仓",$D$4="亚马逊"),CONCATENATE("12KG+："&VLOOKUP("*"&$E$4&"*",'海运快递派'!$A$37:$F$38,3,0)," 51KG+："&VLOOKUP("*"&$E$4&"*",'海运快递派'!$A$37:$F$38,4,0)," 101KG+："&VLOOKUP("*"&$E$4&"*",'海运快递派'!$A$37:$F$38,5,0)),"-"))))))),"-") | BN22: =IFERROR(IF($E$4="","-",IF(AND($G$4="卡派",$F$4="KG",$C$4="珠三角",$D$4="亚马逊"),VLOOKUP("*"&$E$4&"*",'普船玩具专线'!$A$44:$D$49,4,0),IF(AND($G$4="卡派",$F$4="KG",$C$4="汕头仓",$D$4="亚马逊"),VLOOKUP("*"&$E$4&"*",'普船玩具专线'!$A$44:$D$49,4,0),IF(AND($G$4="卡派",$F$4="KG",$C$4="义乌仓",$D$4="亚马逊"),VLOOKUP("*"&$E$4&"*",'普船玩具专线'!$A$44:$D$49,4,0),IF(AND($G$4="快递派",$F$4="KG",$C$4="珠三角",$D$4="亚马逊"),VLOOKUP("*"&$E$4&"*",'海运快递派'!$A$37:$F$38,6,0),IF(AND($G$4="快递派",$F$4="KG",$C$4="汕头仓",$D$4="亚马逊"),VLOOKUP("*"&$E$4&"*",'海运快递派'!$A$37:$F$38,6,0),IF(AND($G$4="快递派",$F$4="KG",$C$4="义乌仓",$D$4="亚马逊"),VLOOKUP("*"&$E$4&"*",'海运快递派'!$A$37:$F$38,6,0),"-"))))))),"-") | BO22: =CONCATENATE("①",'海运船期表'!$B$25,"-"&'海运船期表'!$C$25," : ",TEXT('海运船期表'!$I$25,"MM-DD")," ②",'海运船期表'!$B$26,"-"&'海运船期表'!$C$26," : ",TEXT('海运船期表'!$I$26,"MM-DD")) | BP22: =CONCATENATE("①",'海运船期表'!$B$25,"-"&'海运船期表'!$C$25," : ",TEXT('海运船期表'!$J$25,"MM-DD")," ②",'海运船期表'!$B$26,"-"&'海运船期表'!$C$26," : ",TEXT('海运船期表'!$J$26,"MM-DD")) | BQ22: =CONCATENATE("①："&'海运船期表'!$K$25," ②："&'海运船期表'!$K$26)

Sheet 美西特快专线
A2: 美森360 | I2: 美森432 | P2: EX456
A3: 热门卡派仓 | I3: 热门卡派仓 | P3: 热门卡派仓
B4: 珠三角/汕头交货价 | D4: 义乌交货价 | I4: 珠三角/汕头交货价 | K4: 义乌交货价 | P4: 珠三角/汕头/义乌交货价
A5: 仓库 重量段 | B5: 8KG+ | C5: 101KG+ | D5: 8KG+ | E5: 101KG+ | F5: 参考签收时效 （开船后） | G5: 理赔时效 （开船后第二天算起） | I5: 8KG+ | J5: 101KG+ | K5: 8KG+ | L5: 101KG+ | M5: 签收时效 （开船后） | N5: 理赔时效 （开船后第二天算起） | P5: 8KG+ | Q5: 101KG+ | R5: 签收时效 （开船后） | S5: 理赔时效 （开船后第二天算起）
A6: ONT8,LAX9,LGB8 | B6: 10.5 | C6: 10 | D6: 10.2 | E6: 9.7 | F6: 12-16个自然日 | G6: 13个工作日 | I6: 10.2 | J6: 9.7 | K6: 9.9 | L6: 9.4 | M6: 14-18个自然日 | N6: 15个工作日 | P6: 6.1 | Q6: 5.6 | R6: 16-20个自然日 | S6: 18个工作日
A7: SBD1,POC1,POC3 | B7: 10.8 | C7: 10.3 | D7: 10.5 | E7: 10 | F7: 12-16个自然日 | G7: 14个工作日 | I7: 10.5 | J7: 10 | K7: 10.2 | L7: 9.7 | M7: 14-18个自然日 | N7: 16个工作日 | P7: 6.4 | Q7: 5.9 | R7: 16-20个自然日 | S7: 19个工作日
A8: GYR3,GYR2,LAS1,VGT2,SMF3,SCK4 | B8: 11.3 | C8: 10.8 | D8: 11 | E8: 10.5 | F8: 13-17个自然日 | G8: 15个工作日 | I8: 11 | J8: 10.5 | K8: 10.7 | L8: 10.2 | M8: 15-19个自然日 | N8: 17个工作日 | P8: 6.9 | Q8: 6.4 | R8: 17-21个自然日 | S8: 20个工作日
A9: MIT2,GEU3,GEU5,GEU2,HLI2,TCY1,TCY2 | B9: 11.3 | C9: 10.8 | D9: 11 | E9: 10.5 | F9: 13-17个自然日 | G9: 17个工作日 | I9: 11 | J9: 10.5 | K9: 10.7 | L9: 10.2 | M9: 15-19个自然日 | N9: 19个工作日 | P9: 6.9 | Q9: 6.4 | R9: 17-21个自然日 | S9: 22个工作日
A10: FTW1,ABQ2,IAH3,PSC2 | B10: 13.1 | C10: 12.6 | D10: 12.8 | E10: 12.3 | F10: 15-19个自然日 | G10: 18个工作日 | I10: 12.8 | J10: 12.3 | K10: 12.5 | L10: 12 | M10: 17-21个自然日 | N10: 20个工作日 | P10: 8.6 | Q10: 8.1 | R10: 20-24个自然日 | S10: 23个工作日
A11: MQJ1,MEM1,FWA4,MDW2,IND9 | B11: 13.6 | C11: 13.1 | D11: 13.3 | E11: 12.8 | F11: 16-21个自然日 | G11: 19个工作日 | I11: 13.3 | J11: 12.8 | K11: 13 | L11: 12.5 | M11: 18-23个自然日 | N11: 21个工作日 | P11: 9.1 | Q11: 8.6 | R11: 20-25个自然日 | S11: 24个工作日
A12: CLT2,RDU2 | B12: 14.3 | C12: 13.8 | D12: 14 | E12: 13.5 | F12: 21-26个自然日 | G12: 20个工作日 | I12: 14 | J12: 13.5 | K12: 13.7 | L12: 13.2 | M12: 23-28个自然日 | N12: 22个工作日 | P12: 9.8 | Q12: 9.3 | R12: 25-30个自然日 | S12: 25个工作日
A13: ORF2,RMN3,TEB3,TEB9,ABE8,AVP1,AVP3,SWF1,SWF2 | B13: 14.8 | C13: 14.3 | D13: 14.5 | E13: 14 | F13: 22-27个自然日 | G13: 22个工作日 | I13: 14.5 | J13: 14 | K13: 14.2 | L13: 13.7 | M13: 24-29个自然日 | N13: 24个工作日 | P13: 10.3 | Q13: 9.8 | R13: 26-31个自然日 | S13: 27个工作日
A14: JOT1,POC2,IUSP,IUSQ,IUTI,IUSJ,IUSW,IUTF | B14: 10.8 | C14: 10.3 | D14: 10.5 | E14: 10 | F14: 13-17个自然日 | G14: 不参与时效延误赔付 | I14: 10.5 | J14: 10 | K14: 10.2 | L14: 9.7 | M14: 15-19个自然日 | N14: 不参与时效延误赔付 | P14: 6.4 | Q14: 5.9 | R14: 17-21个自然日 | S14: 不参与时效延误赔付
A15: SCK8,QXY5,QXY8,IUTE,MCC1,PSP3 | B15: 11.3 | C15: 10.8 | D15: 11 | E15: 10.5 | F15: 15-19个自然日 | G15: 不参与时效延误赔付 | I15: 11 | J15: 10.5 | K15: 10.7 | L15: 10.2 | M15: 17-21个自然日 | N15: 不参与时效延误赔付 | P15: 6.9 | Q15: 6.4 | R15: 19-23个自然日 | S15: 不参与时效延误赔付
A16: AMA1,SAT1,SAT4 | B16: 13.1 | C16: 12.6 | D16: 12.8 | E16: 12.3 | F16: 16-20个自然日 | G16: 不参与时效延误赔付 | I16: 12.8 | J16: 12.3 | K16: 12.5 | L16: 12 | M16: 18-22个自然日 | N16: 不参与时效延误赔付 | P16: 8.6 | Q16: 8.1 | R16: 20-24个自然日 | S16: 不参与时效延误赔付
A17: RFD2 | B17: 13.6 | C17: 13.1 | D17: 13.3 | E17: 12.8 | F17: 17-22个自然日 | G17: 不参与时效延误赔付 | I17: 13.3 | J17: 12.8 | K17: 13 | L17: 12.5 | M17: 19-24个自然日 | N17: 不参与时效延误赔付 | P17: 9.1 | Q17: 8.6 | R17: 21-26个自然日 | S17: 不参与时效延误赔付
A18: TPA2,TPA3 | B18: 14.3 | C18: 13.8 | D18: 14 | E18: 13.5 | F18: 22-27个自然日 | G18: 不参与时效延误赔付 | I18: 14 | J18: 13.5 | K18: 13.7 | L18: 13.2 | M18: 24-29个自然日 | N18: 不参与时效延误赔付 | P18: 9.8 | Q18: 9.3 | R18: 26-31个自然日 | S18: 不参与时效延误赔付
A19: 其他未开放卡派仓单询 | I19: 其他未开放卡派仓单询 | P19: 其他未开放卡派仓单询
A20: 飞点旗舰产品，选用美森特快服务，到港48小时内专车提柜送仓。 超承诺时效1/KG/工作日赔付，退完运费为止。 如遇海关查验造成理赔时效延误，直接赔付2元/KG，不再做其他延误赔付。 船舶机械故障延误、车祸、天灾等不可抗拒因素不赔付；FBA爆仓删约、推约、改约、不放约、拒收、PO失效、节假日假期、码头罢工、船司调整船期、航线变更等导致的到港时间延误，赔付时效同步顺延 | I20: 飞点尖端产品，选用美森MAX服务，到港48小时内专车提柜送仓。 超承诺时效1/KG/工作日赔付，封顶赔付5元/KG为止。 如遇海关查验造成理赔时效延误，直接赔付2元/KG，不再做其他延误赔付。 船舶机械故障延误、车祸、天灾等不可抗拒因素不赔付；FBA爆仓删约、推约、改约、不放约、拒收、PO失效、节假日假期、码头罢工、船司调整船期、航线变更等导致的到港时间延误，赔付时效同步顺延 | P20: 华东/华南精品航线渠道，目的港专属车架、专用通道优先提柜，48小时内提柜送仓，时效比肩美森MAX。提供甩柜、时效延误双重理赔服务。 超承诺时效0.5/KG/工作日赔付，封顶赔付3元/KG为止，甩柜赔付1/KG。 如遇海关查验造成理赔时效延误，直接赔付2元/KG，不再做其他延误赔付。 船舶机械故障延误、车祸、天灾等不可抗拒因素不赔付； FBA爆仓删约、推约、改约、不放约、拒收、PO失效、柜子进封闭区、节假日假期、码头罢工、船司调整船期、航线变更等导致的到港时间延误，赔付时效同步顺延
A21: 自2025年5月12日起 符合美国清关第232条款的钢铁制品、铝制品关税附加费加收0.5元/KG；
A22: 需加收产品及杂费 | I22: 加收金额 | L22: 备注
A23: 除高价值，高关税产品，其余普通产品无附加费 | I23: 无附加费 | L23: 由于产品本身专利或知识产权问题产生扣关，货物退回等后续问题由客户承担，我司保留追究的权力。
A24: 木制品、蓝牙产品、激光类产品、UL产品 | I24: +1/KG | L24: FDA类产品，海关可能会查验。由于客户提供错误的FDA ID. 产生扣关，关税，货物退回等后续问题由客户承担，我司并保留追究的权力
A25: 化工品（指甲胶、精油、口红、眼影，卸妆水、洗发水等） | I25: +2/KG | L25: 提供真实有效期内商检、MSDS认证视为普货，无需附加费（证书是否有效以相关部门是否认可为准）
A26: 国内贴标费 | I26: 1元/张 | L26: 为了准确快捷入库，请尽量配合贴好入仓标签/FBA标签/SKU标签等，因未贴标签或未及时告知导致仓库未能及时入库延误船期的我司概不负责
A27: 优势:自主装柜，海运市场优质后端，信誉清关行，快捷海外转运派送。
A28: 注明：每周报价表为实时报价，不可控因素或市场变化调节过大时，升或降以到仓价格为准。
A29: 包税附加费，未列明产品请跟业务联系
A30: 单证报关250/票，单票超5个品名以上+50RMB/个 卡派超限附加费：最长边不可超过120CM,次长边不可超过100CM，超长附加单价*1.1倍计算。单箱实重超过30KG单询
A31: 温馨提示：请按我司提供的样板提供电子版发票和装箱单如实申报，如因申报品名/申报数量/申报单价/申报材质/申报HS等不符造成的清关问题，我司概不负责 （清关延误不算在正常派送日内）

Sheet 美西快船专线
A2: 快船600
A3: 热门卡派仓
B4: 珠三角/汕头/义乌交货价
A5: 仓库 重量段 | B5: 8kg+ | C5: 101KG+ | D5: 签收时效 （开船后） | E5: 理赔时效 （开船后第二天算起）
A7: ONT8,LAX9,LGB8,SBD1 | B7: 4.5 | C7: 4.3 | D7: 20-27个自然日 | E7: 26个工作日
A8: GYR3,GYR2,LAS1,VGT2,SMF3,SCK4 | B8: 5.3 | C8: 5.1 | D8: 21-29个自然日 | E8: 27个工作日
A9: MIT2,GEU3,GEU5,GEU2,HLI2,TCY1,TCY2 | B9: 5.3 | C9: 5.1 | D9: 21-29个自然日 | E9: 28个工作日
A10: FTW1,ABQ2,IAH3,PSC2 | B10: 7.4 | C10: 7.2 | D10: 25-32个自然日 | E10: 32个工作日
A11: MDW2,MQJ1,MEM1,FWA4,IND9 | B11: 7.7 | C11: 7.5 | D11: 25-32个自然日 | E11: 33个工作日
A12: CLT2,RDU2 | B12: 8.7 | C12: 8.5 | D12: 28-34个自然日 | E12: 34个工作日
A13: ORF2,RMN3,TEB3,TEB9,ABE8,AVP1,AVP3,SWF1,SWF2 | B13: 9 | C13: 8.8 | D13: 28-34个自然日 | E13: 34个工作日
A14: JOT1,POC1,POC3,POC2 | B14: 4.5 | C14: 4.3 | D14: 20-27个自然日 | E14: 不参与时效赔付
A15: IUSP,IUSQ,IUTI,IUSJ,IUSW,IUTF | B15: 4.8 | C15: 4.6 | D15: 21-29个自然日 | E15: 不参与时效赔付
A16: SCK8,QXY8,IUTE,MCC1,PSP3,QXY5 | B16: 5.5 | C16: 5.3 | D16: 21-29个自然日 | E16: 不参与时效赔付
A17: AMA1,SAT1,SAT4,DFW6,RFD2,FTW5 | B17: 7.4 | C17: 7.2 | D17: 25-32个自然日 | E17: 不参与时效赔付
A18: CMH2,CMH3,DET1,RYY2,JAX3,TPA2,TPA3 | B18: * | C18: 8.3 | D18: 32-40个自然日 | E18: 不参与时效赔付
A19: HGR6,WBW2,PBI3,ABE4 | B19: * | C19: 8.6 | D19: 34-40个自然日 | E19: 不参与时效赔付
A20: 其他未开放卡派仓单询
A21: 选用COSCO/OOCL/EMC/CMA等船司服务里最快优质航线，交货10天内装柜进港，提供甩柜、开船600小时延误理赔服务。 超承诺时效0.3/KG/工作日赔付，封顶赔付3元/KG/工作日；若出现甩柜情况包含在时效赔付内。 如遇海关查验造成理赔时效延误，直接赔付1元/KG，不再做其他延误赔付。 船舶机械故障延误、车祸、天灾等不可抗拒因素不赔付； FBA爆仓删约、推约、改约、不放约、拒收、PO失效、节假日假期、码头罢工、船司调整船期、航线变更等导致的到港时间延误，赔付时效同步顺延
A22: 自2025年5月12日起 符合美国清关第232条款的钢铁制品、铝制品关税附加费加收0.5元/KG；
A23: 需加收产品及杂费 | B23: 加收金额 | C23: 备注
A24: 除高价值，高关税产品，其余普通产品无附加费 | B24: 无附加费 | C24: 由于产品本身专利或知识产权问题产生扣关，货物退回等后续问题由客户承担，我司保留追究的权力。
A25: 木制品、蓝牙产品、激光类产品、UL产品 | B25: +1/KG | C25: FDA类产品，海关可能会查验。由于客户提供错误的FDA ID. 产生扣关，关税，货物退回等后续问题由客户承担，我司并保留追究的权力
A26: 化工品（指甲胶、精油、口红、眼影，卸妆水、洗发水等） | B26: +2/KG | C26: 提供真实有效期内商检、MSDS认证视为普货，无需附加费（证书是否有效以相关部门是否认可为准）
A27: 国内贴标费 | B27: 1元/张 | C27: 为了准确快捷入库，请尽量配合贴好入仓标签/FBA标签/SKU标签等，因未贴标签或未及时告知导致仓库未能及时入库延误船期的我司概不负责
A28: 优势:自主装柜，海运市场优质后端，信誉清关行，快捷海外转运派送。
A29: 注明：每周报价表为实时报价，不可控因素或市场变化调节过大时，升或降以到仓价格为准。
A30: 包税附加费，未列明产品请跟业务联系
A31: 单证报关250/票，单票超5个品名以上+50RMB/个 卡派超限附加费：最长边不可超过120CM,次长边不可超过100CM，超长附加单价*1.1倍计算。单箱实重超过30KG单询
A32: 温馨提示：请按我司提供的样板提供电子版发票和装箱单如实申报，如因申报品名/申报数量/申报单价/申报材质/申报HS等不符造成的清关问题，我司概不负责 （清关延误不算在正常派送日内）

Sheet 美西普船专线
A2: 洛杉矶768 | F2: 奥克兰744 | K2: 西雅图788
A3: 卡派包税 | F3: 卡派包税 | K3: 卡派包税
B4: 珠三角/汕头/义乌交货价 | G4: 珠三角/汕头/义乌交货价 | L4: 珠三角/汕头/义乌交货价
A5: 仓库 重量段 | B5: 8kg+ | C5: 101KG+ | D5: 参考时效（开船后） | F5: 仓库 重量段 | G5: 8kg+ | H5: 101KG+ | I5: 参考时效（开船后） | K5: 仓库 重量段 | L5: 8kg+ | M5: 101KG+ | N5: 参考时效（开船后）
A7: ONT8,LAX9,LGB8,SBD1,JOT1,POC1,POC3,POC2 | B7: 4.2 | C7: 4 | D7: 24-32个自然日 | F7: SCK4,SMF3,SCK1,SCK3,OAK3,SJC7 | G7: 5.2 | H7: 5 | I7: 26-34个自然日 | K7: BFI3,BFI7 | L7: 6.3 | M7: 6.1 | N7: 28-37个自然日
A8: GYR3,GYR2,LAS1,VGT2,MIT2,GEU3,QXY5,GEU5,GEU2,QXY8 | B8: 5.2 | C8: 5 | D8: 25-34个自然日 | F8: TCY1,TCY2,SCK8,SMF7,MCE1,SMF6,QXY5 | G8: 5.6 | H8: 5.4 | I8: 27-34个自然日 | K8: PSC2 | L8: 6.6 | M8: 6.4 | N8: 30-40个自然日
A9: XLX7,KRB1,KRB4,ONT2,ONT6,ONT9,LGB4,LGB6,LGB9,SBD2,SNA4 | B9: 5 | C9: 4.8 | D9: 26-34个自然日 | F9: HLI2,FAT2 | G9: 5.7 | H9: 5.5 | I9: 30-36个自然日 | K9: PDX6,PDX7 | L9: 6.8 | M9: 6.6 | N9: 30-40个自然日
A10: PHX3,PHX5,PHX7,AZA4,LAS6,LAS7 | B10: 6 | C10: 5.8 | D10: 27-36个自然日 | F10: MCC1 | G10: 5.7 | H10: 5.5 | I10: 30-36个自然日 | K10: GEG2 | L10: 7.2 | M10: 7 | N10: 32-40个自然日
A11: 其他未开放卡派仓单询 | F11: 其他未开放卡派仓单询 | K11: 其他未开放卡派仓单询
A12: 低价首选，选用EMC COSCO OOCL CMA TSL 等船公司航线服务， 预计开船后768小时提取，助力卖家安心长期备货 | F12: 美西低价首选，直达奥克兰港口， 预计开船后744小时提取，助力卖家安心长期备货 | K12: 美西低价首选，盐田直达西雅图港口， 预计开船后788小时提取，助力卖家安心长期备货
A13: 自2025年5月12日起 符合美国清关第232条款的钢铁制品、铝制品关税附加费加收0.5元/KG；
A14: 需加收产品及杂费 | C14: 加收金额 | F14: 备注
A15: 除高价值，高关税产品，其余普通产品无附加费 | C15: 无附加费 | F15: 由于产品本身专利或知识产权问题产生扣关，货物退回等后续问题由客户承担，我司保留追究的权力。
A16: 木制品、蓝牙产品、激光类产品、UL产品 | C16: +1/KG | F16: FDA类产品，海关可能会查验。由于客户提供错误的FDA ID. 产生扣关，关税，货物退回等后续问题由客户承担，我司并保留追究的权力
A17: 化工品（指甲胶、精油、口红、眼影，卸妆水、洗发水等） | C17: +2/KG | F17: 提供真实有效期内商检、MSDS认证视为普货，无需附加费（证书是否有效以相关部门是否认可为准）
A18: 国内贴标费 | C18: 1元/张 | F18: 为了准确快捷入库，请尽量配合贴好入仓标签/FBA标签/SKU标签等，因未贴标签或未及时告知导致仓库未能及时入库延误船期的我司概不负责
A19: 优势:自主装柜，海运市场优质后端，信誉清关行，快捷海外转运派送。
A20: 注明：每周报价表为实时报价，不可控因素或市场变化调节过大时，升或降以到仓价格为准。
A21: 包税附加费，未列明产品请跟业务联系
A22: 单证报关250/票，单票超5个品名以上+50RMB/个 卡派超限附加费：最长边不可超过120CM,次长边不可超过100CM，超长附加单价*1.1倍计算。单箱实重超过30KG单询
A23: 温馨提示：请按我司提供的样板提供电子版发票和装箱单如实申报，如因申报品名/申报数量/申报单价/申报材质/申报HS等不符造成的清关问题，我司概不负责 （清关延误不算在正常派送日内）

Sheet 美中普船专线
A1: 3
A2: 芝加哥840 | F2: 休斯顿866
A3: 卡派包税 | F3: 卡派包税
B4: 珠三角/汕头/义乌交货价 | G4: 珠三角/汕头/义乌交货价
A5: 仓库 重量段 | B5: 8kg+ | C5: 101KG+ | D5: 参考时效（开船后） | F5: 仓库 重量段 | G5: 8kg+ | H5: 101KG+ | I5: 参考时效（开船后）
A7: MDW2,ORD2,IGQ2,MDW9,RFD2,RFD4,JVL1,MDW6 | B7: 6.7 | C7: 6.5 | D7: 30-35个自然日 | F7: HOU8,HOU7,HOU3,HOU2,HOU1,IAH3 | G7: 5.9 | H7: 5.7 | I7: 32-37个自然日
A8: IND9,FWA4,MQJ1,MQJ2,STL4,IND2,IND4,IND5,PPO4 | B8: 7.1 | C8: 6.9 | D8: 33-42个自然日 | F8: FTW9,FTW1,FTW5,FTW3,SAT1,FTW2,IUSF,DFW7,DFW6,DAL3,SAT6,SAT4,IUTH | G8: 6.4 | H8: 6.2 | I8: 35-42个自然日
A9: DET1,DET2,LAN2,CMH2,CMH3,CMH7 | B9: 7.4 | C9: 7.2 | D9: 35-45个自然日 | F9: LFT1,AMA1,OKC2 | G9: 7.1 | H9: 6.9 | I9: 38-45个自然日
A10: MKC4,MCI3,STL3 | B10: 7.9 | C10: 7.7 | D10: 38-45个自然日 | F10: LIT2,ICT2,FOE1 | G10: 6.8 | H10: 6.6 | I10: 38-45个自然日
A11: 其他未开放卡派仓单询 | F11: 其他未开放卡派仓单询
A12: 盐田直达洛杉矶港后上火车中转到芝加哥站 预计开船后840小时提取，助力卖家安心长期备货 | F12: 美西低价首选，盐田直达休斯顿港口， 预计开船后866小时提取，助力卖家安心长期备货
A13: 自2025年5月12日起 符合美国清关第232条款的钢铁制品、铝制品关税附加费加收0.5元/KG；
A14: 需加收产品及杂费 | C14: 加收金额 | F14: 备注
A15: 除高价值，高关税产品，其余普通产品无附加费 | C15: 无附加费 | F15: 由于产品本身专利或知识产权问题产生扣关，货物退回等后续问题由客户承担，我司保留追究的权力。
A16: 木制品、蓝牙产品、激光类产品、UL产品 | C16: +1/KG | F16: FDA类产品，海关可能会查验。由于客户提供错误的FDA ID. 产生扣关，关税，货物退回等后续问题由客户承担，我司并保留追究的权力
A17: 化工品（指甲胶、精油、口红、眼影，卸妆水、洗发水等） | C17: +2/KG | F17: 提供真实有效期内商检、MSDS认证视为普货，无需附加费（证书是否有效以相关部门是否认可为准）
A18: 国内贴标费 | C18: 1元/张 | F18: 为了准确快捷入库，请尽量配合贴好入仓标签/FBA标签/SKU标签等，因未贴标签或未及时告知导致仓库未能及时入库延误船期的我司概不负责
A19: 优势:自主装柜，海运市场优质后端，信誉清关行，快捷海外转运派送。
A20: 注明：每周报价表为实时报价，不可控因素或市场变化调节过大时，升或降以到仓价格为准。
A21: 包税附加费，未列明产品请跟业务联系
A22: 单证报关250/票，单票超5个品名以上+50RMB/个 卡派超限附加费：最长边不可超过120CM,次长边不可超过100CM，超长附加单价*1.1倍计算。单箱实重超过30KG单询
A23: 温馨提示：请按我司提供的样板提供电子版发票和装箱单如实申报，如因申报品名/申报数量/申报单价/申报材质/申报HS等不符造成的清关问题，我司概不负责 （清关延误不算在正常派送日内）

Sheet 美东普船专线
A2: 萨凡纳888 | F2: 纽约960
A3: 卡派包税 | F3: 卡派包税
B4: 珠三角/汕头/义乌交货价 | G4: 珠三角/汕头/义乌交货价
A5: 仓库 重量段 | B5: 8kg+ | C5: 101KG+ | D5: 参考时效（开船后） | F5: 仓库 重量段 | G5: 8kg+ | H5: 101KG+ | I5: 参考签收时效 （开船后）
F6: ABE8,TEB6,TEB9,ABE2,ABE3,ABE4,TEB3,TEB4,ACY2 | I6: 26-32个工作日
A7: SAV3,JAX3,XLX6,GSP1,GSO1,IUSR,CAE1 | B7: 6.1 | C7: 5.9 | D7: 37-47个自然日 | F7: ABE8,ACY2,TEB6,TEB9,TTN2,TEB3,TEB4,XEW5 | G7: 5.7 | H7: 5.5 | I7: 40-47个自然日
A8: MGE1,MGE3,RYY2,CLT2,CLT3,RDU2,RDU4 | B8: 6.1 | C8: 5.9 | D8: 37-47个自然日 | F8: ABE3,ABE4,AVP1,AVP3,AVP9,WBW2,HEA2 | G8: 5.9 | H8: 5.7 | I8: 42-50个自然日
A9: MCO1,MCO2,TPA2,TPA3,TPA6 | B9: 6.4 | C9: 6.2 | D9: 40-50个自然日 | F9: HIA1,PHL4,PHL5,PHL6,MDT1,MDT4,PIT2,LBE1,ALB1,SWF1,SWF2 | G9: 6 | H9: 5.8 | I9: 42-50个自然日
A10: TMB8,PBI2,PBI3,XPB2 | B10: 6.4 | C10: 6.2 | D10: 40-50个自然日 | F10: IUSL,MDT2,ILG1,DCA6,BWI1,HGR2,XLX1,HGR6 | G10: 6.2 | H10: 6 | I10: 45-55个自然日
A11: BNA2,BNA6,CHA2 | B11: 6.7 | C11: 6.5 | D11: 42-52个自然日 | F11: BDL6,BOS7,BWI4,CHO1,RIC1,RIC3,XRI3,ORF2,RMN3 | G11: 6.4 | H11: 6.2 | I11: 45-55个自然日
A12: HSV1,HSV2,MEM1 | B12: 6.7 | C12: 6.5 | D12: 42-52个自然日 | F12: CLT6,AKR1,SDF4,SDF8,DTW3,MEM6,IND2,IND4,IND5,IND9,MQJ1,MQJ2,FWA4,DET1,DET2,DTW3,LAN2,CMH2,CMH6,CMH7,CMH3 | G12: 6.7 | H12: 6.5 | I12: 45-55个自然日
A13: 其他未开放卡派仓单询 | F13: 其他未开放卡派仓单询
A14: 选用COSCO/OOCL/EMC等船公司航线服务，直达萨凡纳港口 预计开船后888小时提取，助力卖家安心长期备货 | F14: 选用ZIM/COSCO/EMC美东航线，从盐田出发到达纽约港，最快960小时送仓，美东仓库低价首选，大幅降低卖家美东物流成本
A15: 自2025年5月12日起 符合美国清关第232条款的钢铁制品、铝制品关税附加费加收0.5元/KG；
A16: 需加收产品及杂费 | C16: 加收金额 | E16: 备注
A17: 除高价值，高关税产品，其余普通产品无附加费 | C17: 无附加费 | E17: 由于产品本身专利或知识产权问题产生扣关，货物退回等后续问题由客户承担，我司保留追究的权力。
A18: 木制品、蓝牙产品、激光类产品、UL产品 | C18: +1/KG | E18: FDA类产品，海关可能会查验。由于客户提供错误的FDA ID. 产生扣关，关税，货物退回等后续问题由客户承担，我司并保留追究的权力
A19: 化工品（指甲胶、精油、口红、眼影，卸妆水、洗发水等） | C19: +2/KG | E19: 提供真实有效期内商检、MSDS认证视为普货，无需附加费（证书是否有效以相关部门是否认可为准）
A20: 国内贴标费 | C20: 1元/张 | E20: 为了准确快捷入库，请尽量配合贴好入仓标签/FBA标签/SKU标签等，因未贴标签或未及时告知导致仓库未能及时入库延误船期的我司概不负责
A21: 优势:自主装柜，海运市场优质后端，信誉清关行，快捷海外转运派送。
A22: 注明：每周报价表为实时报价，不可控因素或市场变化调节过大时，升或降以到仓价格为准。
A23: 包税附加费，未列明产品请跟业务联系
A24: 单证报关250/票，单票超5个品名以上+50RMB/个 卡派超限附加费：最长边不可超过120CM,次长边不可超过100CM，超长附加单价*1.1倍计算。单箱实重超过30KG单询
A25: 温馨提示：请按我司提供的样板提供电子版发票和装箱单如实申报，如因申报品名/申报数量/申报单价/申报材质/申报HS等不符造成的清关问题，我司概不负责 （清关延误不算在正常派送日内）

Sheet 普船玩具专线
A2: TY720-玩具专线
B3: 珠三角/汕头/义乌交货价
A4: 仓库 重量段 | B4: 8kg+ | C4: 101KG+ | D4: 参考时效（开船后）
A5: ONT8,LAX9,LGB8,SBD1,JOT1,POC1,POC3,POC2 | B5: 4 | C5: 3.8 | D5: 22-32个自然日
A6: IUSP,IUSQ,IUTI,IUSJ,IUSW,IUTF | B6: 4.3 | C6: 4.1 | D6: 23-32个自然日
A7: GYR3,GYR2,LAS1,VGT2,MIT2,GEU3,QXY5,GEU5,GEU2 | B7: 4.9 | C7: 4.7 | D7: 24-34个自然日
A8: HLI2,TCY1,TCY2,SMF3,SCK4,SCK8,IUTE,MCC1 | B8: 5.3 | C8: 5.1 | D8: 24-34个自然日
A9: AMA1,IAH3,SAT1,SAT4,DFW6,PSC2,ABQ2,RFD2,FTW1,FTW5 | B9: 7.1 | C9: 6.9 | D9: 28-37个自然日
A10: MDW2,MQJ1,MEM1,FWA4,IND9 | B10: 7.4 | C10: 7.2 | D10: 28-38个自然日
A11: 选用COSCO/EMC/CMA/TSL/WHL/YML/ONE船司优质航线服务，交货10天内装柜进港 。玩具卖家备货首选渠道
A12: 奥克兰744-玩具专线
B13: 珠三角/汕头/义乌交货价
A14: 仓库 重量段 | B14: 8kg+ | C14: 101KG+ | D14: 参考时效（开船后）
A15: SCK4,SMF3,SCK1,SCK3,OAK3,SJC7 | B15: 5 | C15: 4.8 | D15: 26-34个自然日
A16: TCY1,TCY2,SMF7,SCK8,MCE1,SMF6 | B16: 5.4 | C16: 5.2 | D16: 27-34个自然日
A17: HLI2,FAT2,MCC1 | B17: 5.5 | C17: 5.3 | D17: 30-36个自然日
A18: 美西低价首选，直达奥克兰港口， 预计开船后744小时提取，助力卖家安心长期备货
A19: 芝加哥840-玩具专线
B20: 珠三角/汕头/义乌交货价
A21: 仓库 重量段 | B21: 8kg+ | C21: 101KG+ | D21: 参考时效（开船后）
A22: MDW2,ORD2,IGQ2,MDW9,RFD2,RFD4,JVL1,MDW6 | B22: 6.5 | C22: 6.3 | D22: 30-35个自然日
A23: IND9,FWA4,MQJ1,MQJ2,STL4,IND2,IND4,IND5,PPO4 | B23: 6.9 | C23: 6.7 | D23: 33-42个自然日
A24: DET1,DET2,LAN2,CMH2,CMH3,CMH7 | B24: 7.2 | C24: 7 | D24: 35-45个自然日
A25: MKC4,MCI3,STL3 | B25: 7.7 | C25: 7.5 | D25: 38-45个自然日
A26: 盐田直达洛杉矶港后上火车中转到芝加哥站 预计开船后840小时提取，助力卖家安心长期备货
A27: 休斯顿866-玩具专线
B28: 珠三角/汕头/义乌交货价
A29: 仓库 重量段 | B29: 8kg+ | C29: 101KG+ | D29: 参考时效（开船后）
A30: HOU8,HOU7,HOU3,HOU2,HOU1,IAH3 | B30: 5.7 | C30: 5.5 | D30: 32-37个自然日
A31: FTW9,FTW1,FTW5,FTW3,SAT1,FTW2,IUSF,DFW7,DFW6,DAL3,SAT6,SAT4,IUTH | B31: 6.2 | C31: 6 | D31: 35-42个自然日
A32: MEM6,LFT1,AMA1,OKC2,LIT2,ICT2,FOE1 | B32: 6.9 | C32: 6.7 | D32: 38-45个自然日
A33: 美西低价首选，盐田直达休斯顿港口， 预计开船后866小时提取，助力卖家安心长期备货
A34: 萨凡纳888-玩具专线
B35: 珠三角/汕头/义乌交货价
A36: 仓库 重量段 | B36: 8kg+ | C36: 101KG+ | D36: 参考时效（开船后）
A37: SAV3,JAX3,XLX6,GSP1,GSO1,IUSR,CAE1,MGE1,MGE3,RYY2,CLT2,CLT3,RDU2,RDU4,XAV3 | B37: 5.9 | C37: 5.7 | D37: 37-47个自然日
A38: MCO1,MCO2,TPA2,TPA3,TPA6,TMB8,PBI2,PBI3,XPB2 | B38: 6.2 | C38: 6 | D38: 40-50个自然日
A39: BNA2,BNA6,CHA2,HSV1,HSV2,MEM1 | B39: 6.5 | C39: 6.3 | D39: 42-52个自然日
A40: 选用ZIM/COSCO/EMC/WHL/MSC等船公司航线服务，直达萨凡纳港口 预计开船后888小时提取，助力卖家安心长期备货
A41: 纽约960-玩具专线
B42: 珠三角/汕头/义乌交货价
A43: 仓库 重量段 | B43: 8kg+ | C43: 101KG+ | D43: 参考签收时效 （开船后）
A44: ABE8,ACY2,TEB6,TEB9,TTN2,TEB3,TEB4,XEW5 | B44: 5.5 | C44: 5.3 | D44: 40-47个自然日
A45: ABE3,ABE4,AVP1,AVP3,AVP9,WBW2,HEA2 | B45: 5.7 | C45: 5.5 | D45: 42-50个自然日
A46: HIA1,PHL4,PHL5,PHL6,MDT1,MDT4,PIT2,LBE1,ALB1,SWF1,SWF2 | B46: 5.8 | C46: 5.6 | D46: 42-50个自然日
A47: IUSL,MDT2,ILG1,DCA6,BWI1,HGR2,XLX1,HGR6 | B47: 6 | C47: 5.8 | D47: 45-55个自然日
A48: BDL6,BOS7,BWI4,CHO1,RIC1,RIC3,XRI3,ORF2,RMN3 | B48: 6.2 | C48: 6 | D48: 45-55个自然日
A49: CLT6,AKR1,SDF4,SDF8,DTW3,MEM6,IND2,IND4,IND5,IND9,MQJ1,MQJ2,FWA4,DET1,DET2,DTW3,LAN2,CMH2,CMH6,CMH7,CMH3 | B49: 6.5 | C49: 6.3 | D49: 45-55个自然日
A50: 选用ZIM/COSCO/EMC/WHL/MSC美东航线，从盐田出发到达纽约港，最快960小时送仓，美东仓库低价首选，大幅降低卖家美东物流成本
A51: 出运产品必须CPC、CPSC认证资质，认证是否有效以美国当地海关判定为准
A52: 需加收产品及杂费 | B52: 加收金额 | C52: 备注
A53: 除高价值，高关税产品，其余普通产品无附加费 | B53: 无附加费 | C53: 由于产品本身专利或知识产权问题产生扣关，货物退回等后续问题由客户承担，我司保留追究的权力。
A54: 木制品、蓝牙产品、激光类产品、UL产品 | B54: +1/KG | C54: FDA类产品，海关可能会查验。由于客户提供错误的FDA ID. 产生扣关，关税，货物退回等后续问题由客户承担，我司并保留追究的权力
A55: 化工品（指甲胶、精油、口红、眼影，卸妆水、洗发水等） | B55: +2/KG | C55: 提供真实有效期内商检、MSDS认证视为普货，无需附加费（证书是否有效以相关部门是否认可为准）
A56: 国内贴标费 | B56: 1元/张 | C56: 为了准确快捷入库，请尽量配合贴好入仓标签/FBA标签/SKU标签等，因未贴标签或未及时告知导致仓库未能及时入库延误船期的我司概不负责
A57: 优势:自主装柜，海运市场优质后端，信誉清关行，快捷海外转运派送。
A58: 注明：每周报价表为实时报价，不可控因素或市场变化调节过大时，升或降以到仓价格为准。
A59: 包税附加费，未列明产品请跟业务联系
A60: 单证报关250/票，单票超5个品名以上+50RMB/个 卡派超限附加费：最长边不可超过120CM,次长边不可超过100CM，超长附加单价*1.1倍计算。单箱实重超过30KG单询
A61: 温馨提示：请按我司提供的样板提供电子版发票和装箱单如实申报，如因申报品名/申报数量/申报单价/申报材质/申报HS等不符造成的清关问题，我司概不负责 （清关延误不算在正常派送日内）

Sheet 沃尔玛专线
A2: 沃尔玛仓专线服务
A3: 卡派包税
C4: 渠道 | D4: 珠三角/汕头/义乌交货价
A5: 仓库 重量段 | C5: 卡派 | D5: 501KG+ | E5: 3001KG+ | F5: 5001KG+ | G5: 参考签收时效 （开船后）
A6: LAX1,LAX2 | C6: 美森360 | D6: 11.1 | E6: 10.9 | F6: 10.7 | G6: 13-17个自然日
A7: LAX2T | D7: 11.4 | E7: 11.2 | F7: 11 | G7: 13-17个自然日
A8: LAX1,LAX2 | C8: 美森432 | D8: 10.6 | E8: 10.4 | F8: 10.2 | G8: 15-19个自然日
A9: LAX2T | D9: 10.9 | E9: 10.7 | F9: 10.5 | G9: 15-19个自然日
A10: LAX1,LAX2 | C10: EX456 | D10: 6.2 | E10: 6 | F10: 5.8 | G10: 17-21个自然日
A11: LAX2T | D11: 6.5 | E11: 6.3 | F11: 6.1 | G11: 17-21个自然日
A12: LAX1,LAX2 | C12: 快船600 | D12: 5 | E12: 4.8 | F12: 4.6 | G12: 23-27个自然日
A13: LAX2T | D13: 5.3 | E13: 5.1 | F13: 4.9 | G13: 25-29个自然日
A14: ORD1s | C14: 芝加哥840 | D14: 6.7 | E14: 6.5 | F14: 6.3 | G14: 27-32个自然日
A15: IND2,IND3,IND2n | D15: 7.1 | E15: 6.9 | F15: 6.7 | G15: 28-33个自然日
A16: KS1,MCI1N | D16: 7.9 | E16: 7.7 | F16: 7.5 | G16: 29-35个自然日
A17: DFW2n,DFW5s | C17: 休斯顿866 | D17: 7.7 | E17: 7.5 | F17: 7.3 | G17: 36-43个自然日
A18: ATL1,ATL3 | C18: 萨凡纳888 | D18: 6 | E18: 5.8 | F18: 5.6 | G18: 36-43个自然日
A19: ATL2n,MCO1 | D19: 8 | E19: 7.8 | F19: 7.6 | G19: 40-47个自然日
A20: NJ3,PHL2 | C20: 纽约960 | D20: 6.2 | E20: 6 | F20: 5.8 | G20: 40-47个自然日
A21: PHL1S.PHL2n,PHL5s,PHL4n | D21: 6.5 | E21: 6.3 | F21: 6.1 | G21: 42-49个自然日
A22: KY1 | D22: 7.2 | E22: 7 | F22: 6.8 | G22: 43-50个自然日
A23: 自2025年5月12日起 符合美国清关第232条款的钢铁制品、铝制品关税附加费加收0.5元/KG；
A24: 需加收产品及杂费 | E24: 加收金额 | F24: 备注
A25: 除高价值，高关税产品，其余普通产品无附加费 | E25: 无附加费 | F25: 由于产品本身专利或知识产权问题产生扣关，货物退回等后续问题由客户承担，我司保留追究的权力。
A26: 木制品、蓝牙产品、激光类产品、UL产品 | E26: +1/KG | F26: FDA类产品，海关可能会查验。由于客户提供错误的FDA ID. 产生扣关，关税，货物退回等后续问题由客户承担，我司并保留追究的权力
A27: 化工品（指甲胶、精油、口红、眼影，卸妆水、洗发水等） | E27: +2/KG | F27: 提供真实有效期内商检、MSDS认证视为普货，无需附加费（证书是否有效以相关部门是否认可为准）
A28: 国内贴标费 | E28: 1元/张 | F28: 为了准确快捷入库，请尽量配合贴好入仓标签/FBA标签/SKU标签等，因未贴标签或未及时告知导致仓库未能及时入库延误船期的我司概不负责
A29: 报价未注明的产品，请将提供产品信息给我司客服或业务进行核实是否有附加费 | E29: 待确定 | F29: 因美对华加增2000亿美金关税影响，请单独询问销售
A30: 优势:自主装柜，海运市场优质后端，信誉清关行，快捷海外转运派送。
A31: 注明：每周报价表为实时报价，不可控因素或市场变化调节过大时，升或降以到仓价格为准。
A32: 包税附加费，未列明产品请跟业务联系
A33: 单证报关250/票，单票超5个品名以上+50RMB/个 卡派超限附加费：最长边不可超过120CM,次长边不可超过100CM，超长附加单价*1.1倍计算。单箱实重超过30KG单询
A34: 温馨提示：请按我司提供的样板提供电子版发票和装箱单如实申报，如因申报品名/申报数量/申报单价/申报材质/申报HS等不符造成的清关问题，我司概不负责 （清关延误不算在正常派送日内）

Sheet 第三方仓专线
A2: 美森360
A3: 卡派包税
C4: 珠三角/汕头/义乌交货价
A5: 邮编仓库/派送城市 重量段 | C5: 301KG+ | D5: 501KG+ | E5: 3001KG+ | F5: 参考签收时效 （开船后） | G5: 备注
A6: 美西中转仓 | C6: 12.8 | D6: 11.8 | E6: 11.1 | F6: 9-12个工作日 | G6: 出货前请提供地址最终确认运费费用，以及提前确认收件人是否需要电话跟邮件预约，避免产生空跑费 必须是商业地址，并且有DOCK
A7: 长岛仓11717 | C7: * | D7: 15.7 | E7: 15 | F7: 15-22个工作日
A8: Local派送90-91开头邮编 | C8: 13.3 | D8: 12.3 | E8: 11.6 | F8: 10-14个工作日
A9: wayfair仓-92571 | C9: 13.9 | D9: 12.9 | E9: 12.2 | F9: 11-15个工作日
A10: 万邑通仓-41048 | C10: * | D10: 14.5 | E10: 13.8 | F10: 12-17个工作日
A11: 美森432
A12: 卡派包税
C13: 珠三角/汕头/义乌交货价
A14: 邮编仓库/派送城市 重量段 | C14: 301KG+ | D14: 501KG+ | E14: 3001KG+ | F14: 参考签收时效 （开船后） | G14: 备注
A15: 美西中转仓 | C15: 12.3 | D15: 11.3 | E15: 10.6 | F15: 10-13个工作日 | G15: 出货前请提供地址最终确认运费费用，以及提前确认收件人是否需要电话跟邮件预约，避免产生空跑费 必须是商业地址，并且有DOCK
A16: 长岛仓11717 | C16: * | D16: 15.2 | E16: 14.5 | F16: 16-23个工作日
A17: Local派送90-91开头邮编 | C17: 12.8 | D17: 11.8 | E17: 11.1 | F17: 11-15个工作日
A18: wayfair仓-92571 | C18: 13.4 | D18: 12.4 | E18: 11.7 | F18: 12-16个工作日
A19: 万邑通仓-41048 | C19: * | D19: 14 | E19: 13.3 | F19: 13-18个工作日
A20: EX456
A21: 卡派包税
C22: 珠三角/汕头/义乌交货价
A23: 仓库 重量段 | C23: 301KG+ | D23: 501KG+ | E23: 3001KG+ | F23: 参考签收时效 （开船后） | G23: 备注
A24: 美西中转仓 | C24: 7.7 | D24: 6.7 | E24: 6 | F24: 12-15个工作日 | G24: 出货前请提供地址最终确认运费费用，以及提前确认收件人是否需要电话跟邮件预约，避免产生空跑费 必须是商业地址，并且有DOCK
A25: 长岛仓11717 | C25: * | D25: 10.6 | E25: 9.9 | F25: 19-25个工作日
A26: Local派送90-91开头邮编 | C26: 8.2 | D26: 7.2 | E26: 6.5 | F26: 13-17个工作日
A27: wayfair仓-92571 | C27: 8.8 | D27: 7.8 | E27: 6.9 | F27: 14-18个工作日
A28: 万邑通仓-41048 | C28: * | D28: 11.4 | E28: 10.5 | F28: 16-20个工作日
A29: 快船600
A30: 卡派包税
C31: 珠三角/汕头/义乌交货价
A32: 仓库 重量段 | C32: 301KG+ | D32: 501KG+ | E32: 3001KG+ | F32: 参考签收时效 （开船后） | G32: 备注
A33: 美西中转仓 | C33: 7.1 | D33: 6.1 | E33: 5.4 | F33: 22-23个自然日 | G33: 出货前请提供地址最终确认运费费用，以及提前确认收件人是否需要电话跟邮件预约，避免产生空跑费 必须是商业地址，并且有DOCK
A34: 长岛仓11717 | C34: * | D34: 9.8 | E34: 9.1 | F34: 26-37个自然日
A35: Local派送90-91开头邮编 | C35: 7.6 | D35: 6.6 | E35: 5.9 | F35: 23-27个自然日
A36: wayfair仓-92571 | C36: 8.5 | D36: 7.5 | E36: 6.6 | F36: 23-27个自然日
A37: 万邑通仓-41048 | C37: * | D37: 11 | E37: 10.1 | F37: 26-32个自然日
A38: 芝加哥840
A39: 卡派包税
C40: 珠三角/汕头/义乌交货价
A41: 邮编 重量段 | C41: 301KG+ | D41: 1001KG+ | E41: 3001KG+ | F41: 参考签收时效 （开船后） | G41: 备注
A42: 60490,60440,60446,60564,60403,60441,60544,60435,60439,60432,60503,60491,60434,60507,60598,60543,60572,60464,60436,60431,60189,60433,60404,60505,60137,60538,60480,60568,60138,60502,60465,60525,60458,60451,60190,60462,60467,60482,60463,60455,60154,60560,60186,60512,60542,60506,60501,60148,60448,60499,60181,60454,60415,60539,60421,60459,60447,60513,60126,60185,60546,60487,60162,60402,60445,60442,60163,60141,60453,60452,60130,60472,60187,60104,60153,60101,60199,60165,60510,60164,60174,60423,60128,60132,60197,60106,60536,60105,60116,60305,60303,60188,60399,60161,60117,60545,60160,60191,60184,60103,60304,60108,60131,60481,60171,60554,60477,60172,60406,60511,60157,60541,60469,60007,60537,60144 | C42: * | D42: 7.7 | E42: 7.2 | F42: 26-32个自然日 | G42: 出货前请提供地址最终确认运费费用，以及提前确认收件人是否需要电话跟邮件预约，避免产生空跑费 必须是商业地址，并且有DOCK
A43: 60009,60175,60183,60119,60147,60173,60176,60450,60426,60428,60193,60177,60443,60018,60120,60019,60548,60520,60068,60017,60429,60478,60168,60194,60122,60008,60133,60551,60416,60056,60196,60473,60430,60005,60121,60016,60169,60095,60407,60107,60422,60449,60471,60078,60006,60067,60476,60004,60466,60461,60425,60484,60074,60151,60038,60094,60935,60025,60412,60438,60444,60549,60029,60070,60077,60195,60192,60424,60419,60062,60950,60076,60531,60409,60026,61360,60468,60474,60065,60090,60203,60011,60475,60179,60136,60082,60010,60969,60557,60204,60112,60089,60015,60091,60411,60202,60047,60401,60201,60961,60093,60208,60479,60043,60550,60115,60069,60021,60420,60035,60022,60110,60118,60140,60013,60102,61353,60917,60518,60530 | C43: * | D43: 8.1 | E43: 7.6 | F43: 26-33个自然日
A44: 60178,60045,60901,60040,60941,60437,60084,60910,60920,60037,60156,60109,60553,60039,60048,60014,60044,60111,60150,61318,60088,60042,60030,60934,60964,60460,60142,60064,60946,61325,60470,61371,60086,60073,60113,60145,61373,60135,60031,60012,60051,60922,60929,61378,60085,61372,60046,60020,60954,60940,61769,60041,60079,60146,60050,61301,61313,60087,60927,60083,60911,60129,61764,60180,61068,61350,60098,60959,61331,61367,60099,61006,61320,60930,61052,60002,60944,61329,60951,61364,61319,60956,60921,60152,61354,61316,60075,61310,61332,61038 | C44: * | D44: 8.5 | E44: 8 | F44: 28-30个自然日
A45: 61317,61312,61741,60071,61016,61362,61370,61311,60034,60958,60096,61324,60912,61359,60928,61330,61743,60033,60938,61326,61333,61739,60970,61008,60968,61015,61337,61020,61334,61323,61322,61374,61012,61065,61109,61740,61315,61356,61011,60931,61726,60955,61321,61377,61091,60974,61108,61327,61061,61358,61773,61731,61126,61112,61125,61335,61084,60952,61021,61073,61753,61107,61010,60918,61064,60966,61720,61328,60924,61114,61102,60936,61111,61369,61110,61336,61054,61376,60926,61130,61131,61132,61728,61104,60953,60962,61375,60957,61081,61379,61103,61368,61115,61776,61338,61516,61541,61088,60973,61730,61758,61080,61845,60949,61037,61770,61051 | C45: * | D45: 8.9 | E45: 8.4 | F45: 28-30个自然日
A46: 休斯顿866
A47: 卡派包税
C48: 珠三角/汕头/义乌交货价
A49: 邮编 重量段 | C49: 301KG+ | D49: 1001KG+ | E49: 3001KG+ | F49: 参考签收时效 （开船后） | G49: 备注
A50: 77005,77487,77489,77496,77497,77545,77025,77030,77031,77035,77036,77042,77045,77047,77053,77054,77063,77071,77072,77074,77085,77096,77099,77215,77225,77230,77231,77235,77236,77242,77245,77251,77254,77263,77265,77272,77274,77401,77402,77411,77477,77478 | C50: * | D50: 6.2 | E50: 5.7 | F50: 36-42个自然日 | G50: 出货前请提供地址最终确认运费费用，以及提前确认收件人是否需要电话跟邮件预约，避免产生空跑费 必须是商业地址，并且有DOCK
A51: 77001,77407,77002,77003,77004,77459,77006,77007,77008,77469,77009,77010,77011,77012,77578,77581,77017,77498,77018,77584,77019,77021,77023,77024,77026,77027,77033,77041,77043,77046,77048,77051,77052,77055,77056,77057,77061,77075,77077,77079,77080,77081,77082,77083,77087,77092,77098,77201,77202,77203,77204,77206,77207,77208,77210,77212,77216,77217,77218,77219,77220,77221,77223,77224,77226,77227,77233,77237,77240,77241,77243,77244,77248,77249,77252,77253,77255,77256,77257,77262,77266,77270,77271,77275,77277,77279,77280,77282,77284,77287,77288,77292,77297,77299 | C51: * | D51: 6.4 | E51: 5.9 | F51: 36-42个自然日
A52: 77406,77441,77546,77549,77491,77492,77511,77512,77471,77481,77013,77494,77015,77016,77583,77020,77022,77028,77029,77034,77037,77038,77039,77040,77049,77050,77059,77060,77062,77064,77065,77066,77070,77076,77078,77084,77086,77088,77089,77093,77094,77095,77209,77213,77222,77228,77229,77234,77238,77259,77269,77289,77291,77293,77315,77413,77449,77450,77501,77502,77503,77504,77505,77506,77508,77536,77547,77587,77588,77598 | C52: * | D52: 6.6 | E52: 6.1 | F52: 37-43个自然日
A53: 77510,77430,77517,77417,77518,77444,77485,77539,77451,77461,77464,77515,77476,77014,77565,77573,77574,77591,77032,77044,77058,77067,77068,77069,77073,77090,77205,77258,77267,77268,77273,77290,77338,77339,77346,77347,77379,77383,77391,77396,77410,77429,77433,77493,77507,77520,77522,77530,77562,77571,77572,77586 | C53: * | D53: 6.8 | E53: 6.3 | F53: 39-40个自然日
A54: 77423,77523,77435,77580,77466,77535,77473,77486,77448,77454,77353,77534,77354,77355,77488,77357,77577,77568,77362,77365,77590,77380,77336,77337,77345,77373,77375,77377,77381,77386,77387,77388,77389,77393,77447,77484,77521,77532,77592 | C54: * | D54: 6.8 | E54: 6.1 | F54: 39-40个自然日
A55: 萨凡纳888
A56: 卡派包税
C57: 珠三角/汕头/义乌交货价
A58: 仓库 重量段 | C58: 301KG+ | D58: 1001KG+ | E58: 3001KG+ | F58: 参考签收时效 （开船后） | G58: 备注
A59: 31302,31407,31322 | C59: * | D59: 6.5 | E59: 6 | F59: 38-45个自然日 | G59: 出货前请提供地址最终确认运费费用，以及提前确认收件人是否需要电话跟邮件预约，避免产生空跑费 必须是商业地址，并且有DOCK
A60: 31312,31308,31404,31401,31414,31421,31403,31405,31412,31402,31326,31415,31408,31318,31307 | C60: * | D60: 6.7 | E60: 6.2 | F60: 38-45个自然日
A61: 31328,31411,31321,31303,30415,31329,31406,31410,31409,31420 | C61: * | D61: 6.9 | E61: 6.4 | F61: 38-45个自然日
A62: 30423,31314,30449,31315,30446,31320,31324 | C62: * | D62: 7.1 | E62: 6.6 | F62: 38-45个自然日
A63: 30467,31331,30424,30429,30417,31333,30460,30414,30452,30461,30458,30459,31313,31323,31310 | C63: * | D63: 7.3 | E63: 6.8 | F63: 40-47个自然日
A64: 31319,30450,30427,30421,30439,31316,31304,30438,30451 | C64: * | D64: 7.5 | E64: 7 | F64: 40-47个自然日
A65: 31599,30464,31327,30420,31305,31545,30455 | C65: * | D65: 7.7 | E65: 7.2 | F65: 40-47个自然日
A66: 30448,31560,30454,31523,31521,30474,30426,30475,31598,31546,30456,31520,30822,30471,30442,30436,30425 | C66: * | D66: 7.9 | E66: 7.4 | F66: 40-47个自然日
A67: 31551,31049,31569,30477,31553,31516,30454,31557,31002,31522,31518,31566,31561,30457,30470,30441,31565,31556,30412,30473,30410 | C67: * | D67: 8.2 | E67: 7.7 | F67: 40-47个自然日
A68: 美东960
A69: 卡派包税
C70: 珠三角/汕头/义乌交货价
A71: 仓库 重量段 | C71: 301KG+ | D71: 501KG+ | E71: 3001KG+ | F71: 参考签收时效 （开船后） | G71: 备注
A72: 长岛仓11717 | C72: * | D72: 6.8 | E72: 6.3 | F72: 38-45个自然日 | G72: 出货前请提供地址最终确认运费费用，以及提前确认收件人是否需要电话跟邮件预约，避免产生空跑费 必须是商业地址，并且有DOCK
A73: 08818,08817,08832,08840,07080,08830,08861,08862,08854,08055,08859,08989,08902,08846,08880,07027,07091,07203,08828,07033,07023,07036,08872,07016,07204,07059,08805,08875,08857,07747,07206,08823,07069,08852,07735,08824,07207,07208,07201,08904,07095,07067,08906,07077,08901,07001,08879,08850,07064,07061,07065,08882,08855,07076,07063,07060,08816,07066,08871,08933,07062 | C73: * | D73: 6.1 | E73: 5.6 | F73: 38-45个自然日
A74: 07083,07090,08873,07730,07202,08810,07205,07111,07980,07112,08812,07019,07902,07921,08544,07051,07738,07003,07028,07701,08836,07092,08835,07922,07733,08890,07946,07734,07765,07081,07088,07933,07974,07939,08528,08512,08831,07751,07746,07758,07040,07748,07103,08807,08869,08553,07928,08536,07002,07018,08844,07718,07726,07108,07106,07041,07976,08542,08540,07101,07192,07193,07175,07184,07188,07191,07198,07195,07017,07978,07102,07105,07901,08541,08543,08502,07114,07029,07920,07737,08876,08821,07477,07107,07050,07039,07752,08520,08504,07395,07032,07189,07763,07716,07104,07099,07305,08558,07728 | C74: * | D74: 6.3 | E74: 5.8 | F74: 38-45个自然日
A75: 07702,07977,07704,08619,08648,07934,07979,08638,08691,07930,08628,08801,07109,08550,07303,07304,07306,08888,07052,07960,07710,07938,07311,07931,07940,07110,08535,07031,07302,08853,07308,07739,07042,07087,07945,07310,07935,07932,07307,08887,07760,08889,07724,07044,07703,07068,08858,07096,07013,08525,07097,07926,07030,07012,07086,07043,08555,07094,07055,07009,07073,08561,07732,07764,08690,07047,07021,07750,08833,07799,08863,07015,07007,07011,07533,07093,07070,07924,07072,07014,07424,08602,08603,07927,08625,07755,07753,07936,07006,07071,07057,08695,07740,08666,07544,07962,07963,08646,08647,07731,08650,07712,07503,08629,08604,08605,08606,08607,08645,07999,08609,07961,07522,08551,07512,08610,07022,08601,07513,08510,07543,07074,07660,07075,08822,07505,07510,08608,07981,07754,08534,07524,07504,07538,07058,07514,07010,08530,07650,07657,07407,07699,07509,07723,07950,07502,07511,07501,07026,08620,07606,07604,07034,07727,07608,07711,07720,07663 | C75: * | D75: 6.5 | E75: 6 | F75: 38-45个自然日
A76: 08829,08501,07836,07853,07870,08730,08809,08827,08724,07803,08826,08738,07020,07605,07004,07878,07603,07054,07719,07666,07662,07607,08527,07035,08720,07602,07024,08560,07507,08701,07715,07644,07717,07474,07508,07440,07452,08559,07845,07876,07631,07970,08736,07653,07410,07470,07046,08526,07506,08557,08514,07444,08803,08868,07670,07661,07762,07646,07621,07005,07045,07865,07649,08750,07601,08562,07652,08903,08820,07442,07869,08867,08742,07628,08505,08515,07834,08511,07626,07630,07457,08022,08755,07423,07676,07806,08556,07481,07641,07866,07620,08802,08518,07852,07847,08825,07677,07857,07417,08533,07831,07885,07420,07850,07627,07432,07828,08041,07840,07436,07463,07656,07842,08733,07458,07880,08723,07645,08804,07802,07401,07675,07874,07465,07403,07821,07446,08739,08834,08016,08848,07820,07640,07624,08641,08042,08640,07882,07856,07843,07648,08757,08722,08735,08060,07801,07435,07647,08011,07456,07632,07838,08808,08073,08886,07495 | C76: * | D76: 6.7 | E76: 6.2 | F76: 38-45个自然日
A77: 10307,10309,10312,10308,10313,10314,10306,10311,10303,10302,10304,10310,10301,10305,11252,11209,11209,11228 | C77: * | D77: 6.9 | E77: 6.4 | F77: 40-48个自然日
A78: 11214,11204,11232,11224,11223,11218,10007,11231,11242,11215,11241,11202,10013,10081,10090,11217,10004,10006,10008,10045,10080,10113,10114,10002,11235,11226,11225,10014,10159,10003,10005,10123,10160,10001,10018,10109,10110,10116,10117,10118,10119,10121,10122,10156,10009,11201,11229,11238,11245,11230,11243,11213,10041,10043,10150,10152,10154,10020,10101,10103,10104,10106,10111,10112,10129,10138,10163,10164,10171,10173,10174,10060,10087,10105,10107,10108,10120,10133,10151,10153,10157,10168,10169,10170,10172,10016,10017,10019,10055,10102,11216,11251,11205,11211,10158,10132,10023,10155,10024,10065,10022,10131,11233,11210,10162,10021,10075,10028,11206,11695,11109,11101,11222,11236,11694,10128,10130,11104,11237,10025,10069,10026,10027,10029,11212,11239,11234,10115,10030,10044,11378,11207,11377,11373,11256,11414,11379,11417,11692,11374,11372,11120,10032,10040,11380,11370,11416,11208,11106,11103,11385,10031,10039,10453,10034,11421,11105,11371,11375,11418,11102,11419,11690,11368,11369,10161,10456,10468,10451,10033,11381,11693,11386,11436,11244,11352,10471,11355,11434,11430,10463,10472,10459,10454,10460,11367,11499,11691,11413,11415,10455,10457,10462,10474,11365,11451,11366,11435,11354,10705,11432,11422,11425,11412,11433,11439,11255,10702,10035,10473,10470,10467,10467,10465,10458,11424,11351,11431,11405,11358,11582,10466,10704,11357,11581,11592,11356,11096,11411,10461,11423,11364,11362,11428,11240,11427,10475,10469,10701,11429,11594,10703,11595,11598,11426,10964,11020,11003,11363,11580,11004,10965,10464,11559,10708,11563,10552,10976,11557,10551,11002,11005,10710,10803,11001,10553,11509,10550,11027,10968,10954,10977,11042,11254,11597 | C78: * | D78: 7.1 | E78: 6.6 | F78: 40-48个自然日
A79: 10982,11040,11010,11010,11565,10707,11026,10801,10706,10522,10962,10983,10805,11507,11024,11552,10709,11577,10901,10804,10994,11596,10502,11550,11571,11551,11576,11558,11570,10913,10931,11530,10960,11549,11501,11531,11572,10503,10538,10530,10974,11575,11051,11052,11599,10533,11553,10583,10989,11556,11548,11055,11053,11050,10523,10956,10543,10528,11514,11054,11547,10606,11510,11555,10920,10601,11853,11545,10602,10605,11579,10979,11554,10607,11590,11520,10532,11542,10580,10595,11802,11801,10577,10573,10927,11710,10925,11815,11793,10970,10923,10984,10591,10603,11756,10987,10610,10604,11560,11732,11773,11803,11791,11797,11783,10975,10594,10993,11758,11762,10910,10570,11771,11747,11714,11775,10510,11735,11804,11701,11709,11765,10986,10562,11561,11724,11726,10514,10990,10950,10959,11757,11746,11707,11798,10917,10560,11703,10545,10520,10912,10911,11743,10969,10926,10922,11721,11729,11740,11702,10980,11795,10949,11718,10549,10521,10507,10928,11731,11706,10918,10598,11725,11717,10988,10548,10566 | C79: * | D79: 7.3 | E79: 6.8 | F79: 40-48个自然日
A80: 自2025年5月12日起 符合美国清关第232条款的钢铁制品、铝制品关税附加费加收0.5元/KG；
A81: 需加收产品及杂费 | C81: 加收金额 | D81: 备注
A82: 除高价值，高关税产品，其余普通产品无附加费 | C82: 无附加费 | D82: 由于产品本身专利或知识产权问题产生扣关，货物退回等后续问题由客户承担，我司保留追究的权力。
A83: 木制品、蓝牙产品、激光类产品、UL产品 | C83: +1/KG | D83: FDA类产品，海关可能会查验。由于客户提供错误的FDA ID. 产生扣关，关税，货物退回等后续问题由客户承担，我司并保留追究的权力
A84: 化工品（指甲胶、精油、口红、眼影，卸妆水、洗发水等） | C84: +2/KG | D84: 提供真实有效期内商检、MSDS认证视为普货，无需附加费（证书是否有效以相关部门是否认可为准）
A85: 国内贴标费 | C85: 1元/张 | D85: 为了准确快捷入库，请尽量配合贴好入仓标签/FBA标签/SKU标签等，因未贴标签或未及时告知导致仓库未能及时入库延误船期的我司概不负责
A86: 报价未注明的产品，请将提供产品信息给我司客服或业务进行核实是否有附加费 | C86: 待确定 | D86: 因美对华加增2000亿美金关税影响，请单独询问销售
A87: 优势:自主装柜，海运市场优质后端，信誉清关行，快捷海外转运派送。
A88: 注明：每周报价表为实时报价，不可控因素或市场变化调节过大时，升或降以到仓价格为准。
A89: 包税附加费，未列明产品请跟业务联系
A90: 单证报关250/票，单票超5个品名以上+50RMB/个 卡派超限附加费：最长边不可超过120CM,次长边不可超过100CM，超长附加单价*1.1倍计算。单箱实重超过30KG单询
A91: 温馨提示：请按我司提供的样板提供电子版发票和装箱单如实申报，如因申报品名/申报数量/申报单价/申报材质/申报HS等不符造成的清关问题，我司概不负责 （清关延误不算在正常派送日内）

Sheet 海运快递派
A2: 美森360快递派
C3: 珠三角/汕头/义乌交货价
A4: 邮编开头 重量段 | C4: 12KG+ | D4: 51KG+ | E4: 101KG+ | F4: 承诺提取时效
A5: 90,91 | C5: 15.9 | D5: 14.9 | E5: 13.4 | F5: 开船后的第二天开始算，12个工作日内提取； 第13个工作日起未提取赔偿1元/KG/工作日，最高赔付5元/KG； 如遇海关查验造成承诺时效延误，直接赔付2元/KG，不再做其他延误赔付。
A6: 8,92-99 | C6: 16.4 | D6: 15.4 | E6: 13.9
A7: 5,6,7 | C7: 16.9 | D7: 15.9 | E7: 14.4
A8: 0,1,2,3,4 | C8: 17.9 | D8: 16.9 | E8: 15.4
A9: 飞点旗舰产品，选用美森特快服务，到港48小时内专车提柜送仓， 开船后第二天算起15天（360小时）提取
A10: 美森432快递派
C11: 珠三角/汕头/义乌交货价
A12: 邮编开头 重量段 | C12: 12KG+ | D12: 51KG+ | E12: 101KG+ | F12: 承诺提取时效
A13: 90,91 | C13: 15.4 | D13: 14.4 | E13: 12.9 | F13: 开船后的第二天开始算，14个工作日内提取； 第15个工作日起未提取赔偿1元/KG/工作日，最高赔付5元/KG； 如遇海关查验造成承诺时效延误，直接赔付2元/KG，不再做其他延误赔付。
A14: 8,92-99 | C14: 15.9 | D14: 14.9 | E14: 13.4
A15: 5,6,7 | C15: 16.4 | D15: 15.4 | E15: 13.9
A16: 0,1,2,3,4 | C16: 17.4 | D16: 16.4 | E16: 14.9
A17: 飞点旗舰产品，选用美森MAX服务，到港48小时内专车提柜送仓， 开船后第二天算起16天提取
A18: EX456快递派
C19: 珠三角/汕头/义乌交货价
A20: 邮编开头 重量段 | C20: 12KG+ | D20: 51KG+ | E20: 101KG+ | F20: 承诺提取时效
A21: 90,91 | C21: 10.5 | D21: 9.5 | E21: 8 | F21: 开船后的第二天开始算，18个工作日内提取； 第19个工作日起未提取赔偿1元/KG/工作日，最高赔付3元/KG； 如遇海关查验造成承诺时效延误，直接赔付2元/KG，不再做其他延误赔付。
A22: 8,92-99 | C22: 11 | D22: 10 | E22: 8.5
A23: 5,6,7 | C23: 11.5 | D23: 10.5 | E23: 9
A24: 0,1,2,3,4 | C24: 12.5 | D24: 11.5 | E24: 10
A25: 华东精品航线渠道，目的港专属车架、专用通道优先提柜，48小时内提柜送仓，时效比肩美森MAX。开船后456小时提取 甩柜赔1元/KG
A26: 快船600快递派
C27: 珠三角/汕头/义乌交货价
A28: 邮编开头 重量段 | C28: 12KG+ | D28: 51KG+ | E28: 101KG+ | F28: 承诺提取时效
A29: 90,91 | C29: 10.1 | D29: 9.1 | E29: 7.6 | F29: 开船后的第二天开始算，25个工作日内提取； 第26个工作日起未提取赔偿1元/KG/工作日，最高赔付3元/KG； 如遇海关查验造成承诺时效延误，直接赔付1元/KG，不再做其他延误赔付。
A30: 8,92-99 | C30: 10.6 | D30: 9.6 | E30: 8.1
A31: 5,6,7 | C31: 11.1 | D31: 10.1 | E31: 8.6
A32: 0,1,2,3,4 | C32: 12.1 | D32: 11.1 | E32: 9.6
A33: 选用COSCO/OOCL/EMC等船司服务里最快优质航线，交货10天内装柜进港
A34: 美东960快递派
C35: 珠三角/汕头/义乌交货价
A36: 邮编开头 重量段 | C36: 12KG+ | D36: 51KG+ | E36: 101KG+ | F36: 参考提取时效
A37: 0,1,2,3 | C37: 13.9 | D37: 11.9 | E37: 9.9 | F37: 开船后35-40个自然日提取
A38: 4,5,6,7 | C38: 14.9 | D38: 12.9 | E38: 10.9 | F38: 开船后35-40个自然日提取
A39: 选用ZIM/COSCO/EMC美东航线，盐田直达纽约港
A40: 快递派非FBA商业地址+1元/KG，住宅地址+2元/KG。单件计费重最低12KG起，不足12KG按12KG计费，后端UPS/Fedex快递派送。体积/6000
A41: 偏远地址单询（+1元/KG） 偏远地址查询网址：https://www.ziplucas.com/index.html | D41: 快递派超限附加费：单件实重不可超过22KG,超过22KG或单边长超过110cm，或次长超过75cm加收160RMB/件，周长大于260CM小于320厘米加收180元/件 地址修正费180元/件
A42: 快递派产品必须是纸箱货物，外箱包装不能缠膜、带护角、扎带，蛇皮袋、麻袋等均不可使用。纸箱必须为长方体或正方体，否则可能会被认定为异性包装。 若箱子包装未达到快递公司标准包装要求，由此产生的相关费用，我们将根据快递公司实际账单进行实报实销。 如因包装问题或其他问题导致亚马逊仓库拒收货物、私人地址拒收、未知原因、地址更正产生的退回运费及丢件费用由客户自行承担。
A43: 自2025年5月12日起 符合美国清关第232条款的钢铁制品、铝制品关税附加费加收0.5元/KG；
A44: 需加收产品及杂费 加收金额 | D44: 加收金额 | E44: 备注
A45: 除高价值，高关税产品，其余普通产品无附加费 | D45: 无附加费 | E45: 由于产品本身专利或知识产权问题产生扣关，货物退回等后续问题由客户承担，我司保留追究的权力。
A46: 木制品、蓝牙产品、激光类产品、UL产品 | D46: +1/KG | E46: FDA类产品，海关可能会查验。由于客户提供错误的FDA ID. 产生扣关，关税，货物退回等后续问题由客户承担，我司并保留追究的权力
A47: 化工品（指甲胶、精油、口红、眼影，卸妆水、洗发水等） | D47: +2/KG | E47: 提供真实有效期内商检、MSDS认证视为普货，无需附加费（证书是否有效以相关部门是否认可为准）
A48: 国内贴标费 | D48: 1元/张 | E48: 为了准确快捷入库，请尽量配合贴好入仓标签/FBA标签/SKU标签等，因未贴标签或未及时告知导致仓库未能及时入库延误船期的我司概不负责
A49: 报价未注明的产品，请将提供产品信息给我司客服或业务进行核实是否有附加费 | D49: 待确定 | E49: 因美对华加增2000亿美金关税影响，请单独询问销售
A50: 优势:自主装柜，海运市场优质后端，信誉清关行，快捷海外转运派送。
A51: 注明：每周报价表为实时报价，不可控因素或市场变化调节过大时，升或降以到仓价格为准。
A52: 包税附加费，未列明产品请跟业务联系
A53: 单证报关250/票，单票超5个品名以上+50RMB/个
A54: 温馨提示：请按我司提供的样板提供电子版发票和装箱单如实申报，如因申报品名/申报数量/申报单价/申报材质/申报HS等不符造成的清关问题，我司概不负责 （清关延误不算在正常派送日内）

Sheet 按方不包税
A2: 美森360
A3: 热门卡派仓
B4: 珠三角/汕头交货价 | C4: 义乌交货价
A5: 仓库 重量段 | B5: 按方不包税 2CBM+ | C5: 按方不包税 2CBM+ | D5: 签收时效 （开船后）
A6: ONT8,LAX9,LGB8 | B6: 1450 | C6: 1420 | D6: 12-16个自然日
A7: SBD1,POC1,POC3,JOT1,POC2,IUSP,IUSQ,IUTI,IUSJ,IUSW,IUTF | B7: 1470 | C7: 1440 | D7: 12-16个自然日
A8: GYR3,GYR2,LAS1,VGT2,MIT2,GEU3,QXY5,GEU5,GEU2,HLI2,TCY1,TCY2,SMF3,SCK4,SCK8,QXY8,IUTE,MCC1,PSP3 | B8: 1570 | C8: 1540 | D8: 13-17个自然日
A9: FTW1,AMA1,IAH3,SAT1,SAT4,PSC2,ABQ2 | B9: 1810 | C9: 1780 | D9: 15-19个自然日
A10: MQJ1,MEM1,FWA4,MDW2,IND9,RFD2 | B10: 1910 | C10: 1880 | D10: 16-21个自然日
A11: CLT2,TPA2,TPA3,RDU2 | B11: 2080 | C11: 2050 | D11: 21-26个自然日
A12: ORF2,RMN3,TEB3,TEB9,ABE8,AVP1,AVP3,SWF1,SWF2 | B12: 2160 | C12: 2130 | D12: 22-27个自然日
A13: 美森432
A14: 热门卡派仓
B15: 珠三角/汕头交货价 | C15: 义乌交货价
A16: 仓库 重量段 | B16: 按方不包税 2CBM+ | C16: 按方不包税 2CBM+ | D16: 签收时效 （开船后）
A17: ONT8,LAX9,LGB8 | B17: 1370 | C17: 1340 | D17: 14-18个自然日
A18: SBD1,POC1,POC3,JOT1,POC2,IUSP,IUSQ,IUTI,IUSJ,IUSW,IUTF | B18: 1390 | C18: 1360 | D18: 14-18个自然日
A19: GYR3,GYR2,LAS1,VGT2,MIT2,GEU3,QXY5,GEU5,GEU2,HLI2,TCY1,TCY2,SMF3,SCK4,SCK8,QXY8,IUTE,MCC1,PSP3 | B19: 1490 | C19: 1460 | D19: 15-19个自然日
A20: FTW1,AMA1,IAH3,SAT1,SAT4,PSC2,ABQ2 | B20: 1730 | C20: 1700 | D20: 17-21个自然日
A21: MQJ1,MEM1,FWA4,MDW2,IND9,RFD2 | B21: 1830 | C21: 1800 | D21: 18-23个自然日
A22: CLT2,TPA2,TPA3,RDU2 | B22: 2000 | C22: 1970 | D22: 23-28个自然日
A23: ORF2,RMN3,TEB3,TEB9,ABE8,AVP1,AVP3,SWF1,SWF2 | B23: 2080 | C23: 2050 | D23: 24-29个自然日
A24: EX456
A25: 热门卡派仓
B26: 珠三角/汕头/义乌交货价
A27: 仓库 重量段 | B27: 按方不包税 2CBM+ | D27: 签收时效 （开船后）
A28: ONT8,LAX9,LGB8 | B28: 640 | D28: 16-20个自然日
A29: SBD1,POC1,POC3,JOT1,POC2,IUSP,IUSQ,IUTI,IUSJ,IUSW,IUTF | B29: 660 | D29: 16-20个自然日
A30: GYR3,GYR2,LAS1,VGT2,MIT2,GEU3,QXY5,GEU5,GEU2,HLI2,TCY1,TCY2,SMF3,SCK4,SCK8,QXY8,IUTE,MCC1,PSP3 | B30: 740 | D30: 17-21个自然日
A31: FTW1,AMA1,IAH3,SAT1,SAT4,PSC2,ABQ2 | B31: 1080 | D31: 20-24个自然日
A32: MQJ1,MEM1,FWA4,MDW2,IND9,RFD2 | B32: 1200 | D32: 20-24个自然日
A33: CLT2,TPA2,TPA3,RDU2 | B33: 1360 | D33: 25-30个自然日
A34: ORF2,RMN3,TEB3,TEB9,ABE8,AVP1,AVP3,SWF1,SWF2 | B34: 1390 | D34: 26-31个自然日
A35: 快船600
A36: 热门卡派仓
B37: 珠三角/汕头/义乌交货价
A38: 仓库 重量段 | B38: 按方不包税 2CBM+ | D38: 签收时效（开船后）
A40: ONT8,LAX9,LGB8,SBD1,JOT1,POC1,POC3,POC2 | B40: 510 | D40: 20-27个自然日
A41: IUSP,IUSQ,IUTI,IUSJ,IUSW,IUTF | B41: 590 | D41: 21-29个自然日
A42: GYR3,GYR2,LAS1,VGT2,MIT2,GEU3,QXY5,GEU5,GEU2,MCC1,PSP3 | B42: 590 | D42: 21-29个自然日
A43: HLI2,TCY1,TCY2,SMF3,SCK4,SCK8,QXY8,IUTE | B43: 620 | D43: 21-29个自然日
A44: AMA1,IAH3,SAT1,SAT4,DFW6,PSC2,ABQ2,RFD2,FTW1,FTW5 | B44: 920 | D44: 25-32个自然日
A45: MDW2,MQJ1,MEM1,FWA4,IND9 | B45: 1030 | D45: 25-32个自然日
A46: CLT2,TPA2,TPA3,RDU2 | B46: 1220 | D46: 28-34个自然日
A47: ORF2,RMN3,TEB3,TEB9,ABE8,AVP1,AVP3,SWF1,SWF2 | B47: 1250 | D47: 28-34个自然日
A48: CMH2,CMH3,DET1,RYY2,JAX3 | B48: 1190 | D48: 32-40个自然日
A49: HGR6,WBW2,PBI3,ABE4 | B49: 1220 | D49: 34-40个自然日
A50: 洛杉矶768
A51: 热门卡派仓
B52: 珠三角/汕头/义乌交货价
A53: 仓库 重量段 | B53: 按方不包税 2CBM+ | D53: 参考时效（开船后）
A55: ONT8,LAX9,LGB8,SBD1,JOT1,POC1,POC3,POC2 | B55: 460 | D55: 24-32个自然日
A56: GYR3,GYR2,LAS1,VGT2,MIT2,GEU3,QXY5,GEU5,GEU2,QXY8 | B56: 570 | D56: 25-34个自然日
A57: XLX7,KRB1,KRB4,ONT2,ONT6,ONT9,LGB4,LGB6,LGB9,SBD2,SNA4 | B57: 580 | D57: 26-34个自然日
A58: PHX3,PHX5,PHX7,AZA4,LAS6,LAS7 | B58: 690 | D58: 27-36个自然日
A59: 奥克兰744
A60: 热门卡派仓
B61: 珠三角/汕头/义乌交货价
A62: 仓库 重量段 | B62: 按方不包税 2CBM+ | D62: 参考时效（开船后）
A64: SCK4,SMF3,SCK1,SCK3,OAK3,SJC7 | B64: 550 | D64: 26-34个自然日
A65: TCY2,SCK8,SMF7,MCE1,SMF6,QXY5 | B65: 570 | D65: 27-34个自然日
A66: HLI2,FAT2,MCC1 | B66: 620 | D66: 30-36个自然日
A67: 西雅图788
A68: 热门卡派仓
B69: 珠三角/汕头/义乌交货价
A70: 仓库 重量段 | B70: 按方不包税 2CBM+ | D70: 参考时效（开船后）
A72: BFI3,BFI7 | B72: 770 | D72: 26-35个自然日
A73: PSC2 | B73: 810 | D73: 29-38个自然日
A74: PDX6,PDX7 | B74: 840 | D74: 29-38个自然日
A75: GEG2 | B75: 940 | D75: 32-40个自然日
A76: 芝加哥840
A77: 热门卡派仓
B78: 珠三角/汕头/义乌交货价
A79: 仓库 重量段 | B79: 按方不包税 2CBM+ | D79: 参考时效（开船后）
A81: MDW2,ORD2,IGQ2,MDW9,RFD2,RFD4,JVL1,MDW6 | B81: 850 | D81: 30-35个自然日
A82: IND9,FWA4,MQJ1,MQJ2,STL4,IND2,IND4,IND5,PPO4 | B82: 940 | D82: 33-42个自然日
A83: DET1,DET2,LAN2,CMH2,CMH3,CMH7 | B83: 990 | D83: 35-45个自然日
A84: MKC4,MCI3,STL3 | B84: 1050 | D84: 38-45个自然日
A85: 休斯顿866
A86: 热门卡派仓
B87: 珠三角/汕头/义乌交货价
A88: 仓库 重量段 | B88: 按方不包税 2CBM+ | D88: 参考时效（开船后）
A90: HOU8,HOU7,HOU3,HOU2,HOU1,IAH3 | B90: 770 | D90: 32-37个自然日
A91: FTW9,FTW1,FTW5,FTW3,SAT1,FTW2,IUSF,DFW7,DFW6,DAL3,SAT6,SAT4,IUTH | B91: 850 | D91: 35-42个自然日
A92: LFT1,AMA1,OKC2,LIT2,ICT2,FOE1 | B92: 950 | D92: 38-45个自然日
A93: 萨凡纳888
A94: 卡派不包税
B95: 珠三角/汕头/义乌交货价
A96: 仓库 重量段 | B96: 按方不包税 2CBM+ | D96: 参考时效（开船后）
A98: SAV3,JAX3,XLX6,GSP1,GSO1,IUSR,CAE1,MGE1,MGE3,RYY2,CLT2,CLT3,RDU2,RDU4 | B98: 690 | D98: 37-47个自然日
A99: MCO1,MCO2,TPA2,TPA3,TPA6,TMB8,PBI2,PBI3,XPB2 | B99: 740 | D99: 40-50个自然日
A100: BNA2,BNA6,CHA2,HSV1,HSV2,MEM1 | B100: 800 | D100: 42-52个自然日
A101: 纽约960
A102: 卡派不包税
B103: 珠三角/汕头/义乌交货价
A104: 仓库 重量段 | B104: 按方不包税 2CBM+ | D104: 参考签收时效 （开船后）
A105: ABE8,ACY2,TEB6,TEB9,TTN2,TEB3,TEB4,XEW5 | B105: 630 | D105: 40-47个自然日
A106: ABE3,ABE4,AVP1,AVP3,AVP9,WBW2,HEA2 | B106: 670 | D106: 42-50个自然日
A107: HIA1,PHL4,PHL5,PHL6,MDT1,MDT4,PIT2,LBE1,ALB1,SWF1,SWF2 | B107: 720 | D107: 42-50个自然日
A108: IUSL,MDT2,ILG1,DCA6,BWI1,HGR2,XLX1,HGR6 | B108: 750 | D108: 45-55个自然日
...
